Workbook

Sheet Dashboard
I3: Recommendation | J3: =IF($C$9>=C8,"Buy",IF($C$9<=0,"Hold","Sell")) -> Buy
B5: Company Overview | E5: Methodologies | I5: Key Statisitics | M5: Links
B6: Ticker | C6: ARCC | E6: DCF | F6: =Valuation!C31 -> 128.46401 | I6: IPO | M6: Financial Statements'!A1 | N6: ESG Guideline'!A1 | O6: 1
B7: Stock Exchange | C7: EGX30 | E7: P/E | F7: =Valuation!C46 -> 112.81179 | I7: Incorporated | M7: IS!A1 | N7: ESG Scorecard '!A1 | O7: =O6+1 -> 2
B8: Current Price | C8: =Valuation!K3 -> 73.45 | E8: EV/EBITDA | F8: =Valuation!C67 -> 114.29905 | I8: Chairman | M8: Revenue Bridge'!A1 | N8: ESG Integration'!A1 | O8: =O7+1 -> 3
B9: Target Price | C9: =Valuation!E74 -> 123.99143 | E9: Overall Valuation | F9: =SUM(F6:F8) -> 355.57485 | I9: Headquarters | M9: COGS Bridge'!A1 | N9: Elasticity Analysis'!A1 | O9: =O8+1 -> 4
B10: =IF(C10="","Nothing Yet",IF(C10>0,"Upside","Downside")) -> Upside | C10: =C9/C8-1 -> 0.68810662 | I10: Primary industry | M10: Assumptions!A1 | N10: Valuation!A1 | O10: =O9+1 -> 5
I11: Sector | M11: BS!A1 | O11: =O10+1 -> 6
M12: Debt!A1 | O12: =O11+1 -> 7
M13: Ratios!A1 | O13: =O12+1 -> 8

Sheet Financial Statements
B1: Figures in EGPmn | N1: Core | O1: CAGR | R1: Financial Statements'!A1
B2: Income Statement
D3: 2021 | E3: =D3+1 -> 2022 | F3: =E3+1 -> 2023 | G3: =F3+1 -> 2024 | H3: =G3+1 -> 2025 | I3: =H3+1 -> 2026 | J3: =I3+1 -> 2027 | K3: =J3+1 -> 2028 | L3: =K3+1 -> 2029 | M3: =L3+1 -> 2030 | O3: Historic | P3: Fcsted
B4: Net Sales | D4: =IS!C13 -> 2448.6314 | E4: =IS!D13 -> 4675.0028 | F4: =IS!E13 -> 6042.8313 | G4: =IS!F13 -> 8729.7828 | H4: =IS!G13 -> 12447.32 | I4: ='Revenue Bridge'!H15 -> 14726.167 | J4: ='Revenue Bridge'!I15 -> 16143.641 | K4: ='Revenue Bridge'!J15 -> 17268.587 | L4: ='Revenue Bridge'!K15 -> 18276.163 | M4: ='Revenue Bridge'!L15 -> 19302.88 | O4: =_xlfn.RRI(4,D4,H4) -> 0.50154417 | P4: =_xlfn.RRI(4,I4,M4) -> 0.069998327
B5: Cost of Sales | D5: =-IS!C25+IS!C20+IS!C21+IS!C22 -> -2024.7314 | E5: =-IS!D25+IS!D20+IS!D21+IS!D22 -> -3550.2143 | F5: =-IS!E25+IS!E20+IS!E21+IS!E22 -> -4512.007 | G5: =-IS!F25+IS!F20+IS!F21+IS!F22 -> -6390.0166 | H5: =-IS!G25+IS!G20+IS!G21+IS!G22 -> -7103.6073 | I5: =-'COGS Bridge'!I11 -> -8065.2624 | J5: =-'COGS Bridge'!J11 -> -8776.0602 | K5: =-'COGS Bridge'!K11 -> -9405.4201 | L5: =-'COGS Bridge'!L11 -> -9967.3074 | M5: =-'COGS Bridge'!M11 -> -10539.716 | O5: =_xlfn.RRI(4,D5,H5) -> 0.36860424 | P5: =_xlfn.RRI(4,I5,M5) -> 0.069184377
B6: Gross Profit | D6: =D4+D5 -> 423.89997 | E6: =E4+E5 -> 1124.7885 | F6: =F4+F5 -> 1530.8244 | G6: =G4+G5 -> 2339.7662 | H6: =H4+H5 -> 5343.7128 | I6: =I4+I5 -> 6660.9043 | J6: =J4+J5 -> 7367.5812 | K6: =K4+K5 -> 7863.1672 | ... M6: =M4+M5 -> 8763.1637 | O6: =_xlfn.RRI(4,D6,H6) -> 0.8842778 | P6: =_xlfn.RRI(4,I6,M6) -> 0.070981408
B7: Margin | D7: =IFERROR(D6/D4,0) -> 0.17311711 | E7: =IFERROR(E6/E4,0) -> 0.24059633 | F7: =IFERROR(F6/F4,0) -> 0.25332899 | G7: =IFERROR(G6/G4,0) -> 0.26802112 | H7: =IFERROR(H6/H4,0) -> 0.42930629 | I7: =IFERROR(I6/I4,0) -> 0.4523176 | J7: =IFERROR(J6/J4,0) -> 0.45637666 | K7: =IFERROR(K6/K4,0) -> 0.45534514 | ... M7: =IFERROR(M6/M4,0) -> 0.45398219
B8: General & Administrative Expenses | D8: =-IS!C37+IS!C35 -> -78.96535 | E8: =-IS!D37+IS!D35 -> -112.72108 | F8: =-IS!E37+IS!E35 -> -181.32399 | G8: =-IS!F37+IS!F35 -> -263.95244 | H8: =-IS!G37+IS!G35 -> -380.0087 | I8: =-IS!H37+IS!H35 -> -433.40615 | J8: =-IS!I37+IS!I35 -> -478.83741 | K8: =-IS!J37+IS!J35 -> -515.47492 | ... M8: =-IS!L37+IS!L35 -> -577.04951
B9: Gain on Disposal of Property, Plant, and Equipment | D9: =IS!C83 -> 0.12 | E9: =IS!D83 -> 0.2 | F9: =IS!E83 -> 0.087675 | G9: =IS!F83 -> 0 | H9: =IS!G83 -> 1.14 | I9: =IS!H83 -> 0 | J9: =IS!I83 -> 0 | K9: =IS!J83 -> 0 | ... M9: =IS!L83 -> 0
B10: Other Income | D10: =IS!C70 -> 46.323288 | E10: =IS!D70 -> 104.2275 | F10: =IS!E70 -> 14.913053 | G10: =IS!F70 -> 18.292936 | H10: =IS!G70 -> 53.339508 | I10: =IS!H70 -> 63.104868 | J10: =IS!I70 -> 69.179059 | K10: =IS!J70 -> 73.9997 | ... M10: =IS!L70 -> 82.717092
B11: Other Operating Income | D11: =-(IS!C44+IS!C54)-IS!C52 -> -7.368018 | E11: =-(IS!D44+IS!D54)-IS!D52 -> -112.63989 | F11: =-(IS!E44+IS!E54)-IS!E52 -> -19.965948 | G11: =-(IS!F44+IS!F54)-IS!F52 -> -54.946498 | H11: =-(IS!G44+IS!G54)-IS!G52 -> -78.10927 | I11: =-(IS!H44+IS!H54)-IS!H52 -> -90.708218 | J11: =-(IS!I44+IS!I54)-IS!I52 -> -99.439384 | K11: =-(IS!J44+IS!J54)-IS!J52 -> -106.36867 | ... M11: =-(IS!L44+IS!L54)-IS!L52 -> -118.89923
B12: EBITDA | D12: =D6+SUM(D8:D11) -> 384.00989 | E12: =E6+SUM(E8:E11) -> 1003.8551 | F12: =F6+SUM(F8:F11) -> 1344.5352 | G12: =G6+SUM(G8:G11) -> 2039.1602 | H12: =H6+SUM(H8:H11) -> 4940.0744 | I12: =I6+SUM(I8:I11) -> 6199.8949 | J12: =J6+SUM(J8:J11) -> 6858.4835 | K12: =K6+SUM(K8:K11) -> 7315.3233 | ... M12: =M6+SUM(M8:M11) -> 8149.932 | O12: =_xlfn.RRI(4,D12,H12) -> 0.89385955 | P12: =_xlfn.RRI(4,I12,M12) -> 0.070760683
B13: Margin | D13: =IFERROR(D12/D4,0) -> 0.15682634 | E13: =IFERROR(E12/E4,0) -> 0.21472823 | F13: =IFERROR(F12/F4,0) -> 0.22250086 | G13: =IFERROR(G12/G4,0) -> 0.23358659 | H13: =IFERROR(H12/H4,0) -> 0.39687855 | I13: =IFERROR(I12/I4,0) -> 0.42101213 | J13: =IFERROR(J12/J4,0) -> 0.42484117 | K13: =IFERROR(K12/K4,0) -> 0.42362025 | ... M13: =IFERROR(M12/M4,0) -> 0.42221327
B14: Depreciation | D14: =-(IS!C20+IS!C35) -> -217.92949 | E14: =-(IS!D20+IS!D35) -> -208.21501 | F14: =-(IS!E20+IS!E35) -> -215.37694 | G14: =-(IS!F20+IS!F35) -> -221.56286 | H14: =-(IS!G20+IS!G35) -> -259.08968 | I14: =BS!H91 -> -318.57094 | J14: =BS!I91 -> -328.89888 | K14: =BS!J91 -> -344.2128 | L14: =BS!K91 -> -358.03881 | M14: =BS!L91 -> -376.41643
B15: Amortization | D15: =-(IS!C21+IS!C22) -> -40.527821 | E15: =-(IS!D21+IS!D22) -> -33.64381 | F15: =-(IS!E21+IS!E22) -> -35.047582 | G15: =-(IS!F21+IS!F22) -> -35.238663 | H15: =-(IS!G21+IS!G22) -> -30.681613 | I15: =BS!H137+BS!H144+BS!H158 -> -24.782969 | J15: =BS!I137+BS!I144+BS!I158 -> -26.125423 | K15: =BS!J137+BS!J144+BS!J158 -> -26.35488 | L15: =BS!K137+BS!K144+BS!K158 -> 2.4018247 | M15: =BS!L137+BS!L144+BS!L158 -> 0
B16: Total Depreciation & Amortization | D16: =SUM(D14:D15) -> -258.45731 | E16: =SUM(E14:E15) -> -241.85882 | F16: =SUM(F14:F15) -> -250.42452 | G16: =SUM(G14:G15) -> -256.80153 | H16: =SUM(H14:H15) -> -289.7713 | I16: =SUM(I14:I15) -> -343.35391 | J16: =SUM(J14:J15) -> -355.0243 | K16: =SUM(K14:K15) -> -370.56768 | ... M16: =SUM(M14:M15) -> -376.41643
B17: EBIT | D17: =D12+D16 -> 125.55258 | E17: =E12+E16 -> 761.99625 | F17: =F12+F16 -> 1094.1106 | G17: =G12+G16 -> 1782.3587 | H17: =H12+H16 -> 4650.3031 | I17: =I12+I16 -> 5856.5409 | J17: =J12+J16 -> 6503.4592 | K17: =K12+K16 -> 6944.7556 | ... M17: =M12+M16 -> 7773.5156 | O17: =_xlfn.RRI(4,D17,H17) -> 1.4669702 | P17: =_xlfn.RRI(4,I17,M17) -> 0.073356703
B18: Margin | D18: =IFERROR(D17/D4,0) -> 0.051274594 | E18: =IFERROR(E17/E4,0) -> 0.16299375 | F18: =IFERROR(F17/F4,0) -> 0.18105927 | G18: =IFERROR(G17/G4,0) -> 0.20416988 | H18: =IFERROR(H17/H4,0) -> 0.37359874 | I18: =IFERROR(I17/I4,0) -> 0.39769623 | J18: =IFERROR(J17/J4,0) -> 0.40284958 | K18: =IFERROR(K17/K4,0) -> 0.40216119 | ... M18: =IFERROR(M17/M4,0) -> 0.40271274
B19: Finance Costs | D19: =-IS!C79 -> -70.126214 | E19: =-IS!D79 -> -58.08122 | F19: =-IS!E79 -> -76.979253 | G19: =-IS!F79 -> -91.188916 | H19: =-IS!G79 -> -49.841733 | I19: =-IS!H79 -> -98.124734 | J19: =-IS!I79 -> -91.568676 | K19: =-IS!J79 -> -71.755428 | ... M19: =-IS!L79 -> -34.246877
B20: FX exchange | D20: =-IS!C84 -> -1.060989 | E20: =-IS!D84 -> -192.05848 | F20: =-IS!E84 -> -115.14417 | G20: =-IS!F84 -> -243.81213 | H20: =-IS!G84 -> -101.57824 | I20: =-IS!H84 -> 0 | J20: =-IS!I84 -> 0 | K20: =-IS!J84 -> 0 | ... M20: =-IS!L84 -> 0
B21: Interest Income | D21: =IS!C66 -> 0.743822 | E21: =IS!D66 -> 9.96778 | F21: =IS!E66 -> 30.813502 | G21: =IS!F66 -> 56.458493 | H21: =IS!G66 -> 226.27478 | I21: =IS!H66 -> 267.70101 | J21: =IS!I66 -> 293.46871 | K21: =IS!J66 -> 313.91864 | ... M21: =IS!L66 -> 350.89922
B22: Investment in a Joint Venture | D22: =IS!C63 -> 0.068872 | E22: =IS!D63 -> 0.047164 | F22: =IS!E63 -> -2.569276 | G22: =IS!F63 -> 2.05 | H22: =IS!G63 -> 0 | I22: =IS!H63 -> 0 | J22: =IS!I63 -> 0 | K22: =IS!J63 -> 0 | ... M22: =IS!L63 -> 0
B23: Non recurring Items
B24: Bad Debt | D24: =IS!C94 -> 0 | E24: =IS!D94 -> -0.00681 | F24: =IS!E94 -> 0 | G24: =IS!F94 -> 0 | H24: =IS!G94 -> 0 | I24: =IS!H94 -> 0 | J24: =IS!I94 -> 0 | K24: =IS!J94 -> 0 | ... M24: =IS!L94 -> 0
B25: EBT | D25: =D17+SUM(D19:D24) -> 55.17807 | E25: =E17+SUM(E19:E24) -> 521.86468 | F25: =F17+SUM(F19:F24) -> 930.23143 | G25: =G17+SUM(G19:G24) -> 1505.8661 | H25: =H17+SUM(H19:H24) -> 4725.1579 | I25: =I17+SUM(I19:I24) -> 6026.1172 | J25: =J17+SUM(J19:J24) -> 6705.3592 | K25: =K17+SUM(K19:K24) -> 7186.9188 | ... M25: =M17+SUM(M19:M24) -> 8090.168 | O25: =_xlfn.RRI(4,D25,H25) -> 2.0420227 | P25: =_xlfn.RRI(4,I25,M25) -> 0.076415619
B26: Margin | D26: =IFERROR(D25/D4,0) -> 0.02253425 | E26: =IFERROR(E25/E4,0) -> 0.11162874 | F26: =IFERROR(F25/F4,0) -> 0.15393967 | G26: =IFERROR(G25/G4,0) -> 0.17249755 | H26: =IFERROR(H25/H4,0) -> 0.37961247 | I26: =IFERROR(I25/I4,0) -> 0.40921153 | J26: =IFERROR(J25/J4,0) -> 0.41535606 | K26: =IFERROR(K25/K4,0) -> 0.41618453 | ... M26: =IFERROR(M25/M4,0) -> 0.41911715
B27: Income Taxes | D27: =-IS!C91 -> -20.988687 | E27: =-IS!D91 -> -162.87764 | F27: =-IS!E91 -> -232.7328 | G27: =-IS!F91 -> -345.731 | H27: =-IS!G91 -> -1125.4677 | I27: =-IS!H91 -> -1355.8764 | J27: =-IS!I91 -> -1508.7058 | K27: =-IS!J91 -> -1617.0567 | ... M27: =-IS!L91 -> -1820.2878
B28: Net Profit | D28: =D25+D27 -> 34.189383 | E28: =E25+E27 -> 358.98704 | F28: =F25+F27 -> 697.49863 | G28: =G25+G27 -> 1160.1351 | H28: =H25+H27 -> 3599.6902 | I28: =I25+I27 -> 4670.2408 | J28: =J25+J27 -> 5196.6534 | K28: =K25+K27 -> 5569.8621 | ... M28: =M25+M27 -> 6269.8802 | O28: =_xlfn.RRI(4,D28,H28) -> 2.2032694 | P28: =_xlfn.RRI(4,I28,M28) -> 0.076415619
B29: Margin | D29: =IFERROR(D28/D4,0) -> 0.01396265 | E29: =IFERROR(E28/E4,0) -> 0.076788625 | F29: =IFERROR(F28/F4,0) -> 0.1154258 | G29: =IFERROR(G28/G4,0) -> 0.13289393 | H29: =IFERROR(H28/H4,0) -> 0.28919399 | I29: =IFERROR(I28/I4,0) -> 0.31713893 | J29: =IFERROR(J28/J4,0) -> 0.32190094 | K29: =IFERROR(K28/K4,0) -> 0.32254301 | ... M29: =IFERROR(M28/M4,0) -> 0.32481579
B31: Profit Attributable
B32: Owners of the Parent Company | D32: 34.18181 | E32: 358.98648 | F32: 697.48874 | G32: 1160.1294 | H32: 3599.5859 | I32: =I28-I33 -> 4670.1366 | J32: =J28-J33 -> 5196.5491 | K32: =K28-K33 -> 5569.7578 | L32: =L28-L33 -> 5930.9319 | M32: =M28-M33 -> 6269.7759
B33: Non-Controlling Interests | D33: 0.007573 | E33: 0.00056 | F33: 0.009889 | G33: 0.005711 | H33: 0.104284 | I33: 0.104284 | J33: 0.104284 | K33: 0.104284 | L33: 0.104284 | M33: 0.104284
B34: Total | D34: =SUM(D32:D33) -> 34.189383 | E34: =SUM(E32:E33) -> 358.98704 | F34: =SUM(F32:F33) -> 697.49863 | G34: =SUM(G32:G33) -> 1160.1351 | H34: =SUM(H32:H33) -> 3599.6902 | I34: =SUM(I32:I33) -> 4670.2408 | J34: =SUM(J32:J33) -> 5196.6534 | K34: =SUM(K32:K33) -> 5569.8621 | ... M34: =SUM(M32:M33) -> 6269.8802
B35: Checker | D35: =D34=D28 -> FALSE | E35: =E34=E28 -> TRUE | F35: =F34=F28 -> TRUE | G35: =G34=G28 -> TRUE | H35: =H34=H28 -> TRUE | I35: =I34=I28 -> TRUE | J35: =J34=J28 -> TRUE | K35: =K34=K28 -> TRUE | ... M35: =M34=M28 -> TRUE
D36: =D34-D28 -> -2.4868996e-13 | E36: =E34-E28 -> 0 | F36: =F34-F28 -> 0 | G36: =G34-G28 -> 0 | H36: =H34-H28 -> 0
B38: Balance Sheet Statement
D39: =D3 -> 2021 | E39: =E3 -> 2022 | F39: =F3 -> 2023 | G39: =G3 -> 2024 | H39: =H3 -> 2025 | I39: =I3 -> 2026 | J39: =J3 -> 2027 | K39: =K3 -> 2028 | ... M39: =M3 -> 2030
B40: Non-Current Assets
B41: Property, Plant, and Equipment | D41: =BS!C121 -> 2019.9452 | E41: =BS!D121 -> 1839.1046 | F41: =BS!E121 -> 1683.6071 | G41: =BS!F121 -> 1669.6306 | H41: =BS!G121 -> 2522.3235 | I41: =BS!H121 -> 2826.9947 | J41: =BS!I121 -> 2752.0964 | K41: =BS!J121 -> 2679.5839 | ... M41: =BS!L121 -> 2536.3893
B42: Assets Under Construction | D42: =BS!C128 -> 3.261312 | E42: =BS!D128 -> 3.952133 | F42: =BS!E128 -> 2.426563 | G42: =BS!F128 -> 706.85563 | H42: =BS!G128 -> 391.54375 | I42: =BS!H128 -> 0 | J42: =BS!I128 -> 0 | K42: =BS!J128 -> 0 | ... M42: =BS!L128 -> 0
B43: Intangible Assets | D43: =BS!C139 -> 219.42461 | E43: =BS!D139 -> 191.26836 | F43: =BS!E139 -> 163.11212 | G43: =BS!F139 -> 134.95587 | H43: =BS!G139 -> 106.79962 | I43: =BS!H139 -> 78.643368 | J43: =BS!I139 -> 50.487119 | K43: =BS!J139 -> 22.33087 | ... M43: =BS!L139 -> 0
B44: Right of Use Assets | D44: =BS!C151 -> 17.631358 | E44: =BS!D151 -> 12.992066 | F44: =BS!E151 -> 12.901506 | G44: =BS!F151 -> 4.436332 | H44: =BS!G151 -> 0.82203 | I44: =BS!H151 -> 2.3843734 | J44: =BS!I151 -> 2.0521718 | K44: =BS!J151 -> 1.0008015 | ... M44: =BS!L151 -> 0
B45: Other Assets | D45: =BS!C160 -> 0 | E45: =BS!D160 -> 0 | F45: =BS!E160 -> 0 | G45: =BS!F160 -> 0 | H45: =BS!G160 -> 0 | I45: =BS!H160 -> 0 | J45: =BS!I160 -> 0 | K45: =BS!J160 -> 0 | ... M45: =BS!L160 -> 0
B46: Investment in a Joint Venture | D46: 2.523361 | E46: 2.569276 | F46: 0 | G46: 0 | H46: 0 | I46: 0 | J46: 0 | K46: 0 | L46: 0 | M46: 0
B47: Total Non-Current Assets | D47: =SUM(D41:D46) -> 2262.7858 | E47: =SUM(E41:E46) -> 2049.8864 | F47: =SUM(F41:F46) -> 1862.0473 | G47: =SUM(G41:G46) -> 2515.8784 | H47: =SUM(H41:H46) -> 3021.4889 | I47: =SUM(I41:I46) -> 2908.0224 | J47: =SUM(J41:J46) -> 2804.6357 | K47: =SUM(K41:K46) -> 2702.9155 | ... M47: =SUM(M41:M46) -> 2536.3893
B48: Current Assets
B49: Inventories | D49: =BS!C170 -> 369.73064 | E49: =BS!D170 -> 624.48627 | F49: =BS!E170 -> 986.10603 | G49: =BS!F170 -> 852.49004 | H49: =BS!G170 -> 1053.6462 | I49: =BS!H170 -> 1196.2842 | J49: =BS!I170 -> 1301.7137 | K49: =BS!J170 -> 1395.0638 | ... M49: =BS!L170 -> 1563.3089
B50: Trade Receivables | D50: =BS!C177 -> 58.876151 | E50: =BS!D177 -> 79.554875 | F50: =BS!E177 -> 228.61593 | G50: =BS!F177 -> 160.04816 | H50: =BS!G177 -> 244.41642 | I50: =BS!H177 -> 289.164 | J50: =BS!I177 -> 316.99763 | K50: =BS!J177 -> 339.08714 | ... M50: =BS!L177 -> 379.03265
B51: Debtors & other Debit Balances | D51: =BS!C201 -> 153.27274 | E51: =BS!D201 -> 198.93478 | F51: =BS!E201 -> 249.56613 | G51: =BS!F201 -> 632.97998 | H51: =BS!G201 -> 1004.7791 | I51: =BS!H201 -> 553.24621 | J51: =BS!I201 -> 602.32559 | K51: =BS!J201 -> 644.46314 | ... M51: =BS!L201 -> 720.79351
B52: Due from Related Parties | D52: =BS!C207 -> 0 | E52: =BS!D207 -> 0.07614 | F52: =BS!E207 -> 0.095368 | G52: =BS!F207 -> 0.156657 | H52: =BS!G207 -> 0 | I52: =BS!H207 -> 0 | J52: =BS!I207 -> 0 | K52: =BS!J207 -> 0 | ... M52: =BS!L207 -> 0
B53: Cash & Bank Balances | D53: =BS!C214 -> 128.25046 | E53: =BS!D214 -> 818.44202 | F53: =BS!E214 -> 561.09668 | G53: =BS!F214 -> 1687.0629 | H53: =BS!G214 -> 3459.3912 | I53: =I128 -> 7053.4238 | J53: =J128 -> 10415.968 | K53: =K128 -> 14031.155 | L53: =L128 -> 17887.772 | M53: =M128 -> 22013.994
B54: Total Current Assets | D54: =SUM(D49:D53) -> 710.12999 | E54: =SUM(E49:E53) -> 1721.4941 | F54: =SUM(F49:F53) -> 2025.4801 | G54: =SUM(G49:G53) -> 3332.7377 | H54: =SUM(H49:H53) -> 5762.2329 | I54: =SUM(I49:I53) -> 9092.1182 | J54: =SUM(J49:J53) -> 12637.005 | K54: =SUM(K49:K53) -> 16409.769 | ... M54: =SUM(M49:M53) -> 24677.129
B55: Total Assets | D55: =D47+D54 -> 2972.9158 | E55: =E47+E54 -> 3771.3805 | F55: =F47+F54 -> 3887.5274 | G55: =G47+G54 -> 5848.6161 | H55: =H47+H54 -> 8783.7218 | I55: =I47+I54 -> 12000.141 | J55: =J47+J54 -> 15441.64 | K55: =K47+K54 -> 19112.685 | ... M55: =M47+M54 -> 27213.518
B56: Equity
B57: Issued & Paid-Up Capital | D57: =BS!C220 -> 757.4794 | E57: =BS!D220 -> 757.4794 | F57: =BS!E220 -> 757.4794 | G57: =BS!F220 -> 757.4794 | H57: =BS!G220 -> 757.4794 | I57: =BS!H220 -> 757.4794 | J57: =BS!I220 -> 757.4794 | K57: =BS!J220 -> 757.4794 | ... M57: =BS!L220 -> 757.4794
B58: Treasury Shares | D58: 0 | E58: 0 | F58: 0 | G58: 0 | H58: -143.32799 | I58: -143.32799 | J58: -143.32799 | K58: -143.32799 | L58: -143.32799 | M58: -143.32799
B59: Legal Reserve | D59: 257.83077 | E59: 260.54312 | F59: 294.82953 | G59: 363.62777 | H59: 379.50577 | I59: 379.50577 | J59: 379.50577 | K59: 379.50577 | L59: 379.50577 | M59: 379.50577
B60: Retained Earnings | D60: =BS!C228 -> 45.625489 | E60: =BS!D228 -> 145.00398 | F60: =BS!E228 -> 701.91273 | G60: =BS!F228 -> 1182.3651 | H60: =BS!G228 -> 3648.917 | I60: =BS!H228 -> 6751.4419 | J60: =BS!I228 -> 10205.38 | K60: =BS!J228 -> 13908.457 | ... M60: =BS!L228 -> 22023.024
B61: Equity Attributable to Owners of the Parent Company | D61: =SUM(D57:D60) -> 1060.9357 | E61: =SUM(E57:E60) -> 1163.0265 | F61: =SUM(F57:F60) -> 1754.2217 | G61: =SUM(G57:G60) -> 2303.4723 | H61: =SUM(H57:H60) -> 4642.5742 | I61: =SUM(I57:I60) -> 7745.099 | J61: =SUM(J57:J60) -> 11199.037 | K61: =SUM(K57:K60) -> 14902.115 | ... M61: =SUM(M57:M60) -> 23016.681
B62: Non-Controlling Interests | D62: =BS!C237 -> 0.038681 | E62: =BS!D237 -> 0.038121 | F62: =BS!E237 -> 0.04801 | G62: =BS!F237 -> 0.053721 | H62: =BS!G237 -> 0.158005 | I62: =BS!H237 -> 0.262289 | J62: =BS!I237 -> 0.366573 | K62: =BS!J237 -> 0.470857 | ... M62: =BS!L237 -> 0.679425
B63: Total Equity | D63: =D61+D62 -> 1060.9743 | E63: =E61+E62 -> 1163.0646 | F63: =F61+F62 -> 1754.2697 | G63: =G61+G62 -> 2303.526 | H63: =H61+H62 -> 4642.7322 | I63: =I61+I62 -> 7745.3613 | J63: =J61+J62 -> 11199.403 | K63: =K61+K62 -> 14902.585 | ... M63: =M61+M62 -> 23017.361
B64: Liablilities
B65: Non-Current Liabilities
B66: Borrowings | D66: =Debt!C14 -> 272.76091 | E66: =Debt!D14 -> 177.47609 | F66: =Debt!E14 -> 0 | G66: =Debt!F14 -> 120.39238 | H66: =Debt!G14 -> 888.52254 | I66: =Debt!H14 -> 743.02939 | J66: =Debt!I14 -> 479.09969 | K66: =Debt!J14 -> 215.16998 | ... M66: =Debt!L14 -> 0
B67: Deferred Tax Liabilities | D67: =Debt!C49 -> 301.47283 | E67: =Debt!D49 -> 266.20171 | F67: =Debt!E49 -> 282.21862 | G67: =-Debt!F49 -> 241.14699 | H67: =-Debt!G49 -> 255.31616 | I67: =-Debt!H49 -> 255.31616 | J67: =-Debt!I49 -> 255.31616 | K67: =-Debt!J49 -> 255.31616 | L67: =-Debt!K49 -> 255.31616 | M67: =-Debt!L49 -> 255.31616
B68: N.C Lease Liabilities | D68: =Debt!C63 -> 6.979776 | E68: =Debt!D63 -> 6.724129 | F68: =Debt!E63 -> 1.739258 | G68: =Debt!F63 -> 1.642532 | H68: =Debt!G63 -> 0 | I68: =Debt!H63 -> 0.65064509 | J68: =Debt!I63 -> 0.50356044 | K68: =Debt!J63 -> 0.38972571 | ... M68: =Debt!L63 -> 0.2334393
B69: N.C Creditors & other Credit Balances | D69: =Debt!C80 -> 0 | E69: =Debt!D80 -> 0 | F69: =Debt!E80 -> 0 | G69: =Debt!F80 -> 0 | H69: =Debt!G80 -> 103.02084 | I69: =Debt!H80 -> 0 | J69: =Debt!I80 -> 0 | K69: =Debt!J80 -> 0 | ... M69: =Debt!L80 -> 0
B70: N.C Trade & Notes Payable | D70: =Debt!C94 -> 7.610691 | E70: =Debt!D94 -> 4.544514 | F70: =Debt!E94 -> 1.788996 | G70: =Debt!F94 -> 301.14206 | H70: =Debt!G94 -> 0 | I70: =Debt!H94 -> 0 | J70: =Debt!I94 -> 0 | K70: =Debt!J94 -> 0 | ... M70: =Debt!L94 -> 0
B71: Total Non-Current Liabilities | D71: =SUM(D66:D70) -> 588.8242 | E71: =SUM(E66:E70) -> 454.94644 | F71: =SUM(F66:F70) -> 285.74687 | G71: =SUM(G66:G70) -> 664.32396 | H71: =SUM(H66:H70) -> 1246.8595 | I71: =SUM(I66:I70) -> 998.9962 | J71: =SUM(J66:J70) -> 734.91941 | K71: =SUM(K66:K70) -> 470.87587 | ... M71: =SUM(M66:M70) -> 255.5496
B72: Current Liabilites
B73: Trade & Notes Payable | D73: =Debt!C89 -> 693.70363 | E73: =Debt!D89 -> 811.1819 | F73: =Debt!E89 -> 1067.6646 | G73: =Debt!F89 -> 839.31169 | H73: =Debt!G89 -> 720.17624 | I73: =Debt!H89 -> 709.47267 | J73: =Debt!I89 -> 771.99904 | K73: =Debt!J89 -> 827.36161 | ... M73: =Debt!L89 -> 927.14164
B74: Credit Facilities | D74: =Debt!C43 -> 240.38696 | E74: =Debt!D43 -> 360.6442 | F74: =Debt!E43 -> 90.074273 | G74: =Debt!F43 -> 615.04423 | H74: =Debt!G43 -> 99.916937 | I74: =Debt!H43 -> 134.16668 | J74: =Debt!I43 -> 146.39711 | K74: =Debt!J43 -> 156.78447 | ... M74: =Debt!L43 -> 175.52873
B75: Current Income Tax Liability | D75: =Debt!C53 -> 43.280867 | E75: =Debt!D53 -> 198.38656 | F75: =Debt!E53 -> 216.7159 | G75: =Debt!F53 -> 374.0144 | H75: =Debt!G53 -> 1102.2591 | I75: =Debt!H53 -> 1102.2591 | J75: =Debt!I53 -> 1102.2591 | K75: =Debt!J53 -> 1102.2591 | ... M75: =Debt!L53 -> 1102.2591
B76: Current Portion of Long-Term Borrowings | D76: =Debt!C9 -> 114.33478 | E76: =Debt!D9 -> 163.53478 | F76: =Debt!E9 -> 0 | G76: =Debt!F9 -> 25.481075 | H76: =Debt!G9 -> 145.49314 | I76: =Debt!H9 -> 263.9297 | J76: =Debt!I9 -> 263.9297 | K76: =Debt!J9 -> 263.9297 | ... M76: =Debt!L9 -> 10.458559
B77: Lease Liabilities | D77: =Debt!C62 -> 9.566342 | E77: =Debt!D62 -> 6.411505 | F77: =Debt!E62 -> 9.481649 | G77: =Debt!F62 -> 3.625821 | H77: =Debt!G62 -> 1.176042 | I77: =Debt!H62 -> 0.52539691 | J77: =Debt!I62 -> 0.40662584 | K77: =Debt!J62 -> 0.31470412 | ... M77: =Debt!L62 -> 0.18850259
B78: Creditors & other Credit Balances | D78: =Debt!C79 -> 184.25439 | E78: =Debt!D79 -> 299.002 | F78: =Debt!E79 -> 309.89932 | G78: =Debt!F79 -> 345.08734 | H78: =Debt!G79 -> 713.42449 | I78: =Debt!H79 -> 846.26778 | J78: =Debt!I79 -> 927.72572 | K78: =Debt!J79 -> 992.37291 | ... M78: =Debt!L79 -> 1109.2775
B79: Due to Related Parties | D79: =Debt!C106 -> 11.792907 | E79: =Debt!D106 -> 0.369246 | F79: =Debt!E106 -> 0 | G79: =Debt!F106 -> 0 | H79: =Debt!G106 -> 0 | I79: =Debt!H106 -> 0 | J79: =Debt!I106 -> 0 | K79: =Debt!J106 -> 0 | ... M79: =Debt!L106 -> 0
B80: Dividends Payable | D80: 0 | E80: 249.9682 | F80: 99.229802 | G80: 600.30242 | H80: 0 | I80: 0 | J80: 0 | K80: 0 | L80: 0 | M80: 0
B81: Provisions | D81: =IS!C46 -> 25.797396 | E81: =IS!D46 -> 63.871019 | F81: =IS!E46 -> 54.445334 | G81: =IS!F46 -> 77.899139 | H81: =IS!G46 -> 111.68412 | I81: =IS!H46 -> 199.16177 | J81: =IS!I46 -> 294.60036 | K81: =IS!J46 -> 396.20126 | ... M81: =IS!L46 -> 615.75381
B82: Total Current Liabilities | D82: =SUM(D73:D81) -> 1323.1173 | E82: =SUM(E73:E81) -> 2153.3694 | F82: =SUM(F73:F81) -> 1847.5109 | G82: =SUM(G73:G81) -> 2880.7661 | H82: =SUM(H73:H81) -> 2894.1301 | I82: =SUM(I73:I81) -> 3255.7831 | J82: =SUM(J73:J81) -> 3507.3177 | K82: =SUM(K73:K81) -> 3739.2238 | ... M82: =SUM(M73:M81) -> 3940.6078
B83: Total Liabilites | D83: =D71+D82 -> 1911.9415 | E83: =E71+E82 -> 2608.3159 | F83: =F71+F82 -> 2133.2578 | G83: =G71+G82 -> 3545.0901 | H83: =H71+H82 -> 4140.9896 | I83: =I71+I82 -> 4254.7793 | J83: =J71+J82 -> 4242.2371 | K83: =K71+K82 -> 4210.0996 | ... M83: =M71+M82 -> 4196.1574
B84: Total Equity & Liabilities | D84: =D63+D83 -> 2972.9158 | E84: =E63+E83 -> 3771.3805 | F84: =F63+F83 -> 3887.5274 | G84: =G63+G83 -> 5848.6161 | H84: =H63+H83 -> 8783.7218 | I84: =I63+I83 -> 12000.141 | J84: =J63+J83 -> 15441.64 | K84: =K63+K83 -> 19112.685 | ... M84: =M63+M83 -> 27213.518
B85: Checker | D85: =D84=D55 -> TRUE | E85: =E84=E55 -> TRUE | F85: =F84=F55 -> TRUE | G85: =G84=G55 -> TRUE | H85: =H84=H55 -> TRUE | I85: =I84=I55 -> TRUE | J85: =J84=J55 -> TRUE | K85: =K84=K55 -> TRUE | ... M85: =M84=M55 -> TRUE
B87: Working Capital | D87: =(D49+D50+D52+D51)-(D73+D78+D79+D81+D75) -> -376.94966 | E87: =(E49+E50+E52+E51)-(E73+E78+E79+E81+E75) -> -469.75866 | F87: =(F49+F50+F52+F51)-(F73+F78+F79+F81+F75) -> -184.3417 | G87: =(G49+G50+G52+G51)-(G73+G78+G79+G81+G75) -> 9.362262 | H87: =(H49+H50+H52+H51)-(H73+H78+H79+H81+H75) -> -344.70226 | I87: =(I49+I50+I52+I51)-(I73+I78+I79+I81+I75) -> -818.46689 | J87: =(J49+J50+J52+J51)-(J73+J78+J79+J81+J75) -> -875.54734 | K87: =(K49+K50+K52+K51)-(K73+K78+K79+K81+K75) -> -939.58082 | ... M87: =(M49+M50+M52+M51)-(M73+M78+M79+M81+M75) -> -1091.297
B88: NWC | D88: =D49+D50-D73 -> -265.09684 | E88: =E49+E50-E73 -> -107.14076 | F88: =F49+F50-F73 -> 147.05735 | G88: =G49+G50-G73 -> 173.22651 | H88: =H49+H50-H73 -> 577.88639 | I88: =I49+I50-I73 -> 775.97555 | J88: =J49+J50-J73 -> 846.71226 | K88: =K49+K50-K73 -> 906.78933 | ... M88: =M49+M50-M73 -> 1015.1999
B89: CHG in NWC | E89: =E88-D88 -> 157.95608 | F89: =F88-E88 -> 254.19811 | G89: =G88-F88 -> 26.169157 | H89: =H88-G88 -> 404.65988 | I89: =I88-H88 -> 198.08916 | J89: =J88-I88 -> 70.736705 | K89: =K88-J88 -> 60.077071 | L89: =L88-K88 -> 53.699814 | M89: =M88-L88 -> 54.710732
B92: Cashflow Statement
D93: =D39 -> 2021 | E93: =E39 -> 2022 | F93: =F39 -> 2023 | G93: =G39 -> 2024 | H93: =H39 -> 2025 | I93: =I39 -> 2026 | J93: =J39 -> 2027 | K93: =K39 -> 2028 | ... M93: =M39 -> 2030
B94: Net Profit | D94: =D34 -> 34.189383 | E94: =E34 -> 358.98704 | F94: =F34 -> 697.49863 | G94: =G34 -> 1160.1351 | H94: =H34 -> 3599.6902 | I94: =I34 -> 4670.2408 | J94: =J34 -> 5196.6534 | K94: =K34 -> 5569.8621 | ... M94: =M34 -> 6269.8802
B95: Depreciation & Amortization | D95: =-D16 -> 258.45731 | E95: =-E16 -> 241.85882 | F95: =-F16 -> 250.42452 | G95: =-G16 -> 256.80153 | H95: =-H16 -> 289.7713 | I95: =-I16 -> 343.35391 | J95: =-J16 -> 355.0243 | K95: =-K16 -> 370.56768 | ... M95: =-M16 -> 376.41643
B96: ADJ NP | D96: =SUM(D94:D95) -> 292.6467 | E96: =SUM(E94:E95) -> 600.84586 | F96: =SUM(F94:F95) -> 947.92315 | G96: =SUM(G94:G95) -> 1416.9366 | H96: =SUM(H94:H95) -> 3889.4615 | I96: =SUM(I94:I95) -> 5013.5948 | J96: =SUM(J94:J95) -> 5551.6777 | K96: =SUM(K94:K95) -> 5940.4298 | ... M96: =SUM(M94:M95) -> 6646.2966
B97: Inventories | D97: =IFERROR(INDEX(C$40:C$84,MATCH($B97,$B$40:$B$84,0)),0)-IFERROR(INDEX(D$40:D$84,MATCH($B97,$B$40:$B$84,0)),0) -> -369.73064 | E97: =IFERROR(INDEX(D$40:D$84,MATCH($B97,$B$40:$B$84,0)),0)-IFERROR(INDEX(E$40:E$84,MATCH($B97,$B$40:$B$84,0)),0) -> -254.75563 | F97: =IFERROR(INDEX(E$40:E$84,MATCH($B97,$B$40:$B$84,0)),0)-IFERROR(INDEX(F$40:F$84,MATCH($B97,$B$40:$B$84,0)),0) -> -361.61976 | G97: =IFERROR(INDEX(F$40:F$84,MATCH($B97,$B$40:$B$84,0)),0)-IFERROR(INDEX(G$40:G$84,MATCH($B97,$B$40:$B$84,0)),0) -> 133.61599 | H97: =IFERROR(INDEX(G$40:G$84,MATCH($B97,$B$40:$B$84,0)),0)-IFERROR(INDEX(H$40:H$84,MATCH($B97,$B$40:$B$84,0)),0) -> -201.15617 | I97: =IFERROR(INDEX(H$40:H$84,MATCH($B97,$B$40:$B$84,0)),0)-IFERROR(INDEX(I$40:I$84,MATCH($B97,$B$40:$B$84,0)),0) -> -142.638 | J97: =IFERROR(INDEX(I$40:I$84,MATCH($B97,$B$40:$B$84,0)),0)-IFERROR(INDEX(J$40:J$84,MATCH($B97,$B$40:$B$84,0)),0) -> -105.42945 | K97: =IFERROR(INDEX(J$40:J$84,MATCH($B97,$B$40:$B$84,0)),0)-IFERROR(INDEX(K$40:K$84,MATCH($B97,$B$40:$B$84,0)),0) -> -93.350124 | ... M97: =IFERROR(INDEX(L$40:L$84,MATCH($B97,$B$40:$B$84,0)),0)-IFERROR(INDEX(M$40:M$84,MATCH($B97,$B$40:$B$84,0)),0) -> -84.90284
B98: Trade Receivables | D98: =IFERROR(INDEX(C$40:C$84,MATCH($B98,$B$40:$B$84,0)),0)-IFERROR(INDEX(D$40:D$84,MATCH($B98,$B$40:$B$84,0)),0) -> -58.876151 | E98: =IFERROR(INDEX(D$40:D$84,MATCH($B98,$B$40:$B$84,0)),0)-IFERROR(INDEX(E$40:E$84,MATCH($B98,$B$40:$B$84,0)),0) -> -20.678724 | F98: =IFERROR(INDEX(E$40:E$84,MATCH($B98,$B$40:$B$84,0)),0)-IFERROR(INDEX(F$40:F$84,MATCH($B98,$B$40:$B$84,0)),0) -> -149.06106 | G98: =IFERROR(INDEX(F$40:F$84,MATCH($B98,$B$40:$B$84,0)),0)-IFERROR(INDEX(G$40:G$84,MATCH($B98,$B$40:$B$84,0)),0) -> 68.567774 | H98: =IFERROR(INDEX(G$40:G$84,MATCH($B98,$B$40:$B$84,0)),0)-IFERROR(INDEX(H$40:H$84,MATCH($B98,$B$40:$B$84,0)),0) -> -84.368259 | I98: =IFERROR(INDEX(H$40:H$84,MATCH($B98,$B$40:$B$84,0)),0)-IFERROR(INDEX(I$40:I$84,MATCH($B98,$B$40:$B$84,0)),0) -> -44.747588 | J98: =IFERROR(INDEX(I$40:I$84,MATCH($B98,$B$40:$B$84,0)),0)-IFERROR(INDEX(J$40:J$84,MATCH($B98,$B$40:$B$84,0)),0) -> -27.833628 | K98: =IFERROR(INDEX(J$40:J$84,MATCH($B98,$B$40:$B$84,0)),0)-IFERROR(INDEX(K$40:K$84,MATCH($B98,$B$40:$B$84,0)),0) -> -22.089512 | ... M98: =IFERROR(INDEX(L$40:L$84,MATCH($B98,$B$40:$B$84,0)),0)-IFERROR(INDEX(M$40:M$84,MATCH($B98,$B$40:$B$84,0)),0) -> -20.16068
B99: Debtors & other Debit Balances | D99: =IFERROR(INDEX(C$40:C$84,MATCH($B99,$B$40:$B$84,0)),0)-IFERROR(INDEX(D$40:D$84,MATCH($B99,$B$40:$B$84,0)),0) -> -153.27274 | E99: =IFERROR(INDEX(D$40:D$84,MATCH($B99,$B$40:$B$84,0)),0)-IFERROR(INDEX(E$40:E$84,MATCH($B99,$B$40:$B$84,0)),0) -> -45.662034 | F99: =IFERROR(INDEX(E$40:E$84,MATCH($B99,$B$40:$B$84,0)),0)-IFERROR(INDEX(F$40:F$84,MATCH($B99,$B$40:$B$84,0)),0) -> -50.631358 | G99: =IFERROR(INDEX(F$40:F$84,MATCH($B99,$B$40:$B$84,0)),0)-IFERROR(INDEX(G$40:G$84,MATCH($B99,$B$40:$B$84,0)),0) -> -383.41384 | H99: =IFERROR(INDEX(G$40:G$84,MATCH($B99,$B$40:$B$84,0)),0)-IFERROR(INDEX(H$40:H$84,MATCH($B99,$B$40:$B$84,0)),0) -> -371.79909 | I99: =IFERROR(INDEX(H$40:H$84,MATCH($B99,$B$40:$B$84,0)),0)-IFERROR(INDEX(I$40:I$84,MATCH($B99,$B$40:$B$84,0)),0) -> 451.53285 | J99: =IFERROR(INDEX(I$40:I$84,MATCH($B99,$B$40:$B$84,0)),0)-IFERROR(INDEX(J$40:J$84,MATCH($B99,$B$40:$B$84,0)),0) -> -49.079378 | K99: =IFERROR(INDEX(J$40:J$84,MATCH($B99,$B$40:$B$84,0)),0)-IFERROR(INDEX(K$40:K$84,MATCH($B99,$B$40:$B$84,0)),0) -> -42.137546 | ... M99: =IFERROR(INDEX(L$40:L$84,MATCH($B99,$B$40:$B$84,0)),0)-IFERROR(INDEX(M$40:M$84,MATCH($B99,$B$40:$B$84,0)),0) -> -38.316496
B100: Due from Related Parties | D100: =IFERROR(INDEX(C$40:C$84,MATCH($B100,$B$40:$B$84,0)),0)-IFERROR(INDEX(D$40:D$84,MATCH($B100,$B$40:$B$84,0)),0) -> 0 | E100: =IFERROR(INDEX(D$40:D$84,MATCH($B100,$B$40:$B$84,0)),0)-IFERROR(INDEX(E$40:E$84,MATCH($B100,$B$40:$B$84,0)),0) -> -0.07614 | F100: =IFERROR(INDEX(E$40:E$84,MATCH($B100,$B$40:$B$84,0)),0)-IFERROR(INDEX(F$40:F$84,MATCH($B100,$B$40:$B$84,0)),0) -> -0.019228 | G100: =IFERROR(INDEX(F$40:F$84,MATCH($B100,$B$40:$B$84,0)),0)-IFERROR(INDEX(G$40:G$84,MATCH($B100,$B$40:$B$84,0)),0) -> -0.061289 | H100: =IFERROR(INDEX(G$40:G$84,MATCH($B100,$B$40:$B$84,0)),0)-IFERROR(INDEX(H$40:H$84,MATCH($B100,$B$40:$B$84,0)),0) -> 0.156657 | I100: =IFERROR(INDEX(H$40:H$84,MATCH($B100,$B$40:$B$84,0)),0)-IFERROR(INDEX(I$40:I$84,MATCH($B100,$B$40:$B$84,0)),0) -> 0 | J100: =IFERROR(INDEX(I$40:I$84,MATCH($B100,$B$40:$B$84,0)),0)-IFERROR(INDEX(J$40:J$84,MATCH($B100,$B$40:$B$84,0)),0) -> 0 | K100: =IFERROR(INDEX(J$40:J$84,MATCH($B100,$B$40:$B$84,0)),0)-IFERROR(INDEX(K$40:K$84,MATCH($B100,$B$40:$B$84,0)),0) -> 0 | ... M100: =IFERROR(INDEX(L$40:L$84,MATCH($B100,$B$40:$B$84,0)),0)-IFERROR(INDEX(M$40:M$84,MATCH($B100,$B$40:$B$84,0)),0) -> 0
B101: Trade & Notes Payable | D101: =IFERROR(INDEX(D$40:D$84,MATCH($B101,$B$40:$B$84,0)),0)-IFERROR(INDEX(C$40:C$84,MATCH($B101,$B$40:$B$84,0)),0) -> 693.70363 | E101: =E73-D73 -> 117.47827 | F101: =F73-E73 -> 256.48271 | G101: =G73-F73 -> -228.35292 | H101: =H73-G73 -> -119.13545 | I101: =I73-H73 -> -10.703572 | J101: =J73-I73 -> 62.526372 | K101: =K73-J73 -> 55.362564 | L101: =L73-K73 -> 49.427247 | M101: =M73-L73 -> 50.352787
B102: Credit Facilities | D102: =IFERROR(INDEX(D$40:D$84,MATCH($B102,$B$40:$B$84,0)),0)-IFERROR(INDEX(C$40:C$84,MATCH($B102,$B$40:$B$84,0)),0) -> 240.38696 | E102: =IFERROR(INDEX(E$40:E$84,MATCH($B102,$B$40:$B$84,0)),0)-IFERROR(INDEX(D$40:D$84,MATCH($B102,$B$40:$B$84,0)),0) -> 120.25724 | F102: =IFERROR(INDEX(F$40:F$84,MATCH($B102,$B$40:$B$84,0)),0)-IFERROR(INDEX(E$40:E$84,MATCH($B102,$B$40:$B$84,0)),0) -> -270.56993 | G102: =IFERROR(INDEX(G$40:G$84,MATCH($B102,$B$40:$B$84,0)),0)-IFERROR(INDEX(F$40:F$84,MATCH($B102,$B$40:$B$84,0)),0) -> 524.96996 | H102: =IFERROR(INDEX(H$40:H$84,MATCH($B102,$B$40:$B$84,0)),0)-IFERROR(INDEX(G$40:G$84,MATCH($B102,$B$40:$B$84,0)),0) -> -515.12729 | I102: =IFERROR(INDEX(I$40:I$84,MATCH($B102,$B$40:$B$84,0)),0)-IFERROR(INDEX(H$40:H$84,MATCH($B102,$B$40:$B$84,0)),0) -> 34.249746 | J102: =IFERROR(INDEX(J$40:J$84,MATCH($B102,$B$40:$B$84,0)),0)-IFERROR(INDEX(I$40:I$84,MATCH($B102,$B$40:$B$84,0)),0) -> 12.230423 | K102: =IFERROR(INDEX(K$40:K$84,MATCH($B102,$B$40:$B$84,0)),0)-IFERROR(INDEX(J$40:J$84,MATCH($B102,$B$40:$B$84,0)),0) -> 10.387365 | ... M102: =IFERROR(INDEX(M$40:M$84,MATCH($B102,$B$40:$B$84,0)),0)-IFERROR(INDEX(L$40:L$84,MATCH($B102,$B$40:$B$84,0)),0) -> 9.4595216
B103: Current Income Tax Liability | D103: =IFERROR(INDEX(D$40:D$84,MATCH($B103,$B$40:$B$84,0)),0)-IFERROR(INDEX(C$40:C$84,MATCH($B103,$B$40:$B$84,0)),0) -> 43.280867 | E103: =IFERROR(INDEX(E$40:E$84,MATCH($B103,$B$40:$B$84,0)),0)-IFERROR(INDEX(D$40:D$84,MATCH($B103,$B$40:$B$84,0)),0) -> 155.10569 | F103: =IFERROR(INDEX(F$40:F$84,MATCH($B103,$B$40:$B$84,0)),0)-IFERROR(INDEX(E$40:E$84,MATCH($B103,$B$40:$B$84,0)),0) -> 18.32934 | G103: =IFERROR(INDEX(G$40:G$84,MATCH($B103,$B$40:$B$84,0)),0)-IFERROR(INDEX(F$40:F$84,MATCH($B103,$B$40:$B$84,0)),0) -> 157.2985 | H103: =IFERROR(INDEX(H$40:H$84,MATCH($B103,$B$40:$B$84,0)),0)-IFERROR(INDEX(G$40:G$84,MATCH($B103,$B$40:$B$84,0)),0) -> 728.24471 | I103: =IFERROR(INDEX(I$40:I$84,MATCH($B103,$B$40:$B$84,0)),0)-IFERROR(INDEX(H$40:H$84,MATCH($B103,$B$40:$B$84,0)),0) -> 0 | J103: =IFERROR(INDEX(J$40:J$84,MATCH($B103,$B$40:$B$84,0)),0)-IFERROR(INDEX(I$40:I$84,MATCH($B103,$B$40:$B$84,0)),0) -> 0 | K103: =IFERROR(INDEX(K$40:K$84,MATCH($B103,$B$40:$B$84,0)),0)-IFERROR(INDEX(J$40:J$84,MATCH($B103,$B$40:$B$84,0)),0) -> 0 | ... M103: =IFERROR(INDEX(M$40:M$84,MATCH($B103,$B$40:$B$84,0)),0)-IFERROR(INDEX(L$40:L$84,MATCH($B103,$B$40:$B$84,0)),0) -> 0
B104: Current Portion of Long-Term Borrowings | D104: =IFERROR(INDEX(D$40:D$84,MATCH($B104,$B$40:$B$84,0)),0)-IFERROR(INDEX(C$40:C$84,MATCH($B104,$B$40:$B$84,0)),0) -> 114.33478 | E104: =IFERROR(INDEX(E$40:E$84,MATCH($B104,$B$40:$B$84,0)),0)-IFERROR(INDEX(D$40:D$84,MATCH($B104,$B$40:$B$84,0)),0) -> 49.199999 | F104: =IFERROR(INDEX(F$40:F$84,MATCH($B104,$B$40:$B$84,0)),0)-IFERROR(INDEX(E$40:E$84,MATCH($B104,$B$40:$B$84,0)),0) -> -163.53478 | G104: =IFERROR(INDEX(G$40:G$84,MATCH($B104,$B$40:$B$84,0)),0)-IFERROR(INDEX(F$40:F$84,MATCH($B104,$B$40:$B$84,0)),0) -> 25.481075 | H104: =IFERROR(INDEX(H$40:H$84,MATCH($B104,$B$40:$B$84,0)),0)-IFERROR(INDEX(G$40:G$84,MATCH($B104,$B$40:$B$84,0)),0) -> 120.01207 | I104: =IFERROR(INDEX(I$40:I$84,MATCH($B104,$B$40:$B$84,0)),0)-IFERROR(INDEX(H$40:H$84,MATCH($B104,$B$40:$B$84,0)),0) -> 118.43656 | J104: =IFERROR(INDEX(J$40:J$84,MATCH($B104,$B$40:$B$84,0)),0)-IFERROR(INDEX(I$40:I$84,MATCH($B104,$B$40:$B$84,0)),0) -> 0 | K104: =IFERROR(INDEX(K$40:K$84,MATCH($B104,$B$40:$B$84,0)),0)-IFERROR(INDEX(J$40:J$84,MATCH($B104,$B$40:$B$84,0)),0) -> 0 | ... M104: =IFERROR(INDEX(M$40:M$84,MATCH($B104,$B$40:$B$84,0)),0)-IFERROR(INDEX(L$40:L$84,MATCH($B104,$B$40:$B$84,0)),0) -> -194.25286
B105: Lease Liabilities | D105: =IFERROR(INDEX(D$40:D$84,MATCH($B105,$B$40:$B$84,0)),0)-IFERROR(INDEX(C$40:C$84,MATCH($B105,$B$40:$B$84,0)),0) -> 9.566342 | E105: =IFERROR(INDEX(E$40:E$84,MATCH($B105,$B$40:$B$84,0)),0)-IFERROR(INDEX(D$40:D$84,MATCH($B105,$B$40:$B$84,0)),0) -> -3.154837 | F105: =IFERROR(INDEX(F$40:F$84,MATCH($B105,$B$40:$B$84,0)),0)-IFERROR(INDEX(E$40:E$84,MATCH($B105,$B$40:$B$84,0)),0) -> 3.070144 | G105: =IFERROR(INDEX(G$40:G$84,MATCH($B105,$B$40:$B$84,0)),0)-IFERROR(INDEX(F$40:F$84,MATCH($B105,$B$40:$B$84,0)),0) -> -5.855828 | H105: =IFERROR(INDEX(H$40:H$84,MATCH($B105,$B$40:$B$84,0)),0)-IFERROR(INDEX(G$40:G$84,MATCH($B105,$B$40:$B$84,0)),0) -> -2.449779 | I105: =IFERROR(INDEX(I$40:I$84,MATCH($B105,$B$40:$B$84,0)),0)-IFERROR(INDEX(H$40:H$84,MATCH($B105,$B$40:$B$84,0)),0) -> -0.65064509 | J105: =IFERROR(INDEX(J$40:J$84,MATCH($B105,$B$40:$B$84,0)),0)-IFERROR(INDEX(I$40:I$84,MATCH($B105,$B$40:$B$84,0)),0) -> -0.11877108 | K105: =IFERROR(INDEX(K$40:K$84,MATCH($B105,$B$40:$B$84,0)),0)-IFERROR(INDEX(J$40:J$84,MATCH($B105,$B$40:$B$84,0)),0) -> -0.091921721 | ... M105: =IFERROR(INDEX(M$40:M$84,MATCH($B105,$B$40:$B$84,0)),0)-IFERROR(INDEX(L$40:L$84,MATCH($B105,$B$40:$B$84,0)),0) -> -0.0550596
...

Sheet IS
B2: Footnotes BD | C2: 2021 | D2: =C2+1 -> 2022 | E2: =D2+1 -> 2023 | F2: =E2+1 -> 2024 | G2: =F2+1 -> 2025 | H2: =G2+1 -> 2026 | I2: =H2+1 -> 2027 | J2: =I2+1 -> 2028 | K2: =J2+1 -> 2029 | L2: =K2+1 -> 2030
B4: Revenue
B5: Local
B6: Sales | C6: 2054.1196 | D6: 3821.5448 | E6: 3906.434 | F6: 4703.4792 | G6: 8350.4546 | H6: ='Revenue Bridge'!H6 -> 10320.725 | I6: ='Revenue Bridge'!I6 -> 10902.035 | J6: ='Revenue Bridge'!J6 -> 11738.811 | K6: ='Revenue Bridge'!K6 -> 12495.316 | L6: ='Revenue Bridge'!L6 -> 13301.991
B7: Services | C7: 92.559521 | D7: 103.05889 | E7: 82.820228 | F7: 179.82523 | G7: 281.86355 | H7: ='Revenue Bridge'!H7 -> 290.31945 | I7: ='Revenue Bridge'!I7 -> 299.02904 | J7: ='Revenue Bridge'!J7 -> 307.99991 | K7: ='Revenue Bridge'!K7 -> 317.2399 | L7: ='Revenue Bridge'!L7 -> 326.7571
B8: Total Local Sales | C8: =SUM(C6:C7) -> 2146.6791 | D8: =SUM(D6:D7) -> 3924.6037 | E8: =SUM(E6:E7) -> 3989.2543 | F8: =SUM(F6:F7) -> 4883.3045 | G8: =SUM(G6:G7) -> 8632.3182 | H8: =SUM(H6:H7) -> 10611.044 | I8: =SUM(I6:I7) -> 11201.064 | J8: =SUM(J6:J7) -> 12046.811 | ... L8: =SUM(L6:L7) -> 13628.748
B9: Export
B10: Sales | C10: 237.80973 | D10: 667.51415 | E10: 1622.381 | F10: 3222.781 | G10: 3356.4224 | H10: ='Revenue Bridge'!H10 -> 3642.7859 | I10: ='Revenue Bridge'!I10 -> 4456.0709 | J10: ='Revenue Bridge'!J10 -> 4720.6741 | K10: ='Revenue Bridge'!K10 -> 4947.472 | L10: ='Revenue Bridge'!L10 -> 5142.5129
B11: Services | C11: 64.142523 | D11: 82.884935 | E11: 431.19609 | F11: 623.6973 | G11: 458.57954 | H11: ='Revenue Bridge'!H11 -> 472.33693 | I11: ='Revenue Bridge'!I11 -> 486.50704 | J11: ='Revenue Bridge'!J11 -> 501.10225 | K11: ='Revenue Bridge'!K11 -> 516.13532 | L11: ='Revenue Bridge'!L11 -> 531.61938
B12: Total Export Sales | C12: =SUM(C10:C11) -> 301.95225 | D12: =SUM(D10:D11) -> 750.39909 | E12: =SUM(E10:E11) -> 2053.5771 | F12: =SUM(F10:F11) -> 3846.4783 | G12: =SUM(G10:G11) -> 3815.0019 | H12: =SUM(H10:H11) -> 4115.1228 | I12: =SUM(I10:I11) -> 4942.5779 | J12: =SUM(J10:J11) -> 5221.7763 | ... L12: =SUM(L10:L11) -> 5674.1322
B13: Total Revenue | C13: =C8+C12 -> 2448.6314 | D13: =D8+D12 -> 4675.0028 | E13: =E8+E12 -> 6042.8313 | F13: =F8+F12 -> 8729.7828 | G13: =G8+G12 -> 12447.32 | H13: =H8+H12 -> 14726.167 | I13: =I8+I12 -> 16143.641 | J13: =J8+J12 -> 17268.587 | ... L13: =L8+L12 -> 19302.88
B14: rev YOY | D14: =('Financial Statements'!E4-'Financial Statements'!D4)/'Financial Statements'!D4 -> 0.90923097 | E14: =('Financial Statements'!F4-'Financial Statements'!E4)/'Financial Statements'!E4 -> 0.29258346 | F14: =('Financial Statements'!G4-'Financial Statements'!F4)/'Financial Statements'!F4 -> 0.44465108 | G14: =('Financial Statements'!H4-'Financial Statements'!G4)/'Financial Statements'!G4 -> 0.42584533 | H14: =('Financial Statements'!I4-'Financial Statements'!H4)/'Financial Statements'!H4 -> 0.18307931 | I14: =('Financial Statements'!J4-'Financial Statements'!I4)/'Financial Statements'!I4 -> 0.096255509 | J14: =('Financial Statements'!K4-'Financial Statements'!J4)/'Financial Statements'!J4 -> 0.069683522 | K14: =('Financial Statements'!L4-'Financial Statements'!K4)/'Financial Statements'!K4 -> 0.058347329 | L14: =('Financial Statements'!M4-'Financial Statements'!L4)/'Financial Statements'!L4 -> 0.056177916
B15: Services % of total | C15: =(C7+C11)/C13 -> 0.063995768 | D15: =(D7+D11)/D13 -> 0.039774056 | E15: =(E7+E11)/E13 -> 0.085062165 | F15: =(F7+F11)/F13 -> 0.092043816 | G15: =(G7+G11)/G13 -> 0.059486145 | H15: =(H7+H11)/H13 -> 0.051789199 | I15: =(I7+I11)/I13 -> 0.048659163 | J15: =(J7+J11)/J13 -> 0.046853987 | ... L15: =(L7+L11)/L13 -> 0.044468829
B16: Sales % of total | C16: =(C6+C10)/C13 -> 0.93600423 | D16: =(D6+D10)/D13 -> 0.96022594 | E16: =(E6+E10)/E13 -> 0.91493784 | F16: =(F6+F10)/F13 -> 0.90795618 | G16: =(G6+G10)/G13 -> 0.94051385 | H16: =(H6+H10)/H13 -> 0.9482108 | I16: =(I6+I10)/I13 -> 0.95134084 | J16: =(J6+J10)/J13 -> 0.95314601 | ... L16: =(L6+L10)/L13 -> 0.95553117
B18: Cost of Sales
B19: Raw materials | C19: 1705.51 | D19: 3118.7494 | E19: 3779.8177 | F19: 5225.344 | G19: 5698.1847 | H19: ='COGS Bridge'!I5 -> 6474.3241 | I19: ='COGS Bridge'!J5 -> 7008.5278 | J19: ='COGS Bridge'!K5 -> 7494.7175 | K19: ='COGS Bridge'!L5 -> 7938.1413 | L19: ='COGS Bridge'!M5 -> 8400.9751
B20: Depreciation | C20: 215.82438 | D20: 205.95811 | E20: 212.76065 | F20: 217.7172 | G20: 254.76555 | H20: ='COGS Bridge'!I6 -> 0 | I20: ='COGS Bridge'!J6 -> 0 | J20: ='COGS Bridge'!K6 -> 0 | K20: ='COGS Bridge'!L6 -> 0 | L20: ='COGS Bridge'!M6 -> 0
B21: Amortization of Licenses, Intangible assets | C21: 34.624973 | D21: 28.156249 | E21: 28.156249 | F21: 28.156249 | G21: 28.156249 | H21: ='COGS Bridge'!I7 -> 0 | I21: ='COGS Bridge'!J7 -> 0 | J21: ='COGS Bridge'!K7 -> 0 | K21: ='COGS Bridge'!L7 -> 0 | L21: ='COGS Bridge'!M7 -> 0
B22: Amortization of right of use | C22: 5.902848 | D22: 5.487561 | E22: 6.891333 | F22: 7.082414 | G22: 2.525364 | H22: ='COGS Bridge'!I8 -> 0 | I22: ='COGS Bridge'!J8 -> 0 | J22: ='COGS Bridge'!K8 -> 0 | K22: ='COGS Bridge'!L8 -> 0 | L22: ='COGS Bridge'!M8 -> 0
B23: Transportation costs | C23: 114.65141 | D23: 165.49009 | E23: 498.18933 | F23: 792.24221 | G23: 764.27933 | H23: ='COGS Bridge'!I9 -> 865.1642 | I23: ='COGS Bridge'!J9 -> 961.19743 | J23: ='COGS Bridge'!K9 -> 1039.0544 | K23: ='COGS Bridge'!L9 -> 1103.4758 | L23: ='COGS Bridge'!M9 -> 1163.0635
B24: Overhead costs | C24: 204.57001 | D24: 265.97482 | E24: 233.99995 | F24: 372.4304 | G24: 641.14321 | H24: ='COGS Bridge'!I10 -> 725.77411 | I24: ='COGS Bridge'!J10 -> 806.33504 | J24: ='COGS Bridge'!K10 -> 871.64818 | K24: ='COGS Bridge'!L10 -> 925.69036 | L24: ='COGS Bridge'!M10 -> 975.67764
B25: Total | C25: =SUM(C19:C24) -> 2281.0836 | D25: =SUM(D19:D24) -> 3789.8162 | E25: =SUM(E19:E24) -> 4759.8152 | F25: =SUM(F19:F24) -> 6642.9725 | G25: =SUM(G19:G24) -> 7389.0544 | H25: =SUM(H19:H24) -> 8065.2624 | I25: =SUM(I19:I24) -> 8776.0602 | J25: =SUM(J19:J24) -> 9405.4201 | ... L25: =SUM(L19:L24) -> 10539.716
B26: cost YOY | D26: =('Financial Statements'!E5-'Financial Statements'!D5)/'Financial Statements'!D5 -> 0.75342484 | E26: =('Financial Statements'!F5-'Financial Statements'!E5)/'Financial Statements'!E5 -> 0.27091116 | F26: =('Financial Statements'!G5-'Financial Statements'!F5)/'Financial Statements'!F5 -> 0.4162249 | G26: =('Financial Statements'!H5-'Financial Statements'!G5)/'Financial Statements'!G5 -> 0.11167274 | H26: =('Financial Statements'!I5-'Financial Statements'!H5)/'Financial Statements'!H5 -> 0.13537561 | I26: =('Financial Statements'!J5-'Financial Statements'!I5)/'Financial Statements'!I5 -> 0.088130769 | J26: =('Financial Statements'!K5-'Financial Statements'!J5)/'Financial Statements'!J5 -> 0.071713254 | K26: =('Financial Statements'!L5-'Financial Statements'!K5)/'Financial Statements'!K5 -> 0.059740804 | L26: =('Financial Statements'!M5-'Financial Statements'!L5)/'Financial Statements'!L5 -> 0.057428635
B28: General & Administrative Expenses
B29: Professional services | C29: 15.94042 | D29: 21.611801 | E29: 23.08047 | F29: 27.516804 | G29: 29.752555 | H29: =G29*(1+Assumptions!J8) -> 33.679892 | I29: =H29*(1+Assumptions!K8) -> 37.41836 | J29: =I29*(1+Assumptions!L8) -> 40.449247 | K29: =J29*(1+Assumptions!M8) -> 42.957101 | L29: =K29*(1+Assumptions!N8) -> 45.276784
B30: Salaries and wages | C30: 29.372277 | D30: 37.393849 | E30: 74.139823 | F30: 124.88201 | G30: 178.98118 | H30: =G30*(1+Assumptions!J8) -> 202.6067 | I30: =H30*(1+Assumptions!K8) -> 225.09604 | J30: =I30*(1+Assumptions!L8) -> 243.32882 | K30: =J30*(1+Assumptions!M8) -> 258.41521 | L30: =K30*(1+Assumptions!N8) -> 272.36963
B31: Security and cleaning services | C31: 1.415022 | D31: 1.410636 | E31: 2.428688 | F31: 4.738183 | G31: 3.2704 | H31: =G31*(1+Assumptions!J8) -> 3.7020928 | I31: =H31*(1+Assumptions!K8) -> 4.1130251 | J31: =I31*(1+Assumptions!L8) -> 4.4461801 | K31: =J31*(1+Assumptions!M8) -> 4.7218433 | L31: =K31*(1+Assumptions!N8) -> 4.9768228
B32: Rentals | C32: 0.780775 | D32: 0.131736 | E32: 0.502419 | F32: 2.110584 | G32: 3.132247 | H32: =G32*(1+10%) -> 3.4454717 | I32: =H32*(1+10%) -> 3.7900189 | J32: =I32*(1+10%) -> 4.1690208 | K32: =J32*(1+10%) -> 4.5859228 | L32: =K32*(1+10%) -> 5.0445151
B33: Transportation costs | C33: 1.768887 | D33: 3.503839 | E33: 7.153216 | F33: 12.440064 | G33: 9.713478 | H33: =G33*(1+Assumptions!J8) -> 10.995657 | I33: =H33*(1+Assumptions!K8) -> 12.216175 | J33: =I33*(1+Assumptions!L8) -> 13.205685 | K33: =J33*(1+Assumptions!M8) -> 14.024438 | L33: =K33*(1+Assumptions!N8) -> 14.781757
B34: Advertising | C34: 1.240353 | D34: 2.221255 | E34: 3.401355 | F34: 4.677984 | G34: 7.803161 | H34: =H38*'Financial Statements'!I4 -> 7.8912356 | I34: =I38*'Financial Statements'!J4 -> 8.6508105 | J34: =J38*'Financial Statements'!K4 -> 9.2536294 | K34: =K38*'Financial Statements'!L4 -> 9.793554 | L34: =L38*'Financial Statements'!M4 -> 10.343735
B35: Depreciation | C35: 2.10511 | D35: 2.256901 | E35: 2.61629 | F35: 3.84566 | G35: 4.324134
B36: Other expenses | C36: 28.447616 | D36: 46.447966 | E36: 70.618015 | F36: 87.586815 | G36: 147.35568 | H36: =H39*'Financial Statements'!I4 -> 171.0851 | I36: =I39*'Financial Statements'!J4 -> 187.55298 | J36: =J39*'Financial Statements'!K4 -> 200.62233 | K36: =K39*'Financial Statements'!L4 -> 212.32811 | L36: =L39*'Financial Statements'!M4 -> 224.25626
B37: Total | C37: =IF('Financial Statements'!$N$1="Core",SUM(IS!C29:C36),SUM(IS!C29:C36,IS!C40)) -> 81.07046 | D37: =IF('Financial Statements'!$N$1="Core",SUM(IS!D29:D36),SUM(IS!D29:D36,IS!D40)) -> 114.97798 | E37: =IF('Financial Statements'!$N$1="Core",SUM(IS!E29:E36),SUM(IS!E29:E36,IS!E40)) -> 183.94028 | F37: =IF('Financial Statements'!$N$1="Core",SUM(IS!F29:F36),SUM(IS!F29:F36,IS!F40)) -> 267.7981 | G37: =IF('Financial Statements'!$N$1="Core",SUM(IS!G29:G36),SUM(IS!G29:G36,IS!G40)) -> 384.33283 | H37: =IF('Financial Statements'!$N$1="Core",SUM(IS!H29:H36),SUM(IS!H29:H36,IS!H40)) -> 433.40615 | I37: =IF('Financial Statements'!$N$1="Core",SUM(IS!I29:I36),SUM(IS!I29:I36,IS!I40)) -> 478.83741 | J37: =IF('Financial Statements'!$N$1="Core",SUM(IS!J29:J36),SUM(IS!J29:J36,IS!J40)) -> 515.47492 | ... L37: =IF('Financial Statements'!$N$1="Core",SUM(IS!L29:L36),SUM(IS!L29:L36,IS!L40)) -> 577.04951
B38: Advertising % of sales | C38: =C34/'Financial Statements'!D4 -> 0.00050654951 | D38: =D34/'Financial Statements'!E4 -> 0.00047513447 | E38: =E34/'Financial Statements'!F4 -> 0.00056287439 | F38: =F34/'Financial Statements'!G4 -> 0.00053586488 | G38: =G34/'Financial Statements'!H4 -> 0.00062689486 | H38: =MEDIAN(C38:G38) -> 0.00053586488 | I38: =H38 -> 0.00053586488 | J38: =I38 -> 0.00053586488 | K38: =J38 -> 0.00053586488 | L38: =K38 -> 0.00053586488
B39: Other expenses % of sales | C39: =C36/'Financial Statements'!D4 -> 0.011617762 | D39: =D36/'Financial Statements'!E4 -> 0.0099353878 | E39: =E36/'Financial Statements'!F4 -> 0.011686246 | F39: =F36/'Financial Statements'!G4 -> 0.010033104 | G39: =G36/'Financial Statements'!H4 -> 0.011838346 | H39: =MEDIAN(C39:G39) -> 0.011617762 | I39: =H39 -> 0.011617762 | J39: =I39 -> 0.011617762 | K39: =J39 -> 0.011617762 | L39: =K39 -> 0.011617762
B40: Carbon & CBAM Compliance Costs | C40: 0 | D40: 0 | E40: 0 | F40: 0 | G40: 0 | H40: =IF('Financial Statements'!$N$1="Core",0,'ESG Integration'!I87) -> 0 | I40: =IF('Financial Statements'!$N$1="Core",0,'ESG Integration'!J87) -> 0 | J40: =IF('Financial Statements'!$N$1="Core",0,'ESG Integration'!K87) -> 0 | K40: =IF('Financial Statements'!$N$1="Core",0,'ESG Integration'!L87) -> 0 | L40: =IF('Financial Statements'!$N$1="Core",0,'ESG Integration'!M87) -> 0
B42: Provisions
B43: Beg. balance | C43: 18.500287 | D43: =C46 -> 25.797396 | E43: =D46 -> 63.871019 | F43: =E46 -> 54.445334 | G43: =F46 -> 77.899139 | H43: =G46 -> 111.68412 | I43: =H46 -> 199.16177 | J43: =I46 -> 294.60036 | K43: =J46 -> 396.20126 | L43: =K46 -> 503.22504
B44: Formed during the year | C44: 7.368018 | D44: 111.93989 | E44: 15.220195 | F44: 56.05295 | G44: 74.505707 | H44: =H47*'Financial Statements'!I4 -> 88.14616 | I44: =I47*'Financial Statements'!J4 -> 96.630714 | J44: =J47*'Financial Statements'!K4 -> 103.36428 | K44: =K47*'Financial Statements'!L4 -> 109.39531 | L44: =L47*'Financial Statements'!M4 -> 115.54091
B45: Used during year | C45: -0.070909 | D45: -73.866262 | E45: -24.64588 | F45: -32.599145 | G45: -40.72073 | H45: =-H47*H43 -> -0.66850567 | I45: =-I47*I43 -> -1.1921191 | J45: =-J47*J43 -> -1.7633843 | K45: =-K47*K43 -> -2.371535 | L45: =-L47*L43 -> -3.0121454
B46: Ending balance | C46: =SUM(C43:C45) -> 25.797396 | D46: =SUM(D43:D45) -> 63.871019 | E46: =SUM(E43:E45) -> 54.445334 | F46: =SUM(F43:F45) -> 77.899139 | G46: =SUM(G43:G45) -> 111.68412 | H46: =SUM(H43:H45) -> 199.16177 | I46: =SUM(I43:I45) -> 294.60036 | J46: =SUM(J43:J45) -> 396.20126 | ... L46: =SUM(L43:L45) -> 615.75381
B47: % of sales | C47: =C44/'Financial Statements'!D4 -> 0.0030090352 | D47: =D44/'Financial Statements'!E4 -> 0.023944346 | E47: =E44/'Financial Statements'!F4 -> 0.0025187191 | F47: =F44/'Financial Statements'!G4 -> 0.0064208871 | G47: =G44/'Financial Statements'!H4 -> 0.0059856826 | H47: =G47 -> 0.0059856826 | I47: =H47 -> 0.0059856826 | J47: =I47 -> 0.0059856826 | K47: =J47 -> 0.0059856826 | L47: =K47 -> 0.0059856826
B48: Used % of beg. | C48: =-C45/C43 -> 0.0038328595 | D48: =-D45/D43 -> 2.8633224 | E48: =-E45/E43 -> 0.38586953 | F48: =-F45/F43 -> 0.59875002 | G48: =-G45/G43 -> 0.52273659 | H48: =HARMEAN(C48:G48) -> 0.018696777 | I48: =H48 -> 0.018696777 | J48: =I48 -> 0.018696777 | K48: =J48 -> 0.018696777 | L48: =K48 -> 0.018696777
B50: Expected Credit Losses on Trade Receivables
B51: Beg. balance | C51: 2.51272 | D51: =C55 -> 2.51272 | E51: =D55 -> 3.21272 | F51: =E55 -> 5.142081 | G51: =F55 -> 4.035629 | H51: =G55 -> 7.639192 | I51: =H55 -> 10.20125 | J51: =I55 -> 13.00992 | K51: =J55 -> 16.014309 | L51: =K55 -> 19.193995
B52: ECL for the year | C52: 0 | D52: 0.7 | E52: 4.745753 | F52: 0 | G52: 3.603563 | H52: =H56*'Financial Statements'!I50 -> 2.5620581 | I52: =I56*'Financial Statements'!J50 -> 2.8086703 | J52: =J56*'Financial Statements'!K50 -> 3.0043884 | K52: =K56*'Financial Statements'!L50 -> 3.1796864 | L52: =L56*'Financial Statements'!M50 -> 3.3583146
B53: Used during year | C53: 0 | D53: 0 | E53: -2.816392 | F53: 0 | G53: 0
B54: Reversal of ECL on T/R | C54: 0 | D54: 0 | E54: 0 | F54: -1.106452 | G54: 0
B55: Ending balance | C55: =SUM(C51:C54) -> 2.51272 | D55: =SUM(D51:D54) -> 3.21272 | E55: =SUM(E51:E54) -> 5.142081 | F55: =SUM(F51:F54) -> 4.035629 | G55: =SUM(G51:G54) -> 7.639192 | H55: =SUM(H51:H54) -> 10.20125 | I55: =SUM(I51:I54) -> 13.00992 | J55: =SUM(J51:J54) -> 16.014309 | ... L55: =SUM(L51:L54) -> 22.55231
B56: ECL % of AR | C56: =C52/'Financial Statements'!D50 -> 0 | D56: =D52/'Financial Statements'!E50 -> 0.008798958 | E56: =E52/'Financial Statements'!F50 -> 0.020758628 | F56: =F52/'Financial Statements'!G50 -> 0 | G56: =G52/'Financial Statements'!H50 -> 0.014743539 | H56: =AVERAGE(C56:G56) -> 0.0088602249 | I56: =H56 -> 0.0088602249 | J56: =I56 -> 0.0088602249 | K56: =J56 -> 0.0088602249 | L56: =K56 -> 0.0088602249
B58: Investment in a joint venture
B59: Impairment losses on IJV | C59: 0 | D59: 0 | E59: -0.78 | F59: 0 | G59: 0
B60: Reversal for impairment | C60: 0 | D60: 0 | E60: 0 | F60: 0.78 | G60: 0
B61: Gain on disposal | C61: 0 | D61: 0 | E61: 0 | F61: 1.27 | G61: 0
B62: Share of loss | C62: 0.068872 | D62: =0.045915+0.001249 -> 0.047164 | E62: -1.789276 | F62: 0 | G62: 0
B63: Total | C63: =SUM(C59:C62) -> 0.068872 | D63: =SUM(D59:D62) -> 0.047164 | E63: =SUM(E59:E62) -> -2.569276 | F63: =SUM(F59:F62) -> 2.05 | G63: =SUM(G59:G62) -> 0
B65: Interest Income
C66: 0.743822 | D66: 9.96778 | E66: 30.813502 | F66: 56.458493 | G66: 226.27478 | H66: =H67*'Financial Statements'!I4 -> 267.70101 | I66: =I67*'Financial Statements'!J4 -> 293.46871 | J66: =J67*'Financial Statements'!K4 -> 313.91864 | K66: =K67*'Financial Statements'!L4 -> 332.23496 | L66: =L67*'Financial Statements'!M4 -> 350.89922
B67: % of sales | C67: =C66/C13 -> 0.00030377051 | D67: =D66/D13 -> 0.0021321442 | E67: =E66/E13 -> 0.0050991829 | F67: =F66/F13 -> 0.0064673422 | G67: =G66/G13 -> 0.018178594 | H67: =G67 -> 0.018178594 | I67: =H67 -> 0.018178594 | J67: =I67 -> 0.018178594 | K67: =J67 -> 0.018178594 | L67: =K67 -> 0.018178594
B69: Other Income
C70: 46.323288 | D70: 104.2275 | E70: 14.913053 | F70: 18.292936 | G70: 53.339508 | H70: =H71*'Financial Statements'!I4 -> 63.104868 | I70: =I71*'Financial Statements'!J4 -> 69.179059 | J70: =J71*'Financial Statements'!K4 -> 73.9997 | K70: =K71*'Financial Statements'!L4 -> 78.317385 | L70: =L71*'Financial Statements'!M4 -> 82.717092
B71: % of sales | C71: =C70/C13 -> 0.018918033 | D71: =D70/D13 -> 0.022294639 | E71: =E70/E13 -> 0.0024678916 | F71: =F70/F13 -> 0.0020954629 | G71: =G70/G13 -> 0.0042852202 | H71: =MEDIAN(C71:G71) -> 0.0042852202 | I71: =H71 -> 0.0042852202 | J71: =I71 -> 0.0042852202 | K71: =J71 -> 0.0042852202 | L71: =K71 -> 0.0042852202
B73: Finance Costs
B74: Loan interest expense | C74: 35.222555 | D74: 36.391375 | E74: 32.100606 | F74: 2.754107 | G74: 24.61313 | H74: =Debt!H25+Debt!H33 -> 70.6347 | I74: =Debt!I25+Debt!I33 -> 69.060007 | J74: =Debt!J25+Debt!J33 -> 50.911301 | K74: =Debt!K25+Debt!K33 -> 32.762596 | L74: =Debt!L25+Debt!L33 -> 14.61389
B75: Electricity agreement intereset | C75: 0.57275
B76: lease liability interest | C76: 2.546832 | D76: 1.05921 | E76: 1.296489 | F76: 1.237302 | G76: 1.162675 | H76: =Debt!H59 -> 0.25954119 | I76: =Debt!I59 -> 0.20086939 | J76: =Debt!J59 -> 0.15546091 | K76: =Debt!K59 -> 0.12031746 | L76: =Debt!L59 -> 0.09311853
B77: Finance interest on long-term & notes payable | C77: 0.205127 | D77: 0.588878 | E77: 0.933823 | F77: 1.244481 | G77: 1.058558 | H77: =MEDIAN(C77:G77) -> 0.933823 | I77: =H77 -> 0.933823 | J77: =I77 -> 0.933823 | K77: =J77 -> 0.933823 | L77: =K77 -> 0.933823
B78: Credit facilities interest expense | C78: 31.57895 | D78: 20.041757 | E78: 42.648335 | F78: 85.953026 | G78: 23.00737 | H78: =Debt!H43*(0.6%+Assumptions!J13) -> 26.29667 | I78: =Debt!I43*(0.6%+Assumptions!K13) -> 21.373977 | J78: =Debt!J43*(0.6%+Assumptions!L13) -> 19.754843 | K78: =Debt!K43*(0.6%+Assumptions!M13) -> 17.603336 | L78: =Debt!L43*(0.6%+Assumptions!N13) -> 18.606045
B79: Total | C79: =SUM(C74:C78) -> 70.126214 | D79: =SUM(D74:D78) -> 58.08122 | E79: =SUM(E74:E78) -> 76.979253 | F79: =SUM(F74:F78) -> 91.188916 | G79: =SUM(G74:G78) -> 49.841733 | H79: =SUM(H74:H78) -> 98.124734 | I79: =SUM(I74:I78) -> 91.568676 | J79: =SUM(J74:J78) -> 71.755428 | ... L79: =SUM(L74:L78) -> 34.246877
B80: % of Total Debt | C80: =C79/AVERAGE(B81:C81) -> 0.10888677 | D80: =D79/AVERAGE(C81:D81) -> 0.085487765 | E80: =E79/AVERAGE(D81:E81) -> 0.18865478 | F80: =F79/AVERAGE(E81:F81) -> 0.21023836 | G80: =G79/AVERAGE(F81:G81) -> 0.052429256 | H80: =H79/AVERAGE(G81:H81) -> 0.086172199 | I80: =I79/AVERAGE(H81:I81) -> 0.090098339 | J80: =J79/AVERAGE(I81:J81) -> 0.093986824 | ... L80: =L79/AVERAGE(K81:L81) -> 0.12054651
C81: ='Financial Statements'!D66+'Financial Statements'!D68+'Financial Statements'!D74+'Financial Statements'!D76+'Financial Statements'!D77 -> 644.02877 | D81: ='Financial Statements'!E66+'Financial Statements'!E68+'Financial Statements'!E74+'Financial Statements'!E76+'Financial Statements'!E77 -> 714.79071 | E81: ='Financial Statements'!F66+'Financial Statements'!F68+'Financial Statements'!F74+'Financial Statements'!F76+'Financial Statements'!F77 -> 101.29518 | F81: ='Financial Statements'!G66+'Financial Statements'!G68+'Financial Statements'!G74+'Financial Statements'!G76+'Financial Statements'!G77 -> 766.18604 | G81: ='Financial Statements'!H66+'Financial Statements'!H68+'Financial Statements'!H74+'Financial Statements'!H76+'Financial Statements'!H77 -> 1135.1087 | H81: ='Financial Statements'!I66+'Financial Statements'!I68+'Financial Statements'!I74+'Financial Statements'!I76+'Financial Statements'!I77 -> 1142.3018 | I81: ='Financial Statements'!J66+'Financial Statements'!J68+'Financial Statements'!J74+'Financial Statements'!J76+'Financial Statements'!J77 -> 890.33668 | J81: ='Financial Statements'!K66+'Financial Statements'!K68+'Financial Statements'!K74+'Financial Statements'!K76+'Financial Statements'!K77 -> 636.58859 | ... L81: ='Financial Statements'!M66+'Financial Statements'!M68+'Financial Statements'!M74+'Financial Statements'!M76+'Financial Statements'!M77 -> 186.40923
B83: Gain on disposal of Fixed Assets | C83: 0.12 | D83: 0.2 | E83: 0.087675 | F83: 0 | G83: 1.14
B84: Foreign Currency exchange differences | C84: 1.060989 | D84: 192.05848 | E84: 115.14417 | F84: 243.81213 | G84: 101.57824
B86: Income Tax
B87: Current income tax for the year | C87: 43.280867 | D87: 198.14876 | E87: 216.7159 | F87: 374.0144 | G87: 1102.2591
B88: current income tax related to prior years | C88: 0 | D88: 0 | E88: 0 | F88: 12.788222 | G88: 9.039382
B89: total current income tax | C89: =SUM(C87:C88) -> 43.280867 | D89: =SUM(D87:D88) -> 198.14876 | E89: =SUM(E87:E88) -> 216.7159 | F89: =SUM(F87:F88) -> 386.80262 | G89: =SUM(G87:G88) -> 1111.2985
B90: Deferred tax for the year | C90: -22.29218 | D90: -35.271117 | E90: 16.016906 | F90: -41.071622 | G90: 14.169166
B91: Total Tax | C91: =C89+C90 -> 20.988687 | D91: =D89+D90 -> 162.87764 | E91: =E89+E90 -> 232.7328 | F91: =F89+F90 -> 345.731 | G91: =G89+G90 -> 1125.4677 | H91: ='Financial Statements'!I25*IS!H92 -> 1355.8764 | I91: ='Financial Statements'!J25*IS!I92 -> 1508.7058 | J91: ='Financial Statements'!K25*IS!J92 -> 1617.0567 | K91: ='Financial Statements'!L25*IS!K92 -> 1721.9137 | L91: ='Financial Statements'!M25*IS!L92 -> 1820.2878
B92: Tax Rate | C92: 0.225 | D92: 0.225 | E92: 0.225 | F92: 0.225 | G92: 0.225 | H92: 0.225 | I92: 0.225 | J92: 0.225 | K92: 0.225 | L92: 0.225
B94: Bad debt | D94: -0.00681

Sheet BS
B2: Footnotes BD | C2: 2021 | D2: =C2+1 -> 2022 | E2: =D2+1 -> 2023 | F2: =E2+1 -> 2024 | G2: =F2+1 -> 2025 | H2: =G2+1 -> 2026 | I2: =H2+1 -> 2027 | J2: =I2+1 -> 2028 | K2: =J2+1 -> 2029 | L2: =K2+1 -> 2030
B3: Assets BD
B4: Fixed Assets
B5: Beg. Balance
B6: Freehold Land | C6: 50.243436 | D6: =C54 -> 50.243436 | E6: =D54 -> 50.243436 | F6: =E54 -> 50.243436 | G6: =F54 -> 50.243436 | H6: =G54 -> 50.243436 | I6: =H54 -> 50.243436 | J6: =I54 -> 50.243436 | K6: =J54 -> 50.243436 | L6: =K54 -> 50.243436
B7: Buildings | C7: 636.36164 | D7: =C55 -> 662.06626 | E7: =D55 -> 669.65322 | F7: =E55 -> 695.14882 | G7: =F55 -> 731.93125 | H7: =G55 -> 914.33184 | I7: =H55 -> 1018.0241 | J7: =I55 -> 1131.6974 | K7: =J55 -> 1253.2918 | L7: =K55 -> 1381.9809
B8: Vehicles | C8: 46.283623 | D8: =C56 -> 47.674756 | E8: =D56 -> 61.176691 | F8: =E56 -> 67.485657 | G8: =F56 -> 182.24758 | H8: =G56 -> 239.96017 | I8: =H56 -> 306.53404 | J8: =I56 -> 379.51602 | K8: =J56 -> 457.58364 | L8: =K56 -> 540.20629
B9: Machinery & Equipment | C9: 2875.1717 | D9: =C57 -> 2882.4983 | E9: =D57 -> 2886.6432 | F9: =E57 -> 2903.4066 | G9: =F57 -> 2942.8895 | H9: =G57 -> 3798.0515 | I9: =H57 -> 4236.0496 | J9: =I57 -> 4286.9753 | K9: =J57 -> 4341.4498 | L9: =K57 -> 4399.1027
B10: Furniture & Fixtures | C10: 15.765021 | D10: =C58 -> 15.836471 | E10: =D58 -> 15.892264 | F10: =E58 -> 17.375697 | G10: =F58 -> 20.188085 | H10: =G58 -> 22.238758 | I10: =H58 -> 24.516921 | J10: =I58 -> 27.01437 | K10: =J58 -> 29.685851 | L10: =K58 -> 32.513204
B11: Other Installations | C11: 303.17949 | D11: =C59 -> 303.43283 | E11: =D59 -> 304.06282 | F11: =E59 -> 308.45338 | G11: =F59 -> 320.11178 | H11: =G59 -> 327.44967 | I11: =H59 -> 334.01992 | J11: =I59 -> 341.22259 | K11: =J59 -> 348.92717 | L11: =K59 -> 357.0813
B12: Computers & Software | C12: 21.679132 | D12: =C60 -> 22.362299 | E12: =D60 -> 23.5171 | F12: =E60 -> 28.093778 | G12: =F60 -> 30.182102 | H12: =G60 -> 37.134556 | I12: =H60 -> 43.26405 | J12: =I60 -> 49.983542 | K12: =J60 -> 57.171271 | L12: =K60 -> 64.778385
B13: Total | C13: =SUM(C6:C12) -> 3948.684 | D13: =SUM(D6:D12) -> 3984.1144 | E13: =SUM(E6:E12) -> 4011.1887 | F13: =SUM(F6:F12) -> 4070.2074 | G13: =SUM(G6:G12) -> 4277.7937 | H13: =SUM(H6:H12) -> 5389.41 | I13: =SUM(I6:I12) -> 6012.6521 | J13: =SUM(J6:J12) -> 6266.6527 | ... L13: =SUM(L6:L12) -> 6825.9062
B15: Additions
B16: =B6 -> Freehold Land | C16: 0 | D16: 0 | E16: 0 | F16: 0 | G16: 0 | H16: =H25*'Financial Statements'!I$4 -> 0 | I16: =I25*'Financial Statements'!J$4 -> 0 | J16: =J25*'Financial Statements'!K$4 -> 0 | K16: =K25*'Financial Statements'!L$4 -> 0 | L16: =L25*'Financial Statements'!M$4 -> 0
B17: =B7 -> Buildings | C17: 25.704619 | D17: 7.586965 | E17: 25.495598 | F17: 36.782424 | G17: 182.4006 | H17: =H26*'Financial Statements'!I$4 -> 103.69229 | I17: =I26*'Financial Statements'!J$4 -> 113.67325 | J17: =J26*'Financial Statements'!K$4 -> 121.5944 | K17: =K26*'Financial Statements'!L$4 -> 128.68911 | L17: =L26*'Financial Statements'!M$4 -> 135.9186
B18: =B8 -> Vehicles | C18: 1.831833 | D18: 13.501935 | E18: 7.080896 | F18: 114.76192 | G18: 57.878966 | H18: =H27*'Financial Statements'!I$4 -> 66.573874 | I18: =I27*'Financial Statements'!J$4 -> 72.981976 | J18: =J27*'Financial Statements'!K$4 -> 78.067617 | K18: =K27*'Financial Statements'!L$4 -> 82.622654 | L18: =L27*'Financial Statements'!M$4 -> 87.264222
B19: =B9 -> Machinery & Equipment | C19: 3.899559 | D19: 4.444885 | E19: 17.040662 | F19: 39.482876 | G19: 73.272624 | H19: =H28*'Financial Statements'!I$4 -> 46.454283 | I19: =I28*'Financial Statements'!J$4 -> 50.925764 | J19: =J28*'Financial Statements'!K$4 -> 54.47445 | K19: =K28*'Financial Statements'!L$4 -> 57.652889 | L19: =L28*'Financial Statements'!M$4 -> 60.891708
B20: =B10 -> Furniture & Fixtures | C20: 0.07145 | D20: 0.055793 | E20: 1.483433 | F20: 2.812388 | G20: 2.050673 | H20: =H29*'Financial Statements'!I$4 -> 2.2781633 | I20: =I29*'Financial Statements'!J$4 -> 2.4974491 | J20: =J29*'Financial Statements'!K$4 -> 2.6714801 | K20: =K29*'Financial Statements'!L$4 -> 2.8273539 | L20: =L29*'Financial Statements'!M$4 -> 2.9861887
B21: =B11 -> Other Installations | C21: 0.253335 | D21: 0.629997 | E21: 1.130954 | F21: 10.614696 | G21: 7.33789 | H21: =H30*'Financial Statements'!I$4 -> 6.57025 | I21: =I30*'Financial Statements'!J$4 -> 7.2026728 | J21: =J30*'Financial Statements'!K$4 -> 7.7045804 | K21: =K30*'Financial Statements'!L$4 -> 8.1541221 | L21: =L30*'Financial Statements'!M$4 -> 8.6122037
B22: =B12 -> Computers & Software | C22: 0.683167 | D22: 1.154801 | E22: 4.576678 | F22: 2.088324 | G22: 6.952454 | H22: =H31*'Financial Statements'!I$4 -> 6.129494 | I22: =I31*'Financial Statements'!J$4 -> 6.7194916 | J22: =J31*'Financial Statements'!K$4 -> 7.1877295 | K22: =K31*'Financial Statements'!L$4 -> 7.6071143 | L22: =L31*'Financial Statements'!M$4 -> 8.0344661
B23: =B13 -> Total | C23: =SUM(C16:C22) -> 32.443963 | D23: =SUM(D16:D22) -> 27.374376 | E23: =SUM(E16:E22) -> 56.808221 | F23: =SUM(F16:F22) -> 206.54263 | G23: =SUM(G16:G22) -> 329.8932 | H23: =SUM(H16:H22) -> 231.69836 | I23: =SUM(I16:I22) -> 254.0006 | J23: =SUM(J16:J22) -> 271.70026 | ... L23: =SUM(L16:L22) -> 303.70738
B25: =B16 -> Freehold Land | C25: =IFERROR(C16/'Financial Statements'!D$4,0) -> 0 | D25: =IFERROR(D16/'Financial Statements'!E$4,0) -> 0 | E25: =IFERROR(E16/'Financial Statements'!F$4,0) -> 0 | F25: =IFERROR(F16/'Financial Statements'!G$4,0) -> 0 | G25: =IFERROR(G16/'Financial Statements'!H$4,0) -> 0 | H25: =G25 -> 0 | I25: =H25 -> 0 | J25: =I25 -> 0 | K25: =J25 -> 0 | L25: =K25 -> 0
B26: =B17 -> Buildings | C26: =IFERROR(C17/'Financial Statements'!D$4,0) -> 0.010497545 | D26: =IFERROR(D17/'Financial Statements'!E$4,0) -> 0.0016228792 | E26: =IFERROR(E17/'Financial Statements'!F$4,0) -> 0.0042191477 | F26: =IFERROR(F17/'Financial Statements'!G$4,0) -> 0.0042134409 | G26: =IFERROR(G17/'Financial Statements'!H$4,0) -> 0.014653804 | H26: =AVERAGE(C26:G26) -> 0.0070413636 | I26: =H26 -> 0.0070413636 | J26: =I26 -> 0.0070413636 | K26: =J26 -> 0.0070413636 | L26: =K26 -> 0.0070413636
B27: =B18 -> Vehicles | C27: =IFERROR(C18/'Financial Statements'!D$4,0) -> 0.00074810485 | D27: =IFERROR(D18/'Financial Statements'!E$4,0) -> 0.0028881127 | E27: =IFERROR(E18/'Financial Statements'!F$4,0) -> 0.0011717845 | F27: =IFERROR(F18/'Financial Statements'!G$4,0) -> 0.013146023 | G27: =IFERROR(G18/'Financial Statements'!H$4,0) -> 0.0046499138 | H27: =AVERAGE(C27:G27) -> 0.0045207877 | I27: =H27 -> 0.0045207877 | J27: =I27 -> 0.0045207877 | K27: =J27 -> 0.0045207877 | L27: =K27 -> 0.0045207877
B28: =B19 -> Machinery & Equipment | C28: =IFERROR(C19/'Financial Statements'!D$4,0) -> 0.0015925464 | D28: =IFERROR(D19/'Financial Statements'!E$4,0) -> 0.00095077697 | E28: =IFERROR(E19/'Financial Statements'!F$4,0) -> 0.0028199797 | F28: =IFERROR(F19/'Financial Statements'!G$4,0) -> 0.0045227787 | G28: =IFERROR(G19/'Financial Statements'!H$4,0) -> 0.0058866184 | H28: =AVERAGE(C28:G28) -> 0.0031545401 | I28: =H28 -> 0.0031545401 | J28: =I28 -> 0.0031545401 | K28: =J28 -> 0.0031545401 | L28: =K28 -> 0.0031545401
B29: =B20 -> Furniture & Fixtures | C29: =IFERROR(C20/'Financial Statements'!D$4,0) -> 2.9179566e-05 | D29: =IFERROR(D20/'Financial Statements'!E$4,0) -> 1.1934324e-05 | E29: =IFERROR(E20/'Financial Statements'!F$4,0) -> 0.00024548641 | F29: =IFERROR(F20/'Financial Statements'!G$4,0) -> 0.00032216013 | G29: =IFERROR(G20/'Financial Statements'!H$4,0) -> 0.00016474815 | H29: =AVERAGE(C29:G29) -> 0.00015470172 | I29: =H29 -> 0.00015470172 | J29: =I29 -> 0.00015470172 | K29: =J29 -> 0.00015470172 | L29: =K29 -> 0.00015470172
B30: =B21 -> Other Installations | C30: =IFERROR(C21/'Financial Statements'!D$4,0) -> 0.00010345984 | D30: =IFERROR(D21/'Financial Statements'!E$4,0) -> 0.00013475864 | E30: =IFERROR(E21/'Financial Statements'!F$4,0) -> 0.00018715631 | F30: =IFERROR(F21/'Financial Statements'!G$4,0) -> 0.0012159175 | G30: =IFERROR(G21/'Financial Statements'!H$4,0) -> 0.00058951565 | H30: =AVERAGE(C30:G30) -> 0.00044616159 | I30: =H30 -> 0.00044616159 | J30: =I30 -> 0.00044616159 | K30: =J30 -> 0.00044616159 | L30: =K30 -> 0.00044616159
B31: =B22 -> Computers & Software | C31: =IFERROR(C22/'Financial Statements'!D$4,0) -> 0.00027899953 | D31: =IFERROR(D22/'Financial Statements'!E$4,0) -> 0.00024701611 | E31: =IFERROR(E22/'Financial Statements'!F$4,0) -> 0.00075737312 | F31: =IFERROR(F22/'Financial Statements'!G$4,0) -> 0.00023921832 | G31: =IFERROR(G22/'Financial Statements'!H$4,0) -> 0.00055855027 | H31: =AVERAGE(C31:G31) -> 0.00041623147 | I31: =H31 -> 0.00041623147 | J31: =I31 -> 0.00041623147 | K31: =J31 -> 0.00041623147 | L31: =K31 -> 0.00041623147
B33: Transferred from assets under construction
B34: =B16 -> Freehold Land | C34: 0 | D34: 0 | E34: 0 | F34: 0 | G34: 0
B35: =B17 -> Buildings | C35: 0 | D35: 0 | E35: 0 | F35: 0 | G35: 0
B36: =B18 -> Vehicles | C36: 0 | D36: 0 | E36: 0 | F36: 0 | G36: 0
B37: =B19 -> Machinery & Equipment | C37: 3.427052 | D37: 0 | E37: 0 | F37: 0 | G37: 781.88944 | H37: =G128 -> 391.54375
B38: =B20 -> Furniture & Fixtures | C38: 0 | D38: 0 | E38: 0 | F38: 0 | G38: 0
B39: =B21 -> Other Installations | C39: 0 | D39: 0 | E39: 3.261312 | F39: 1.0437 | G39: 0
B40: =B22 -> Computers & Software | C40: 0 | D40: 0 | E40: 0 | F40: 0 | G40: 0
B41: =B23 -> Total | C41: =SUM(C34:C40) -> 3.427052 | D41: =SUM(D34:D40) -> 0 | E41: =SUM(E34:E40) -> 3.261312 | F41: =SUM(F34:F40) -> 1.0437 | G41: =SUM(G34:G40) -> 781.88944 | H41: =SUM(H34:H40) -> 391.54375 | I41: =SUM(I34:I40) -> 0 | J41: =SUM(J34:J40) -> 0 | ... L41: =SUM(L34:L40) -> 0
B43: Disposals
B44: =B34 -> Freehold Land | C44: 0 | D44: 0 | E44: 0 | F44: 0 | G44: 0
B45: =B35 -> Buildings | C45: 0 | D45: 0 | E45: 0 | F45: 0 | G45: 0
B46: =B36 -> Vehicles | C46: -0.4407 | D46: 0 | E46: -0.77193 | F46: 0 | G46: -0.166375
B47: =B37 -> Machinery & Equipment | C47: 0 | D47: -0.3 | E47: -0.277255 | F47: 0 | G47: 0
B48: =B38 -> Furniture & Fixtures | C48: 0 | D48: 0 | E48: 0 | F48: 0 | G48: 0
B49: =B39 -> Other Installations | C49: 0 | D49: 0 | E49: -0.001706 | F49: 0 | G49: 0
B50: =B40 -> Computers & Software | C50: 0 | D50: 0 | E50: 0 | F50: 0 | G50: 0
B51: =B41 -> Total | C51: =SUM(C44:C50) -> -0.4407 | D51: =SUM(D44:D50) -> -0.3 | E51: =SUM(E44:E50) -> -1.050891 | F51: =SUM(F44:F50) -> 0 | G51: =SUM(G44:G50) -> -0.166375
B53: Ending Balance
B54: =B44 -> Freehold Land | C54: =C6+C16+C34+C44 -> 50.243436 | D54: =D6+D16+D34+D44 -> 50.243436 | E54: =E6+E16+E34+E44 -> 50.243436 | F54: =F6+F16+F34+F44 -> 50.243436 | G54: =G6+G16+G34+G44 -> 50.243436 | H54: =H6+H16+H34+H44 -> 50.243436 | I54: =I6+I16+I34+I44 -> 50.243436 | J54: =J6+J16+J34+J44 -> 50.243436 | ... L54: =L6+L16+L34+L44 -> 50.243436
B55: =B45 -> Buildings | C55: =C7+C17+C35+C45 -> 662.06626 | D55: =D7+D17+D35+D45 -> 669.65322 | E55: =E7+E17+E35+E45 -> 695.14882 | F55: =F7+F17+F35+F45 -> 731.93125 | G55: =G7+G17+G35+G45 -> 914.33184 | H55: =H7+H17+H35+H45 -> 1018.0241 | I55: =I7+I17+I35+I45 -> 1131.6974 | J55: =J7+J17+J35+J45 -> 1253.2918 | ... L55: =L7+L17+L35+L45 -> 1517.8995
B56: =B46 -> Vehicles | C56: =C8+C18+C36+C46 -> 47.674756 | D56: =D8+D18+D36+D46 -> 61.176691 | E56: =E8+E18+E36+E46 -> 67.485657 | F56: =F8+F18+F36+F46 -> 182.24758 | G56: =G8+G18+G36+G46 -> 239.96017 | H56: =H8+H18+H36+H46 -> 306.53404 | I56: =I8+I18+I36+I46 -> 379.51602 | J56: =J8+J18+J36+J46 -> 457.58364 | ... L56: =L8+L18+L36+L46 -> 627.47051
B57: =B47 -> Machinery & Equipment | C57: =C9+C19+C37+C47 -> 2882.4983 | D57: =D9+D19+D37+D47 -> 2886.6432 | E57: =E9+E19+E37+E47 -> 2903.4066 | F57: =F9+F19+F37+F47 -> 2942.8895 | G57: =G9+G19+G37+G47 -> 3798.0515 | H57: =H9+H19+H37+H47 -> 4236.0496 | I57: =I9+I19+I37+I47 -> 4286.9753 | J57: =J9+J19+J37+J47 -> 4341.4498 | ... L57: =L9+L19+L37+L47 -> 4459.9944
B58: =B48 -> Furniture & Fixtures | C58: =C10+C20+C38+C48 -> 15.836471 | D58: =D10+D20+D38+D48 -> 15.892264 | E58: =E10+E20+E38+E48 -> 17.375697 | F58: =F10+F20+F38+F48 -> 20.188085 | G58: =G10+G20+G38+G48 -> 22.238758 | H58: =H10+H20+H38+H48 -> 24.516921 | I58: =I10+I20+I38+I48 -> 27.01437 | J58: =J10+J20+J38+J48 -> 29.685851 | ... L58: =L10+L20+L38+L48 -> 35.499393
B59: =B49 -> Other Installations | C59: =C11+C21+C39+C49 -> 303.43283 | D59: =D11+D21+D39+D49 -> 304.06282 | E59: =E11+E21+E39+E49 -> 308.45338 | F59: =F11+F21+F39+F49 -> 320.11178 | G59: =G11+G21+G39+G49 -> 327.44967 | H59: =H11+H21+H39+H49 -> 334.01992 | I59: =I11+I21+I39+I49 -> 341.22259 | J59: =J11+J21+J39+J49 -> 348.92717 | ... L59: =L11+L21+L39+L49 -> 365.6935
B60: =B50 -> Computers & Software | C60: =C12+C22+C40+C50 -> 22.362299 | D60: =D12+D22+D40+D50 -> 23.5171 | E60: =E12+E22+E40+E50 -> 28.093778 | F60: =F12+F22+F40+F50 -> 30.182102 | G60: =G12+G22+G40+G50 -> 37.134556 | H60: =H12+H22+H40+H50 -> 43.26405 | I60: =I12+I22+I40+I50 -> 49.983542 | J60: =J12+J22+J40+J50 -> 57.171271 | ... L60: =L12+L22+L40+L50 -> 72.812851
B61: =B51 -> Total | C61: =SUM(C54:C60) -> 3984.1144 | D61: =SUM(D54:D60) -> 4011.1887 | E61: =SUM(E54:E60) -> 4070.2074 | F61: =SUM(F54:F60) -> 4277.7937 | G61: =SUM(G54:G60) -> 5389.41 | H61: =SUM(H54:H60) -> 6012.6521 | I61: =SUM(I54:I60) -> 6266.6527 | J61: =SUM(J54:J60) -> 6538.3529 | ... L61: =SUM(L54:L60) -> 7129.6136
B63: Beg. Accumulated Depreciation
B64: =B54 -> Freehold Land | C64: 0 | D64: =C94 -> 0 | E64: =D94 -> 0 | F64: =E94 -> 0 | G64: =F94 -> 0 | H64: =G94 -> 0 | I64: =H94 -> 0 | J64: =I94 -> 0 | K64: =J94 -> 0 | L64: =K94 -> 0
B65: =B55 -> Buildings | C65: -264.07433 | D65: =C95 -> -302.0161 | E65: =D95 -> -330.34034 | F65: =E95 -> -358.9855 | G65: =F95 -> -388.89134 | H65: =G95 -> -419.04217 | I65: =H95 -> -462.74531 | J65: =I95 -> -508.07389 | K65: =J95 -> -557.71047 | L65: =K95 -> -612.00093
B66: =B56 -> Vehicles | C66: -28.141018 | D66: =C96 -> -32.508527 | E66: =D96 -> -37.240898 | F66: =E96 -> -42.982928 | G66: =F96 -> -55.563186 | H66: =G96 -> -84.118521 | I66: =H96 -> -112.35887 | J66: =I96 -> -146.66053 | K66: =J96 -> -189.21032 | L66: =K96 -> -239.3653
B67: =B57 -> Machinery & Equipment | C67: -1287.635 | D67: =C97 -> -1444.1879 | E67: =D97 -> -1600.9805 | F67: =E97 -> -1762.4417 | G67: =F97 -> -1920.7009 | H67: =G97 -> -2099.047 | I67: =H97 -> -2323.7038 | J67: =I97 -> -2549.9665 | K67: =J97 -> -2777.6791 | L67: =K97 -> -3005.5513
B68: =B58 -> Furniture & Fixtures | C68: -8.727368 | D68: =C98 -> -10.209528 | E68: =D98 -> -11.446424 | F68: =E98 -> -12.553665 | G68: =F98 -> -13.639763 | H68: =G98 -> -14.731612 | I68: =H98 -> -16.389156 | J68: =I98 -> -18.075163 | K68: =J98 -> -19.836358 | L68: =K98 -> -21.736709
B69: =B59 -> Other Installations | C69: -137.35339 | D69: =C99 -> -153.87493 | E69: =D99 -> -169.82804 | F69: =E99 -> -185.8795 | G69: =F99 -> -202.85144 | H69: =G99 -> -220.39834 | I69: =H99 -> -238.13912 | J69: =I99 -> -256.17128 | K69: =J99 -> -274.63708 | L69: =K99 -> -293.59707
B70: =B60 -> Computers & Software | C70: -20.749262 | D70: =C100 -> -21.372212 | E70: =D100 -> -22.247938 | F70: =E100 -> -23.756987 | G70: =F100 -> -26.516549 | H70: =G100 -> -29.748834 | I70: =H100 -> -32.321164 | J70: =I100 -> -35.608901 | K70: =J100 -> -39.695739 | L70: =K100 -> -44.556579
B71: =B61 -> Total | C71: =SUM(C64:C70) -> -1746.6804 | D71: =SUM(D64:D70) -> -1964.1692 | E71: =SUM(E64:E70) -> -2172.0842 | F71: =SUM(F64:F70) -> -2386.6003 | G71: =SUM(G64:G70) -> -2608.1631 | H71: =SUM(H64:H70) -> -2867.0865 | I71: =SUM(I64:I70) -> -3185.6574 | J71: =SUM(J64:J70) -> -3514.5563 | ... L71: =SUM(L64:L70) -> -4216.8079
B73: Disposals
B74: =B64 -> Freehold Land | C74: 0 | D74: 0 | E74: 0 | F74: 0 | G74: 0
B75: =B65 -> Buildings | C75: 0 | D75: 0 | E75: 0 | F75: 0 | G75: 0
B76: =B66 -> Vehicles | C76: 0.4407 | D76: 0 | E76: 0.581877 | F76: 0 | G76: 0.166375
B77: =B67 -> Machinery & Equipment | C77: 0 | D77: 0.3 | E77: 0.277255 | F77: 0 | G77: 0
B78: =B68 -> Furniture & Fixtures | C78: 0 | D78: 0 | E78: 0 | F78: 0 | G78: 0
B79: =B69 -> Other Installations | C79: 0 | D79: 0 | E79: 0.001706 | F79: 0 | G79: 0
B80: =B70 -> Computers & Software | C80: 0 | D80: 0 | E80: 0 | F80: 0 | G80: 0
B81: =B71 -> Total | C81: =SUM(C74:C80) -> 0.4407 | D81: =SUM(D74:D80) -> 0.3 | E81: =SUM(E74:E80) -> 0.860838 | F81: =SUM(F74:F80) -> 0 | G81: =SUM(G74:G80) -> 0.166375
B83: Depreciation Expense
B84: =B74 -> Freehold Land | C84: 0 | D84: 0 | E84: 0 | F84: 0 | G84: 0 | H84: =IF(H64<H54,H54*H104,H54-H64) -> 0 | I84: =IF(I64<I54,I54*I104,I54-I64) -> 0 | J84: =IF(J64<J54,J54*J104,J54-J64) -> 0 | K84: =IF(K64<K54,K54*K104,K54-K64) -> 0 | L84: =IF(L64<L54,L54*L104,L54-L64) -> 0
B85: =B75 -> Buildings | C85: -37.941772 | D85: -28.324245 | E85: -28.645153 | F85: -29.905846 | G85: -30.150833 | H85: =IF(H65<H55,H55*H105,H55-H65) -> -43.703136 | I85: =IF(I65<I55,I55*I105,I55-I65) -> -45.328579 | J85: =IF(J65<J55,J55*J105,J55-J65) -> -49.636582 | K85: =IF(K65<K55,K55*K105,K55-K65) -> -54.290453 | L85: =IF(L65<L55,L55*L105,L55-L65) -> -59.152024
B86: =B76 -> Vehicles | C86: -4.808209 | D86: -4.732371 | E86: -6.323907 | F86: -12.580258 | G86: -28.72171 | H86: =IF(H66<H56,H56*H106,H56-H66) -> -28.240348 | I86: =IF(I66<I56,I56*I106,I56-I66) -> -34.301659 | J86: =IF(J66<J56,J56*J106,J56-J66) -> -42.549791 | K86: =IF(K66<K56,K56*K106,K56-K66) -> -50.154981 | L86: =IF(L66<L56,L56*L106,L56-L66) -> -61.245685
B87: =B77 -> Machinery & Equipment | C87: -156.55286 | D87: -157.09266 | E87: -161.73842 | F87: -158.25916 | G87: -178.34611 | H87: =IF(H67<H57,H57*H107,H57-H67) -> -224.65681 | I87: =IF(I67<I57,I57*I107,I57-I67) -> -226.26273 | J87: =IF(J67<J57,J57*J107,J57-J67) -> -227.7126 | K87: =IF(K67<K57,K57*K107,K57-K67) -> -227.87219 | L87: =IF(L67<L57,L57*L107,L57-L67) -> -229.2628
B88: =B78 -> Furniture & Fixtures | C88: -1.48216 | D88: -1.236896 | E88: -1.107241 | F88: -1.086098 | G88: -1.091849 | H88: =IF(H68<H58,H58*H108,H58-H68) -> -1.657544 | I88: =IF(I68<I58,I58*I108,I58-I68) -> -1.6860069 | J88: =IF(J68<J58,J58*J108,J58-J68) -> -1.7611951 | K88: =IF(K68<K58,K58*K108,K58-K68) -> -1.9003515 | L88: =IF(L68<L58,L58*L108,L58-L68) -> -2.107902
B89: =B79 -> Other Installations | C89: -16.521537 | D89: -15.953106 | E89: -16.053171 | F89: -16.97194 | G89: -17.546898 | H89: =IF(H69<H59,H59*H109,H59-H69) -> -17.740776 | I89: =IF(I69<I59,I59*I109,I59-I69) -> -18.032169 | J89: =IF(J69<J59,J59*J109,J59-J69) -> -18.465792 | K89: =IF(K69<K59,K59*K109,K59-K69) -> -18.959993 | L89: =IF(L69<L59,L59*L109,L59-L69) -> -19.423005
B90: =B80 -> Computers & Software | C90: -0.62295 | D90: -0.875726 | E90: -1.509049 | F90: -2.759562 | G90: -3.232285 | H90: =IF(H70<H60,H60*H110,H60-H70) -> -2.57233 | I90: =IF(I70<I60,I60*I110,I60-I70) -> -3.2877373 | J90: =IF(J70<J60,J60*J110,J60-J70) -> -4.0868374 | K90: =IF(K70<K60,K60*K110,K60-K70) -> -4.8608399 | L90: =IF(L70<L60,L60*L110,L60-L70) -> -5.2250143
B91: =B81 -> Total | C91: =SUM(C84:C90) -> -217.92949 | D91: =SUM(D84:D90) -> -208.21501 | E91: =SUM(E84:E90) -> -215.37694 | F91: =SUM(F84:F90) -> -221.56286 | G91: =SUM(G84:G90) -> -259.08968 | H91: =SUM(H84:H90) -> -318.57094 | I91: =SUM(I84:I90) -> -328.89888 | J91: =SUM(J84:J90) -> -344.2128 | ... L91: =SUM(L84:L90) -> -376.41643
B93: Ending Accumulated Depreciation
B94: =B84 -> Freehold Land | C94: =C64+C74+C84 -> 0 | D94: =D64+D74+D84 -> 0 | E94: =E64+E74+E84 -> 0 | F94: =F64+F74+F84 -> 0 | G94: =G64+G74+G84 -> 0 | H94: =H64+H74+H84 -> 0 | I94: =I64+I74+I84 -> 0 | J94: =J64+J74+J84 -> 0 | ... L94: =L64+L74+L84 -> 0
B95: =B85 -> Buildings | C95: =C65+C75+C85 -> -302.0161 | D95: =D65+D75+D85 -> -330.34034 | E95: =E65+E75+E85 -> -358.9855 | F95: =F65+F75+F85 -> -388.89134 | G95: =G65+G75+G85 -> -419.04217 | H95: =H65+H75+H85 -> -462.74531 | I95: =I65+I75+I85 -> -508.07389 | J95: =J65+J75+J85 -> -557.71047 | ... L95: =L65+L75+L85 -> -671.15295
B96: =B86 -> Vehicles | C96: =C66+C76+C86 -> -32.508527 | D96: =D66+D76+D86 -> -37.240898 | E96: =E66+E76+E86 -> -42.982928 | F96: =F66+F76+F86 -> -55.563186 | G96: =G66+G76+G86 -> -84.118521 | H96: =H66+H76+H86 -> -112.35887 | I96: =I66+I76+I86 -> -146.66053 | J96: =J66+J76+J86 -> -189.21032 | ... L96: =L66+L76+L86 -> -300.61099
B97: =B87 -> Machinery & Equipment | C97: =C67+C77+C87 -> -1444.1879 | D97: =D67+D77+D87 -> -1600.9805 | E97: =E67+E77+E87 -> -1762.4417 | F97: =F67+F77+F87 -> -1920.7009 | G97: =G67+G77+G87 -> -2099.047 | H97: =H67+H77+H87 -> -2323.7038 | I97: =I67+I77+I87 -> -2549.9665 | J97: =J67+J77+J87 -> -2777.6791 | ... L97: =L67+L77+L87 -> -3234.8141
B98: =B88 -> Furniture & Fixtures | C98: =C68+C78+C88 -> -10.209528 | D98: =D68+D78+D88 -> -11.446424 | E98: =E68+E78+E88 -> -12.553665 | F98: =F68+F78+F88 -> -13.639763 | G98: =G68+G78+G88 -> -14.731612 | H98: =H68+H78+H88 -> -16.389156 | I98: =I68+I78+I88 -> -18.075163 | J98: =J68+J78+J88 -> -19.836358 | ... L98: =L68+L78+L88 -> -23.844612
B99: =B89 -> Other Installations | C99: =C69+C79+C89 -> -153.87493 | D99: =D69+D79+D89 -> -169.82804 | E99: =E69+E79+E89 -> -185.8795 | F99: =F69+F79+F89 -> -202.85144 | G99: =G69+G79+G89 -> -220.39834 | H99: =H69+H79+H89 -> -238.13912 | I99: =I69+I79+I89 -> -256.17128 | J99: =J69+J79+J89 -> -274.63708 | ... L99: =L69+L79+L89 -> -313.02007
B100: =B90 -> Computers & Software | C100: =C70+C80+C90 -> -21.372212 | D100: =D70+D80+D90 -> -22.247938 | E100: =E70+E80+E90 -> -23.756987 | F100: =F70+F80+F90 -> -26.516549 | G100: =G70+G80+G90 -> -29.748834 | H100: =H70+H80+H90 -> -32.321164 | I100: =I70+I80+I90 -> -35.608901 | J100: =J70+J80+J90 -> -39.695739 | ... L100: =L70+L80+L90 -> -49.781593
B101: =B91 -> Total | C101: =SUM(C94:C100) -> -1964.1692 | D101: =SUM(D94:D100) -> -2172.0842 | E101: =SUM(E94:E100) -> -2386.6003 | F101: =SUM(F94:F100) -> -2608.1631 | G101: =SUM(G94:G100) -> -2867.0865 | H101: =SUM(H94:H100) -> -3185.6574 | I101: =SUM(I94:I100) -> -3514.5563 | J101: =SUM(J94:J100) -> -3858.7691 | ... L101: =SUM(L94:L100) -> -4593.2243
B103: Depreciation Rate
B104: =B94 -> Freehold Land | C104: =IFERROR(C84/C54,0) -> 0 | D104: =IFERROR(D84/D54,0) -> 0 | E104: =IFERROR(E84/E54,0) -> 0 | F104: =IFERROR(F84/F54,0) -> 0 | G104: =IFERROR(G84/G54,0) -> 0 | H104: =AVERAGE(C104:G104) -> 0 | I104: =AVERAGE(D104:H104) -> 0 | J104: =AVERAGE(E104:I104) -> 0 | K104: =AVERAGE(F104:J104) -> 0 | L104: =AVERAGE(G104:K104) -> 0
B105: =B95 -> Buildings | C105: =IFERROR(C85/C55,0) -> -0.057308119 | D105: =IFERROR(D85/D55,0) -> -0.042296884 | E105: =IFERROR(E85/E55,0) -> -0.041207224 | F105: =IFERROR(F85/F55,0) -> -0.040858819 | G105: =IFERROR(G85/G55,0) -> -0.03297581 | H105: =AVERAGE(C105:G105) -> -0.042929371 | I105: =AVERAGE(D105:H105) -> -0.040053622 | J105: =AVERAGE(E105:I105) -> -0.039604969 | K105: =AVERAGE(F105:J105) -> -0.039284518 | L105: =AVERAGE(G105:K105) -> -0.038969658
B106: =B96 -> Vehicles | C106: =IFERROR(C86/C56,0) -> -0.1008544 | D106: =IFERROR(D86/D56,0) -> -0.077355786 | E106: =IFERROR(E86/E56,0) -> -0.093707423 | F106: =IFERROR(F86/F56,0) -> -0.069028396 | G106: =IFERROR(G86/G56,0) -> -0.11969366 | H106: =AVERAGE(C106:G106) -> -0.092127932 | I106: =AVERAGE(D106:H106) -> -0.090382639 | J106: =AVERAGE(E106:I106) -> -0.092988009 | K106: =AVERAGE(F106:J106) -> -0.092844126 | L106: =AVERAGE(G106:K106) -> -0.097607272
B107: =B97 -> Machinery & Equipment | C107: =IFERROR(C87/C57,0) -> -0.05431152 | D107: =IFERROR(D87/D57,0) -> -0.054420534 | E107: =IFERROR(E87/E57,0) -> -0.05570643 | F107: =IFERROR(F87/F57,0) -> -0.053776794 | G107: =IFERROR(G87/G57,0) -> -0.046957263 | H107: =AVERAGE(C107:G107) -> -0.053034508 | I107: =AVERAGE(D107:H107) -> -0.052779106 | J107: =AVERAGE(E107:I107) -> -0.05245082 | K107: =AVERAGE(F107:J107) -> -0.051799698 | L107: =AVERAGE(G107:K107) -> -0.051404279
B108: =B98 -> Furniture & Fixtures | C108: =IFERROR(C88/C58,0) -> -0.093591558 | D108: =IFERROR(D88/D58,0) -> -0.077830069 | E108: =IFERROR(E88/E58,0) -> -0.063723544 | F108: =IFERROR(F88/F58,0) -> -0.053798961 | G108: =IFERROR(G88/G58,0) -> -0.049096672 | H108: =AVERAGE(C108:G108) -> -0.067608161 | I108: =AVERAGE(D108:H108) -> -0.062411481 | J108: =AVERAGE(E108:I108) -> -0.059327764 | K108: =AVERAGE(F108:J108) -> -0.058448608 | L108: =AVERAGE(G108:K108) -> -0.059378537
B109: =B99 -> Other Installations | C109: =IFERROR(C89/C59,0) -> -0.054448746 | D109: =IFERROR(D89/D59,0) -> -0.05246648 | E109: =IFERROR(E89/E59,0) -> -0.052044075 | F109: =IFERROR(F89/F59,0) -> -0.053018792 | G109: =IFERROR(G89/G59,0) -> -0.05358655 | H109: =AVERAGE(C109:G109) -> -0.053112929 | I109: =AVERAGE(D109:H109) -> -0.052845765 | J109: =AVERAGE(E109:I109) -> -0.052921622 | K109: =AVERAGE(F109:J109) -> -0.053097132 | L109: =AVERAGE(G109:K109) -> -0.053112799
B110: =B100 -> Computers & Software | C110: =IFERROR(C90/C60,0) -> -0.027857154 | D110: =IFERROR(D90/D60,0) -> -0.03723784 | E110: =IFERROR(E90/E60,0) -> -0.053714705 | F110: =IFERROR(F90/F60,0) -> -0.091430411 | G110: =IFERROR(G90/G60,0) -> -0.087042511 | H110: =AVERAGE(C110:G110) -> -0.059456524 | I110: =AVERAGE(D110:H110) -> -0.065776398 | J110: =AVERAGE(E110:I110) -> -0.07148411 | K110: =AVERAGE(F110:J110) -> -0.075037991 | L110: =AVERAGE(G110:K110) -> -0.071759507
B111: =B101 -> Total | C111: =SUM(C104:C110) -> -0.3883715 | D111: =SUM(D104:D110) -> -0.34160759 | E111: =SUM(E104:E110) -> -0.3601034 | F111: =SUM(F104:F110) -> -0.36191217 | G111: =SUM(G104:G110) -> -0.38935246 | H111: =SUM(H104:H110) -> -0.36826943 | I111: =SUM(I104:I110) -> -0.36424901 | J111: =SUM(J104:J110) -> -0.36877729 | ... L111: =SUM(L104:L110) -> -0.37223205
...

Sheet Debt
B2: Footnotes BD | C2: 2021 | D2: =C2+1 -> 2022 | E2: =D2+1 -> 2023 | F2: =E2+1 -> 2024 | G2: =F2+1 -> 2025 | H2: =G2+1 -> 2026 | I2: =H2+1 -> 2027 | J2: =I2+1 -> 2028 | K2: =J2+1 -> 2029 | L2: =K2+1 -> 2030
B4: Borrowings
B5: Current
B6: Bank Loans - CIB | C6: 45.9 | D6: 56.1 | E6: 0 | F6: 0 | G6: 0 | H6: =G6 -> 0 | I6: =H6 -> 0 | J6: =I6 -> 0 | K6: =J6 -> 0 | L6: =K6 -> 0
B7: Bank Loans - NBE | C7: 0 | D7: 0 | E7: 0 | F7: 25.481075 | G7: 27.056585 | H7: =H27 -> 27.056585 | I7: =I27 -> 27.056585 | J7: =J27 -> 27.056585 | K7: =K27 -> 27.056585 | L7: =L27 -> 10.458559
B8: Bank Loans - EBRD | C8: 68.434781 | D8: 107.43478 | E8: 0 | F8: 0 | G8: 118.43656 | H8: =H35 -> 236.87312 | I8: =I35 -> 236.87312 | J8: =J35 -> 236.87312 | K8: =K35 -> 177.65484 | L8: =L35 -> 0
B9: Total Current Borrowings | C9: =SUM(C6:C8) -> 114.33478 | D9: =SUM(D6:D8) -> 163.53478 | E9: =SUM(E6:E8) -> 0 | F9: =SUM(F6:F8) -> 25.481075 | G9: =SUM(G6:G8) -> 145.49314 | H9: =SUM(H6:H8) -> 263.9297 | I9: =SUM(I6:I8) -> 263.9297 | J9: =SUM(J6:J8) -> 263.9297 | ... L9: =SUM(L6:L8) -> 10.458559
B10: Non-Current
B11: Bank Loans - CIB | C11: 153 | D11: 96.9 | E11: 0 | F11: 0 | G11: 0 | H11: =G11 -> 0 | I11: =H11 -> 0 | J11: =I11 -> 0 | K11: =J11 -> 0 | L11: =K11 -> 0
B12: Bank Loans - NBE | C12: 0 | D12: 0 | E12: 0 | F12: 120.39238 | G12: 118.6849 | H12: =H28 -> 91.628314 | I12: =I28 -> 64.571729 | J12: =J28 -> 37.515144 | K12: =K28 -> 10.458559 | L12: =L28 -> 0
B13: Bank Loans - EBRD | C13: 119.76091 | D13: 80.57609 | E13: 0 | F13: 0 | G13: 769.83764 | H13: =H36 -> 651.40108 | I13: =I36 -> 414.52796 | J13: =J36 -> 177.65484 | K13: =K36 -> 0 | L13: =L36 -> 0
B14: Total Non-Current Borrowings | C14: =SUM(C11:C13) -> 272.76091 | D14: =SUM(D11:D13) -> 177.47609 | E14: =SUM(E11:E13) -> 0 | F14: =SUM(F11:F13) -> 120.39238 | G14: =SUM(G11:G13) -> 888.52254 | H14: =SUM(H11:H13) -> 743.02939 | I14: =SUM(I11:I13) -> 479.09969 | J14: =SUM(J11:J13) -> 215.16998 | ... L14: =SUM(L11:L13) -> 0
B16: Long-Term Bank Loan Debt Schedule
B17: 6M EURIBOR Proxy | C17: 0.0282
A18: https://www.euribor-rates.eu/en/current-euribor-rates/ | B18: 3M EURIBOR Proxy | C18: 0.02647
B19: NBE All-in Rate | C19: =C17+0.03 -> 0.0582 | D19: (6M EURIBOR + 3.0% margin per KfW facility agreement)
B20: EBRD All-in Rate | C20: =C18+0.0435 -> 0.06997 | D20: (3M EURIBOR + 4.35% margin per EBRD facility agreement)
B22: NBE Loan | M22: Phase 3,20 equal quarterly instalments
B23: Beg. Balance | H23: =G7+G12 -> 145.74148 | I23: =H26 -> 118.6849 | J23: =I26 -> 91.628314 | K23: =J26 -> 64.571729 | L23: =K26 -> 37.515144
B24: Scheduled Repayment | H24: =MIN($G$7,H23) -> 27.056585 | I24: =MIN($G$7,I23) -> 27.056585 | J24: =MIN($G$7,J23) -> 27.056585 | K24: =MIN($G$7,K23) -> 27.056585 | L24: =MIN($G$7,L23) -> 27.056585 | M24: (assumed last actual annual instalment, held flat until repaid)
B25: Interest Expense | H25: =H23*$C$19 -> 8.4821544 | I25: =I23*$C$19 -> 6.9074611 | J25: =J23*$C$19 -> 5.3327679 | K25: =K23*$C$19 -> 3.7580746 | L25: =L23*$C$19 -> 2.1833814 | M25: (Beg. Balance x NBE rate)
B26: Ending Balance | H26: =H23-H24 -> 118.6849 | I26: =I23-I24 -> 91.628314 | J26: =J23-J24 -> 64.571729 | K26: =K23-K24 -> 37.515144 | L26: =L23-L24 -> 10.458559
B27: Current Portion (next 12 months due) | H27: =MIN($G$7,H26) -> 27.056585 | I27: =MIN($G$7,I26) -> 27.056585 | J27: =MIN($G$7,J26) -> 27.056585 | K27: =MIN($G$7,K26) -> 27.056585 | L27: =MIN($G$7,L26) -> 10.458559
B28: Non-Current Portion | H28: =H26-H27 -> 91.628314 | I28: =I26-I27 -> 64.571729 | J28: =J26-J27 -> 37.515144 | K28: =K26-K27 -> 10.458559 | L28: =L26-L27 -> 0
B30: EBRD Loan | M30: (15 equal quarterly instalments, first due ~18 months after FY2025 agreement date)
B31: Beg. Balance | H31: =G8+G13 -> 888.27419 | I31: =H34 -> 888.27419 | J31: =I34 -> 651.40108 | K31: =J34 -> 414.52796 | L31: =K34 -> 177.65484
B32: Scheduled Repayment | H32: 0 | I32: =MIN($H$31/15*4,I31) -> 236.87312 | J32: =MIN($H$31/15*4,J31) -> 236.87312 | K32: =MIN($H$31/15*4,K31) -> 236.87312 | L32: =L31 -> 177.65484 | M32: (18-month grace in 2026; ~4 instalments/yr from 2027; final payoff 2030)
B33: Interest Expense | H33: =H31*$C$20 -> 62.152545 | I33: =I31*$C$20 -> 62.152545 | J33: =J31*$C$20 -> 45.578533 | K33: =K31*$C$20 -> 29.004521 | L33: =L31*$C$20 -> 12.430509 | M33: (Beg. Balance x EBRD rate)
B34: Ending Balance | H34: =H31-H32 -> 888.27419 | I34: =I31-I32 -> 651.40108 | J34: =J31-J32 -> 414.52796 | K34: =K31-K32 -> 177.65484 | L34: =L31-L32 -> 0
B35: Current Portion (next 12 months due) | H35: =I32 -> 236.87312 | I35: =J32 -> 236.87312 | J35: =K32 -> 236.87312 | K35: =L32 -> 177.65484 | L35: 0
B36: Non-Current Portion | H36: =H34-H35 -> 651.40108 | I36: =I34-I35 -> 414.52796 | J36: =J34-J35 -> 177.65484 | K36: =K34-K35 -> 0 | L36: =L34-L35 -> 0
B39: Credit Facilities
B40: CF - CIB | C40: 240.38696 | D40: 162.16464 | E40: 73.528497 | F40: 615.04423 | G40: 99.916937
B41: CF -NBE | C41: 0 | D41: 198.47956 | E41: 16.545438 | F41: 0 | G41: 0
B42: CF - EG | C42: 0 | D42: 0 | E42: 0.000338 | F42: 0 | G42: 0
B43: Total | C43: =SUM(C40:C41) -> 240.38696 | D43: =SUM(D40:D42) -> 360.6442 | E43: =SUM(E40:E42) -> 90.074273 | F43: =SUM(F40:F42) -> 615.04423 | G43: =SUM(G40:G42) -> 99.916937 | H43: =H44*'Financial Statements'!I88 -> 134.16668 | I43: =I44*'Financial Statements'!J88 -> 146.39711 | J43: =J44*'Financial Statements'!K88 -> 156.78447 | K43: =K44*'Financial Statements'!L88 -> 166.0692 | L43: =L44*'Financial Statements'!M88 -> 175.52873
C44: =-C43/'Financial Statements'!D87 -> 0.63771635 | D44: =-D43/'Financial Statements'!E87 -> 0.76772231 | E44: =-E43/'Financial Statements'!F87 -> 0.48862668 | F44: =F43/'Financial Statements'!G87 -> 65.693977 | G44: =G43/'Financial Statements'!H88 -> 0.17290066 | H44: =G44 -> 0.17290066 | I44: =H44 -> 0.17290066 | J44: =I44 -> 0.17290066 | K44: =J44 -> 0.17290066 | L44: =K44 -> 0.17290066
B46: Deferred Tax Liabilities
B47: Beg. Balance | C47: 323.76501 | D47: =C49 -> 301.47283 | E47: =D49 -> 266.20171 | F47: =-E49 -> -282.21862 | G47: =F49 -> -241.14699
B48: Recognized in profit or loss from Dp of FA | C48: -22.29218 | D48: -35.271117 | E48: 16.016906 | F48: 41.071622 | G48: -14.169166
B49: Ending Balance | C49: =SUM(C47:C48) -> 301.47283 | D49: =SUM(D47:D48) -> 266.20171 | E49: =SUM(E47:E48) -> 282.21862 | F49: =SUM(F47:F48) -> -241.14699 | G49: =SUM(G47:G48) -> -255.31616 | H49: =G49 -> -255.31616 | I49: =H49 -> -255.31616 | J49: =I49 -> -255.31616 | K49: =J49 -> -255.31616 | L49: =K49 -> -255.31616
B51: Current Income Tax Liabilites
B52: Current tax liability | C52: 43.280867 | D52: 198.38656 | E52: 216.7159 | F52: 374.0144 | G52: 1102.2591
B53: Total | C53: =SUM(C52) -> 43.280867 | D53: =SUM(D52) -> 198.38656 | E53: =SUM(E52) -> 216.7159 | F53: =SUM(F52) -> 374.0144 | G53: =SUM(G52) -> 1102.2591 | H53: =G53 -> 1102.2591 | I53: =H53 -> 1102.2591 | J53: =I53 -> 1102.2591 | K53: =J53 -> 1102.2591 | L53: =K53 -> 1102.2591
B55: Lease Liabilities
B56: Beg. Balance | C56: 0.915298 | D56: =C61 -> 16.546118 | E56: =D61 -> 13.135634 | F56: =E61 -> 11.220907 | G56: =F61 -> 5.268353 | H56: =G61 -> 1.176042 | I56: =H61 -> 0.91018628 | J56: =I61 -> 0.70442983 | K56: =J61 -> 0.54518662 | L56: =K61 -> 0.42194189
B57: Additions | C57: 19.998237 | D57: 0.928837 | E57: 7.400643 | F57: 2.719197 | G57: 0 | H57: =G57 -> 0 | I57: =H57 -> 0 | J57: =I57 -> 0 | K57: =J57 -> 0 | L57: =K57 -> 0
B58: Disposals | C58: 0 | D58: 0 | E58: -0.78414 | F58: -5.625996 | G58: -0.996004
B59: Interest expenses | C59: 2.546832 | D59: 1.05921 | E59: 1.296489 | F59: 1.237302 | G59: 1.162675 | H59: =H65*H56 -> 0.25954119 | I59: =I65*I56 -> 0.20086939 | J59: =J65*J56 -> 0.15546091 | K59: =K65*K56 -> 0.12031746 | L59: =L65*L56 -> 0.09311853
B60: Payment during the year | C60: -6.914249 | D60: -5.398531 | E60: -9.827719 | F60: -4.283057 | G60: -4.258982 | H60: =-H64*H56 -> -0.52539691 | I60: =-I64*I56 -> -0.40662584 | J60: =-J64*J56 -> -0.31470412 | K60: =-K64*K56 -> -0.24356219 | L60: =-L64*L56 -> -0.18850259
B61: Ending Balance | C61: =SUM(C56:C60) -> 16.546118 | D61: =SUM(D56:D60) -> 13.135634 | E61: =SUM(E56:E60) -> 11.220907 | F61: =SUM(F56:F60) -> 5.268353 | G61: =SUM(G56:G60) -> 1.176042 | H61: =SUM(H56:H60) -> 0.91018628 | I61: =SUM(I56:I60) -> 0.70442983 | J61: =SUM(J56:J60) -> 0.54518662 | ... L61: =SUM(L56:L60) -> 0.32655783
B62: Current Portion | C62: 9.566342 | D62: 6.411505 | E62: 9.481649 | F62: 3.625821 | G62: 1.176042 | H62: =-H60 -> 0.52539691 | I62: =-I60 -> 0.40662584 | J62: =-J60 -> 0.31470412 | K62: =-K60 -> 0.24356219 | L62: =-L60 -> 0.18850259
B63: Non-Current Portion | C63: =C61-C62 -> 6.979776 | D63: =D61-D62 -> 6.724129 | E63: =E61-E62 -> 1.739258 | F63: =F61-F62 -> 1.642532 | G63: =G61-G62 -> 0 | H63: =H60+H56 -> 0.65064509 | I63: =I60+I56 -> 0.50356044 | J63: =J60+J56 -> 0.38972571 | K63: =K60+K56 -> 0.30162443 | L63: =L60+L56 -> 0.2334393
B64: Payments % of beg.+addidions | C64: =-C60/(C56+C57) -> 0.3306112 | D64: =-D60/(D56+D57) -> 0.30892961 | E64: =-E60/(E56+E57) -> 0.47855407 | F64: =-F60/(F56+F57) -> 0.30724713 | G64: =-G60/(G56+G57) -> 0.80840862 | H64: =AVERAGE(C64:G64) -> 0.44675013 | I64: =H64 -> 0.44675013 | J64: =I64 -> 0.44675013 | K64: =J64 -> 0.44675013 | L64: =K64 -> 0.44675013
B65: Interest % of beg.+additions | C65: =C59/(C56+C57) -> 0.12177913 | D65: =D59/(D56+D57) -> 0.060613032 | E65: =E59/(E56+E57) -> 0.063131647 | F65: =F59/(F56+F57) -> 0.088758448 | G65: =G59/(G56+G57) -> 0.22069041 | H65: =G65 -> 0.22069041 | I65: =H65 -> 0.22069041 | J65: =I65 -> 0.22069041 | K65: =J65 -> 0.22069041 | L65: =K65 -> 0.22069041
B67: Creditors and Other Credit Balance
B68: Advances from Customers | C68: 67.954027 | D68: 140.38614 | E68: 113.05304 | F68: 75.134462 | G68: 261.32829
B69: Accrued Development Fees | C69: 11.290171 | D69: 10.433957 | E69: 9.862067 | F69: 9.173338 | G69: 9.822747
B70: Accrued Customers Rebates | C70: 54.422249 | D70: 74.784633 | E70: 97.34114 | F70: 115.64245 | G70: 228.43664
B71: Accrued Expenses | C71: 12.544736 | D71: 22.914785 | E71: 31.500223 | F71: 48.828254 | G71: 99.082676
B72: Retention | C72: 5.09633 | D72: 4.830301 | E72: 4.830301 | F72: 30.472002 | G72: 18.59704
B73: Accrued Interests | C73: 1.427344 | D73: 2.759721 | E73: 0 | F73: 12.334452 | G73: 5.755165
B74: Accrued Taxes | C74: 14.438738 | D74: 27.009775 | E74: 40.087197 | F74: 41.798685 | G74: 75.494262
B75: Accrued Revenue - Grant | C75: 13.240502 | D75: 12.193446 | E75: 10.95907 | F75: 0 | G75: 0
B76: Deferred Revenue - EBRD Grant | C76: 0 | D76: 0 | E76: 0 | F76: 0 | G76: 5.53642
B77: Deferred Revenue - Other Grant | C77: 0 | D77: 0 | E77: 0 | F77: 9.466637 | G77: 7.90815
B78: Other | C78: 3.840297 | D78: 3.689246 | E78: 2.266284 | F78: 2.237059 | G78: 1.463098
B79: Total Current Portion | C79: =SUM(C68:C78) -> 184.25439 | D79: =SUM(D68:D78) -> 299.002 | E79: =SUM(E68:E78) -> 309.89932 | F79: =SUM(F68:F78) -> 345.08734 | G79: =SUM(G68:G78) -> 713.42449 | H79: =H82*'Revenue Bridge'!H15 -> 846.26778 | I79: =I82*'Revenue Bridge'!I15 -> 927.72572 | J79: =J82*'Revenue Bridge'!J15 -> 992.37291 | K79: =K82*'Revenue Bridge'!K15 -> 1050.2752 | L79: =L82*'Revenue Bridge'!L15 -> 1109.2775
B80: Non-Current Portion | C80: 0 | D80: 0 | E80: 0 | F80: 0 | G80: 103.02084
B81: Total | C81: =C79+C80 -> 184.25439 | D81: =D79+D80 -> 299.002 | E81: =E79+E80 -> 309.89932 | F81: =F79+F80 -> 345.08734 | G81: =G79+G80 -> 816.44532 | H81: =H79+H80 -> 846.26778 | I81: =I79+I80 -> 927.72572 | J81: =J79+J80 -> 992.37291 | ... L81: =L79+L80 -> 1109.2775
B82: % of sales | C82: =C79/'Financial Statements'!D4 -> 0.075247911 | D82: =D79/'Financial Statements'!E4 -> 0.063957608 | E82: =E79/'Financial Statements'!F4 -> 0.051283795 | F82: =F79/'Financial Statements'!G4 -> 0.039529889 | G82: =G79/'Financial Statements'!H4 -> 0.057315509 | H82: =AVERAGE(C82:G82) -> 0.057466942 | I82: =H82 -> 0.057466942 | J82: =I82 -> 0.057466942 | K82: =J82 -> 0.057466942 | L82: =K82 -> 0.057466942
B84: Trade and Notes Payable
B85: Current
B86: Local trade payables | C86: 418.97654 | D86: 501.68332 | E86: 310.24657 | F86: 368.42041 | G86: 574.53253 | H86: ='COGS Bridge'!I11/Debt!H97 -> 248.19343 | I86: ='COGS Bridge'!J11/Debt!I97 -> 270.06691 | J86: ='COGS Bridge'!K11/Debt!J97 -> 289.43428 | K86: ='COGS Bridge'!L11/Debt!K97 -> 306.72532 | L86: ='COGS Bridge'!M11/Debt!L97 -> 324.34014
B87: Foreign trade payables | C87: 271.31597 | D87: 306.4324 | E87: 754.66252 | F87: 469.10229 | G87: 145.64371 | H87: ='COGS Bridge'!I11/Debt!H98 -> 461.27924 | I87: ='COGS Bridge'!J11/Debt!I98 -> 501.93214 | J87: ='COGS Bridge'!K11/Debt!J98 -> 537.92733 | K87: ='COGS Bridge'!L11/Debt!K98 -> 570.06354 | L87: ='COGS Bridge'!M11/Debt!L98 -> 602.80151
B88: Notes payable | C88: 3.411122 | D88: 3.066177 | E88: 2.755518 | F88: 1.788996 | G88: 0 | H88: =G88 -> 0 | I88: =H88 -> 0 | J88: =I88 -> 0 | K88: =J88 -> 0 | L88: =K88 -> 0
B89: Total Current Portion | C89: =SUM(C86:C88) -> 693.70363 | D89: =SUM(D86:D88) -> 811.1819 | E89: =SUM(E86:E88) -> 1067.6646 | F89: =SUM(F86:F88) -> 839.31169 | G89: =SUM(G86:G88) -> 720.17624 | H89: =SUM(H86:H88) -> 709.47267 | I89: =SUM(I86:I88) -> 771.99904 | J89: =SUM(J86:J88) -> 827.36161 | ... L89: =SUM(L86:L88) -> 927.14164
B90: Non-Current
B91: =B86 -> Local trade payables | C91: 0 | D91: 0 | E91: 0 | F91: 0 | G91: 0 | H91: 0 | I91: 0 | J91: 0 | K91: 0 | L91: 0
B92: =B87 -> Foreign trade payables | C92: 0 | D92: 0 | E92: 0 | F92: 301.14206 | G92: 0 | H92: 0 | I92: 0 | J92: 0 | K92: 0 | L92: 0
B93: =B88 -> Notes payable | C93: 7.610691 | D93: 4.544514 | E93: 1.788996 | F93: 0 | G93: 0 | H93: 0 | I93: 0 | J93: 0 | K93: 0 | L93: 0
B94: Total Non-Current Portion | C94: =SUM(C91:C93) -> 7.610691 | D94: =SUM(D91:D93) -> 4.544514 | E94: =SUM(E91:E93) -> 1.788996 | F94: =SUM(F91:F93) -> 301.14206 | G94: =SUM(G91:G93) -> 0 | H94: =SUM(H91:H93) -> 0 | I94: =SUM(I91:I93) -> 0 | J94: =SUM(J91:J93) -> 0 | ... L94: =SUM(L91:L93) -> 0
B95: Total Trade and Notes Payable | C95: =C89+C94 -> 701.31432 | D95: =D89+D94 -> 815.72641 | E95: =E89+E94 -> 1069.4536 | F95: =F89+F94 -> 1140.4537 | G95: =G89+G94 -> 720.17624 | H95: =H89+H94 -> 709.47267 | I95: =I89+I94 -> 771.99904 | J95: =J89+J94 -> 827.36161 | ... L95: =L89+L94 -> 927.14164
B96: Local trade payables turnover | C96: =-'Financial Statements'!D5/Debt!C86 -> 4.832565 | D96: =-'Financial Statements'!E5/Debt!D86 -> 7.0766042 | E96: =-'Financial Statements'!F5/Debt!E86 -> 14.543294 | F96: =-'Financial Statements'!G5/Debt!F86 -> 17.344361 | G96: =-'Financial Statements'!H5/Debt!G86 -> 12.364151 | H96: =AVERAGE(C96:G96) -> 11.232195 | I96: =H96 -> 11.232195 | J96: =I96 -> 11.232195 | K96: =J96 -> 11.232195 | L96: =K96 -> 11.232195
B97: DOH | C97: =365/C96 -> 75.529247 | D97: =365/D96 -> 51.578411 | E97: =365/E96 -> 25.097479 | F97: =365/F96 -> 21.044304 | G97: =365/G96 -> 29.520829 | H97: =365/H96 -> 32.495874 | I97: =365/I96 -> 32.495874 | J97: =365/J96 -> 32.495874 | ... L97: =365/L96 -> 32.495874
B98: Foreign trade payables turnover | C98: =-'Financial Statements'!D5/C87 -> 7.4626326 | D98: =-'Financial Statements'!E5/D87 -> 11.585636 | E98: =-'Financial Statements'!F5/E87 -> 5.9788407 | F98: =-'Financial Statements'!G5/F87 -> 13.621798 | G98: =-'Financial Statements'!H5/G87 -> 48.773869 | H98: =AVERAGE(C98:G98) -> 17.484555 | I98: =H98 -> 17.484555 | J98: =I98 -> 17.484555 | K98: =J98 -> 17.484555 | L98: =K98 -> 17.484555
B99: DOH | C99: =365/C98 -> 48.910354 | D99: =365/D98 -> 31.504529 | E99: =365/E98 -> 61.048624 | F99: =365/F98 -> 26.795288 | G99: =365/G98 -> 7.4835154 | H99: =365/H98 -> 20.875567 | I99: =365/I98 -> 20.875567 | J99: =365/J98 -> 20.875567 | ... L99: =365/L98 -> 20.875567
B100: Notes payable turnover | C100: =-'Financial Statements'!D5/C88 -> 593.56757 | D100: =-'Financial Statements'!E5/D88 -> 1157.8635 | E100: =-'Financial Statements'!F5/E88 -> 1637.4442 | F100: =-'Financial Statements'!G5/F88 -> 3571.8451 | G100: 0
B101: DOH | C101: =365/C100 -> 0.61492578 | D101: =365/D100 -> 0.31523579 | E101: =365/E100 -> 0.22290836 | F101: =365/F100 -> 0.10218808
B103: Due to Related Parties
B104: Cementos la Union - Spain company | C104: 2.229273 | D104: 0 | E104: 0 | F104: 0 | G104: 0 | H104: 0 | I104: 0 | J104: 0 | K104: 0 | L104: 0
B105: Andalus reliance for mining company | C105: 9.563634 | D105: 0.369246 | E105: 0 | F105: 0 | G105: 0 | H105: 0 | I105: 0 | J105: 0 | K105: 0 | L105: 0
B106: Total | C106: =SUM(C104:C105) -> 11.792907 | D106: =SUM(D104:D105) -> 0.369246 | E106: =SUM(E104:E105) -> 0 | F106: =SUM(F104:F105) -> 0 | G106: =SUM(G104:G105) -> 0 | H106: =SUM(H104:H105) -> 0 | I106: =SUM(I104:I105) -> 0 | J106: =SUM(J104:J105) -> 0 | ... L106: =SUM(L104:L105) -> 0

Sheet Revenue Bridge
B2: Revenue Bridge | C2: 2021 | D2: =C2+1 -> 2022 | E2: =D2+1 -> 2023 | F2: =E2+1 -> 2024 | G2: =F2+1 -> 2025 | H2: =G2+1 -> 2026 | I2: =H2+1 -> 2027 | J2: =I2+1 -> 2028 | K2: =J2+1 -> 2029 | L2: =K2+1 -> 2030
B4: Sales
B5: =IS!B5 -> Local
B6: =IS!B6 -> Sales | C6: =IS!C6 -> 2054.1196 | D6: =IS!D6 -> 3821.5448 | E6: =IS!E6 -> 3906.434 | F6: =IS!F6 -> 4703.4792 | G6: =IS!G6 -> 8350.4546 | H6: =H57*H70 -> 10320.725 | I6: =I57*I70 -> 10902.035 | J6: =J57*J70 -> 11738.811 | K6: =K57*K70 -> 12495.316 | L6: =L57*L70 -> 13301.991
B7: =IS!B7 -> Services | C7: =IS!C7 -> 92.559521 | D7: =IS!D7 -> 103.05889 | E7: =IS!E7 -> 82.820228 | F7: =IS!F7 -> 179.82523 | G7: =IS!G7 -> 281.86355 | H7: =Assumptions!J172*($G$7/($G$7+$G$11)) -> 290.31945 | I7: =Assumptions!K172*($G$7/($G$7+$G$11)) -> 299.02904 | J7: =Assumptions!L172*($G$7/($G$7+$G$11)) -> 307.99991 | K7: =Assumptions!M172*($G$7/($G$7+$G$11)) -> 317.2399 | L7: =Assumptions!N172*($G$7/($G$7+$G$11)) -> 326.7571
B8: =IS!B8 -> Total Local Sales | C8: =IS!C8 -> 2146.6791 | D8: =IS!D8 -> 3924.6037 | E8: =IS!E8 -> 3989.2543 | F8: =IS!F8 -> 4883.3045 | G8: =IS!G8 -> 8632.3182 | H8: =H6+H7 -> 10611.044 | I8: =I6+I7 -> 11201.064 | J8: =J6+J7 -> 12046.811 | K8: =K6+K7 -> 12812.556 | L8: =L6+L7 -> 13628.748
B9: =IS!B9 -> Export
B10: =IS!B10 -> Sales | C10: =IS!C10 -> 237.80973 | D10: =IS!D10 -> 667.51415 | E10: =IS!E10 -> 1622.381 | F10: =IS!F10 -> 3222.781 | G10: =IS!G10 -> 3356.4224 | H10: =H61*H72 -> 3642.7859 | I10: =I61*I72 -> 4456.0709 | J10: =J61*J72 -> 4720.6741 | K10: =K61*K72 -> 4947.472 | L10: =L61*L72 -> 5142.5129
B11: =IS!B11 -> Services | C11: =IS!C11 -> 64.142523 | D11: =IS!D11 -> 82.884935 | E11: =IS!E11 -> 431.19609 | F11: =IS!F11 -> 623.6973 | G11: =IS!G11 -> 458.57954 | H11: =Assumptions!J172*($G$11/($G$7+$G$11)) -> 472.33693 | I11: =Assumptions!K172*($G$11/($G$7+$G$11)) -> 486.50704 | J11: =Assumptions!L172*($G$11/($G$7+$G$11)) -> 501.10225 | K11: =Assumptions!M172*($G$11/($G$7+$G$11)) -> 516.13532 | L11: =Assumptions!N172*($G$11/($G$7+$G$11)) -> 531.61938
B12: =IS!B12 -> Total Export Sales | C12: =IS!C12 -> 301.95225 | D12: =IS!D12 -> 750.39909 | E12: =IS!E12 -> 2053.5771 | F12: =IS!F12 -> 3846.4783 | G12: =IS!G12 -> 3815.0019 | H12: =H10+H11 -> 4115.1228 | I12: =I10+I11 -> 4942.5779 | J12: =J10+J11 -> 5221.7763 | K12: =K10+K11 -> 5463.6073 | L12: =L10+L11 -> 5674.1322
B13: =B10 -> Sales | C13: =C6+C10 -> 2291.9293 | D13: =D6+D10 -> 4489.059 | E13: =E6+E10 -> 5528.815 | F13: =F6+F10 -> 7926.2603 | G13: =G6+G10 -> 11706.877 | H13: =H6+H10 -> 13963.51 | I13: =I6+I10 -> 15358.105 | J13: =J6+J10 -> 16459.485 | ... L13: =L6+L10 -> 18444.503
B14: =B11 -> Services | C14: =C7+C11 -> 156.70204 | D14: =D7+D11 -> 185.94382 | E14: =E7+E11 -> 514.01632 | F14: =F7+F11 -> 803.52253 | G14: =G7+G11 -> 740.44309 | H14: =H7+H11 -> 762.65638 | I14: =I7+I11 -> 785.53607 | J14: =J7+J11 -> 809.10216 | ... L14: =L7+L11 -> 858.37648
B15: =IS!B13 -> Total Revenue | C15: =SUM(C13:C14) -> 2448.6314 | D15: =SUM(D13:D14) -> 4675.0028 | E15: =SUM(E13:E14) -> 6042.8313 | F15: =SUM(F13:F14) -> 8729.7828 | G15: =SUM(G13:G14) -> 12447.32 | H15: =SUM(H13:H14) -> 14726.167 | I15: =SUM(I13:I14) -> 16143.641 | J15: =SUM(J13:J14) -> 17268.587 | ... L15: =SUM(L13:L14) -> 19302.88
B17: Sales %
B18: =B5 -> Local
B19: =B6 -> Sales | C19: =C6/$C$15 -> 0.83888478 | D19: =D6/$D$15 -> 0.81744225 | E19: =E6/$E$15 -> 0.64645757 | F19: =F6/$F$15 -> 0.53878537 | G19: =G6/$G$15 -> 0.67086365 | H19: =H6/$H$15 -> 0.70084257 | I19: =I6/$G$15 -> 0.87585396 | J19: =J6/$G$15 -> 0.94307939 | K19: =K6/$G$15 -> 1.0038559 | L19: =L6/$G$15 -> 1.068663
B20: =B7 -> Services | C20: =C7/$C$15 -> 0.037800513 | D20: =D7/$D$15 -> 0.022044669 | E20: =E7/$E$15 -> 0.013705534 | F20: =F7/$F$15 -> 0.02059905 | G20: =G7/$G$15 -> 0.022644517 | H20: =AVERAGE(C20:G20) -> 0.023358856 | I20: =AVERAGE(D20:H20) -> 0.020470525 | J20: =AVERAGE(E20:I20) -> 0.020155696 | K20: =AVERAGE(F20:J20) -> 0.021445729 | L20: =AVERAGE(G20:K20) -> 0.021615065
B21: =B8 -> Total Local Sales | C21: =C8/$C$15 -> 0.8766853 | D21: =D8/$D$15 -> 0.83948692 | E21: =E8/$E$15 -> 0.6601631 | F21: =F8/$F$15 -> 0.55938442 | G21: =G8/$G$15 -> 0.69350817 | H21: =H8/$G$15 -> 0.85247619 | I21: =I8/$G$15 -> 0.89987752 | J21: =J8/$G$15 -> 0.96782367 | K21: =K8/$G$15 -> 1.0293425 | L21: =L8/$G$15 -> 1.0949142
B22: =B9 -> Export
B23: =B10 -> Sales | C23: =C10/$C$15 -> 0.097119448 | D23: =D10/$D$15 -> 0.14278369 | E23: =E10/$E$15 -> 0.26848027 | F23: =F10/$F$15 -> 0.36917082 | G23: =G10/$G$15 -> 0.2696502 | H23: =H10/$G$15 -> 0.29265624 | I23: =I10/$G$15 -> 0.3579944 | J23: =J10/$G$15 -> 0.37925224 | K23: =K10/$G$15 -> 0.39747287 | L23: =L10/$G$15 -> 0.41314217
B24: =B11 -> Services | C24: =C11/$C$15 -> 0.026195255 | D24: =D11/$D$15 -> 0.017729387 | E24: =E11/$E$15 -> 0.071356631 | F24: =F11/$F$15 -> 0.071444767 | G24: =G11/$G$15 -> 0.036841629 | H24: =AVERAGE(C24:G24) -> 0.044713534 | I24: =H24 -> 0.044713534 | J24: =I24 -> 0.044713534 | K24: =J24 -> 0.044713534 | L24: =K24 -> 0.044713534
B25: =B12 -> Total Export Sales | C25: =C12/$C$15 -> 0.1233147 | D25: =D12/$D$15 -> 0.16051308 | E25: =E12/$E$15 -> 0.3398369 | F25: =F12/$F$15 -> 0.44061558 | G25: =G12/$G$15 -> 0.30649183 | H25: =H12/$G$15 -> 0.33060312 | I25: =I12/$G$15 -> 0.39707968 | J25: =J12/$G$15 -> 0.41951009 | K25: =K12/$G$15 -> 0.43893844 | L25: =L12/$G$15 -> 0.45585172
B26: =B15 -> Total Revenue | C26: =C15/C$15 -> 1 | D26: =D15/D$15 -> 1 | E26: =E15/E$15 -> 1 | F26: =F15/F$15 -> 1 | G26: =G15/G$15 -> 1 | H26: =H15/H$15 -> 1 | I26: =I15/I$15 -> 1 | J26: =J15/J$15 -> 1 | ... L26: =L15/L$15 -> 1
B27: Local | C27: =C6/C13 -> 0.89624037 | D27: =D6/D13 -> 0.85130199 | E27: =E6/E13 -> 0.70655901 | F27: =F6/F13 -> 0.59340459 | G27: =G6/G13 -> 0.71329481 | H27: =H6/H13 -> 0.73912105 | I27: =I6/I13 -> 0.70985543 | J27: =J6/J13 -> 0.7131943 | ... L27: =L6/L13 -> 0.72118995
B28: Export | C28: =C10/C13 -> 0.10375963 | D28: =D10/D13 -> 0.14869801 | E28: =E10/E13 -> 0.29344099 | F28: =F10/F13 -> 0.40659541 | G28: =G10/G13 -> 0.28670519 | H28: =H10/H13 -> 0.26087895 | I28: =I10/I13 -> 0.29014457 | J28: =J10/J13 -> 0.2868057 | ... L28: =L10/L13 -> 0.27881005
B30: Production Volume
B31: Clinker | C31: 3.19 | D31: 3.81 | E31: 3.93 | F31: 3.61 | G31: 3.8516 | H31: =G31*(1+Assumptions!J137) -> 3.928632 | I31: =H31*(1+Assumptions!K137) -> 4.0072046 | J31: =I31*(1+Assumptions!L137) -> 4.0873487 | K31: =J31*(1+Assumptions!M137) -> 4.1690957 | L31: =K31*(1+0.5%) -> 4.1899412
B32: Cement | C32: 2.8 | D32: 3.25 | E32: 2.76 | F32: 2.94 | G32: 3.4806 | H32: =G32*(1+Assumptions!J70) -> 3.65463 | I32: =H32*(1+Assumptions!K70) -> 3.8299491 | J32: =I32*(1+Assumptions!L70) -> 4.0062415 | K32: =J32*(1+Assumptions!M70) -> 4.1859895 | L32: =K32*(1+Assumptions!N70) -> 4.366083
B33: Total | C33: =SUM(C31:C32) -> 5.99 | D33: =SUM(D31:D32) -> 7.06 | E33: =SUM(E31:E32) -> 6.69 | F33: =SUM(F31:F32) -> 6.55 | G33: =SUM(G31:G32) -> 7.3322 | H33: =SUM(H31:H32) -> 7.583262 | I33: =SUM(I31:I32) -> 7.8371538 | J33: =SUM(J31:J32) -> 8.0935902 | ... L33: =SUM(L31:L32) -> 8.5560241
B35: Capacity & Utilization
B36: Clinker Capacity | C36: 4.2 | D36: 4.2 | E36: 4.2 | F36: 4.2 | G36: 4.2 | H36: 4.2 | I36: 4.2 | J36: 4.2 | K36: 4.2 | L36: 4.2
B37: Cement Capacity | C37: 5 | D37: 5 | E37: 5 | F37: 5 | G37: 5 | H37: 5 | I37: 5 | J37: 5 | K37: 5 | L37: 5
B38: Clinker Utilization | C38: =C31/C36 -> 0.75952381 | D38: =D31/D36 -> 0.90714286 | E38: =E31/E36 -> 0.93571429 | F38: =F31/F36 -> 0.85952381 | G38: =G31/G36 -> 0.91704762 | H38: =H31/H36 -> 0.93538857 | I38: =I31/I36 -> 0.95409634 | J38: =J31/J36 -> 0.97317827 | ... L38: =L31/L36 -> 0.99760504
B39: Cement Utilization | C39: =C32/C37 -> 0.56 | D39: =D32/D37 -> 0.65 | E39: =E32/E37 -> 0.552 | F39: =F32/F37 -> 0.588 | G39: =G32/G37 -> 0.69612 | H39: =H32/H37 -> 0.730926 | I39: =I32/I37 -> 0.76598982 | J39: =J32/J37 -> 0.8012483 | ... L39: =L32/L37 -> 0.87321659
B40: Total Utilization | C40: =C33/C37 -> 1.198 | D40: =D33/D37 -> 1.412 | E40: =E33/E37 -> 1.338 | F40: =F33/F37 -> 1.31 | G40: =G33/G37 -> 1.46644 | H40: =H33/H37 -> 1.5166524 | I40: =I33/I37 -> 1.5674308 | J40: =J33/J37 -> 1.618718 | ... L40: =L33/L37 -> 1.7112048
B42: Volume
B43: Clinker Local | C43: 0.091 | D43: 0.341 | E43: 0.08 | F43: 0 | G43: 0.6116162 | H43: =H49*H45 -> 0.55533214 | I43: =I49*I45 -> 0.54556592 | J43: =J49*J45 -> 0.53654434 | K43: =K49*K45 -> 0.52799062 | L43: =L49*L45 -> 0.51494023 | N43: % | O43: 2025 | P43: 2030
B44: Clinker Export | C44: 0.325 | D44: 0.936 | E44: 1.5419 | F44: 2.0744 | G44: 1.3005 | H44: =H50*H45 -> 1.1808213 | I44: =I50*I45 -> 1.1600551 | J44: =J50*J45 -> 1.1408722 | K44: =K50*K45 -> 1.1226841 | L44: =L50*L45 -> 1.0949346 | N44: Volume
B45: Total Clinker | C45: =SUM(C43:C44) -> 0.416 | D45: =SUM(D43:D44) -> 1.277 | E45: =SUM(E43:E44) -> 1.6219 | F45: =SUM(F43:F44) -> 2.0744 | G45: =SUM(G43:G44) -> 1.9121162 | H45: =H65*H31 -> 1.7361535 | I45: =I65*I31 -> 1.705621 | J45: =J65*J31 -> 1.6774165 | K45: =K65*K31 -> 1.6506748 | L45: =L65*L31 -> 1.6098749 | M45: =_xlfn.RRI(4,C45,G45) -> 0.4642163 | N45: Local | O45: =G57/G62 -> 0.60235701 | P45: =L57/L62 -> 0.72118995
B46: Cement Local | C46: 2.62 | D46: 3.218 | E46: 2.595 | F46: 2.6183 | G46: 2.86244 | H46: =H51*H48 -> 2.9758727 | I46: =I51*I48 -> 3.0037112 | J46: =J51*J48 -> 3.0294272 | K46: =K51*K48 -> 3.0538095 | L46: =L51*L48 -> 3.0910095 | N46: Export | O46: =G61/G62 -> 0.39764299 | P46: =L61/L62 -> 0.27881005
B47: Cement Export | C47: 0.172 | D47: 0.0659 | E47: 0.1593 | F47: 0.3617 | G47: 0.6295 | H47: =H52*H48 -> 0.28797385 | I47: =I52*I48 -> 0.29066777 | J47: =J52*J48 -> 0.29315629 | K47: =K52*K48 -> 0.29551576 | L47: =L52*L48 -> 0.29911559 | N47: ASP
B48: Total Cement | C48: =SUM(C46:C47) -> 2.792 | D48: =SUM(D46:D47) -> 3.2839 | E48: =SUM(E46:E47) -> 2.7543 | F48: =SUM(F46:F47) -> 2.98 | G48: =SUM(G46:G47) -> 3.49194 | H48: =H66*H32 -> 3.2638465 | I48: =I66*I32 -> 3.294379 | J48: =J66*J32 -> 3.3225835 | K48: =K66*K32 -> 3.3493252 | L48: =L66*L32 -> 3.3901251 | M48: =_xlfn.RRI(4,C48,G48) -> 0.057518172 | N48: Local
B49: local clinker % of total | C49: =C43/C45 -> 0.21875 | D49: =D43/D45 -> 0.26703211 | E49: =E43/E45 -> 0.049324866 | F49: =F43/F45 -> 0 | G49: =G43/G45 -> 0.31986351 | H49: =G49 -> 0.31986351 | I49: =H49 -> 0.31986351 | J49: =I49 -> 0.31986351 | K49: =J49 -> 0.31986351 | L49: =K49 -> 0.31986351 | N49: Export
B50: export clinker % of total | C50: =C44/C45 -> 0.78125 | D50: =D44/D45 -> 0.73296789 | E50: =E44/E45 -> 0.95067513 | F50: =F44/F45 -> 1 | G50: =G44/G45 -> 0.68013649 | H50: =G50 -> 0.68013649 | I50: =H50 -> 0.68013649 | J50: =I50 -> 0.68013649 | K50: =J50 -> 0.68013649 | L50: =K50 -> 0.68013649
B51: local cement % of total | C51: =C46/C48 -> 0.93839542 | D51: =D46/D48 -> 0.9799324 | E51: =E46/E48 -> 0.94216316 | F51: =F46/F48 -> 0.87862416 | G51: =G46/G48 -> 0.81972771 | H51: =AVERAGE(C51:G51) -> 0.91176857 | I51: =H51 -> 0.91176857 | J51: =I51 -> 0.91176857 | K51: =J51 -> 0.91176857 | L51: =K51 -> 0.91176857
B52: export cement % of total | C52: =C47/C48 -> 0.061604585 | D52: =D47/D48 -> 0.020067603 | E52: =E47/E48 -> 0.057836837 | F52: =F47/F48 -> 0.12137584 | G52: =G47/G48 -> 0.18027229 | H52: =AVERAGE(C52:G52) -> 0.08823143 | I52: =H52 -> 0.08823143 | J52: =I52 -> 0.08823143 | K52: =J52 -> 0.08823143 | L52: =K52 -> 0.08823143
B54: Local Volume
B55: Clinker | C55: =C43 -> 0.091 | D55: =D43 -> 0.341 | E55: =E43 -> 0.08 | F55: =F43 -> 0 | G55: =G43 -> 0.6116162 | H55: =H43 -> 0.55533214 | I55: =I43 -> 0.54556592 | J55: =J43 -> 0.53654434 | ... L55: =L43 -> 0.51494023
B56: Cement | C56: =C46 -> 2.62 | D56: =D46 -> 3.218 | E56: =E46 -> 2.595 | F56: =F46 -> 2.6183 | G56: =G46 -> 2.86244 | H56: =H46 -> 2.9758727 | I56: =I46 -> 3.0037112 | J56: =J46 -> 3.0294272 | ... L56: =L46 -> 3.0910095
B57: Total Local Volume | C57: =SUM(C55:C56) -> 2.711 | D57: =SUM(D55:D56) -> 3.559 | E57: =SUM(E55:E56) -> 2.675 | F57: =SUM(F55:F56) -> 2.6183 | G57: 2.9236 | H57: =SUM(H55:H56) -> 3.5312048 | I57: =SUM(I55:I56) -> 3.5492772 | J57: =SUM(J55:J56) -> 3.5659715 | K57: =SUM(K55:K56) -> 3.5818001 | L57: =SUM(L55:L56) -> 3.6059498
B58: Export Volume
B59: Clinker | C59: =C44 -> 0.325 | D59: =D44 -> 0.936 | E59: =E44 -> 1.5419 | F59: =F44 -> 2.0744 | G59: =G44 -> 1.3005 | H59: =H44 -> 1.1808213 | I59: =I44 -> 1.1600551 | J59: =J44 -> 1.1408722 | ... L59: =L44 -> 1.0949346
B60: Cement | C60: =C47 -> 0.172 | D60: =D47 -> 0.0659 | E60: =E47 -> 0.1593 | F60: =F47 -> 0.3617 | G60: =G47 -> 0.6295 | H60: =H47 -> 0.28797385 | I60: =I47 -> 0.29066777 | J60: =J47 -> 0.29315629 | ... L60: =L47 -> 0.29911559
B61: Total Export Volume | C61: =SUM(C59:C60) -> 0.497 | D61: =SUM(D59:D60) -> 1.0019 | E61: =SUM(E59:E60) -> 1.7012 | F61: =SUM(F59:F60) -> 2.4361 | G61: =SUM(G59:G60) -> 1.93 | H61: =SUM(H59:H60) -> 1.4687952 | I61: =SUM(I59:I60) -> 1.4507228 | J61: =SUM(J59:J60) -> 1.4340285 | ... L61: =SUM(L59:L60) -> 1.3940502
B62: Total Volume | C62: =C57+C61 -> 3.208 | D62: =D57+D61 -> 4.5609 | E62: =E57+E61 -> 4.3762 | F62: =F57+F61 -> 5.0544 | G62: =G57+G61 -> 4.8536 | H62: =H57+H61 -> 5 | I62: =I57+I61 -> 5 | J62: =J57+J61 -> 5 | ... L62: =L57+L61 -> 5
B64: Production to Sales
B65: Clinker | C65: =IFERROR(C45/C31,0) -> 0.13040752 | D65: =IFERROR(D45/D31,0) -> 0.3351706 | E65: =IFERROR(E45/E31,0) -> 0.4126972 | F65: =IFERROR(F45/F31,0) -> 0.57462604 | G65: =IFERROR(G45/G31,0) -> 0.49644724 | H65: =$G$65*H37/(H31*$G$65+H32*$G$66) -> 0.44192316 | I65: =$G$65*I37/(I31*$G$65+I32*$G$66) -> 0.4256386 | J65: =$G$65*J37/(J31*$G$65+J32*$G$66) -> 0.41039232 | K65: =$G$65*K37/(K31*$G$65+K32*$G$66) -> 0.39593112 | L65: =$G$65*L37/(L31*$G$65+L32*$G$66) -> 0.38422374
B66: Cement | C66: =IFERROR(C48/C32,0) -> 0.99714286 | D66: =IFERROR(D48/D32,0) -> 1.0104308 | E66: =IFERROR(E48/E32,0) -> 0.99793478 | F66: =IFERROR(F48/F32,0) -> 1.0136054 | G66: =IFERROR(G48/G32,0) -> 1.0032581 | H66: =$G$66*H37/(H31*$G$65+H32*$G$66) -> 0.89307167 | I66: =$G$66*I37/(I31*$G$65+I32*$G$66) -> 0.86016261 | J66: =$G$66*J37/(J31*$G$65+J32*$G$66) -> 0.82935177 | K66: =$G$66*K37/(K31*$G$65+K32*$G$66) -> 0.80012749 | L66: =$G$66*L37/(L31*$G$65+L32*$G$66) -> 0.77646833
B67: Total | C67: =IFERROR(C62/C33,0) -> 0.53555927 | D67: =IFERROR(D62/D33,0) -> 0.64601983 | E67: =IFERROR(E62/E33,0) -> 0.65414051 | F67: =IFERROR(F62/F33,0) -> 0.77166412 | G67: =IFERROR(G62/G33,0) -> 0.66195685 | H67: =IFERROR(H62/H33,0) -> 0.65934686 | I67: =IFERROR(I62/I33,0) -> 0.63798672 | J67: =IFERROR(J62/J33,0) -> 0.61777281 | ... L67: =IFERROR(L62/L33,0) -> 0.58438358
B69: Price
B70: Local Sales ASP | C70: =C6/C57 -> 757.69811 | D70: =D6/D57 -> 1073.7693 | E70: =E6/E57 -> 1460.3492 | F70: =F6/F57 -> 1796.3867 | G70: =G6/G57 -> 2856.2234 | H70: =Assumptions!F182 -> 2922.7204 | I70: =I71*'COGS Bridge'!J29 -> 3071.6211 | J70: =J71*'COGS Bridge'!K29 -> 3291.897 | K70: =K71*'COGS Bridge'!L29 -> 3488.5576 | L70: =L71*'COGS Bridge'!M29 -> 3688.9007
B71: Conversion Factor | C71: =C70/'COGS Bridge'!D26 -> 1.4252016 | D71: =D70/'COGS Bridge'!E26 -> 1.5702943 | E71: =E70/'COGS Bridge'!F26 -> 1.6907641 | F71: =F70/'COGS Bridge'!G26 -> 1.737619 | G71: =G70/'COGS Bridge'!H26 -> 2.432874 | H71: =H70/'COGS Bridge'!I26 -> 2.2571626 | I71: 1.75 | J71: 1.75 | K71: 1.75 | L71: 1.75
B72: Export Sales ASP | C72: =C10/C61 -> 478.49039 | D72: =D10/D61 -> 666.24828 | E72: =E10/E61 -> 953.66857 | F72: =F10/F61 -> 1322.9264 | G72: =G10/G61 -> 1739.079 | H72: =Assumptions!F183 -> 2480.1184 | I72: =I73*'COGS Bridge'!J29 -> 3071.6211 | J72: =J73*'COGS Bridge'!K29 -> 3291.897 | K72: =K73*'COGS Bridge'!L29 -> 3488.5576 | L72: =L73*'COGS Bridge'!M29 -> 3688.9007
B73: Conversion Factor | C73: =C72/'COGS Bridge'!D26 -> 0.90002241 | D73: =D72/'COGS Bridge'!E26 -> 0.97433023 | E73: =E72/'COGS Bridge'!F26 -> 1.1041391 | F73: =F72/'COGS Bridge'!G26 -> 1.2796477 | G73: =G72/'COGS Bridge'!H26 -> 1.4813127 | H73: =H72/'COGS Bridge'!I26 -> 1.9153492 | I73: 1.75 | J73: =I73 -> 1.75 | K73: =J73 -> 1.75 | L73: =K73 -> 1.75
B74: Total ASP | C74: =C15/C62 -> 763.28908 | D74: =D15/D62 -> 1025.0176 | E74: =E15/E62 -> 1380.8398 | F74: =F15/F62 -> 1727.165 | G74: =G15/G62 -> 2564.5542 | H74: =H15/H62 -> 2945.2334 | I74: =I15/I62 -> 3228.7283 | J74: =J15/J62 -> 3453.7175 | ... L74: =L15/L62 -> 3860.576
B76: Price Effect
B77: =B70 -> Local Sales ASP | D77: =(D70-C70)*AVERAGE(C57:D57) -> 990.88309 | E77: =(E70-D70)*AVERAGE(D57:E57) -> 1204.9696 | F77: =(F70-E70)*AVERAGE(E57:F57) -> 889.37366 | G77: =(G70-F70)*AVERAGE(F57:G57) -> 2936.7544 | H77: =(H70-G70)*AVERAGE(G57:H57) -> 214.61285 | I77: =(I70-H70)*AVERAGE(H57:I57) -> 527.14414 | J77: =(J70-I70)*AVERAGE(I57:J57) -> 783.65906 | K77: =(K70-J70)*AVERAGE(J57:K57) -> 702.84244 | L77: =(L70-K70)*AVERAGE(K57:L57) -> 720.00805
B78: =B72 -> Export Sales ASP | D78: =(D72-C72)*AVERAGE(C61:D61) -> 140.71515 | E78: =(E72-D72)*AVERAGE(D61:E61) -> 388.46289 | F78: =(F72-E72)*AVERAGE(E61:F61) -> 763.86524 | G78: =(G72-F72)*AVERAGE(F61:G61) -> 908.48179 | H78: =(H72-G72)*AVERAGE(G61:H61) -> 1259.3206 | I78: =(I72-H72)*AVERAGE(H61:I61) -> 863.45141 | J78: =(J72-I72)*AVERAGE(I61:J61) -> 317.72066 | K78: =(K72-J72)*AVERAGE(J61:K61) -> 280.46043 | L78: =(L72-K72)*AVERAGE(K61:L61) -> 281.70745
B79: Total | D79: =SUM(D77:D78) -> 1131.5982 | E79: =SUM(E77:E78) -> 1593.4324 | F79: =SUM(F77:F78) -> 1653.2389 | G79: =SUM(G77:G78) -> 3845.2362 | H79: =SUM(H77:H78) -> 1473.9334 | I79: =SUM(I77:I78) -> 1390.5956 | J79: =SUM(J77:J78) -> 1101.3797 | K79: =SUM(K77:K78) -> 983.30287 | L79: =SUM(L77:L78) -> 1001.7155
B81: Volume Effect
B82: Local | D82: =(D57-C57)*AVERAGE(C70:D70) -> 776.54217 | E82: =(E57-D57)*AVERAGE(D70:E70) -> -1120.0804 | F82: =(F57-E57)*AVERAGE(E70:F70) -> -92.328462 | G82: =(G57-F57)*AVERAGE(F70:G70) -> 710.22092 | H82: =(H57-G57)*AVERAGE(G70:H70) -> 1755.6571 | I82: =(I57-H57)*AVERAGE(H70:I70) -> 54.165873 | J82: =(J57-I57)*AVERAGE(I70:J70) -> 53.117434 | K82: =(K57-J57)*AVERAGE(J70:K70) -> 53.662526 | L82: =(L57-K57)*AVERAGE(K70:L70) -> 86.666573
B83: Export | D83: =(D61-C61)*AVERAGE(C72:D72) -> 288.98928 | E83: =(E61-D61)*AVERAGE(D72:E72) -> 566.40393 | F83: =(F61-E61)*AVERAGE(E72:F72) -> 836.53483 | G83: =(G61-F61)*AVERAGE(F72:G72) -> -774.84046 | H83: =(H61-G61)*AVERAGE(G72:H72) -> -972.95708 | I83: =(I61-H61)*AVERAGE(H72:I72) -> -50.166447 | J83: =(J61-I61)*AVERAGE(I72:J72) -> -53.117434 | K83: =(K61-J61)*AVERAGE(J72:K72) -> -53.662526 | L83: =(L61-K61)*AVERAGE(K72:L72) -> -86.666573
B84: Total | D84: =SUM(D82:D83) -> 1065.5315 | E84: =SUM(E82:E83) -> -553.67643 | F84: =SUM(F82:F83) -> 744.20637 | G84: =SUM(G82:G83) -> -64.619537 | H84: =SUM(H82:H83) -> 782.69999 | I84: =SUM(I82:I83) -> 3.9994264 | J84: =SUM(J82:J83) -> -1.41398e-12 | K84: =SUM(K82:K83) -> 7.4606987e-13 | L84: =SUM(L82:L83) -> 0
B86: Waterfall Bridge
B87: Prior Sales | D87: =C90 -> 2291.9293 | E87: =D90 -> 4489.059 | F87: =E90 -> 5528.815 | G87: =F90 -> 7926.2603 | H87: =G90 -> 11706.877 | I87: =H90 -> 13963.51 | J87: =I90 -> 15358.105 | K87: =J90 -> 16459.485 | L87: =K90 -> 17442.788
B88: Price Effect | C88: =C79 -> 0 | D88: =D79 -> 1131.5982 | E88: =E79 -> 1593.4324 | F88: =F79 -> 1653.2389 | G88: =G79 -> 3845.2362 | H88: =H79 -> 1473.9334 | I88: =I79 -> 1390.5956 | J88: =J79 -> 1101.3797 | ... L88: =L79 -> 1001.7155
B89: Volume Effect | C89: =C84 -> 0 | D89: =D84 -> 1065.5315 | E89: =E84 -> -553.67643 | F89: =F84 -> 744.20637 | G89: =G84 -> -64.619537 | H89: =H84 -> 782.69999 | I89: =I84 -> 3.9994264 | J89: =J84 -> -1.41398e-12 | ... L89: =L84 -> 0
B90: Current Revenue | C90: =C13 -> 2291.9293 | D90: =SUM(D87:D89) -> 4489.059 | E90: =SUM(E87:E89) -> 5528.815 | F90: =SUM(F87:F89) -> 7926.2603 | G90: =SUM(G87:G89) -> 11706.877 | H90: =SUM(H87:H89) -> 13963.51 | I90: =SUM(I87:I89) -> 15358.105 | J90: =SUM(J87:J89) -> 16459.485 | K90: =SUM(K87:K89) -> 17442.788 | L90: =SUM(L87:L89) -> 18444.503
B91: Total | C91: =C13 -> 2291.9293 | D91: =D13 -> 4489.059 | E91: =E13 -> 5528.815 | F91: =F13 -> 7926.2603 | G91: =G13 -> 11706.877 | H91: =H13 -> 13963.51 | I91: =I13 -> 15358.105 | J91: =J13 -> 16459.485 | ... L91: =L13 -> 18444.503
B92: Checker | C92: =C91=C90 -> TRUE | D92: =D91=D90 -> TRUE | E92: =E91=E90 -> TRUE | F92: =F91=F90 -> TRUE | G92: =G91=G90 -> TRUE | H92: =H91=H90 -> TRUE | I92: =I91=I90 -> TRUE | J92: =J91=J90 -> TRUE | ... L92: =L91=L90 -> TRUE
B94: Summary
B95: Prior Sales | C95: =C15 -> 2448.6314 | D95: =C96 -> 2448.6314 | E95: =D96 -> 4489.059 | F95: =E96 -> 5528.815 | G95: =F96 -> 7926.2603 | H95: =G96 -> 11706.877 | I95: =H96 -> 13963.51 | J95: =I96 -> 15358.105 | K95: =J96 -> 16459.485 | L95: =K96 -> 17442.788
B96: New Sales | C96: =C15 -> 2448.6314 | D96: =D13 -> 4489.059 | E96: =E13 -> 5528.815 | F96: =F13 -> 7926.2603 | G96: =G13 -> 11706.877 | H96: =H13 -> 13963.51 | I96: =I13 -> 15358.105 | J96: =J13 -> 16459.485 | K96: =K13 -> 17442.788 | L96: =L13 -> 18444.503
B97: Δ Sales | C97: =C96-C95 -> 0 | D97: =D96-D95 -> 2040.4276 | E97: =E96-E95 -> 1039.756 | F97: =F96-F95 -> 2397.4453 | G97: =G96-G95 -> 3780.6167 | H97: =H96-H95 -> 2256.6334 | I97: =I96-I95 -> 1394.595 | J97: =J96-J95 -> 1101.3797 | ... L97: =L96-L95 -> 1001.7155
B98: % Change | C98: =IF(C95=0,NA(),C97/C95) -> 0 | D98: =IF(D95=0,NA(),D97/D95) -> 0.83329312 | E98: =IF(E95=0,NA(),E97/E95) -> 0.23162004 | F98: =IF(F95=0,NA(),F97/F95) -> 0.43362733 | G98: =IF(G95=0,NA(),G97/G95) -> 0.47697357 | H98: =IF(H95=0,NA(),H97/H95) -> 0.19276135 | I98: =IF(I95=0,NA(),I97/I95) -> 0.09987424 | J98: =IF(J95=0,NA(),J97/J95) -> 0.071713254 | ... L98: =IF(L95=0,NA(),L97/L95) -> 0.057428635
C100: Historic
B101: =B87 -> Prior Sales | C101: =D87 -> 2291.9293 | D101: Δ Quantity | E101: Δ ASP | F101: Elasticity
B102: =B88 -> Price Effect | C102: =SUM(D88:G88) -> 8223.5058 | D102: =D62/C62-1 -> 0.42172693 | E102: =G74/C74-1 -> 2.3598727 | F102: =D102/E102 -> 0.17870749
B103: =B89 -> Volume Effect | C103: =SUM(D89:G89) -> 1191.4419
B104: =B90 -> Current Revenue | C104: =SUM(C101:C103) -> 11706.877

Sheet COGS Bridge
B2: COGS Bridge | C2: Unit | D2: 2021 | E2: =D2+1 -> 2022 | F2: =E2+1 -> 2023 | G2: =F2+1 -> 2024 | H2: =G2+1 -> 2025 | I2: =H2+1 -> 2026 | J2: =I2+1 -> 2027 | K2: =J2+1 -> 2028 | L2: =K2+1 -> 2029 | M2: =L2+1 -> 2030
B4: Cost of Sales
B5: Raw materials | C5: Mn EGP | D5: 1705.51 | E5: 3118.7494 | F5: 3779.8177 | G5: 5225.344 | H5: 5698.1847 | I5: =IF('Financial Statements'!$N$1="Core",(Assumptions!J165+Assumptions!J166)*'Revenue Bridge'!H62,'ESG Integration'!I67*Assumptions!J176) -> 6474.3241 | J5: =IF('Financial Statements'!$N$1="Core",(Assumptions!K165+Assumptions!K166)*'Revenue Bridge'!I62,'ESG Integration'!J67*Assumptions!K176) -> 7008.5278 | K5: =IF('Financial Statements'!$N$1="Core",(Assumptions!L165+Assumptions!L166)*'Revenue Bridge'!J62,'ESG Integration'!K67*Assumptions!L176) -> 7494.7175 | L5: =IF('Financial Statements'!$N$1="Core",(Assumptions!M165+Assumptions!M166)*'Revenue Bridge'!K62,'ESG Integration'!L67*Assumptions!M176) -> 7938.1413 | M5: =IF('Financial Statements'!$N$1="Core",(Assumptions!N165+Assumptions!N166)*'Revenue Bridge'!L62,'ESG Integration'!M67*Assumptions!N176) -> 8400.9751
B6: Depreciation | C6: Mn EGP | D6: 215.82438 | E6: 205.95811 | F6: 212.76065 | G6: 217.7172 | H6: 254.76555
B7: Amortization of Licenses, Intangible assets | C7: Mn EGP | D7: 34.624973 | E7: 28.156249 | F7: 28.156249 | G7: 28.156249 | H7: 28.156249
B8: Amortization of right of use | C8: Mn EGP | D8: 5.902848 | E8: 5.487561 | F8: 6.891333 | G8: 7.082414 | H8: 2.525364
B9: Transportation costs | C9: Mn EGP | D9: 114.65141 | E9: 165.49009 | F9: 498.18933 | G9: 792.24221 | H9: 764.27933 | I9: =H9*(1+Assumptions!J8) -> 865.1642 | J9: =I9*(1+Assumptions!K8) -> 961.19743 | K9: =J9*(1+Assumptions!L8) -> 1039.0544 | L9: =K9*(1+Assumptions!M8) -> 1103.4758 | M9: =L9*(1+Assumptions!N8) -> 1163.0635
B10: Overhead costs | C10: Mn EGP | D10: 204.57001 | E10: 265.97482 | F10: 233.99995 | G10: 372.4304 | H10: 641.14321 | I10: =H10*(1+Assumptions!J8) -> 725.77411 | J10: =I10*(1+Assumptions!K8) -> 806.33504 | K10: =J10*(1+Assumptions!L8) -> 871.64818 | L10: =K10*(1+Assumptions!M8) -> 925.69036 | M10: =L10*(1+Assumptions!N8) -> 975.67764
B11: Total | C11: Mn EGP | D11: =SUM(D5:D10) -> 2281.0836 | E11: =SUM(E5:E10) -> 3789.8162 | F11: =SUM(F5:F10) -> 4759.8152 | G11: =SUM(G5:G10) -> 6642.9725 | H11: =SUM(H5:H10) -> 7389.0544 | I11: =SUM(I5:I10) -> 8065.2624 | J11: =SUM(J5:J10) -> 8776.0602 | K11: =SUM(K5:K10) -> 9405.4201 | ... M11: =SUM(M5:M10) -> 10539.716
B13: COGS %
B14: =B5 -> Raw materials | C14: % | D14: =D5/$D$11 -> 0.74767535 | E14: =E5/$E$11 -> 0.82292893 | F14: =F5/$F$11 -> 0.79411018 | G14: =G5/$G$11 -> 0.78659727 | H14: =H5/$H$11 -> 0.77116562 | I14: =I5/$I$11 -> 0.8027419 | J14: =J5/$J$11 -> 0.79859613 | K14: =K5/$K$11 -> 0.7968509 | L14: =L5/$L$11 -> 0.79641782 | M14: =M5/$M$11 -> 0.79707792
B15: =B6 -> Depreciation | C15: % | D15: =D6/$D$11 -> 0.094614851 | E15: =E6/$E$11 -> 0.054345144 | F15: =F6/$F$11 -> 0.044699351 | G15: =G6/$G$11 -> 0.032774064 | H15: =H6/$H$11 -> 0.034478775
B16: =B7 -> Amortization of Licenses, Intangible assets | C16: % | D16: =D7/$D$11 -> 0.015179178 | E16: =E7/$E$11 -> 0.0074294497 | F16: =F7/$F$11 -> 0.005915408 | G16: =G7/$G$11 -> 0.0042385015 | H16: =H7/$H$11 -> 0.0038105348
B17: =B8 -> Amortization of right of use | C17: % | D17: =D8/$D$11 -> 0.0025877386 | E17: =E8/$E$11 -> 0.0014479755 | F17: =F8/$F$11 -> 0.0014478152 | G17: =G8/$G$11 -> 0.0010661513 | H17: =H8/$H$11 -> 0.00034177093
B18: =B9 -> Transportation costs | C18: % | D18: =D9/$D$11 -> 0.050261817 | E18: =E9/$E$11 -> 0.043667049 | F18: =F9/$F$11 -> 0.10466569 | G18: =G9/$G$11 -> 0.1192602 | H18: =H9/$H$11 -> 0.10343398 | I18: =I9/$I$11 -> 0.10727043 | J18: =J9/$J$11 -> 0.10952494 | K18: =K9/$K$11 -> 0.110474 | L18: =L9/$L$11 -> 0.11070952 | M18: =M9/$M$11 -> 0.11035055
B19: =B10 -> Overhead costs | C19: % | D19: =D10/$D$11 -> 0.089681065 | E19: =E10/$E$11 -> 0.070181456 | F19: =F10/$F$11 -> 0.049161561 | G19: =G10/$G$11 -> 0.056063817 | H19: =H10/$H$11 -> 0.086769317 | I19: =I10/$I$11 -> 0.089987662 | J19: =J10/$J$11 -> 0.091878932 | K19: =K10/$K$11 -> 0.092675093 | L19: =L10/$L$11 -> 0.092872661 | M19: =M10/$M$11 -> 0.092571528
B20: =B11 -> Total | C20: % | D20: =SUM(D14:D19) -> 1 | E20: =SUM(E14:E19) -> 1 | F20: =SUM(F14:F19) -> 1 | G20: =SUM(G14:G19) -> 1 | H20: =SUM(H14:H19) -> 1
B22: COGS /Ton
B23: Clinker Production | C23: Mn ton | D23: 3.189 | E23: 3.9164 | F23: 3.9271 | G23: 3.6067 | H23: 3.8516
B24: Cement Production | C24: Mn ton | D24: 2.796 | E24: 3.2536 | F24: 2.7626 | G24: 2.9354 | H24: 3.4806
B25: Production Volume | C25: Mn ton | D25: =D23+D24 -> 5.985 | E25: =E23+E24 -> 7.17 | F25: =F23+F24 -> 6.6897 | G25: =G23+G24 -> 6.5421 | H25: =H23+H24 -> 7.3322 | I25: ='Revenue Bridge'!H33 -> 7.583262 | J25: ='Revenue Bridge'!I33 -> 7.8371538 | K25: ='Revenue Bridge'!J33 -> 8.0935902 | L25: ='Revenue Bridge'!K33 -> 8.3550852 | M25: ='Revenue Bridge'!L33 -> 8.5560241
B26: RM/ton | D26: =D5/'Revenue Bridge'!C62 -> 531.64276 | E26: =E5/'Revenue Bridge'!D62 -> 683.80131 | F26: =F5/'Revenue Bridge'!E62 -> 863.72143 | G26: =G5/'Revenue Bridge'!F62 -> 1033.8208 | H26: =H5/'Revenue Bridge'!G62 -> 1174.012 | I26: =Assumptions!J165+Assumptions!J166 -> 1294.8648 | J26: =Assumptions!K165+Assumptions!K166 -> 1401.7056 | K26: =Assumptions!L165+Assumptions!L166 -> 1498.9435 | L26: =Assumptions!M165+Assumptions!M166 -> 1587.6283 | M26: =Assumptions!N165+Assumptions!N166 -> 1680.195
B27: Transportation/ton | D27: =D9/'Revenue Bridge'!C62 -> 35.739216 | E27: =E9/'Revenue Bridge'!D62 -> 36.284525 | F27: =F9/'Revenue Bridge'!E62 -> 113.84062 | G27: =G9/'Revenue Bridge'!F62 -> 156.74308 | H27: =H9/'Revenue Bridge'!G62 -> 157.46649 | I27: =I9/I25 -> 114.08866 | J27: =J9/J25 -> 122.64624 | K27: =K9/K25 -> 128.37991 | L27: =L9/L25 -> 132.07236 | M27: =M9/M25 -> 135.93504
B28: Overhead/ton | D28: =D10/'Revenue Bridge'!C62 -> 63.768705 | E28: =E10/'Revenue Bridge'!D62 -> 58.316302 | F28: =F10/'Revenue Bridge'!E62 -> 53.471036 | G28: =G10/'Revenue Bridge'!F62 -> 73.684393 | H28: =H10/'Revenue Bridge'!G62 -> 132.09642 | I28: =I10/I25 -> 95.707377 | J28: =J10/J25 -> 102.88621 | K28: =K10/K25 -> 107.69611 | L28: =L10/L25 -> 110.79365 | M28: =M10/M25 -> 114.034
B29: COGS/ton | D29: =D11/'Revenue Bridge'!C62 -> 711.06097 | E29: =E11/'Revenue Bridge'!D62 -> 830.93605 | F29: =F11/'Revenue Bridge'!E62 -> 1087.6594 | G29: =G11/'Revenue Bridge'!F62 -> 1314.295 | H29: =H11/'Revenue Bridge'!G62 -> 1522.3864 | I29: =I11/'Revenue Bridge'!H62 -> 1613.0525 | J29: =J11/'Revenue Bridge'!I62 -> 1755.212 | K29: =K11/'Revenue Bridge'!J62 -> 1881.084 | ... M29: =M11/'Revenue Bridge'!L62 -> 2107.9433
B32: Effects
B33: Volume Effect | E33: =(E25-D25)*D29 -> 842.60725 | F33: =(F25-E25)*E29 -> -399.09858 | G33: =(G25-F25)*F29 -> -160.53853 | H33: =(H25-G25)*G29 -> 1038.4245 | I33: =(I25-H25)*H29 -> 382.21336 | J33: =(J25-I25)*I29 -> 409.54072 | K33: =(K25-J25)*J29 -> 450.1004 | L33: =(L25-K25)*K29 -> 491.89392 | M33: =(M25-L25)*L29 -> 400.56412
B34: COGS /Ton Effect | E34: =(E11-D11)-E33 -> 666.12538 | F34: =(F11-E11)-F33 -> 1369.0976 | G34: =(G11-F11)-G33 -> 2043.6958 | H34: =(H11-G11)-H33 -> -292.34253 | I34: =(I11-H11)-I33 -> 293.99467 | J34: =(J11-I11)-J33 -> 301.25706 | K34: =(K11-J11)-K33 -> 179.25944 | L34: =(L11-K11)-L33 -> 69.993435 | M34: =(M11-L11)-M33 -> 171.84473
B35: Total COGS Change | E35: =E33+E34 -> 1508.7326 | F35: =F33+F34 -> 969.999 | G35: =G33+G34 -> 1883.1573 | H35: =H33+H34 -> 746.08193 | I35: =I33+I34 -> 676.20803 | J35: =J33+J34 -> 710.79778 | K35: =K33+K34 -> 629.35984 | L35: =L33+L34 -> 561.88736 | M35: =M33+M34 -> 572.40886
B37: Inflation Impact
B38: COGS/ton growth | C38: % | E38: =E29/D29-1 -> 0.16858622 | F38: =F29/E29-1 -> 0.30895686 | G38: =G29/F29-1 -> 0.20836994 | H38: =H29/G29-1 -> 0.15832929
B39: Inflation | C39: % | E39: =Assumptions!F8 -> 0.132 | F39: =Assumptions!G8 -> 0.357 | G39: =Assumptions!H8 -> 0.275 | H39: =Assumptions!I8 -> 0.149
B40: Difference | E40: =E38-E39 -> 0.036586216 | F40: =F38-F39 -> -0.048043145 | G40: =G38-G39 -> -0.066630056 | H40: =H38-H39 -> 0.0093292888
B43: FX Sensitivity
B44: EX rate | C44: USD/EGP | D44: =Assumptions!E6 -> 15.66 | E44: =Assumptions!F6 -> 24.69 | F44: =Assumptions!G6 -> 30.84 | G44: =Assumptions!H6 -> 50.79 | H44: =Assumptions!I6 -> 47.09
B45: YoY depreciation | E45: =E44/D44-1 -> 0.57662835 | F45: =F44/E44-1 -> 0.2490887 | G45: =G44/F44-1 -> 0.64688716 | H45: =H44/G44-1 -> -0.072848986
B46: Coal Cost | C46: =Assumptions!D141 -> USD/ton | D46: =Assumptions!E141 -> 183.88 | E46: =Assumptions!F141 -> 370.39333 | F46: =Assumptions!G141 -> 136.92 | G46: =Assumptions!H141 -> 139.52 | H46: =Assumptions!I141 -> 109.25667
B47: Imported coal exposure | D47: =60%*D46 -> 110.328 | E47: =60%*E46 -> 222.236 | F47: =60%*F46 -> 82.152 | G47: =60%*G46 -> 83.712 | H47: =60%*H46 -> 65.554
B48: FX Impact | E48: =E47*E45 -> 128.14758 | F48: =F47*F45 -> 20.463135 | G48: =G47*G45 -> 54.152218 | H48: =H47*H45 -> -4.7755424
B49: Volume Effect
B50: Δ Production Volume | E50: =E25-D25 -> 1.185 | F50: =F25-E25 -> -0.4803 | G50: =G25-F25 -> -0.1476 | H50: =H25-G25 -> 0.7901 | I50: =I25-H25 -> 0.251062 | J50: =J25-I25 -> 0.25389175 | K50: =K25-J25 -> 0.25643648 | L50: =L25-K25 -> 0.26149492 | M50: =M25-L25 -> 0.20093898
B51: RM Volume effect | E51: =E50*E26 -> 810.30455 | F51: =F50*F26 -> -414.8454 | G51: =G50*G26 -> -152.59195 | H51: =H50*H26 -> 927.58689 | I51: =I50*I26 -> 325.09135 | J51: =J50*J26 -> 355.88148 | K51: =K50*K26 -> 384.3838 | L51: =L50*L26 -> 415.15673 | M51: =M50*M26 -> 337.61668
B52: Transportation Volume effect | E52: =E50*E27 -> 42.997163 | F52: =F50*F27 -> -54.67765 | G52: =G50*G27 -> -23.135278 | H52: =H50*H27 -> 124.41427 | I52: =I50*I27 -> 28.643327 | J52: =J50*J27 -> 31.138868 | K52: =K50*K27 -> 32.921294 | L52: =L50*L27 -> 34.536251 | M52: =M50*M27 -> 27.314649
B53: Overhead Volume effect | E53: =E50*E28 -> 69.104817 | F53: =F50*F28 -> -25.682139 | G53: =G50*G28 -> -10.875816 | H53: =H50*H28 -> 104.36939 | I53: =I50*I28 -> 24.028485 | J53: =J50*J28 -> 26.12196 | K53: =K50*K28 -> 27.617211 | L53: =L50*L28 -> 28.971976 | M53: =M50*M28 -> 22.913876
B54: Total Volume Effect | E54: =E51+E52+E53 -> 922.40653 | F54: =F51+F52+F53 -> -495.20519 | G54: =G51+G52+G53 -> -186.60305 | H54: =H51+H52+H53 -> 1156.3705 | I54: =I51+I52+I53 -> 377.76317 | J54: =J51+J52+J53 -> 413.14231 | K54: =K51+K52+K53 -> 444.9223 | L54: =L51+L52+L53 -> 478.66496 | M54: =M51+M52+M53 -> 387.84521
B56: Price Effect
B57: =B34 -> COGS /Ton Effect | E57: =E34 -> 666.12538 | F57: =F34 -> 1369.0976 | G57: =G34 -> 2043.6958 | H57: =H34 -> -292.34253 | I57: =I34 -> 293.99467 | J57: =J34 -> 301.25706 | K57: =K34 -> 179.25944 | L57: =L34 -> 69.993435 | M57: =M34 -> 171.84473
B58: Δ RM | E58: =E5-D5 -> 1413.2394 | F58: =F5-E5 -> 661.06832 | G58: =G5-F5 -> 1445.5263 | H58: =H5-G5 -> 472.84071 | I58: =I5-H5 -> 776.13941 | J58: =J5-I5 -> 534.20363 | K58: =K5-J5 -> 486.18971 | L58: =L5-K5 -> 443.42379 | M58: =M5-L5 -> 462.83389
B59: RM Cost effect | E59: =E58-E51 -> 602.93486 | F59: =F58-F51 -> 1075.9137 | G59: =G58-G51 -> 1598.1183 | H59: =H58-H51 -> -454.74619 | I59: =I58-I51 -> 451.04806 | J59: =J58-J51 -> 178.32215 | K59: =K58-K51 -> 101.80591 | L59: =L58-L51 -> 28.267066 | M59: =M58-M51 -> 125.2172
B60: Δ Transportation | E60: =E9-D9 -> 50.838686 | F60: =F9-E9 -> 332.69923 | G60: =G9-F9 -> 294.05289 | H60: =H9-G9 -> -27.962882 | I60: =I9-H9 -> 100.88487 | J60: =J9-I9 -> 96.033227 | K60: =K9-J9 -> 77.856992 | L60: =L9-K9 -> 64.421374 | M60: =M9-L9 -> 59.587693
B61: Transportation Cost effect | E61: =E60-E52 -> 7.8415234 | F61: =F60-F52 -> 387.37689 | G61: =G60-G52 -> 317.18817 | H61: =H60-H52 -> -152.37715 | I61: =I60-I52 -> 72.241545 | J61: =J60-J52 -> 64.894358 | K61: =K60-K52 -> 44.935698 | L61: =L60-L52 -> 29.885123 | M61: =M60-M52 -> 32.273044
B62: Δ Overhead | E62: =E10-D10 -> 61.404815 | F62: =F10-E10 -> -31.974872 | G62: =G10-F10 -> 138.43045 | H62: =H10-G10 -> 268.71281 | I62: =I10-H10 -> 84.630903 | J62: =J10-I10 -> 80.560926 | K62: =K10-J10 -> 65.313138 | L62: =L10-K10 -> 54.042187 | M62: =M10-L10 -> 49.98728
B63: Overhead Cost effect | E63: =E62-E53 -> -7.7000024 | F63: =F62-F53 -> -6.2927334 | G63: =G62-G53 -> 149.30626 | H63: =H62-H53 -> 164.34343 | I63: =I62-I53 -> 60.602418 | J63: =J62-J53 -> 54.438967 | K63: =K62-K53 -> 37.695927 | L63: =L62-L53 -> 25.07021 | M63: =M62-M53 -> 27.073404
B64: Total Cost Effect | E64: =E59+E61+E63 -> 603.07639 | F64: =F59+F61+F63 -> 1456.9979 | G64: =G59+G61+G63 -> 2064.6127 | H64: =H59+H61+H63 -> -442.77991 | I64: =I59+I61+I63 -> 583.89202 | J64: =J59+J61+J63 -> 297.65548 | K64: =K59+K61+K63 -> 184.43754 | L64: =L59+L61+L63 -> 83.222399 | M64: =M59+M61+M63 -> 184.56365
B66: Depreciation & Amortization Effect
B67: =B6 -> Depreciation | E67: =E6-D6 -> -9.866277 | F67: =F6-E6 -> 6.802543 | G67: =G6-F6 -> 4.956555 | H67: =H6-G6 -> 37.048344 | I67: =I6-H6 -> -254.76555 | J67: =J6-I6 -> 0 | K67: =K6-J6 -> 0 | L67: =L6-K6 -> 0 | M67: =M6-L6 -> 0
B68: =B7 -> Amortization of Licenses, Intangible assets | E68: =E7-D7 -> -6.468724 | F68: =F7-E7 -> 0 | G68: =G7-F7 -> 0 | H68: =H7-G7 -> 0 | I68: =I7-H7 -> -28.156249 | J68: =J7-I7 -> 0 | K68: =K7-J7 -> 0 | L68: =L7-K7 -> 0 | M68: =M7-L7 -> 0
B69: =B8 -> Amortization of right of use | E69: =E8-D8 -> -0.415287 | F69: =F8-E8 -> 1.403772 | G69: =G8-F8 -> 0.191081 | H69: =H8-G8 -> -4.55705 | I69: =I8-H8 -> -2.525364 | J69: =J8-I8 -> 0 | K69: =K8-J8 -> 0 | L69: =L8-K8 -> 0 | M69: =M8-L8 -> 0
B71: Waterfall Bridge
B72: Prior COGS | E72: =D76 -> 2281.0836 | F72: =E76 -> 3789.8162 | G72: =F76 -> 4759.8152 | H72: =G76 -> 6642.9725 | I72: =H76 -> 7389.0544 | J72: =I76 -> 8065.2624 | K72: =J76 -> 8776.0602 | L72: =K76 -> 9405.4201 | M72: =L76 -> 9967.3074
B73: Volume Effect | D73: 0 | E73: =E54 -> 922.40653 | F73: =F54 -> -495.20519 | G73: =G54 -> -186.60305 | H73: =H54 -> 1156.3705 | I73: =I54 -> 377.76317 | J73: =J54 -> 413.14231 | K73: =K54 -> 444.9223 | L73: =L54 -> 478.66496 | M73: =M54 -> 387.84521 | N73: =SUM(D73:H73) -> 1396.9688
B74: Price Effect | D74: 0 | E74: =E64 -> 603.07639 | F74: =F64 -> 1456.9979 | G74: =G64 -> 2064.6127 | H74: =H64 -> -442.77991 | I74: =I64 -> 583.89202 | J74: =J64 -> 297.65548 | K74: =K64 -> 184.43754 | L74: =L64 -> 83.222399 | M74: =M64 -> 184.56365 | N74: =SUM(D74:H74) -> 3681.907
B75: Depreciation & Amortization | E75: =E67+E68+E69 -> -16.750288 | F75: =F67+F68+F69 -> 8.206315 | G75: =G67+G68+G69 -> 5.147636 | H75: =H67+H68+H69 -> 32.491294 | I75: =I67+I68+I69 -> -285.44716 | J75: =J67+J68+J69 -> 0 | K75: =K67+K68+K69 -> 0 | L75: =L67+L68+L69 -> 0 | M75: =M67+M68+M69 -> 0
B76: Current COGS | D76: =D11 -> 2281.0836 | E76: =SUM(E72:E75) -> 3789.8162 | F76: =SUM(F72:F75) -> 4759.8152 | G76: =SUM(G72:G75) -> 6642.9725 | H76: =SUM(H72:H75) -> 7389.0544 | I76: =SUM(I72:I75) -> 8065.2624 | J76: =SUM(J72:J75) -> 8776.0602 | K76: =SUM(K72:K75) -> 9405.4201 | L76: =SUM(L72:L75) -> 9967.3074 | M76: =SUM(M72:M75) -> 10539.716
B77: Total | D77: =D11 -> 2281.0836 | E77: =E11 -> 3789.8162 | F77: =F11 -> 4759.8152 | G77: =G11 -> 6642.9725 | H77: =H11 -> 7389.0544 | I77: =I11 -> 8065.2624 | J77: =J11 -> 8776.0602 | K77: =K11 -> 9405.4201 | ... M77: =M11 -> 10539.716
B78: Checker | D78: =D77=D76 -> TRUE | E78: =E77=E76 -> TRUE | F78: =F77=F76 -> TRUE | G78: =G77=G76 -> TRUE | H78: =H77=H76 -> TRUE | I78: =I77=I76 -> TRUE | J78: =J77=J76 -> TRUE | K78: =K77=K76 -> TRUE | L78: =L76=L77 -> TRUE | M78: =M77=M76 -> TRUE
B80: RM Cost Driver Analysis
B81: RM Cost | C81: EGP Mn | D81: =D5 -> 1705.51 | E81: =E5 -> 3118.7494 | F81: =F5 -> 3779.8177 | G81: =G5 -> 5225.344 | H81: =H5 -> 5698.1847 | I81: =I5 -> 6474.3241 | J81: =J5 -> 7008.5278 | K81: =K5 -> 7494.7175 | ... M81: =M5 -> 8400.9751
B82: Production Volume | C82: Mn ton | D82: =D25 -> 5.985 | E82: =E25 -> 7.17 | F82: =F25 -> 6.6897 | G82: =G25 -> 6.5421 | H82: =H25 -> 7.3322 | I82: =I25 -> 7.583262 | J82: =J25 -> 7.8371538 | K82: =K25 -> 8.0935902 | ... M82: =M25 -> 8.5560241
B83: RM/ton | C83: Mn ton | D83: =D26 -> 531.64276 | E83: =E26 -> 683.80131 | F83: =F26 -> 863.72143 | G83: =G26 -> 1033.8208 | H83: =H26 -> 1174.012 | I83: =I26 -> 1294.8648 | J83: =J26 -> 1401.7056 | K83: =K26 -> 1498.9435 | ... M83: =M26 -> 1680.195
B84: RM/ton GR | C84: % | E84: =E83/D83-1 -> 0.2862045 | F84: =F83/E83-1 -> 0.26311754 | G84: =G83/F83-1 -> 0.19693781 | H84: =H83/G83-1 -> 0.13560491 | I84: =I83/H83-1 -> 0.10294001 | J84: =J83/I83-1 -> 0.082511104 | K84: =K83/J83-1 -> 0.069371161 | L84: =L83/K83-1 -> 0.059164845 | M84: =M83/L83-1 -> 0.05830507
B85: Egypt Inflation | C85: % | D85: =Assumptions!E8 -> 0.049 | E85: =Assumptions!F8 -> 0.132 | F85: =Assumptions!G8 -> 0.357 | G85: =Assumptions!H8 -> 0.275 | H85: =Assumptions!I8 -> 0.149 | I85: =Assumptions!J8 -> 0.132 | J85: =Assumptions!K8 -> 0.111 | K85: =Assumptions!L8 -> 0.081 | ... M85: =Assumptions!N8 -> 0.054
B86: EX Rate | C86: USD/EGP | D86: =Assumptions!E153 -> 15.65 | E86: =Assumptions!F153 -> 19 | F86: =Assumptions!G153 -> 30.63 | G86: =Assumptions!H153 -> 45.31 | H86: =Assumptions!I153 -> 49.22 | I86: =Assumptions!J153 -> 50.96 | J86: =Assumptions!K153 -> 50.23 | K86: =Assumptions!L153 -> 51.23 | ... M86: =Assumptions!N153 -> 52.72
B87: FX Depreciation | C87: % | E87: =E86/D86-1 -> 0.21405751 | F87: =F86/E86-1 -> 0.61210526 | G87: =G86/F86-1 -> 0.47926869 | H87: =H86/G86-1 -> 0.086294416 | I87: =I86/H86-1 -> 0.035351483 | J87: =J86/I86-1 -> -0.014324961 | K87: =K86/J86-1 -> 0.019908421 | L87: =L86/K86-1 -> 0.020105407 | M87: =M86/L86-1 -> 0.0088021431
B88: Coal Price | C88: =Assumptions!D141 -> USD/ton | D88: =Assumptions!E141 -> 183.88 | E88: =Assumptions!F141 -> 370.39333 | F88: =Assumptions!G141 -> 136.92 | G88: =Assumptions!H141 -> 139.52 | H88: =Assumptions!I141 -> 109.25667 | I88: =Assumptions!J141 -> 112.53437 | J88: =Assumptions!K141 -> 115.9104 | ... M88: =Assumptions!N141 -> 126.65842
B89: Coal Price GR | C89: % | E89: =E88/D88-1 -> 1.0143209 | F89: =F88/E88-1 -> -0.63033892 | G89: =G88/F88-1 -> 0.018989191 | H89: =H88/G88-1 -> -0.21691036 | I89: =I88/H88-1 -> 0.03 | J89: =J88/I88-1 -> 0.03 | K89: =K88/J88-1 -> 0.03 | L89: =L88/K88-1 -> 0.03 | M89: =M88/L88-1 -> 0.03
B90: Inflation Impact on RM/ton | E90: =D83*(1+E85) -> 601.8196 | F90: =E83*(1+F85) -> 927.91837 | G90: =F83*(1+G85) -> 1101.2448 | H90: =G83*(1+H85) -> 1187.8601 | I90: =H83*(1+I85) -> 1328.9816 | J90: =I83*(1+J85) -> 1438.5948 | K90: =J83*(1+K85) -> 1515.2437 | L90: =K83*(1+L85) -> 1591.878 | M90: =L83*(1+M85) -> 1673.3602
B91: Inflation impact in EGP | E91: =(E90-D83)*E25 -> 503.16797 | F91: =(F90-E83)*F25 -> 1633.0699 | G91: =(G90-F83)*G25 -> 1553.9018 | H91: =(H90-G83)*H25 -> 1129.447 | I91: =(I90-H83)*I25 -> 1175.175 | J91: =(J90-I83)*J25 -> 1126.4341 | K91: =(K90-J83)*K25 -> 918.93126 | L91: =(L90-K83)*L25 -> 776.47563 | M91: =(M90-L83)*M25 -> 733.52443
B92: Residual / Other | E92: =E59-E91 -> 99.766892 | F92: =F59-F91 -> -557.15622 | G92: =G59-G91 -> 44.216474 | H92: =H59-H91 -> -1584.1932 | I92: =I59-I91 -> -724.12691 | J92: =J59-J91 -> -948.11192 | K92: =K59-K91 -> -817.12535 | L92: =L59-L91 -> -748.20857 | M92: =M59-M91 -> -608.30722
B93: FX Impact for all COGS
B94: FX Impact using Elasticty | E94: =E87*'Elasticity Analysis'!$E$127 -> 0.089955425 | F94: =F87*'Elasticity Analysis'!$E$127 -> 0.25723082 | G94: =G87*'Elasticity Analysis'!$E$127 -> 0.20140765 | H94: =H87*'Elasticity Analysis'!$E$127 -> 0.036264324 | I94: =I87*'Elasticity Analysis'!$H$127 -> 0.026321378 | J94: =J87*'Elasticity Analysis'!$H$127 -> -0.010665824 | K94: =K87*'Elasticity Analysis'!$H$127 -> 0.014823058 | L94: =L87*'Elasticity Analysis'!$H$127 -> 0.014969726 | M94: =M87*'Elasticity Analysis'!$H$127 -> 0.0065537431
B95: FX Impact/ton | E95: =E94*E34 -> 59.921591 | F95: =F94*F34 -> 352.1741 | G95: =G94*G34 -> 411.61596 | H95: =H94*H34 -> -10.601604 | I95: =I94*I34 -> 7.7383448 | J95: =J94*J34 -> -3.2131549 | K95: =K94*K34 -> 2.657173 | L95: =L94*L34 -> 1.0477826 | M95: =M94*M34 -> 1.1262262
B96: FX impact on total COGS | E96: =E95*E25 -> 429.63781 | F96: =F95*F25 -> 2355.9391 | G96: =G95*G25 -> 2692.8328 | H96: =H95*H25 -> -77.733082 | I96: =I95*I25 -> 58.681896 | J96: =J95*J25 -> -25.181989 | K96: =K95*K25 -> 21.50607 | L96: =L95*L25 -> 8.7543125 | M96: =M95*M25 -> 9.636019
B98: FX Impact for RM
B99: FX-Exposed RM Cost | D99: =D5*60% -> 1023.306 | E99: =E5*60% -> 1871.2496 | F99: =F5*60% -> 2267.8906 | G99: =G5*60% -> 3135.2064 | H99: =H5*60% -> 3418.9108 | I99: =I5*60% -> 3884.5945 | J99: =J5*60% -> 4205.1167 | K99: =K5*60% -> 4496.8305 | ... M99: =M5*60% -> 5040.5851
B100: FX-Impact | E100: =E99*E87 -> 400.55503 | F100: =F99*F87 -> 1388.1878 | G100: =G99*G87 -> 1502.6063 | H100: =H99*H87 -> 295.03291 | I100: =I99*I87 -> 137.32618 | J100: =J99*J87 -> -60.238131 | K100: =K99*K87 -> 89.524796 | L100: =L99*L87 -> 95.759736 | M100: =M99*M87 -> 44.367951
B101: FX Contricution | E101: =E94 -> 0.089955425 | F101: =F94 -> 0.25723082 | G101: =G94 -> 0.20140765 | H101: =H94 -> 0.036264324 | I101: =I94 -> 0.026321378 | J101: =J94 -> -0.010665824 | K101: =K94 -> 0.014823058 | L101: =L94 -> 0.014969726 | M101: =M94 -> 0.0065537431
B102: FX Share of RM | E102: =E101/E84 -> 0.31430472 | F102: =F101/F84 -> 0.97762704 | G102: =G101/G84 -> 1.0226967 | H102: =H101/H84 -> 0.26742633 | I102: =I101/I84 -> 0.25569628 | J102: =J101/J84 -> -0.12926532 | K102: =K101/K84 -> 0.21367753 | L102: =L101/L84 -> 0.25301725 | M102: =M101/M84 -> 0.11240434
B103: FX-Impact | E103: =E102*E59 -> 189.50527 | F103: =F102*F59 -> 1051.8423 | G103: =G102*G59 -> 1634.3903 | H103: =H102*H59 -> -121.6111 | I103: =I102*I59 -> 115.33131 | J103: =J102*J59 -> -23.05087 | K103: =K102*K59 -> 21.753636 | L103: =L102*L59 -> 7.1520552 | M103: =M102*M59 -> 14.074958
B104: Remaining RM unit-cost effect | E104: =E59-E103 -> 413.42959 | F104: =F59-F103 -> 24.071378 | G104: =G59-G103 -> -36.271994 | H104: =H59-H103 -> -333.13508 | I104: =I59-I103 -> 335.71675 | J104: =J59-J103 -> 201.37302 | K104: =K59-K103 -> 80.052277 | L104: =L59-L103 -> 21.11501 | M104: =M59-M103 -> 111.14225
B106: RM Waterfall Bridge
B107: Prior RM | E107: =D112 -> 1705.51 | F107: =E112 -> 3118.7494 | G107: =F112 -> 3779.8177 | H107: =G112 -> 5225.344 | I107: =H112 -> 5698.1847 | J107: =I112 -> 6474.3241 | K107: =J112 -> 7008.5278 | L107: =K112 -> 7494.7175 | M107: =L112 -> 7938.1413
B108: RM Volume effect | D108: 0 | E108: =E51 -> 810.30455 | F108: =F51 -> -414.8454 | G108: =G51 -> -152.59195 | H108: =H51 -> 927.58689 | I108: =I51 -> 325.09135 | J108: =J51 -> 355.88148 | K108: =K51 -> 384.3838 | L108: =L51 -> 415.15673 | M108: =M51 -> 337.61668
B109: Inflation Impact | D109: 0 | E109: =E91 -> 503.16797 | F109: =F91 -> 1633.0699 | G109: =G91 -> 1553.9018 | H109: =H91 -> 1129.447 | I109: =I91 -> 1175.175 | J109: =J91 -> 1126.4341 | K109: =K91 -> 918.93126 | L109: =L91 -> 776.47563 | M109: =M91 -> 733.52443
B110: =B103 -> FX-Impact | E110: =E103 -> 189.50527 | F110: =F103 -> 1051.8423 | G110: =G103 -> 1634.3903 | H110: =H103 -> -121.6111 | I110: =I103 -> 115.33131 | J110: =J103 -> -23.05087 | K110: =K103 -> 21.753636 | L110: =L103 -> 7.1520552 | M110: =M103 -> 14.074958
B111: Residual / Other | D111: 0 | E111: =E92-E110 -> -89.738381 | F111: =F92-F110 -> -1608.9986 | G111: =G92-G110 -> -1590.1738 | H111: =H92-H110 -> -1462.5821 | I111: =I92-I110 -> -839.45822 | J111: =J92-J110 -> -925.06105 | K111: =K92-K110 -> -838.87898 | L111: =L92-L110 -> -755.36062 | M111: =M92-M110 -> -622.38218
B112: Current RM | D112: =D5 -> 1705.51 | E112: =SUM(E107:E111) -> 3118.7494 | F112: =SUM(F107:F111) -> 3779.8177 | G112: =SUM(G107:G111) -> 5225.344 | H112: =SUM(H107:H111) -> 5698.1847 | I112: =SUM(I107:I111) -> 6474.3241 | J112: =SUM(J107:J111) -> 7008.5278 | K112: =SUM(K107:K111) -> 7494.7175 | L112: =SUM(L107:L111) -> 7938.1413 | M112: =SUM(M107:M111) -> 8400.9751
B113: Total | D113: =D5 -> 1705.51 | E113: =E5 -> 3118.7494 | F113: =F5 -> 3779.8177 | G113: =G5 -> 5225.344 | H113: =H5 -> 5698.1847 | I113: =I5 -> 6474.3241 | J113: =J5 -> 7008.5278 | K113: =K5 -> 7494.7175 | ... M113: =M5 -> 8400.9751
B114: Checker | D114: =D113=D112 -> TRUE | E114: =E113=E112 -> TRUE | F114: =F113=F112 -> TRUE | G114: =G113=G112 -> TRUE | H114: =H113=H112 -> TRUE | I114: =I113=I112 -> FALSE | J114: =J113=J112 -> TRUE | K114: =K113=K112 -> TRUE | ... M114: =M113=M112 -> TRUE
I115: =I112-I113 -> 0 | J115: =J112-J113 -> 0 | K115: =K112-K113 -> 0 | L115: =L112-L113 -> 0 | M115: =M112-M113 -> 0
...

Sheet Assumptions
B2: Historic Source | C2: Assumptions | D2: Unit | E2: 2021 | F2: =E2+1 -> 2022 | G2: =F2+1 -> 2023 | H2: =G2+1 -> 2024 | I2: =H2+1 -> 2025 | J2: =I2+1 -> 2026 | K2: =J2+1 -> 2027 | L2: =K2+1 -> 2028 | M2: =L2+1 -> 2029 | N2: =M2+1 -> 2030 | P2: Fcsting Source
C4: Economic Data
B5: World Bank | C5: Egypt Real GDP Growth (%) | D5: % | E5: 0.033 | F5: 0.066 | G5: 0.038 | H5: 0.024 | I5: 0.044 | J5: 0.042 | K5: 0.048 | L5: 0.045 | M5: 0.045 | N5: 0.045
C6: Exchange Rate/USD | D6: USD | E6: 15.66 | F6: 24.69 | G6: 30.84 | H6: 50.79 | I6: 47.09 | J6: 50.96 | K6: 50.23 | L6: 51.23 | M6: 52.26 | N6: 52.72
C7: Exchange Rate /EURO | D7: EUR | E7: 17.7928 | F7: 26.2728 | G7: 34.2712 | H7: 52.8472 | I7: 55.9255
C8: Egypt inflation | D8: % | E8: 0.049 | F8: 0.132 | G8: 0.357 | H8: 0.275 | I8: 0.149 | J8: 0.132 | K8: 0.111 | L8: 0.081 | M8: 0.062 | N8: 0.054
C9: World Inflation | D9: % | E9: 0.0471 | F9: 0.0867 | G9: 0.0675 | H9: 0.0579 | I9: 0.0413 | J9: 0.0442 | K9: 0.0366 | L9: 0.0336 | M9: 0.0322 | N9: 0.032
C10: Nominal GDP | D10: USDbn | E10: 423.3 | F10: 475.23 | G10: 393.83 | H10: 383.11 | I10: 364.64 | J10: 429.65 | K10: 457.07 | L10: 508.47 | M10: 560.08 | N10: 610.98
C11: Nominal GDP | D11: EGPbn | E11: 6628.878 | F11: 11733.429 | G11: 12145.717 | H11: 19458.157 | I11: 17170.898 | J11: 21894.964 | K11: 22958.626 | L11: 26048.918 | M11: 29269.781 | N11: 32210.866
C12: Nominal GDP % | F12: =F11/E11-1 -> 0.77004747 | G12: =G11/F11-1 -> 0.035137939 | H12: =H11/G11-1 -> 0.60205911 | I12: =I11/H11-1 -> -0.11754758 | J12: =J11/I11-1 -> 0.27512053 | K12: =K11/J11-1 -> 0.048580217 | L12: =L11/K11-1 -> 0.13460265 | M12: =M11/L11-1 -> 0.1236467 | N12: =N11/M11-1 -> 0.10048196
C13: Interest Rate | E13: 0.0875 | F13: 0.1675 | G13: 0.1975 | H13: 0.2775 | I13: 0.205 | J13: 0.19 | K13: =J13-5% -> 0.14 | L13: =K13-2% -> 0.12 | M13: =L13-2% -> 0.1 | N13: =M13 -> 0.1
C16: Market "Industry" Data | D16: Unit
C17: Volume
C18: Domestic Cement Consumption ('000 tons) | E18: 51.95 | F18: 50.76 | G18: 47.36 | H18: 49.17 | I18: 54.6
C19: YoY Growth % | E19: =IFERROR(E18/D18-1,"") | F19: =IFERROR(F18/E18-1,"") -> -0.022906641 | G19: =IFERROR(G18/F18-1,"") -> -0.066981875 | H19: =IFERROR(H18/G18-1,"") -> 0.038217905 | I19: =IFERROR(I18/H18-1,"") -> 0.11043319
C20: Industry Production Capacity ('000 tons) | E20: 53.7 | F20: 52.37 | G20: 49.19 | H20: 50.75 | I20: 56.18
C21: Volumes & Sales
B22: ACC iR | C22: MKT Local Volumes | D22: K Ton | E22: 48.6 | F22: 51.2 | G22: 47.5606 | H22: 47.686 | I22: 53.9929
C23: % GR | F23: =F22/E22-1 -> 0.053497942 | G23: =G22/F22-1 -> -0.071082031 | H23: =H22/G22-1 -> 0.0026366362 | I23: =I22/H22-1 -> 0.13225894
B24: ACC iR | C24: MKT Export Volumes | D24: K Ton | E24: 8 | F24: 9.6 | G24: =9.872+3.4974 -> 13.3694 | H24: =12.2414+7.5617 -> 19.8031 | I24: =11.063+7.5689 -> 18.6319
C25: % GR | F25: =F24/E24-1 -> 0.2 | G25: =G24/F24-1 -> 0.39264583 | H25: =H24/G24-1 -> 0.48122578 | I25: =I24/H24-1 -> -0.059142256
B26: ACC iR | C26: Total MKT Volume | D26: K Ton | E26: =E22+E24 -> 56.6 | F26: 60.7 | G26: =G22+G24 -> 60.93 | H26: =H22+H24 -> 67.4891 | I26: =I22+I24 -> 72.6248
C27: % GR | F27: =F26/E26-1 -> 0.072438163 | G27: =G26/F26-1 -> 0.0037891269 | H27: =H26/G26-1 -> 0.10764976 | I27: =I26/H26-1 -> 0.076096733
B28: SCRIBD | C28: MKT Local Sales | D28: EGP | E28: 49.557 | F28: 48.4 | G28: 52.974 | H28: 49.138 | I28: 54
C29: =C27 -> % GR | F29: =F28/E28-1 -> -0.023346853 | G29: =G28/F28-1 -> 0.094504132 | H29: =H28/G28-1 -> -0.072412882 | I29: =I28/H28-1 -> 0.098945826
B30: SCRIBD | C30: MKT Export Sales | D30: EGP | E30: 80.5 | F30: 95.56 | G30: 13.369 | H30: 19.829 | I30: 18.5
C31: =C29 -> % GR | F31: =F30/E30-1 -> 0.18708075 | G31: =G30/F30-1 -> -0.86009837 | H31: =H30/G30-1 -> 0.48320742 | I31: =I30/H30-1 -> -0.067023047
B32: calculated | C32: Total MKT Sales | D32: EGP | E32: =E28+E30 -> 130.057 | F32: =F28+F30 -> 143.96 | G32: =G28+G30 -> 66.343 | H32: =H28+H30 -> 68.967 | I32: =I28+I30 -> 72.5
C33: =C31 -> % GR | F33: =F32/E32-1 -> 0.10689928 | G33: =G32/F32-1 -> -0.53915671 | H33: =H32/G32-1 -> 0.039552025 | I33: =I32/H32-1 -> 0.051227399
C34: Demand & Capacity
C35: Domestic Cement Demand | D35: Mt | E35: 51.95 | F35: 50.76 | G35: 47.36 | H35: 49.17 | I35: 54.6
C36: % GR | F36: =F35/E35-1 -> -0.022906641 | G36: =G35/F35-1 -> -0.066981875 | H36: =H35/G35-1 -> 0.038217905 | I36: =I35/H35-1 -> 0.11043319
C37: Industry Capacity | D37: Mt | E37: 83 | F37: 83 | G37: 83 | H37: 83 | I37: 91
C38: Industry Production | D38: Mt | E38: 53.7 | F38: 52.37 | G38: 49.19 | H38: 50.75 | I38: 56.18
C39: Utilization | D39: % | E39: =E38/E37 -> 0.64698795 | F39: =F38/F37 -> 0.63096386 | G39: =G38/G37 -> 0.5926506 | H39: =H38/H37 -> 0.61144578 | I39: =I38/I37 -> 0.61736264
C40: Export Price | D40: USD/ton | E40: 73.5 | F40: 89.2 | G40: 96 | H40: 113.1
B42: volume fcsting | C42: Consumption & Production
C43: Consumption /Domestic Sales | D43: Mt | E43: 45 | F43: 51 | G43: 47.36 | H43: 47.6 | I43: =I28 -> 54 | J43: =I43*(1+J70) -> 56.7 | K43: =J43*(1+K70) -> 59.42 | L43: =K43*(1+L70) -> 62.1551 | M43: =L43*(1+M70) -> 64.943811 | N43: =M43*(1+N70) -> 67.737884
C44: % GR | F44: =F43/E43-1 -> 0.13333333 | G44: =G43/F43-1 -> -0.071372549 | H44: =H43/G43-1 -> 0.0050675676 | I44: =I43/H43-1 -> 0.13445378 | J44: =J70 -> 0.05 | K44: =K70 -> 0.047971781 | L44: =L70 -> 0.046029956 | M44: =M70 -> 0.044866978 | N44: =N70 -> 0.043022924
C45: Consumption per capita | D45: ton/person | E45: 0.148 | F45: 0.48 | G45: 0.42 | H45: 0.428 | I45: 0.46 | J45: =J43/J57 -> 0.51545455 | K45: =K43/K57 -> 0.53053571 | L45: =L43/L57 -> 0.54047913 | M45: =M43/M57 -> 0.55507531 | N45: =N43/N57 -> 0.56448237
C46: % GR | F46: =F45/E45-1 -> 2.2432432 | G46: =G45/F45-1 -> -0.125 | H46: =H45/G45-1 -> 0.019047619 | I46: =I45/H45-1 -> 0.074766355 | J46: =J45/I45-1 -> 0.12055336 | K46: =K45/J45-1 -> 0.029257999 | L46: =L45/K45-1 -> 0.018742218 | M46: =M45/L45-1 -> 0.027006004 | N46: =N45/M45-1 -> 0.016947351
B47: CAPMS | C47: Production | D47: Mt | E47: 55.2 | F47: 80 | G47: 50 | H47: 55.1 | I47: 65 | J47: =J72+J43 -> 67.92 | K47: =K72+K43 -> 70.8644 | L47: =L72+L43 -> 73.828388 | M47: =M72+M43 -> 76.850565 | N47: =N72+N43 -> 79.882773
C48: % GR | F48: =F47/E47-1 -> 0.44927536 | G48: =G47/F47-1 -> -0.375 | H48: =H47/G47-1 -> 0.102 | I48: =I47/H47-1 -> 0.17967332 | J48: =J47/I47-1 -> 0.044923077 | K48: =K47/J47-1 -> 0.043351001 | L48: =L47/K47-1 -> 0.041826192 | M48: =M47/L47-1 -> 0.040935165 | N48: =N47/M47-1 -> 0.039455894
C49: Production - Consumption | E49: =E47-E43 -> 10.2 | F49: =F47-F43 -> 29 | G49: =G47-G43 -> 2.64 | H49: =H47-H43 -> 7.5 | I49: =I47-I43 -> 11 | J49: =J72 -> 11.22 | K49: =K72 -> 11.4444 | L49: =L72 -> 11.673288 | M49: =M72 -> 11.906754 | N49: =N72 -> 12.144889
C50: Production/Consumption | E50: =E47/E43 -> 1.2266667 | F50: =F47/F43 -> 1.5686275 | G50: =G47/G43 -> 1.0557432 | H50: =H47/H43 -> 1.157563 | I50: =I47/I43 -> 1.2037037 | J50: =J47/J43 -> 1.1978836 | K50: =K47/K43 -> 1.1926018 | L50: =L47/L43 -> 1.187809 | ... N50: =N47/N43 -> 1.1792924
C51: Surplus % | E51: =E49/E43 -> 0.22666667 | F51: =F49/F43 -> 0.56862745 | G51: =G49/G43 -> 0.055743243 | H51: =H49/H43 -> 0.15756303 | I51: =I49/I43 -> 0.2037037 | J51: =J49/J43 -> 0.1978836 | K51: =K49/K43 -> 0.19260182 | L51: =L49/L43 -> 0.18780901 | ... N51: =N49/N43 -> 0.17929241
C52: Domestic Cement Price | D52: K EGP/ton | E52: 795 | F52: 1250 | G52: 1980 | H52: 2455 | I52: 3900 | J52: =I52*(1+J93) -> 4096.4079 | K52: =J52*(1+K93) -> 4305.3846 | L52: =K52*(1+L93) -> 4506.3566 | M52: =L52*(1+M93) -> 4719.0662 | N52: =M52*(1+N93) -> 5017.4834
C53: % GR | F53: =F52/E52-1 -> 0.57232704 | G53: =G52/F52-1 -> 0.584 | H53: =H52/G52-1 -> 0.23989899 | I53: =I52/H52-1 -> 0.5885947 | J53: =J52/I52-1 -> 0.050360997 | K53: =K52/J52-1 -> 0.051014636 | L53: =L52/K52-1 -> 0.046679205 | M53: =M52/L52-1 -> 0.047202121 | N53: =N52/M52-1 -> 0.0632365
C55: Cement Domestic Consumption
C56: Egypt Housing Supply-Demand Gap
C57: Population | D57: Mn | E57: 102 | F57: 104 | G57: 105 | H57: 107 | I57: 108 | J57: 110 | K57: 112 | L57: 115 | M57: 117 | N57: 120
C58: Population CAGR | F58: =F57/E57-1 -> 0.019607843 | G58: =G57/F57-1 -> 0.0096153846 | H58: =H57/G57-1 -> 0.019047619 | I58: =I57/H57-1 -> 0.0093457944 | J58: =J57/I57-1 -> 0.018518519 | K58: =K57/J57-1 -> 0.018181818 | L58: =L57/K57-1 -> 0.026785714 | M58: =M57/L57-1 -> 0.017391304 | N58: =N57/M57-1 -> 0.025641026
B59: https://www.mordorintelligence.com/industry-reports/residential-real-estate-market-in-egypt | C59: Annual new Housing Unit Need | D59: unit/yr | I59: 0.7 | J59: =I59*(1+J58) -> 0.71296296 | K59: =J59*(1+K58) -> 0.72592593 | L59: =K59*(1+L58) -> 0.74537037 | M59: =L59*(1+M58) -> 0.75833333 | N59: =M59*(1+N58) -> 0.77777778
B60: https://www.mordorintelligence.com/industry-reports/residential-real-estate-market-in-egypt | C60: Annual Housing Delivery Capacity | D60: unit/yr | I60: 0.5 | J60: =I60*(1+J61) -> 0.52 | K60: =J60*(1+K61) -> 0.5408 | L60: =K60*(1+L61) -> 0.562432 | M60: =L60*(1+M61) -> 0.58492928 | N60: =M60*(1+N61) -> 0.60832645
B61: https://www.mordorintelligence.com/industry-reports/residential-real-estate-market-in-egypt | C61: Delivery capacity annual GR | I61: 0.04 | J61: =I61 -> 0.04 | K61: =J61 -> 0.04 | L61: =K61 -> 0.04 | M61: =L61 -> 0.04 | N61: =M61 -> 0.04
C62: Annual Housing Shortfall | D62: unit/yr | I62: =I59-I60 -> 0.2 | J62: =J59-J60 -> 0.19296296 | K62: =K59-K60 -> 0.18512593 | L62: =L59-L60 -> 0.18293837 | M62: =M59-M60 -> 0.17340405 | N62: =N59-N60 -> 0.16945133
C63: Cement Intensity | D63: ton/unit | I63: 45 | J63: =I63 -> 45 | K63: =J63 -> 45 | L63: =K63 -> 45 | M63: =L63 -> 45 | N63: =M63 -> 45
C64: Implied Cement Demand | D64: Mn | I64: =I62*I63 -> 9 | J64: =J62*J63 -> 8.6833333 | K64: =K62*K63 -> 8.3306667 | L64: =L62*L63 -> 8.2322267 | M64: =M62*M63 -> 7.8031824 | N64: =N62*N63 -> 7.6253097
C65: Demand Realization Rate | I65: 0.15 | J65: =I65 -> 0.15 | K65: =J65 -> 0.15 | L65: =K65 -> 0.15 | M65: =L65 -> 0.15 | N65: =M65 -> 0.15
C66: Total Housing-gap-driven incremental growth | J66: =(I65*I64)/I43 -> 0.025 | K66: =(J65*J64)/J43 -> 0.022971781 | L66: =(K65*K64)/K43 -> 0.021029956 | M66: =(L65*L64)/L43 -> 0.019866978 | N66: =(M65*M64)/M43 -> 0.018022924
C67: Annual taper in underlying GR | I67: 0.005 | J67: =I67 -> 0.005 | K67: =J67 -> 0.005 | L67: =K67 -> 0.005 | M67: =L67 -> 0.005 | N67: =M67 -> 0.005
C68: Underlying growth floor | I68: 0.02 | J68: =I68 -> 0.02 | K68: =J68 -> 0.02 | L68: =K68 -> 0.02 | M68: =L68 -> 0.02 | N68: =M68 -> 0.02
B69: world bank | C69: Underlying (non-housing) consumption GR | I69: 0.025 | J69: 0.025 | K69: 0.025 | L69: 0.025 | M69: 0.025 | N69: 0.025
C70: Total Domestic Consumption GR | F70: =F44 -> 0.13333333 | G70: =G44 -> -0.071372549 | H70: =H44 -> 0.0050675676 | I70: =I44 -> 0.13445378 | J70: =J66+J69 -> 0.05 | K70: =K66+K69 -> 0.047971781 | L70: =L66+L69 -> 0.046029956 | M70: =M66+M69 -> 0.044866978 | N70: =N66+N69 -> 0.043022924
C71: Export Volume Annual GR | I71: 0.02 | J71: =I71 -> 0.02 | K71: =J71 -> 0.02 | L71: =K71 -> 0.02 | M71: =L71 -> 0.02 | N71: =M71 -> 0.02
C72: Export in Mt | E72: =E47-E43 -> 10.2 | F72: =F47-F43 -> 29 | G72: =G47-G43 -> 2.64 | H72: =H47-H43 -> 7.5 | I72: =I47-I43 -> 11 | J72: =I72*(1+J71) -> 11.22 | K72: =J72*(1+K71) -> 11.4444 | L72: =K72*(1+L71) -> 11.673288 | M72: =L72*(1+M71) -> 11.906754 | N72: =M72*(1+N71) -> 12.144889
C74: Supply Side
C75: Idled-line restart capacity addition | D75: Mt | I75: 12.6
C76: Phase-in, % of total addition | J76: 0.6 | K76: 0.4
C77: New capacity added in year | D77: Mt | J77: =J76*$I$75 -> 7.56 | K77: =K76*$I$75 -> 5.04 | L77: =K77*(1+1.5%) -> 5.1156 | M77: =L77*(1+1.5%) -> 5.192334 | P77: Global Cement: average new capacity increase for 2 next years
B78: Global cement | C78: Installed capacity | H78: 76 | I78: 76 | J78: =I78+J77 -> 83.56 | K78: =J78+K77 -> 88.6 | L78: =K78+L77 -> 93.7156 | M78: =L78+M77 -> 98.907934 | N78: =M78+N77 -> 98.907934
C79: Maximum capacity utilization | H79: 0.92 | I79: 0.92 | J79: 0.92 | K79: 0.92 | L79: 0.92 | M79: 0.92 | N79: 0.92
C80: Practical capacity ceiling | D80: Mt | H80: =H78*H79 -> 69.92 | I80: =I78*I79 -> 69.92 | J80: =J78*J79 -> 76.8752 | K80: =K78*K79 -> 81.512 | L80: =L78*L79 -> 86.218352 | M80: =M78*M79 -> 90.995299 | N80: =N78*N79 -> 90.995299
C81: Actual production, capacity-constrained | H81: =MIN(H47,H80) -> 55.1 | I81: =MIN(I47,I80) -> 65 | J81: =MIN(J47,J80) -> 67.92 | K81: =MIN(K47,K80) -> 70.8644 | L81: =MIN(L47,L80) -> 73.828388 | M81: =MIN(M47,M80) -> 76.850565 | N81: =MIN(N47,N80) -> 79.882773
C82: Unmet demand / effective shortage | H82: =MAX(H47-H81,0) -> 0 | I82: =MAX(I47-I81,0) -> 0 | J82: =MAX(J47-J81,0) -> 0 | K82: =MAX(K47-K81,0) -> 0 | L82: =MAX(L47-L81,0) -> 0 | M82: =MAX(M47-M81,0) -> 0 | N82: =MAX(N47-N81,0) -> 0
C83: Capacity utilization | H83: =IFERROR(H81/H78,0) -> 0.725 | I83: =IFERROR(I81/I78,0) -> 0.85526316 | J83: =IFERROR(J81/J78,0) -> 0.8128291 | K83: =IFERROR(K81/K78,0) -> 0.79982393 | L83: =IFERROR(L81/L78,0) -> 0.78779187 | M83: =IFERROR(M81/M78,0) -> 0.77699091 | N83: =IFERROR(N81/N78,0) -> 0.80764778
C85: Domestic Price
C86: Change in Utilization | I86: =I83-H83 -> 0.13026316 | J86: =J83-I83 -> -0.042434053 | K86: =K83-J83 -> -0.013005177 | L86: =L83-K83 -> -0.012032055 | M86: =M83-L83 -> -0.010800966 | N86: =N83-M83 -> 0.03065687
C87: New capacity added as % of prior-year production | J87: =J77/I81 -> 0.11630769 | K87: =K77/J81 -> 0.074204947 | L87: =L77/K81 -> 0.072188574 | M87: =M77/L81 -> 0.070329776 | N87: =N77/M81 -> 0
C88: Unmet demand as % of prior-year production | J88: =J82/I81 -> 0 | K88: =K82/J81 -> 0 | L88: =L82/K81 -> 0 | M88: =M82/L81 -> 0 | N88: =N82/M81 -> 0
C89: Energy cost price weight | J89: 0.6 | K89: 0.6 | L89: 0.6 | M89: 0.6 | N89: 0.6
C90: utilization tightness sensitivity price weight | J90: 1.2 | K90: 1.2 | L90: 1.2 | M90: 1.2 | N90: 1.2
C91: new-capacity price weight | J91: 0.5 | K91: 0.5 | L91: 0.5 | M91: 0.5 | N91: 0.5
C92: Unmet demand / effective shortage price weight | J92: 1.5 | K92: 1.5 | L92: 1.5 | M92: 1.5 | N92: 1.5
C93: Domestic Price GR | J93: =(J156*J89)+(J86*J90)+(J92*J88)+(J87*J91) -> 0.050360997 | K93: =(K156*K89)+(K86*K90)+(K92*K88)+(K87*K91) -> 0.051014636 | L93: =(L156*L89)+(L86*L90)+(L92*L88)+(L87*L91) -> 0.046679205 | M93: =(M156*M89)+(M86*M90)+(M92*M88)+(M87*M91) -> 0.047202121 | N93: =(N156*N89)+(N86*N90)+(N92*N88)+(N87*N91) -> 0.0632365
C95: Total % apply to ACC
C96: Local Volume | J96: =65%*J70 -> 0.0325 | K96: =65%*K70 -> 0.031181658 | L96: =65%*L70 -> 0.029919472 | M96: =65%*M70 -> 0.029163536 | N96: =65%*N70 -> 0.0279649
C97: Export Volume | J97: =35%*J71 -> 0.007 | K97: =35%*K71 -> 0.007 | L97: =35%*L71 -> 0.007 | M97: =35%*M71 -> 0.007 | N97: =35%*N71 -> 0.007
C98: Total | J98: =J96+J97 -> 0.0395 | K98: =K96+K97 -> 0.038181658 | L98: =L96+L97 -> 0.036919472 | M98: =M96+M97 -> 0.036163536 | N98: =N96+N97 -> 0.0349649
C99: Local ASP | J99: =65%*J93 -> 0.032734648 | K99: =70%*K93 -> 0.035710246 | L99: =70%*L93 -> 0.032675444 | M99: =70%*M93 -> 0.033041485 | N99: =70%*N93 -> 0.04426555
C100: Export ASP | J100: =35%*J154 -> 0.012373019 | K100: =30%*K154 -> -0.0042974882 | L100: =30%*L154 -> 0.0059725264 | M100: =30%*M154 -> 0.0060316221 | N100: =30%*N154 -> 0.0026406429
C101: Total | J101: =J99+J100 -> 0.045107667 | K101: =K99+K100 -> 0.031412757 | L101: =L99+L100 -> 0.03864797 | M101: =M99+M100 -> 0.039073107 | N101: =N99+N100 -> 0.046906193
C103: Export Volumes Fcsting
B104: Egypt, Arab Rep. Cement clinkers exports by country | 2023 | Data | C104: Clinker Export Mix
B105: Egypt, Arab Rep. Cement clinkers exports by country | 2024 | Data | C105: Africa | D105: Mt | G105: 7.25 | H105: 5.65 | I105: =$I$110*I118 -> 4.8432774 | J105: =I105*(1+J127) -> 5.0370085 | K105: =J105*(1+K127) -> 5.2384889 | L105: =K105*(1+L127) -> 5.4480284 | M105: =L105*(1+M127) -> 5.6659496 | N105: =M105*(1+N127) -> 5.8925875
C106: Europe | D106: Mt | G106: 0.46 | H106: 0.59 | I106: =$I$110*I119 -> 0.39318916 | J106: =I106*(1+J128) -> 0.39712105 | K106: =J106*(1+K128) -> 0.40109226 | L106: =K106*(1+L128) -> 0.40510318 | M106: =L106*(1+M128) -> 0.40915421 | N106: =M106*(1+N128) -> 0.41324575
C107: Middle East | D107: Mt | G107: 0.17 | H107: 0.53 | I107: =$I$110*I120 -> 0.2610431 | J107: =I107*(1+J129) -> 0.26626396 | K107: =J107*(1+K129) -> 0.27158924 | L107: =K107*(1+L129) -> 0.27702102 | M107: =L107*(1+M129) -> 0.28256144 | N107: =M107*(1+N129) -> 0.28821267
C108: Americas | D108: Mt | G108: 0.085 | H108: 0.5 | I108: =$I$110*I121 -> 0.21770519 | J108: =I108*(1+J130) -> 0.22205929 | K108: =J108*(1+K130) -> 0.22650047 | L108: =K108*(1+L130) -> 0.23103048 | M108: =L108*(1+M130) -> 0.23565109 | N108: =M108*(1+N130) -> 0.24036412
C109: Asia | D109: Mt | G109: 0.023 | I109: =$I$110*I122 -> 0.0087151289 | J109: =I109*(1+J131) -> 0.0087151289 | K109: =J109*(1+K131) -> 0.0087151289 | L109: =K109*(1+L131) -> 0.0087151289 | M109: =L109*(1+M131) -> 0.0087151289 | N109: =M109*(1+N131) -> 0.0087151289
C110: Total Egypt clinker exported | G110: 7.99 | H110: 12.241 | I110: 7.5689
...

Sheet Ratios
B2: Ratio | C2: Formula | D2: 2021 | E2: =D2+1 -> 2022 | F2: =E2+1 -> 2023 | G2: =F2+1 -> 2024 | H2: =G2+1 -> 2025 | I2: =H2+1 -> 2026 | J2: =I2+1 -> 2027 | K2: =J2+1 -> 2028 | L2: =K2+1 -> 2029 | M2: =L2+1 -> 2030
B4: Profitability Ratios
B5: Gross Profit Margin | C5: Gross Profit/Revenue | D5: ='Financial Statements'!D7 -> 0.17311711 | E5: ='Financial Statements'!E7 -> 0.24059633 | F5: ='Financial Statements'!F7 -> 0.25332899 | G5: ='Financial Statements'!G7 -> 0.26802112 | H5: ='Financial Statements'!H7 -> 0.42930629 | I5: ='Financial Statements'!I7 -> 0.4523176 | J5: ='Financial Statements'!J7 -> 0.45637666 | K5: ='Financial Statements'!K7 -> 0.45534514 | ... M5: ='Financial Statements'!M7 -> 0.45398219
B6: EBITDA Margin | C6: EBITDA/Revenue | D6: ='Financial Statements'!D13 -> 0.15682634 | E6: ='Financial Statements'!E13 -> 0.21472823 | F6: ='Financial Statements'!F13 -> 0.22250086 | G6: ='Financial Statements'!G13 -> 0.23358659 | H6: ='Financial Statements'!H13 -> 0.39687855 | I6: ='Financial Statements'!I13 -> 0.42101213 | J6: ='Financial Statements'!J13 -> 0.42484117 | K6: ='Financial Statements'!K13 -> 0.42362025 | ... M6: ='Financial Statements'!M13 -> 0.42221327
B7: Operating Margin | C7: EBIT/Revenue | D7: ='Financial Statements'!D26 -> 0.02253425 | E7: ='Financial Statements'!E26 -> 0.11162874 | F7: ='Financial Statements'!F26 -> 0.15393967 | G7: ='Financial Statements'!G26 -> 0.17249755 | H7: ='Financial Statements'!H26 -> 0.37961247 | I7: ='Financial Statements'!I26 -> 0.40921153 | J7: ='Financial Statements'!J26 -> 0.41535606 | K7: ='Financial Statements'!K26 -> 0.41618453 | ... M7: ='Financial Statements'!M26 -> 0.41911715
B8: Net Profit Margin | C8: Net Profit/Revenue | D8: ='Financial Statements'!D29 -> 0.01396265 | E8: ='Financial Statements'!E29 -> 0.076788625 | F8: ='Financial Statements'!F29 -> 0.1154258 | G8: ='Financial Statements'!G29 -> 0.13289393 | H8: ='Financial Statements'!H29 -> 0.28919399 | I8: ='Financial Statements'!I29 -> 0.31713893 | J8: ='Financial Statements'!J29 -> 0.32190094 | K8: ='Financial Statements'!K29 -> 0.32254301 | ... M8: ='Financial Statements'!M29 -> 0.32481579
B9: Return on Equity (ROE) | C9: Net Profit/Equity | D9: ='Financial Statements'!D28/'Financial Statements'!D63 -> 0.032224514 | E9: ='Financial Statements'!E28/'Financial Statements'!E63 -> 0.30865614 | F9: ='Financial Statements'!F28/'Financial Statements'!F63 -> 0.39760058 | G9: ='Financial Statements'!G28/'Financial Statements'!G63 -> 0.50363448 | H9: ='Financial Statements'!H28/'Financial Statements'!H63 -> 0.77533875 | I9: ='Financial Statements'!I28/'Financial Statements'!I63 -> 0.60297262 | J9: ='Financial Statements'!J28/'Financial Statements'!J63 -> 0.46401163 | K9: ='Financial Statements'!K28/'Financial Statements'!K63 -> 0.3737514 | ... M9: ='Financial Statements'!M28/'Financial Statements'!M63 -> 0.27239788
B10: Return on Assets (ROA) | C10: Net Profit/Assets | D10: ='Financial Statements'!D28/'Financial Statements'!D55 -> 0.011500286 | E10: ='Financial Statements'!E28/'Financial Statements'!E55 -> 0.095187172 | F10: ='Financial Statements'!F28/'Financial Statements'!F55 -> 0.1794196 | G10: ='Financial Statements'!G28/'Financial Statements'!G55 -> 0.19836062 | H10: ='Financial Statements'!H28/'Financial Statements'!H55 -> 0.40981378 | I10: ='Financial Statements'!I28/'Financial Statements'!I55 -> 0.38918218 | J10: ='Financial Statements'!J28/'Financial Statements'!J55 -> 0.33653506 | K10: ='Financial Statements'!K28/'Financial Statements'!K55 -> 0.29142227 | ... M10: ='Financial Statements'!M28/'Financial Statements'!M55 -> 0.2303958
B11: ROIC | C11: NOPAT/IC | D11: =('Financial Statements'!D17*(1-Valuation!$C$4))/('Financial Statements'!D88+'Financial Statements'!D41) -> 0.055448238 | E11: =('Financial Statements'!E17*(1-Valuation!$C$4))/('Financial Statements'!E88+'Financial Statements'!E41) -> 0.34096965 | F11: =('Financial Statements'!F17*(1-Valuation!$C$4))/('Financial Statements'!F88+'Financial Statements'!F41) -> 0.46318469 | G11: =('Financial Statements'!G17*(1-Valuation!$C$4))/('Financial Statements'!G88+'Financial Statements'!G41) -> 0.74955784 | H11: =('Financial Statements'!H17*(1-Valuation!$C$4))/('Financial Statements'!H88+'Financial Statements'!H41) -> 1.162497 | I11: =('Financial Statements'!I17*(1-Valuation!$C$4))/('Financial Statements'!I88+'Financial Statements'!I41) -> 1.2597437 | J11: =('Financial Statements'!J17*(1-Valuation!$C$4))/('Financial Statements'!J88+'Financial Statements'!J41) -> 1.4005137 | K11: =('Financial Statements'!K17*(1-Valuation!$C$4))/('Financial Statements'!K88+'Financial Statements'!K41) -> 1.5007322 | ... M11: =('Financial Statements'!M17*(1-Valuation!$C$4))/('Financial Statements'!M88+'Financial Statements'!M41) -> 1.6962758
B13: Efficiency Ratios
B14: Inventory Turnover | C14: COGS/Inventory | D14: =BS!C171 -> 5.4762337 | E14: =BS!D171 -> 5.6850158 | F14: =BS!E171 -> 4.57558 | G14: =BS!F171 -> 7.4957082 | H14: =BS!G171 -> 6.7419283 | I14: =BS!H171 -> 6.7419283 | J14: =BS!I171 -> 6.7419283 | K14: =BS!J171 -> 6.7419283 | ... M14: =BS!L171 -> 6.7419283
B15: Inventory DOH | C15: 365/Inventory Turnover | D15: =BS!C172 -> 66.651648 | E15: =BS!D172 -> 64.203867 | F15: =BS!E172 -> 79.771308 | G15: =BS!F172 -> 48.694532 | H15: =BS!G172 -> 54.138814 | I15: =BS!H172 -> 54.138814 | J15: =BS!I172 -> 54.138814 | K15: =BS!J172 -> 54.138814 | ... M15: =BS!L172 -> 54.138814
B16: Accounts Receivables Turnover | C16: Revenue/Receivables | D16: =BS!C178 -> 41.589528 | E16: =BS!D178 -> 58.764505 | F16: =BS!E178 -> 26.432241 | G16: =BS!F178 -> 54.544725 | H16: =BS!G178 -> 50.926694 | I16: =BS!H178 -> 50.926694 | J16: =BS!I178 -> 50.926694 | K16: =BS!J178 -> 50.926694 | ... M16: =BS!L178 -> 50.926694
B17: Accounts Receivables DOH | C17: 365/Receivables Turnover | D17: =BS!C179 -> 8.7762476 | E17: =BS!D179 -> 6.2112325 | F17: =BS!E179 -> 13.808894 | G17: =BS!F179 -> 6.6917561 | H17: =BS!G179 -> 7.1671646 | I17: =BS!H179 -> 7.1671646 | J17: =BS!I179 -> 7.1671646 | K17: =BS!J179 -> 7.1671646 | ... M17: =BS!L179 -> 7.1671646
B18: Accounts Payables Turnover | C18: COGS/Payables | D18: =Debt!C98 -> 7.4626326 | E18: =Debt!D98 -> 11.585636 | F18: =Debt!E98 -> 5.9788407 | G18: =Debt!F98 -> 13.621798 | H18: =Debt!G98 -> 48.773869 | I18: =Debt!H98 -> 17.484555 | J18: =Debt!I98 -> 17.484555 | K18: =Debt!J98 -> 17.484555 | ... M18: =Debt!L98 -> 17.484555
B19: Accounts Payables DOH | C19: 365/Payable Turnover | D19: =Debt!C99 -> 48.910354 | E19: =Debt!D99 -> 31.504529 | F19: =Debt!E99 -> 61.048624 | G19: =Debt!F99 -> 26.795288 | H19: =Debt!G99 -> 7.4835154 | I19: =Debt!H99 -> 20.875567 | J19: =Debt!I99 -> 20.875567 | K19: =Debt!J99 -> 20.875567 | ... M19: =Debt!L99 -> 20.875567
B20: PP&E Turnover | C20: Sales/Fixed Assets | D20: ='Financial Statements'!D4/'Financial Statements'!D41 -> 1.2122266 | E20: ='Financial Statements'!E4/'Financial Statements'!E41 -> 2.5419995 | F20: ='Financial Statements'!F4/'Financial Statements'!F41 -> 3.5892171 | G20: ='Financial Statements'!G4/'Financial Statements'!G41 -> 5.2285715 | H20: ='Financial Statements'!H4/'Financial Statements'!H41 -> 4.9348626 | I20: ='Financial Statements'!I4/'Financial Statements'!I41 -> 5.2091243 | J20: ='Financial Statements'!J4/'Financial Statements'!J41 -> 5.8659433 | K20: ='Financial Statements'!K4/'Financial Statements'!K41 -> 6.4445034 | ... M20: ='Financial Statements'!M4/'Financial Statements'!M41 -> 7.6103776
B22: Cash Conversion Cycle | C22: OC - APP | D22: =(D15+D17)-D19 -> 26.517542 | E22: =(E15+E17)-E19 -> 38.910571 | F22: =(F15+F17)-F19 -> 32.531578 | G22: =(G15+G17)-G19 -> 28.591 | H22: =(H15+H17)-H19 -> 53.822463 | I22: =(I15+I17)-I19 -> 40.430412 | J22: =(J15+J17)-J19 -> 40.430412 | K22: =(K15+K17)-K19 -> 40.430412 | ... M22: =(M15+M17)-M19 -> 40.430412
B24: Liquidity Ratios
B25: Current Ratio | C25: Current Assets/Current Liabilities | D25: ='Financial Statements'!D54/'Financial Statements'!D82 -> 0.53670978 | E25: ='Financial Statements'!E54/'Financial Statements'!E82 -> 0.79944206 | F25: ='Financial Statements'!F54/'Financial Statements'!F82 -> 1.0963292 | G25: ='Financial Statements'!G54/'Financial Statements'!G82 -> 1.1568928 | H25: ='Financial Statements'!H54/'Financial Statements'!H82 -> 1.9910069 | I25: ='Financial Statements'!I54/'Financial Statements'!I82 -> 2.7926056 | J25: ='Financial Statements'!J54/'Financial Statements'!J82 -> 3.6030397 | K25: ='Financial Statements'!K54/'Financial Statements'!K82 -> 4.3885497 | ... M25: ='Financial Statements'!M54/'Financial Statements'!M82 -> 6.2622646
B26: Quick Ratio | C26: (CA-Inventory)/CL | D26: =('Financial Statements'!D54-'Financial Statements'!D49)/'Financial Statements'!D82 -> 0.25727073 | E26: =('Financial Statements'!E54-'Financial Statements'!E49)/'Financial Statements'!E82 -> 0.50943782 | F26: =('Financial Statements'!F54-'Financial Statements'!F49)/'Financial Statements'!F82 -> 0.56258078 | G26: =('Financial Statements'!G54-'Financial Statements'!G49)/'Financial Statements'!G82 -> 0.86096808 | H26: =('Financial Statements'!H54-'Financial Statements'!H49)/'Financial Statements'!H82 -> 1.6269437 | I26: =('Financial Statements'!I54-'Financial Statements'!I49)/'Financial Statements'!I82 -> 2.425172 | J26: =('Financial Statements'!J54-'Financial Statements'!J49)/'Financial Statements'!J82 -> 3.2318975 | K26: =('Financial Statements'!K54-'Financial Statements'!K49)/'Financial Statements'!K82 -> 4.0154606 | ... M26: =('Financial Statements'!M54-'Financial Statements'!M49)/'Financial Statements'!M82 -> 5.8655469
B27: Cash Ratio | C27: (Cash+MKTable Equivalents)/CL | D27: =('Financial Statements'!D54-('Financial Statements'!D49+'Financial Statements'!D50))/'Financial Statements'!D82 -> 0.21277267 | E27: =('Financial Statements'!E54-('Financial Statements'!E49+'Financial Statements'!E50))/'Financial Statements'!E82 -> 0.47249345 | F27: =('Financial Statements'!F54-('Financial Statements'!F49+'Financial Statements'!F50))/'Financial Statements'!F82 -> 0.43883811 | G27: =('Financial Statements'!G54-('Financial Statements'!G49+'Financial Statements'!G50))/'Financial Statements'!G82 -> 0.80541058 | H27: =('Financial Statements'!H54-('Financial Statements'!H49+'Financial Statements'!H50))/'Financial Statements'!H82 -> 1.5424912 | I27: =('Financial Statements'!I54-('Financial Statements'!I49+'Financial Statements'!I50))/'Financial Statements'!I82 -> 2.3363565 | J27: =('Financial Statements'!J54-('Financial Statements'!J49+'Financial Statements'!J50))/'Financial Statements'!J82 -> 3.1415157 | K27: =('Financial Statements'!K54-('Financial Statements'!K49+'Financial Statements'!K50))/'Financial Statements'!K82 -> 3.9247768 | ... M27: =('Financial Statements'!M54-('Financial Statements'!M49+'Financial Statements'!M50))/'Financial Statements'!M82 -> 5.7693605
B29: Solvency Ratios
B30: Total Liabilities to Equity | C30: Total Liabilities/Equity | D30: ='Financial Statements'!D83/'Financial Statements'!D63 -> 1.8020619 | E30: ='Financial Statements'!E83/'Financial Statements'!E63 -> 2.2426233 | F30: ='Financial Statements'!F83/'Financial Statements'!F63 -> 1.2160375 | G30: ='Financial Statements'!G83/'Financial Statements'!G63 -> 1.5389842 | H30: ='Financial Statements'!H83/'Financial Statements'!H63 -> 0.89192945 | I30: ='Financial Statements'!I83/'Financial Statements'!I63 -> 0.54933258 | J30: ='Financial Statements'!J83/'Financial Statements'!J63 -> 0.37879134 | K30: ='Financial Statements'!K83/'Financial Statements'!K63 -> 0.282508 | ... M30: ='Financial Statements'!M83/'Financial Statements'!M63 -> 0.18230402
B31: Total Assets to Equity | C31: Total Assets/Equity | D31: ='Financial Statements'!D55/'Financial Statements'!D63 -> 2.8020619 | E31: ='Financial Statements'!E55/'Financial Statements'!E63 -> 3.2426233 | F31: ='Financial Statements'!F55/'Financial Statements'!F63 -> 2.2160375 | G31: ='Financial Statements'!G55/'Financial Statements'!G63 -> 2.5389842 | H31: ='Financial Statements'!H55/'Financial Statements'!H63 -> 1.8919294 | I31: ='Financial Statements'!I55/'Financial Statements'!I63 -> 1.5493326 | J31: ='Financial Statements'!J55/'Financial Statements'!J63 -> 1.3787913 | K31: ='Financial Statements'!K55/'Financial Statements'!K63 -> 1.282508 | ... M31: ='Financial Statements'!M55/'Financial Statements'!M63 -> 1.182304
B32: Interest Coverage | C32: EBIT/Interest Expenses | D32: =-'Financial Statements'!D17/'Financial Statements'!D19 -> 1.7903801 | E32: =-'Financial Statements'!E17/'Financial Statements'!E19 -> 13.119494 | F32: =-'Financial Statements'!F17/'Financial Statements'!F19 -> 14.213059 | G32: =-'Financial Statements'!G17/'Financial Statements'!G19 -> 19.545782 | H32: =-'Financial Statements'!H17/'Financial Statements'!H19 -> 93.301392 | I32: =-'Financial Statements'!I17/'Financial Statements'!I19 -> 59.684656 | J32: =-'Financial Statements'!J17/'Financial Statements'!J19 -> 71.02275 | K32: =-'Financial Statements'!K17/'Financial Statements'!K19 -> 96.783697 | ... M32: =-'Financial Statements'!M17/'Financial Statements'!M19 -> 226.98466
B34: Leverage Ratios
B35: Degree of Operating Leverage (DOL) | C35: % change in EBIT/% change in Sales | E35: =('Financial Statements'!E17/'Financial Statements'!D17-1)/('Financial Statements'!E4/'Financial Statements'!D4-1) -> 5.5751956 | F35: =('Financial Statements'!F17/'Financial Statements'!E17-1)/('Financial Statements'!F4/'Financial Statements'!E4-1) -> 1.4896529 | G35: =('Financial Statements'!G17/'Financial Statements'!F17-1)/('Financial Statements'!G4/'Financial Statements'!F4-1) -> 1.4147001 | H35: =('Financial Statements'!H17/'Financial Statements'!G17-1)/('Financial Statements'!H4/'Financial Statements'!G4-1) -> 3.7785375 | I35: =('Financial Statements'!I17/'Financial Statements'!H17-1)/('Financial Statements'!I4/'Financial Statements'!H4-1) -> 1.4168127 | J35: =('Financial Statements'!J17/'Financial Statements'!I17-1)/('Financial Statements'!J4/'Financial Statements'!I4-1) -> 1.1475791 | K35: =('Financial Statements'!K17/'Financial Statements'!J17-1)/('Financial Statements'!K4/'Financial Statements'!J4-1) -> 0.97376889 | L35: =('Financial Statements'!L17/'Financial Statements'!K17-1)/('Financial Statements'!L4/'Financial Statements'!K4-1) -> 1.0547162 | M35: =('Financial Statements'!M17/'Financial Statements'!L17-1)/('Financial Statements'!M4/'Financial Statements'!L4-1) -> 0.96916447
B36: Degree of Financial Leverage (DFL) | C36: % change in EPS/% change in EBIT | E36: =('Financial Statements'!E28/'Financial Statements'!D28-1)/('Financial Statements'!E17/'Financial Statements'!D17-1) -> 1.8740764 | F36: =('Financial Statements'!F28/'Financial Statements'!E28-1)/('Financial Statements'!F17/'Financial Statements'!E17-1) -> 2.163515 | G36: =('Financial Statements'!G28/'Financial Statements'!F28-1)/('Financial Statements'!G17/'Financial Statements'!F17-1) -> 1.0544179 | H36: =('Financial Statements'!H28/'Financial Statements'!G28-1)/('Financial Statements'!H17/'Financial Statements'!G17-1) -> 1.3068521 | I36: =('Financial Statements'!I28/'Financial Statements'!H28-1)/('Financial Statements'!I17/'Financial Statements'!H17-1) -> 1.1465431 | J36: =('Financial Statements'!J28/'Financial Statements'!I28-1)/('Financial Statements'!J17/'Financial Statements'!I17-1) -> 1.0204195 | K36: =('Financial Statements'!K28/'Financial Statements'!J28-1)/('Financial Statements'!K17/'Financial Statements'!J17-1) -> 1.0583809 | L36: =('Financial Statements'!L28/'Financial Statements'!K28-1)/('Financial Statements'!L17/'Financial Statements'!K17-1) -> 1.0536965 | M36: =('Financial Statements'!M28/'Financial Statements'!L28-1)/('Financial Statements'!M17/'Financial Statements'!L17-1) -> 1.0493156
B37: Degree of Total Leverage (DTL) | C37: DOL*DFL | E37: =E35*E36 -> 10.448343 | F37: =F35*F36 -> 3.2228864 | G37: =G35*G36 -> 1.4916852 | H37: =H35*H36 -> 4.9379895 | I37: =I35*I36 -> 1.6244368 | J37: =J35*J36 -> 1.1710121 | K37: =K35*K36 -> 1.0306184 | L37: =L35*L36 -> 1.1113507 | M37: =M35*M36 -> 1.0169594
B39: Cash Flow Ratios
B40: CapEX | C40: (Net FAnew - Net FAold)+Depreciation | D40: =BS!C23 -> 32.443963 | E40: =BS!D23 -> 27.374376 | F40: =BS!E23 -> 56.808221 | G40: =BS!F23 -> 206.54263 | H40: =BS!G23 -> 329.8932 | I40: =BS!H23 -> 231.69836 | J40: =BS!I23 -> 254.0006 | K40: =BS!J23 -> 271.70026 | ... M40: =BS!L23 -> 303.70738
B41: CapEX % of Sales | D41: =D40/'Financial Statements'!D4 -> 0.013249836 | E41: =E40/'Financial Statements'!E4 -> 0.005855478 | F41: =F40/'Financial Statements'!F4 -> 0.0094009278 | G41: =G40/'Financial Statements'!G4 -> 0.023659538 | H41: =H40/'Financial Statements'!H4 -> 0.026503151 | I41: =I40/'Financial Statements'!I4 -> 0.015733786 | J41: =J40/'Financial Statements'!J4 -> 0.015733786 | K41: =K40/'Financial Statements'!K4 -> 0.015733786 | ... M41: =M40/'Financial Statements'!M4 -> 0.015733786
B42: Free Cash Flow (FCF) | C42: Cash from Operations - CapEX | D42: ='Financial Statements'!D109-Ratios!D40 -> -6.646567 | E42: ='Financial Statements'!E109-Ratios!E40 -> 10.699247 | F42: ='Financial Statements'!F109-Ratios!F40 -> -66.233906 | G42: ='Financial Statements'!G109-Ratios!G40 -> -183.08883 | H42: ='Financial Statements'!H109-Ratios!H40 -> -296.10823 | I42: ='Financial Statements'!I109-Ratios!I40 -> -144.2207 | J42: ='Financial Statements'!J109-Ratios!J40 -> -158.56201 | K42: ='Financial Statements'!K109-Ratios!K40 -> -170.09936 | ... M42: ='Financial Statements'!M109-Ratios!M40 -> -191.17862
B43: FCF Margin | C43: FCF/Revenue | D43: =D42/'Financial Statements'!D4 -> -0.0027144008 | E43: =E42/'Financial Statements'!E4 -> 0.0022886076 | F43: =F42/'Financial Statements'!F4 -> -0.01096074 | G43: =G42/'Financial Statements'!G4 -> -0.020972896 | H43: =H42/'Financial Statements'!H4 -> -0.023788914 | I43: =I42/'Financial Statements'!I4 -> -0.0097934993 | J43: =J42/'Financial Statements'!J4 -> -0.009821948 | K43: =K42/'Financial Statements'!K4 -> -0.0098502187 | ... M43: =M42/'Financial Statements'!M4 -> -0.0099041499
B44: FCF Conversion Ratio | C44: FCF/Net Profit | D44: =D42/'Financial Statements'!D34 -> -0.19440441 | E44: =E42/'Financial Statements'!E34 -> 0.029803992 | F44: =F42/'Financial Statements'!F34 -> -0.094959192 | G44: =G42/'Financial Statements'!G34 -> -0.15781681 | H44: =H42/'Financial Statements'!H34 -> -0.082259363 | I44: =I42/'Financial Statements'!I34 -> -0.030880785 | J44: =J42/'Financial Statements'!J34 -> -0.030512331 | K44: =K42/'Financial Statements'!K34 -> -0.030539241 | ... M44: =M42/'Financial Statements'!M34 -> -0.03049159
B45: FCF to Debt | C45: FCF/Total Liabilities | D45: =D42/'Financial Statements'!D83 -> -0.0034763444 | E45: =E42/'Financial Statements'!E83 -> 0.0041019752 | F45: =F42/'Financial Statements'!F83 -> -0.031048243 | G45: =G42/'Financial Statements'!G83 -> -0.051645747 | H45: =H42/'Financial Statements'!H83 -> -0.071506633 | I45: =I42/'Financial Statements'!I83 -> -0.033896166 | J45: =J42/'Financial Statements'!J83 -> -0.037376979 | K45: =K42/'Financial Statements'!K83 -> -0.040402692 | ... M45: =M42/'Financial Statements'!M83 -> -0.045560401
B46: Operating Cash flow Margin | C46: OCF/Revenue | D46: ='Financial Statements'!D109/'Financial Statements'!D4 -> 0.010535435 | E46: ='Financial Statements'!E109/'Financial Statements'!E4 -> 0.0081440856 | F46: ='Financial Statements'!F109/'Financial Statements'!F4 -> -0.0015598127 | G46: ='Financial Statements'!G109/'Financial Statements'!G4 -> 0.0026866424 | H46: ='Financial Statements'!H109/'Financial Statements'!H4 -> 0.002714237 | I46: ='Financial Statements'!I109/'Financial Statements'!I4 -> 0.0059402868 | J46: ='Financial Statements'!J109/'Financial Statements'!J4 -> 0.0059118381 | K46: ='Financial Statements'!K109/'Financial Statements'!K4 -> 0.0058835674 | ... M46: ='Financial Statements'!M109/'Financial Statements'!M4 -> 0.0058296362
B47: Cash Conversion Ratio | C47: OCF/Net Profit | D47: ='Financial Statements'!D109/'Financial Statements'!D28 -> 0.75454406 | E47: ='Financial Statements'!E109/'Financial Statements'!E28 -> 0.10605849 | F47: ='Financial Statements'!F109/'Financial Statements'!F28 -> -0.013513553 | G47: ='Financial Statements'!G109/'Financial Statements'!G28 -> 0.020216443 | H47: ='Financial Statements'!H109/'Financial Statements'!H28 -> 0.0093855235 | I47: ='Financial Statements'!I109/'Financial Statements'!I28 -> 0.018730866 | J47: ='Financial Statements'!J109/'Financial Statements'!J28 -> 0.018365395 | K47: ='Financial Statements'!K109/'Financial Statements'!K28 -> 0.018241187 | ... M47: ='Financial Statements'!M109/'Financial Statements'!M28 -> 0.017947515
B49: Tobin's Q Ratio
B50: Shares Outstanding | C50: Investing / stock analysis | D50: 374.9 | E50: 374.9 | F50: 374.9 | G50: 374.9 | H50: 374.9 | I50: 374.9 | J50: 374.9 | K50: 374.9 | L50: 374.9 | M50: 374.9
A51: will be updated to the final one | B51: Share Prices | C51: Investing / stock analysis | D51: 4.52 | E51: 6.87 | F51: 10.1 | G51: 17.01 | H51: 72.11 | I51: 72.11 | J51: 72.11 | K51: 72.11 | L51: 72.11 | M51: 72.11
B52: Market Value | C52: no. of shares*share price | D52: =D50*D51 -> 1694.548 | E52: =E50*E51 -> 2575.563 | F52: =F50*F51 -> 3786.49 | G52: =G50*G51 -> 6377.049 | H52: =H50*H51 -> 27034.039 | I52: =I50*I51 -> 27034.039 | J52: =J50*J51 -> 27034.039 | K52: =K50*K51 -> 27034.039 | ... M52: =M50*M51 -> 27034.039
B53: Tobin's Q Ratio | C53: Market Value of firm/Total Assets | D53: =D52/'Financial Statements'!D55 -> 0.56999528 | E53: =E52/'Financial Statements'!E55 -> 0.68292314 | F53: =F52/'Financial Statements'!F55 -> 0.97400985 | G53: =G52/'Financial Statements'!G55 -> 1.0903518 | H53: =H52/'Financial Statements'!H55 -> 3.0777431 | I53: =I52/'Financial Statements'!I55 -> 2.2528102 | J53: =J52/'Financial Statements'!J55 -> 1.7507233 | K53: =K52/'Financial Statements'!K55 -> 1.4144553 | ... M53: =M52/'Financial Statements'!M55 -> 0.99340478
B55: Z-Score Ratio
B56: A | C56: Working Capital/Total Assets | D56: ='Financial Statements'!D87/'Financial Statements'!D54 -> -0.53081783 | E56: ='Financial Statements'!E87/'Financial Statements'!E54 -> -0.27287846 | F56: ='Financial Statements'!F87/'Financial Statements'!F54 -> -0.091011359 | G56: ='Financial Statements'!G87/'Financial Statements'!G54 -> 0.0028091806 | H56: ='Financial Statements'!H87/'Financial Statements'!H54 -> -0.059820952 | I56: ='Financial Statements'!I87/'Financial Statements'!I54 -> -0.090019385 | J56: ='Financial Statements'!J87/'Financial Statements'!J54 -> -0.069284404 | K56: ='Financial Statements'!K87/'Financial Statements'!K54 -> -0.057257405 | ... M56: ='Financial Statements'!M87/'Financial Statements'!M54 -> -0.044223014
B57: B | C57: R.E/Total Assets | D57: ='Financial Statements'!D60/'Financial Statements'!D54 -> 0.064249489 | E57: ='Financial Statements'!E60/'Financial Statements'!E54 -> 0.084231472 | F57: ='Financial Statements'!F60/'Financial Statements'!F54 -> 0.3465414 | G57: ='Financial Statements'!G60/'Financial Statements'!G54 -> 0.35477293 | H57: ='Financial Statements'!H60/'Financial Statements'!H54 -> 0.63324706 | I57: ='Financial Statements'!I60/'Financial Statements'!I54 -> 0.74255984 | J57: ='Financial Statements'!J60/'Financial Statements'!J54 -> 0.807579 | K57: ='Financial Statements'!K60/'Financial Statements'!K54 -> 0.84757177 | ... M57: ='Financial Statements'!M60/'Financial Statements'!M54 -> 0.89244678
B58: C | C58: EBIT/Total Assets | D58: ='Financial Statements'!D17/'Financial Statements'!D55 -> 0.042232134 | E58: ='Financial Statements'!E17/'Financial Statements'!E55 -> 0.20204704 | F58: ='Financial Statements'!F17/'Financial Statements'!F55 -> 0.28144126 | G58: ='Financial Statements'!G17/'Financial Statements'!G55 -> 0.30474879 | H58: ='Financial Statements'!H17/'Financial Statements'!H55 -> 0.52942285 | I58: ='Financial Statements'!I17/'Financial Statements'!I55 -> 0.48803936 | J58: ='Financial Statements'!J17/'Financial Statements'!J55 -> 0.42116375 | K58: ='Financial Statements'!K17/'Financial Statements'!K55 -> 0.36335845 | ... M58: ='Financial Statements'!M17/'Financial Statements'!M55 -> 0.28564905
B59: D | C59: Market Value of firm/Total Liabilities | D59: =D52/'Financial Statements'!D83 -> 0.886297 | E59: =E52/'Financial Statements'!E83 -> 0.98744291 | F59: =F52/'Financial Statements'!F83 -> 1.7749801 | G59: =G52/'Financial Statements'!G83 -> 1.7988398 | H59: =H52/'Financial Statements'!H83 -> 6.5284006 | I59: =I52/'Financial Statements'!I83 -> 6.3538052 | J59: =J52/'Financial Statements'!J83 -> 6.3725903 | K59: =K52/'Financial Statements'!K83 -> 6.421235 | ... M59: =M52/'Financial Statements'!M83 -> 6.4425702
B60: E | C60: Revenue/Total Assets | D60: ='Financial Statements'!D4/'Financial Statements'!D55 -> 0.82364638 | E60: ='Financial Statements'!E4/'Financial Statements'!E55 -> 1.2395999 | F60: ='Financial Statements'!F4/'Financial Statements'!F55 -> 1.5544151 | G60: ='Financial Statements'!G4/'Financial Statements'!G55 -> 1.4926237 | H60: ='Financial Statements'!H4/'Financial Statements'!H55 -> 1.4170895 | I60: ='Financial Statements'!I4/'Financial Statements'!I55 -> 1.2271662 | J60: ='Financial Statements'!J4/'Financial Statements'!J55 -> 1.0454616 | K60: ='Financial Statements'!K4/'Financial Statements'!K55 -> 0.90351446 | ... M60: ='Financial Statements'!M4/'Financial Statements'!M55 -> 0.70931218
B61: Z-Score Ratio | C61: (1.2*A)+(1.4*B)+(3.3*C)+(0.6*D)+(1.0*E) | D61: =(1.2*D56)+(1.4*D57)+(3.3*D58)+(0.6*D59)+(1*D60) -> 0.94775851 | E61: =(1.2*E56)+(1.4*E57)+(3.3*E58)+(0.6*E59)+(1*E60) -> 2.2892908 | F61: =(1.2*F56)+(1.4*F57)+(3.3*F58)+(0.6*F59)+(1*F60) -> 3.9241036 | G61: =(1.2*G56)+(1.4*G57)+(3.3*G58)+(0.6*G59)+(1*G60) -> 4.0776516 | H61: =(1.2*H56)+(1.4*H57)+(3.3*H58)+(0.6*H59)+(1*H60) -> 7.895986 | I61: =(1.2*I56)+(1.4*I57)+(3.3*I58)+(0.6*I59)+(1*I60) -> 7.5815397 | J61: =(1.2*J56)+(1.4*J57)+(3.3*J58)+(0.6*J59)+(1*J60) -> 7.3063254 | K61: =(1.2*K56)+(1.4*K57)+(3.3*K58)+(0.6*K59)+(1*K60) -> 7.0732299 | ... M61: =(1.2*M56)+(1.4*M57)+(3.3*M58)+(0.6*M59)+(1*M60) -> 6.7138541
D62: =IF(3<D61,"Safe Zone",IF(1.8<D61,"Grey Zone","Distress Zone")) -> Distress Zone | E62: =IF(3<E61,"Safe Zone",IF(1.8<E61,"Grey Zone","Distress Zone")) -> Grey Zone | F62: =IF(3<F61,"Safe Zone",IF(1.8<F61,"Grey Zone","Distress Zone")) -> Safe Zone | G62: =IF(3<G61,"Safe Zone",IF(1.8<G61,"Grey Zone","Distress Zone")) -> Safe Zone | H62: =IF(3<H61,"Safe Zone",IF(1.8<H61,"Grey Zone","Distress Zone")) -> Safe Zone | I62: =IF(3<I61,"Safe Zone",IF(1.8<I61,"Grey Zone","Distress Zone")) -> Safe Zone | J62: =IF(3<J61,"Safe Zone",IF(1.8<J61,"Grey Zone","Distress Zone")) -> Safe Zone | K62: =IF(3<K61,"Safe Zone",IF(1.8<K61,"Grey Zone","Distress Zone")) -> Safe Zone | ... M62: =IF(3<M61,"Safe Zone",IF(1.8<M61,"Grey Zone","Distress Zone")) -> Safe Zone

Sheet Valuation
B2: WACC | C2: 2026 | D2: =C2+1 -> 2027 | E2: =D2+1 -> 2028 | F2: =E2+1 -> 2029 | G2: =F2+1 -> 2030 | J2: Assumptions | K2: =C2 -> 2026 | L2: =D2 -> 2027 | M2: =E2 -> 2028 | N2: =F2 -> 2029 | O2: =G2 -> 2030 | S2: Table 1:WACC & Terminal Growth Rate SA
B3: Interest Rate | C3: =IS!H80 -> 0.086172199 | D3: =IS!I80 -> 0.090098339 | E3: =IS!J80 -> 0.093986824 | F3: =IS!K80 -> 0.10098475 | G3: =IS!L80 -> 0.12054651 | J3: Share Price | K3: 73.45 | L3: 73.45 | M3: 73.45 | N3: 73.45 | O3: 73.45 | R3: WACC
B4: Tax Rate | C4: 0.225 | D4: 0.225 | E4: 0.225 | F4: 0.225 | G4: 0.225 | J4: Shares Outstanding | K4: 347.9 | L4: 347.9 | M4: 347.9 | N4: 347.9 | O4: 347.9 | R4: TGR | S4: =C31 -> 128.46401 | T4: =U4-1% -> 0.15398494 | U4: =V4-1% -> 0.16398494 | V4: =G12 -> 0.17398494 | W4: =V4+1% -> 0.18398494 | X4: =W4+1% -> 0.19398494
B5: Cost of Debt | C5: =C3*(1-C4) -> 0.066783454 | D5: =D3*(1-D4) -> 0.069826213 | E5: =E3*(1-E4) -> 0.072839789 | F5: =F3*(1-F4) -> 0.078263185 | G5: =G3*(1-G4) -> 0.093423543 | J5: Market Cap | K5: =K3*K4 -> 25553.255 | L5: =L3*L4 -> 25553.255 | M5: =M3*M4 -> 25553.255 | N5: =N3*N4 -> 25553.255 | O5: =O3*O4 -> 25553.255 | S5: =S6-1% -> 0.03 | T5: =$S$4*($S5/$K$8)*(T$4/$G$12) -> 68.218051 | U5: =$S$4*($S5/$K$8)*(U$4/$G$12) -> 72.648227 | V5: =$S$4*($S5/$K$8)*(V$4/$G$12) -> 77.078404 | W5: =$S$4*($S5/$K$8)*(W$4/$G$12) -> 81.508581 | X5: =$S$4*($S5/$K$8)*(X$4/$G$12) -> 85.938758 | Z5: =IF(T5>$K$15,"Buy",IF(T5>=$K$16,"Hold","Sell")) -> Sell | AA5: =IF(U5>$K$15,"Buy",IF(U5>=$K$16,"Hold","Sell")) -> Sell | AB5: =IF(V5>$K$15,"Buy",IF(V5>=$K$16,"Hold","Sell")) -> Hold | AC5: =IF(W5>$K$15,"Buy",IF(W5>=$K$16,"Hold","Sell")) -> Hold | AD5: =IF(X5>$K$15,"Buy",IF(X5>=$K$16,"Hold","Sell")) -> Hold
B6: RFR | C6: =(1+$K$11)*(1+K12)/(1+K13)-1 -> 0.15943773 | D6: =(1+$K$11)*(1+L12)/(1+L13)-1 -> 0.1401556 | E6: =(1+$K$11)*(1+M12)/(1+M13)-1 -> 0.10936832 | F6: =(1+$K$11)*(1+N12)/(1+N13)-1 -> 0.089869706 | G6: =(1+$K$11)*(1+O12)/(1+O13)-1 -> 0.081659765 | J6: Interest Bearing Debt | K6: ='Financial Statements'!I66+'Financial Statements'!I68+'Financial Statements'!I74+'Financial Statements'!I76+'Financial Statements'!I77 -> 1142.3018 | L6: ='Financial Statements'!J66+'Financial Statements'!J68+'Financial Statements'!J74+'Financial Statements'!J76+'Financial Statements'!J77 -> 890.33668 | M6: ='Financial Statements'!K66+'Financial Statements'!K68+'Financial Statements'!K74+'Financial Statements'!K76+'Financial Statements'!K77 -> 636.58859 | N6: ='Financial Statements'!L66+'Financial Statements'!L68+'Financial Statements'!L74+'Financial Statements'!L76+'Financial Statements'!L77 -> 381.78437 | O6: ='Financial Statements'!M66+'Financial Statements'!M68+'Financial Statements'!M74+'Financial Statements'!M76+'Financial Statements'!M77 -> 186.40923 | S6: =S7-1% -> 0.04 | T6: =$S$4*($S6/$K$8)*(T$4/$G$12) -> 90.957401 | U6: =$S$4*($S6/$K$8)*(U$4/$G$12) -> 96.864303 | V6: =$S$4*($S6/$K$8)*(V$4/$G$12) -> 102.77121 | W6: =$S$4*($S6/$K$8)*(W$4/$G$12) -> 108.67811 | X6: =$S$4*($S6/$K$8)*(X$4/$G$12) -> 114.58501 | Z6: =IF(T6>$K$15,"Buy",IF(T6>=$K$16,"Hold","Sell")) -> Buy | AA6: =IF(U6>$K$15,"Buy",IF(U6>=$K$16,"Hold","Sell")) -> Buy | AB6: =IF(V6>$K$15,"Buy",IF(V6>=$K$16,"Hold","Sell")) -> Buy | AC6: =IF(W6>$K$15,"Buy",IF(W6>=$K$16,"Hold","Sell")) -> Buy | AD6: =IF(X6>$K$15,"Buy",IF(X6>=$K$16,"Hold","Sell")) -> Buy | AF6: Buy | AG6: =COUNTIF(Z5:AD9,"Buy") -> 20 | AH6: =AG6/$AG$9 -> 0.8
B7: Beta | C7: =Beta!I6 -> 0.68875362 | D7: =C7 -> 0.68875362 | E7: =D7 -> 0.68875362 | F7: =E7 -> 0.68875362 | G7: =F7 -> 0.68875362 | J7: Total Capitalization | K7: =K5+K6 -> 26695.557 | L7: =L5+L6 -> 26443.592 | M7: =M5+M6 -> 26189.844 | N7: =N5+N6 -> 25935.039 | O7: =O5+O6 -> 25739.664 | S7: =K8 -> 0.05 | T7: =$S$4*($S7/$K$8)*(T$4/$G$12) -> 113.69675 | U7: =$S$4*($S7/$K$8)*(U$4/$G$12) -> 121.08038 | V7: =$S$4*($S7/$K$8)*(V$4/$G$12) -> 128.46401 | W7: =$S$4*($S7/$K$8)*(W$4/$G$12) -> 135.84763 | X7: =$S$4*($S7/$K$8)*(X$4/$G$12) -> 143.23126 | Z7: =IF(T7>$K$15,"Buy",IF(T7>=$K$16,"Hold","Sell")) -> Buy | AA7: =IF(U7>$K$15,"Buy",IF(U7>=$K$16,"Hold","Sell")) -> Buy | AB7: =IF(V7>$K$15,"Buy",IF(V7>=$K$16,"Hold","Sell")) -> Buy | AC7: =IF(W7>$K$15,"Buy",IF(W7>=$K$16,"Hold","Sell")) -> Buy | AD7: =IF(X7>$K$15,"Buy",IF(X7>=$K$16,"Hold","Sell")) -> Buy | AF7: Sell | AG7: =COUNTIF(Z5:AD9,"Sell") -> 2 | AH7: =AG7/$AG$9 -> 0.08
B8: Equity Risk Premium | C8: 0.1349 | D8: 0.1349 | E8: 0.1349 | F8: 0.1349 | G8: 0.1349 | J8: Terminal Growth Rate | K8: 0.05 | S8: =S7+1% -> 0.06 | T8: =$S$4*($S8/$K$8)*(T$4/$G$12) -> 136.4361 | U8: =$S$4*($S8/$K$8)*(U$4/$G$12) -> 145.29645 | V8: =$S$4*($S8/$K$8)*(V$4/$G$12) -> 154.15681 | W8: =$S$4*($S8/$K$8)*(W$4/$G$12) -> 163.01716 | X8: =$S$4*($S8/$K$8)*(X$4/$G$12) -> 171.87752 | Z8: =IF(T8>$K$15,"Buy",IF(T8>=$K$16,"Hold","Sell")) -> Buy | AA8: =IF(U8>$K$15,"Buy",IF(U8>=$K$16,"Hold","Sell")) -> Buy | AB8: =IF(V8>$K$15,"Buy",IF(V8>=$K$16,"Hold","Sell")) -> Buy | AC8: =IF(W8>$K$15,"Buy",IF(W8>=$K$16,"Hold","Sell")) -> Buy | AD8: =IF(X8>$K$15,"Buy",IF(X8>=$K$16,"Hold","Sell")) -> Buy | AF8: Hold | AG8: =COUNTIF(Z5:AD9,"Hold") -> 3 | AH8: =AG8/$AG$9 -> 0.12
B9: Cost of Equity | C9: =C6+C7*(C8) -> 0.2523506 | D9: =D6+D7*(D8) -> 0.23306846 | E9: =E6+E7*(E8) -> 0.20228118 | F9: =F6+F7*(F8) -> 0.18278257 | G9: =G6+G7*(G8) -> 0.17457263 | J9: R-G | K9: =G12-K8 -> 0.12398494 | S9: =S8+1% -> 0.07 | T9: =$S$4*($S9/$K$8)*(T$4/$G$12) -> 159.17545 | U9: =$S$4*($S9/$K$8)*(U$4/$G$12) -> 169.51253 | V9: =$S$4*($S9/$K$8)*(V$4/$G$12) -> 179.84961 | W9: =$S$4*($S9/$K$8)*(W$4/$G$12) -> 190.18669 | X9: =$S$4*($S9/$K$8)*(X$4/$G$12) -> 200.52377 | Z9: =IF(T9>$K$15,"Buy",IF(T9>=$K$16,"Hold","Sell")) -> Buy | AA9: =IF(U9>$K$15,"Buy",IF(U9>=$K$16,"Hold","Sell")) -> Buy | AB9: =IF(V9>$K$15,"Buy",IF(V9>=$K$16,"Hold","Sell")) -> Buy | AC9: =IF(W9>$K$15,"Buy",IF(W9>=$K$16,"Hold","Sell")) -> Buy | AD9: =IF(X9>$K$15,"Buy",IF(X9>=$K$16,"Hold","Sell")) -> Buy | AF9: Total | AG9: =SUM(AG6:AG8) -> 25 | AH9: =SUM(AH6:AH8) -> 1
B10: Weight of Debt | C10: =1-C11 -> 0.04278996 | D10: =1-D11 -> 0.03366928 | E10: =1-E11 -> 0.024306697 | F10: =1-F11 -> 0.014720794 | G10: =1-G11 -> 0.0072421002
B11: Weight of Equity | C11: =K5/K7 -> 0.95721004 | D11: =L5/L7 -> 0.96633072 | E11: =M5/M7 -> 0.9756933 | F11: =N5/N7 -> 0.98527921 | G11: =O5/O7 -> 0.9927579 | J11: 10 years US t-bonds | K11: 0.04882
B12: WACC | C12: =(C10*C5)+(C11*C9) -> 0.24441019 | D12: =(D10*D5)+(D11*D9) -> 0.22757221 | E12: =(E10*E5)+(E11*E9) -> 0.19913489 | F12: =(F10*F5)+(F11*F9) -> 0.18124396 | G12: =(G10*G5)+(G11*G9) -> 0.17398494 | J12: EGP inf | K12: =Assumptions!J8 -> 0.132 | L12: =Assumptions!K8 -> 0.111 | M12: =Assumptions!L8 -> 0.081 | N12: =Assumptions!M8 -> 0.062 | O12: =Assumptions!N8 -> 0.054 | R12: Table 2: P/E Sensitivity Analysis
J13: US inf | K13: 0.024 | L13: 0.022 | M13: 0.022 | N13: 0.022 | O13: 0.022 | S13: EPS
B14: Income Valuation - DCF | R14: P/E MED | S14: =C46 -> 112.81179 | T14: =U14-0.09 -> 13.24409 | U14: =V14-0.09 -> 13.33409 | V14: =C45 -> 13.42409 | W14: =V14+0.09 -> 13.51409 | X14: =W14+0.09 -> 13.60409
B15: EBIT | C15: ='Financial Statements'!I17+'Financial Statements'!I10 -> 5919.6458 | D15: ='Financial Statements'!J17+'Financial Statements'!J10 -> 6572.6383 | E15: ='Financial Statements'!K17+'Financial Statements'!K10 -> 7018.7553 | F15: ='Financial Statements'!L17+'Financial Statements'!L10 -> 7450.4524 | G15: ='Financial Statements'!M17+'Financial Statements'!M10 -> 7856.2327 | J15: Buy after | K15: =K3*(1+G12) -> 86.229194 | S15: =S16-1 -> 6.4036826 | T15: =$S$14*($S15/$C$42)*(T$14/$C$45) -> 84.810947 | U15: =$S$14*($S15/$C$42)*(U$14/$C$45) -> 85.387278 | V15: =$S$14*($S15/$C$42)*(V$14/$C$45) -> 85.96361 | W15: =$S$14*($S15/$C$42)*(W$14/$C$45) -> 86.539941 | X15: =$S$14*($S15/$C$42)*(X$14/$C$45) -> 87.116273 | Z15: =IF(T15>$K$15,"Buy",IF(T15>=$K$16,"Hold","Sell")) -> Hold | AA15: =IF(U15>$K$15,"Buy",IF(U15>=$K$16,"Hold","Sell")) -> Hold | AB15: =IF(V15>$K$15,"Buy",IF(V15>=$K$16,"Hold","Sell")) -> Hold | AC15: =IF(W15>$K$15,"Buy",IF(W15>=$K$16,"Hold","Sell")) -> Buy | AD15: =IF(X15>$K$15,"Buy",IF(X15>=$K$16,"Hold","Sell")) -> Buy
B16: Tax Rate | C16: =C4 -> 0.225 | D16: =D4 -> 0.225 | E16: =E4 -> 0.225 | F16: =F4 -> 0.225 | G16: =G4 -> 0.225 | J16: Hold until | K16: =K3 -> 73.45 | S16: =S17-1 -> 7.4036826 | T16: =$S$14*($S16/$C$42)*(T$14/$C$45) -> 98.055037 | U16: =$S$14*($S16/$C$42)*(U$14/$C$45) -> 98.721368 | V16: =$S$14*($S16/$C$42)*(V$14/$C$45) -> 99.3877 | W16: =$S$14*($S16/$C$42)*(W$14/$C$45) -> 100.05403 | X16: =$S$14*($S16/$C$42)*(X$14/$C$45) -> 100.72036 | Z16: =IF(T16>$K$15,"Buy",IF(T16>=$K$16,"Hold","Sell")) -> Buy | AA16: =IF(U16>$K$15,"Buy",IF(U16>=$K$16,"Hold","Sell")) -> Buy | AB16: =IF(V16>$K$15,"Buy",IF(V16>=$K$16,"Hold","Sell")) -> Buy | AC16: =IF(W16>$K$15,"Buy",IF(W16>=$K$16,"Hold","Sell")) -> Buy | AD16: =IF(X16>$K$15,"Buy",IF(X16>=$K$16,"Hold","Sell")) -> Buy | AF16: Buy | AG16: =COUNTIF(Z15:AD19,"Buy") -> 22 | AH16: =AG16/$AG$19 -> 0.88
B17: NOPAT | C17: =C15*(1-C16) -> 4587.7255 | D17: =D15*(1-D16) -> 5093.7947 | E17: =E15*(1-E16) -> 5439.5354 | F17: =F15*(1-F16) -> 5774.1006 | G17: =G15*(1-G16) -> 6088.5803 | S17: =C42 -> 8.4036826 | T17: =$S$14*($S17/$C$42)*(T$14/$C$45) -> 111.29913 | U17: =$S$14*($S17/$C$42)*(U$14/$C$45) -> 112.05546 | V17: =$S$14*($S17/$C$42)*(V$14/$C$45) -> 112.81179 | W17: =$S$14*($S17/$C$42)*(W$14/$C$45) -> 113.56812 | X17: =$S$14*($S17/$C$42)*(X$14/$C$45) -> 114.32445 | Z17: =IF(T17>$K$15,"Buy",IF(T17>=$K$16,"Hold","Sell")) -> Buy | AA17: =IF(U17>$K$15,"Buy",IF(U17>=$K$16,"Hold","Sell")) -> Buy | AB17: =IF(V17>$K$15,"Buy",IF(V17>=$K$16,"Hold","Sell")) -> Buy | AC17: =IF(W17>$K$15,"Buy",IF(W17>=$K$16,"Hold","Sell")) -> Buy | AD17: =IF(X17>$K$15,"Buy",IF(X17>=$K$16,"Hold","Sell")) -> Buy | AF17: Sell | AG17: =COUNTIF(Z15:AD19,"Sell") -> 0 | AH17: =AG17/$AG$19 -> 0
