Workbook

Sheet Dashboard
D2: Rameda Pharmaceutical
I3: Recommendation | J3: =IF($C$10>=30%,"Buy",IF($C$10>=0,"Hold","Sell")) -> Buy
B5: Company overview | E5: methodologies | H5: Key Statisitics | K5: Market Data | N5: Shares Ownership | R5: Sensitivity Analysis in numbers "DCF model"
B6: Ticker | C6: RMDA | E6: DCF | H6: IPO | K6: Share price
B7: Stock exchange | C7: EGX30 | E7: Market EV/EBITDA | H7: Incorporated | K7: Share Outstanding
B8: Current price | E8: Market P/B | H8: Chairman | K8: Net Debt
B9: Target side | E9: Own Firm P/E | H9: Headquarters | K9: Enterprise value
B10: =IF(C10>0,"Upside","Downside") -> Upside | C10: =IFERROR(C9/C8-1,"") | E10: Own Firm EV/EBITDA | H10: Primary industry | K10: Equity value
E11: Own Firm P/E | H11: Sector
E12: Overall valuation | N12: Total | O12: =SUM(O6:O11) -> 0
B15: Key financials | N15: Scenario Switcher | O15: 0 | P15: 2
B16: Accounts | C16: 2020 | D16: 2021 | E16: =D16+1 -> 2022 | F16: =E16+1 -> 2023 | G16: =F16+1 -> 2024 | H16: =G16+1 -> 2025 | I16: =H16+1 -> 2026 | J16: =I16+1 -> 2027 | K16: =J16+1 -> 2028 | L16: =K16+1 -> 2029
B17: Revenue | C17: ='Financial Statements'!D4 -> 960.16935 | D17: ='Financial Statements'!E4 -> 1246.4346 | E17: ='Financial Statements'!F4 -> 1483.9514 | F17: ='Financial Statements'!G4 -> 1922.3507 | G17: ='Financial Statements'!H4 -> 2768.6884 | H17: ='Financial Statements'!I4 -> 4056.3218 | I17: ='Financial Statements'!J4 -> 4479.4008 | J17: ='Financial Statements'!K4 -> 5020.6274 | ... L17: ='Financial Statements'!M4 -> 6060.7561 | N17: Formating Notice "When navigating the excel"
B18: GR % | D18: =D17/C17-1 -> 0.29814041 | E18: =E17/D17-1 -> 0.19055696 | F18: =F17/E17-1 -> 0.29542698 | G18: =G17/F17-1 -> 0.44026186 | H18: =H17/G17-1 -> 0.46506982 | I18: =I17/H17-1 -> 0.10430112 | J18: =J17/I17-1 -> 0.12082569 | K18: =K17/J17-1 -> 0.083848841 | L18: =L17/K17-1 -> 0.11378175
B19: EBITDA | C19: ='Financial Statements'!D20 -> 238.10116 | D19: ='Financial Statements'!E20 -> 315.39041 | E19: ='Financial Statements'!F20 -> 397.91412 | F19: ='Financial Statements'!G20 -> 505.70628 | G19: ='Financial Statements'!H20 -> 771.24945 | H19: ='Financial Statements'!I20 -> 1084.681 | I19: ='Financial Statements'!J20 -> 1270.6522 | J19: ='Financial Statements'!K20 -> 1437.0117 | ... L19: ='Financial Statements'!M20 -> 1699.2453
B20: EBITDA Margin | C20: =IFERROR(C19/C$17,"") -> 0.2479783 | D20: =IFERROR(D19/D$17,"") -> 0.25303405 | E20: =IFERROR(E19/E$17,"") -> 0.26814497 | F20: =IFERROR(F19/F$17,"") -> 0.2630666 | G20: =IFERROR(G19/G$17,"") -> 0.2785613 | H20: =IFERROR(H19/H$17,"") -> 0.26740506 | I20: =IFERROR(I19/I$17,"") -> 0.28366566 | J20: =IFERROR(J19/J$17,"") -> 0.28622154 | ... L20: =IFERROR(L19/L$17,"") -> 0.28036853
B21: Net profit | C21: ='Financial Statements'!D38 -> 111.73066 | D21: ='Financial Statements'!E38 -> 180.28439 | E21: ='Financial Statements'!F38 -> 253.07219 | F21: ='Financial Statements'!G38 -> 253.38313 | G21: ='Financial Statements'!H38 -> 401.9611 | H21: ='Financial Statements'!I38 -> 561.23863 | I21: ='Financial Statements'!J38 -> 676.58576 | J21: ='Financial Statements'!K38 -> 915.88298 | ... L21: ='Financial Statements'!M38 -> 1158.4608
B22: Net profit Margin | C22: =IFERROR(C21/C$17,"") -> 0.11636557 | D22: =IFERROR(D21/D$17,"") -> 0.14464007 | E22: =IFERROR(E21/E$17,"") -> 0.17053941 | F22: =IFERROR(F21/F$17,"") -> 0.131809 | G22: =IFERROR(G21/G$17,"") -> 0.14518105 | H22: =IFERROR(H21/H$17,"") -> 0.13836146 | I22: =IFERROR(I21/I$17,"") -> 0.15104381 | J22: =IFERROR(J21/J$17,"") -> 0.18242401 | ... L22: =IFERROR(L21/L$17,"") -> 0.1911413 | N22: Links
B24: Toll manufacturing
B25: Export
B26: Priv Sales
B27: Tenders
B28: Overall sales
B29: RMDA Market share
B31: EPS
B32: EV/Sales
B33: EV/EBITDA
B34: P/B
B35: P/E
B36: Z-score

Sheet BS - Footnotes BD
B1: Balance sheet Breakdown | C1: 2020 | D1: 2021 | E1: 2022 | F1: 2023 | G1: 2024 | H1: =G1+1 -> 2025 | I1: =H1+1 -> 2026 | J1: =I1+1 -> 2027 | K1: =J1+1 -> 2028 | L1: =K1+1 -> 2029
B2: Assests Breakdown
B3: Non-Current Assets Breakdown
B4: Fixed Assets Breakdown
B5: Beginning Balance | C5: 2020 | D5: 2021 | E5: 2022 | F5: 2023 | G5: 2024 | H5: 2025 | I5: 2026 | J5: 2027 | K5: 2028 | L5: 2029
B6: Freehold Land | C6: 18.64 | D6: 18.64 | E6: 18.64 | F6: 18.64 | G6: 18.64 | H6: 18.64
B7: Buildings | C7: 227.84 | D7: 257.23 | E7: 273.34 | F7: 279.17 | G7: 288.43 | H7: 292.19
B8: Machinery & equipment | C8: 313.6 | D8: 397.71 | E8: 414.77 | F8: 444.86 | G8: 482.79 | H8: 502.23
B9: Transportation & dragging equipment | C9: 12.44 | D9: 13.06 | E9: 13.4 | F9: 16.34 | G9: 16.09 | H9: 18.26
B10: Laboratory equipment | C10: 17.13 | D10: 20.29 | E10: 28.26 | F10: 31.98 | G10: 35.19 | H10: 35.73
B11: Tools | C11: 3.75 | D11: 5.69 | E11: 6.02 | F11: 7.35 | G11: 11.57 | H11: 14.8
B12: Office furniture & fixtures | C12: 21.8 | D12: 25.39 | E12: 29.12 | F12: 33.11 | G12: 39.42 | H12: 46.76
B13: Assets under construction | C13: 66.33 | D13: 26.59 | E13: 27.04 | F13: 12.86 | G13: 38.09 | H13: 64.61
B14: Total Beginning Balance | C14: =SUM(C6:C13) -> 681.53 | D14: =SUM(D6:D13) -> 764.6 | E14: =SUM(E6:E13) -> 810.59 | F14: =SUM(F6:F13) -> 844.31 | G14: =SUM(G6:G13) -> 930.22 | H14: =SUM(H6:H13) -> 993.22 | I14: =SUM(I6:I13) -> 0 | J14: =SUM(J6:J13) -> 0 | ... L14: =SUM(L6:L13) -> 0
B15: Additions
B16: Freehold Land | C16: 0 | D16: 0 | E16: 0 | F16: 0 | G16: 0
B17: Buildings | C17: 6.99 | D17: 2.63 | E17: 5.27 | F17: 4.8 | G17: 3.76
B18: Machinery & equipment | C18: 8.43 | D18: 6.39 | E18: 9.94 | F18: 5.09 | G18: 19.48
B19: Transportation & dragging equipment | C19: 0.68 | D19: 0.34 | E19: 1.9 | F19: 0 | G19: 2.17
B20: Laboratory equipment | C20: 2.97 | D20: 3.45 | E20: 2.18 | F20: 3.2 | G20: 0.54
B21: Tools | C21: 1.29 | D21: 0.36 | E21: 1.33 | F21: 4.23 | G21: 3.28
B22: Office furniture & fixtures | C22: 4.57 | D22: 1.31 | E22: 4.15 | F22: 5.35 | G22: 9.19
B23: Assets under construction | C23: 60.04 | D23: 38.19 | E23: 9.61 | F23: 68.38 | G23: 26.52
B24: Total Additions | C24: =SUM(C16:C23) -> 84.97 | D24: =SUM(D16:D23) -> 52.67 | E24: =SUM(E16:E23) -> 34.38 | F24: =SUM(F16:F23) -> 91.05 | G24: =SUM(G16:G23) -> 64.94 | H24: =SUM(H16:H23) -> 0 | I24: =SUM(I16:I23) -> 0 | J24: =SUM(J16:J23) -> 0 | ... L24: =SUM(L16:L23) -> 0
B25: Transferred from Sales under Construction
B26: Freehold Land | C26: 0 | D26: 0 | E26: 0 | F26: 0 | G26: 0
B27: Buildings | C27: 22.4 | D27: 13.49 | E27: 0.56 | F27: 4.46 | G27: 2.575827
B28: Machinery & equipment | C28: 76.09 | D28: 13.64 | E28: 20.33 | F28: 37.27 | G28: 28.57
B29: Transportation & dragging equipment | C29: 0 | D29: 0 | E29: 1.04 | F29: 0 | G29: 0
B30: Laboratory equipment | C30: 0.53 | D30: 7.94 | E30: 1.81 | F30: 0 | G30: 0
B31: Tools | C31: 0.65 | D31: 0 | E31: 0 | F31: 0 | G31: 0
B32: Office furniture & fixtures | C32: 0.12 | D32: 2.67 | E32: 0.05 | F32: 1.41 | G32: 0
B33: Assets under construction | C33: -99.78 | D33: -37.74 | E33: -23.79 | F33: -43.14 | G33: -31.141189
B34: Total Construction | C34: =SUM(C26:C33) -> 0.01 | D34: =SUM(D26:D33) -> 0 | E34: =SUM(E26:E33) -> 0 | F34: =SUM(F26:F33) -> 0 | G34: =SUM(G26:G33) -> 0.004638 | H34: =SUM(H26:H33) -> 0 | I34: =SUM(I26:I33) -> 0 | J34: =SUM(J26:J33) -> 0 | ... L34: =SUM(L26:L33) -> 0
B35: Disposals
B36: Freehold Land | C36: 0 | D36: 0 | E36: 0 | F36: 0 | G36: 0
B37: Buildings | C37: 0 | D37: 0 | E37: 0 | F37: 0 | G37: 0
B38: Machinery & equipment | C38: -0.41 | D38: -2.97 | E38: -0.18 | F38: -4.43 | G38: -0.04
B39: Transportation & dragging equipment | C39: -0.07 | D39: 0 | E39: 0 | F39: -0.25 | G39: 0
B40: Laboratory equipment | C40: -0.34 | D40: -3.42 | E40: -0.27 | F40: 0 | G40: 0
B41: Tools | C41: 0 | D41: -0.02 | E41: -0.01 | F41: 0 | G41: -0.05
B42: Office furniture & fixtures | C42: -1.1 | D42: -0.24 | E42: -0.21 | F42: -0.45 | G42: -1.85
B43: Assets under construction | C43: 0 | D43: 0 | E43: 0 | F43: 0 | G43: 0
B44: Total Disposals | C44: =SUM(C36:C43) -> -1.92 | D44: =SUM(D36:D43) -> -6.65 | E44: =SUM(E36:E43) -> -0.67 | F44: =SUM(F36:F43) -> -5.13 | G44: =SUM(G36:G43) -> -1.94 | H44: =SUM(H36:H43) -> 0 | I44: =SUM(I36:I43) -> 0 | J44: =SUM(J36:J43) -> 0 | ... L44: =SUM(L36:L43) -> 0
B45: Ending Balance
B46: Freehold Land | C46: 18.64 | D46: 18.64 | E46: 18.64 | F46: 18.64 | G46: 18.64 | H46: 993
B47: Buildings | C47: 257.23 | D47: 273.34 | E47: 279.17 | F47: 288.43 | G47: 292.19 | H47: 0
B48: Machinery & equipment | C48: 397.71 | D48: 414.77 | E48: 444.86 | F48: 482.79 | G48: 502.23 | H48: 993
B49: Transportation & dragging equipment | C49: 13.06 | D49: 13.4 | E49: 16.34 | F49: 16.09 | G49: 18.26 | H49: 0
B50: Laboratory equipment | C50: 20.29 | D50: 28.26 | E50: 31.98 | F50: 35.19 | G50: 35.73 | H50: 993
B51: Tools | C51: 5.69 | D51: 6.02 | E51: 7.35 | F51: 11.57 | G51: 14.8 | H51: 0
B52: Office furniture & fixtures | C52: 25.39 | D52: 29.12 | E52: 33.11 | F52: 39.42 | G52: 46.76 | H52: 993
B53: Assets under construction | C53: 26.59 | D53: 27.04 | E53: 12.86 | F53: 38.09 | G53: 64.61 | H53: 0
B54: Total Ending Balance | C54: 764.59 | D54: 810.6 | E54: 844.3 | F54: 930.23 | G54: 993.21 | H54: 3973 | I54: 0 | J54: 0 | K54: 0 | L54: 0
B55: Beginning Accumlated Depreciation
B56: Freehold Land | C56: 0 | D56: 0 | E56: 0 | F56: 0 | G56: 0 | H56: 0
B57: Buildings | C57: -50.63 | D57: -57.85 | E57: -66.08 | F57: -74.89 | G57: -84.03 | H57: -93.62
B58: Machinery & equipment | C58: -113.6 | D58: -147.38 | E58: -163.14 | F58: -182.46 | G58: -198.8 | H58: -223.37
B59: Transportation & dragging equipment | C59: -9.58 | D59: -10.25 | E59: -10.89 | F59: -11.71 | G59: -12.3 | H59: -13.31
B60: Laboratory equipment | C60: -8.56 | D60: -9.97 | E60: -8.41 | F60: -11.03 | G60: -14.14 | H60: -17.43
B61: Tools | C61: -1.31 | D61: -1.73 | E61: -2.23 | F61: -2.82 | G61: -3.64 | H61: -4.74
B62: Office furniture & fixtures | C62: -14.36 | D62: -15.47 | E62: -17.87 | F62: -20.6 | G62: -23.61 | H62: -27.54
B63: Assets under construction | C63: 0 | D63: 0 | E63: 0 | F63: 0 | G63: 0 | H63: 0
B64: Total Beg.Accumlated Depreciation | C64: -198.04 | D64: -242.66 | E64: -268.62 | F64: -303.51 | G64: -336.54 | H64: -380.02 | I64: 0 | J64: 0 | K64: 0 | L64: 0
B65: Depreciation for the year
B66: Freehold Land | C66: 0 | D66: 0 | E66: 0 | F66: 0 | G66: 0 | H66: 0
B67: Buildings | C67: -7.22 | D67: -8.22 | E67: -8.81 | F67: -9.14 | G67: -9.59 | H67: 0
B68: Machinery & equipment | C68: -34.1 | D68: -18.07 | E68: -19.48 | F68: -20.76 | G68: -24.61 | H68: 0
B69: Transportation & dragging equipment | C69: -0.74 | D69: -0.64 | E69: -0.82 | F69: -0.84 | G69: -1.01 | H69: 0
B70: Laboratory equipment | C70: -1.66 | D70: -1.79 | E70: -2.8 | F70: -3.12 | G70: -3.29 | H70: 0
B71: Tools | C71: -0.42 | D71: -0.52 | E71: -0.59 | F71: -0.82 | G71: -1.13 | H71: 0
B72: Office furniture & fixtures | C72: -2.19 | D72: -2.64 | E72: -2.92 | F72: -3.43 | G72: -4.1 | H72: 0
B73: Assets under construction | C73: 0 | D73: 0 | E73: 0 | F73: 0 | G73: 0 | H73: 0
B74: Total Depreciation | C74: -46.33 | D74: -31.88 | E74: -35.41 | F74: -38.11 | G74: -43.72 | H74: 0 | I74: 0 | J74: 0 | K74: 0 | L74: 0
B75: Disposals for Depreciation | C75: TRUE | D75: TRUE | E75: TRUE | F75: TRUE | G75: TRUE
B76: Freehold Land | C76: 0 | D76: 0 | E76: 0 | F76: 0 | G76: 0
B77: Buildings | C77: 0 | D77: 0 | E77: 0 | F77: 0 | G77: 0
B78: Machinery & equipment | C78: 0.32 | D78: 2.31 | E78: 0.15 | F78: 4.41 | G78: 0.04
B79: Transportation & dragging equipment | C79: 0.07 | D79: 0 | E79: 0 | F79: 0.25 | G79: 0
B80: Laboratory equipment | C80: 0.25 | D80: 3.35 | E80: 0.18 | F80: 0 | G80: 0
B81: Tools | C81: 0 | D81: 0.02 | E81: 0 | F81: 0 | G81: 0.03
B82: Office furniture & fixtures | C82: 1.08 | D82: 0.23 | E82: 0.19 | F82: 0.42 | G82: 0.17
B83: Assets under construction | C83: 0 | D83: 0 | E83: 0 | F83: 0 | G83: 0
B84: Total Disposals | C84: 1.72 | D84: 5.92 | E84: 0.52 | F84: 5.08 | G84: 0.24 | H84: 0 | I84: 0 | J84: 0 | K84: 0 | L84: 0
B85: Ending Accumlated Deprciation
B86: Freehold Land | C86: 0 | D86: 0 | E86: 0 | F86: 0 | G86: 0
B87: Buildings | C87: -57.85 | D87: -66.08 | E87: -74.89 | F87: -84.03 | G87: -93.62
B88: Machinery & equipment | C88: -147.38 | D88: -163.14 | E88: -182.46 | F88: -198.8 | G88: -223.37
B89: Transportation & dragging equipment | C89: -10.25 | D89: -10.89 | E89: -11.71 | F89: -12.3 | G89: -13.31
B90: Laboratory equipment | C90: -9.97 | D90: -8.41 | E90: -11.03 | F90: -14.14 | G90: -17.43
B91: Tools | C91: -1.73 | D91: -2.23 | E91: -2.82 | F91: -3.64 | G91: -4.74
B92: Office furniture & fixtures | C92: -15.47 | D92: -17.87 | E92: -20.6 | F92: -23.61 | G92: -27.54
B93: Assets under construction | C93: 0 | D93: 0 | E93: 0 | F93: 0 | G93: 0
B94: Total ending Accumlated Dep. | C94: -242.66 | D94: -268.62 | E94: -303.51 | F94: -336.54 | G94: -380.02 | H94: 0 | I94: 0 | J94: 0 | K94: 0 | L94: 0
B95: Depreciation Rate
B96: Freehold Land | C96: 0 | D96: 0 | E96: 0 | F96: 0 | G96: 0 | H96: 0
B97: Buildings | C97: -0.03 | D97: -0.03 | E97: -0.03 | F97: -0.03 | G97: -0.03 | H97: #DIV/0!
B98: Machinery & equipment | C98: -0.09 | D98: -0.04 | E98: -0.04 | F98: -0.04 | G98: -0.05 | H98: 0
B99: Transportation & dragging equipment | C99: -0.06 | D99: -0.05 | E99: -0.05 | F99: -0.05 | G99: -0.06 | H99: 0
B100: Laboratory equipment | C100: -0.08 | D100: -0.06 | E100: -0.09 | F100: -0.09 | G100: -0.09 | H100: 0
...

Sheet Financial Statements
B2: Income Statement
B3: For 2020-2024 | D3: 2020 | E3: 2021 | F3: 2022 | G3: 2023 | H3: 2024 | I3: =H3+1 -> 2025 | J3: =I3+1 -> 2026 | K3: =J3+1 -> 2027 | L3: =K3+1 -> 2028 | M3: =L3+1 -> 2029
B4: Revenues | D4: 960.16935 | E4: 1246.4346 | F4: 1483.9514 | G4: 1922.3507 | H4: 2768.6884 | I4: ='IS- Breakdown'!H14 -> 4056.3218 | J4: ='IS- Breakdown'!I14 -> 4479.4008 | K4: ='IS- Breakdown'!J14 -> 5020.6274 | L4: ='IS- Breakdown'!K14 -> 5441.6012 | M4: ='IS- Breakdown'!L14 -> 6060.7561 | N4: =_xlfn.RRI(4,I4,M4) -> 0.10560145
B5: COGS | D5: =-'IS- Breakdown'!C95+'IS- Breakdown'!C90 -> -463.40793 | E5: =-'IS- Breakdown'!D95+'IS- Breakdown'!D90 -> -629.13266 | F5: =-'IS- Breakdown'!E95+'IS- Breakdown'!E90 -> -705.33224 | G5: =-'IS- Breakdown'!F95+'IS- Breakdown'!F90 -> -950.67706 | H5: =-'IS- Breakdown'!G95+'IS- Breakdown'!G90 -> -1409.1501 | I5: =-'IS- Breakdown'!H95 -> -1992.7111 | J5: =-'IS- Breakdown'!I97 -> -2160.5735 | K5: =-'IS- Breakdown'!J97 -> -2420.6717 | L5: =-'IS- Breakdown'!K97 -> -2656.4711 | M5: =-'IS- Breakdown'!L97 -> -2982.111 | N5: =_xlfn.RRI(4,I5,M5) -> 0.10603753
B6: Gross Profit | D6: =D5+D4 -> 496.76142 | E6: =E5+E4 -> 617.30197 | F6: =F4+F5 -> 778.61919 | G6: =G4+G5 -> 971.67366 | H6: =H4+H5 -> 1359.5383 | I6: =I4+I5 -> 2063.6107 | J6: =J4+J5 -> 2318.8272 | K6: =K4+K5 -> 2599.9558 | L6: =L4+L5 -> 2785.1301 | M6: =M4+M5 -> 3078.6451
B7: Gross profit margin | D7: =D6/D4 -> 0.51736855 | E7: =E6/E4 -> 0.49525419 | F7: =F6/F4 -> 0.52469318 | G7: =G6/G4 -> 0.50546118 | H7: =H6/H4 -> 0.49104056 | I7: =I6/I4 -> 0.50873939 | J7: =J6/J4 -> 0.5176646 | K7: =K6/K4 -> 0.51785475 | ... M7: =M6/M4 -> 0.50796386
B8: Mark-up | D8: =ABS(D6/D5) -> 1.0719744 | E8: =ABS(E6/E5) -> 0.98119525 | F8: =ABS(F6/F5) -> 1.1039042 | G8: =ABS(G6/G5) -> 1.022086 | H8: =ABS(H6/H5) -> 0.96479309 | I8: =ABS(I6/I5) -> 1.0355794 | J8: =ABS(J6/J5) -> 1.0732461 | K8: =ABS(K6/K5) -> 1.0740638 | ... M8: =ABS(M6/M5) -> 1.0323711
B10: Selling and marketing expenses | D10: =-214.204258+4.19716 -> -210.0071 | E10: =-251.984883+4.497393 -> -247.48749 | F10: =-296.417891+4.901259 -> -291.51663 | G10: =-363.580501+5.122198 -> -358.4583 | H10: =-447.876799+5.314134 -> -442.56266 | I10: =-'IS- Breakdown'!H146 -> -762.03851 | J10: =-'IS- Breakdown'!I146 -> -819.15825 | K10: =-'IS- Breakdown'!J146 -> -905.47461 | L10: =-'IS- Breakdown'!K146 -> -966.61041 | M10: =-'IS- Breakdown'!L146 -> -1069.2244
B11: S&M Margin | D11: =-D10/D4 -> 0.21871881 | E11: =-E10/E4 -> 0.19855633 | F11: =-F10/F4 -> 0.19644621 | G11: =-G10/G4 -> 0.18646873 | H11: =-H10/H4 -> 0.1598456 | I11: =-I10/I4 -> 0.18786441 | J11: =-J10/J4 -> 0.18287228 | K11: =-K10/K4 -> 0.18035089 | ... M11: =-M10/M4 -> 0.17641766
B12: General and administrative expenses | D12: =-44.735538+1.829115 -> -42.906423 | E12: =-51.901349+1.907312 -> -49.994037 | F12: =-65.91287+2.006816 -> -63.906054 | G12: =-82.330195+2.003262 -> -80.326933 | H12: =-112.423776+2.244169 -> -110.17961 | I12: =-'IS- Breakdown'!H155 -> -170.22874 | J12: =-'IS- Breakdown'!I155 -> -187.92168 | K12: =-'IS- Breakdown'!J155 -> -210.64427 | L12: =-'IS- Breakdown'!K155 -> -228.10969 | M12: =-'IS- Breakdown'!L155 -> -254.03951
B13: Impairment of trade and notes receivable | D13: -1.802092 | E13: -0.1056 | F13: -3.643441 | G13: -3.808579 | H13: -11.442943 | I13: ='BS-Breakdown'!H176-'BS-Breakdown'!G176 -> -9.3790789 | J13: ='BS-Breakdown'!I176-'BS-Breakdown'!H176 -> -3.7057049 | K13: ='BS-Breakdown'!J176-'BS-Breakdown'!I176 -> -4.7405492 | L13: ='BS-Breakdown'!K176-'BS-Breakdown'!J176 -> -3.6872664 | M13: ='BS-Breakdown'!L176-'BS-Breakdown'!K176 -> -5.4231146
B14: Provisions | D14: -1.6 | E14: -1.25 | F14: 0 | G14: -0.673282 | H14: -0.5 | I14: ='BS-Breakdown'!G259-'BS-Breakdown'!H259 -> -4.4405911 | J14: ='BS-Breakdown'!H259-'BS-Breakdown'!I259 -> -1.1211002 | K14: ='BS-Breakdown'!I259-'BS-Breakdown'!J259 -> -1.4341753 | L14: ='BS-Breakdown'!J259-'BS-Breakdown'!K259 -> -1.1155219 | M14: ='BS-Breakdown'!K259-'BS-Breakdown'!L259 -> -1.6406743
B15: Share based payment expenses | D15: 0 | E15: 0 | F15: -17.84792 | G15: -17.768011 | H15: -16.286564 | I15: =I16*I$4 -> -22.027905 | J15: =J16*J$4 -> -24.325441 | K15: =K16*K$4 -> -27.264579 | L15: =L16*L$4 -> -29.550682 | M15: =M16*M$4 -> -32.91301
B16: % of sales | D16: =D15/D$4 -> 0 | E16: =E15/E$4 -> 0 | F16: =F15/F$4 -> -0.012027294 | G16: =G15/G$4 -> -0.0092428561 | H16: =H15/H$4 -> -0.0058824113 | I16: =AVERAGE(D16:H16) -> -0.0054305123 | J16: =I16 -> -0.0054305123 | K16: =J16 -> -0.0054305123 | L16: =K16 -> -0.0054305123 | M16: =L16 -> -0.0054305123
B17: Contribution for health insurance | D17: -2.56337 | E17: -3.272995 | F17: -3.975441 | G17: -5.109505 | H17: -7.471037 | I17: =I18*I$4 -> -10.814882 | J17: =J18*J$4 -> -11.942886 | K17: =K18*K$4 -> -13.385894 | L17: =L18*L$4 -> -14.508286 | M17: =M18*M$4 -> -16.159064
B18: % of sales | D18: =D17/D$4 -> -0.0026697061 | E18: =E17/E$4 -> -0.0026258858 | F18: =F17/F$4 -> -0.0026789563 | G18: =G17/G$4 -> -0.0026579463 | H18: =H17/H$4 -> -0.0026984029 | I18: =AVERAGE(D18:H18) -> -0.0026661795 | J18: =I18 -> -0.0026661795 | K18: =J18 -> -0.0026661795 | L18: =K18 -> -0.0026661795 | M18: =L18 -> -0.0026661795
B20: EBITDA | D20: =D6+SUM(D10:D17) -> 238.10116 | E20: =E6+SUM(E10:E17) -> 315.39041 | F20: =F6+SUM(F10:F17) -> 397.91412 | G20: =G6+SUM(G10:G17) -> 505.70628 | H20: =H6+SUM(H10:H17) -> 771.24945 | I20: =+I6+I10+I12+I13+I14+I15+I17 -> 1084.681 | J20: =+J6+J10+J12+J13+J14+J15+J17 -> 1270.6522 | K20: =+K6+K10+K12+K13+K14+K15+K17 -> 1437.0117 | L20: =+L6+L10+L12+L13+L14+L15+L17 -> 1541.5482 | M20: =+M6+M10+M12+M13+M14+M15+M17 -> 1699.2453
B21: EBITDA Margin | D21: =D20/D4 -> 0.2479783 | E21: =E20/E4 -> 0.25303405 | F21: =F20/F4 -> 0.26814497 | G21: =G20/G4 -> 0.2630666 | H21: =H20/H4 -> 0.2785613 | I21: =I20/I4 -> 0.26740506 | J21: =J20/J4 -> 0.28366566 | K21: =K20/K4 -> 0.28622154 | ... M21: =M20/M4 -> 0.28036853
B23: Depreciation | D23: -46.330194 | E23: -31.877452 | F23: -35.413949 | G23: -38.110835 | H23: -43.718707 | I23: ='BS-Breakdown'!H83 -> -45.612299 | J23: ='BS-Breakdown'!I83 -> -46.485168 | K23: ='BS-Breakdown'!J83 -> -48.989582 | L23: ='BS-Breakdown'!K83 -> -52.042177 | M23: ='BS-Breakdown'!L83 -> -55.00255
B24: Amortization | D24: =D25-D23 -> -9.871612 | E24: =E25-E23 -> -14.304121 | F24: =F25-F23 -> -30.070417 | G24: =G25-G23 -> -34.773153 | H24: =H25-H23 -> -39.713887 | I24: ='BS-Breakdown'!H131+'BS-Breakdown'!H144 -> -46.106065 | J24: ='BS-Breakdown'!I131+'BS-Breakdown'!I144 -> -53.643418 | K24: ='BS-Breakdown'!J131+'BS-Breakdown'!J144 -> -58.497262 | L24: ='BS-Breakdown'!K131+'BS-Breakdown'!K144 -> -68.977208 | M24: ='BS-Breakdown'!L131+'BS-Breakdown'!L144 -> -68.977208
B25: Depreciation and amortization Total | D25: -56.201806 | E25: -46.181573 | F25: -65.484366 | G25: -72.883988 | H25: -83.432594 | I25: =SUM(I23:I24) -> -91.718364 | J25: =SUM(J23:J24) -> -100.12859 | K25: =SUM(K23:K24) -> -107.48684 | L25: =SUM(L23:L24) -> -121.01938 | M25: =SUM(M23:M24) -> -123.97976
B26: EBIT | D26: =D20+SUM(D23:D24) -> 181.89935 | E26: =E20+SUM(E23:E24) -> 269.20883 | F26: =F20+SUM(F23:F24) -> 332.42975 | G26: =G20+SUM(G23:G24) -> 432.82229 | H26: =H20+SUM(H23:H24) -> 687.81686 | I26: =+I20+I25 -> 992.96263 | J26: =+J20+J25 -> 1170.5236 | K26: =+K20+K25 -> 1329.5248 | L26: =+L20+L25 -> 1420.5288 | M26: =+M20+M25 -> 1575.2655
B27: EBIT Margin | D27: =D26/D4 -> 0.18944507 | E27: =E26/E4 -> 0.21598311 | F27: =F26/F4 -> 0.2240166 | G27: =G26/G4 -> 0.22515261 | H27: =H26/H4 -> 0.24842696 | I27: =I26/I4 -> 0.24479385 | J27: =J26/J4 -> 0.26131254 | K27: =K26/K4 -> 0.26481249 | ... M27: =M26/M4 -> 0.25991238
B29: Finance income | D29: 64.160293 | E29: 59.973 | F29: 56.732176 | G29: 62.902521 | H29: 65.852148 | I29: ='IS- Breakdown'!H166 -> 45.747704 | J29: ='IS- Breakdown'!I166 -> 15.428505 | K29: ='IS- Breakdown'!J166 -> 6.8757761 | L29: ='IS- Breakdown'!K166 -> 11.654233 | M29: ='IS- Breakdown'!L166 -> 15.598651
B30: Finance expenses | D30: -100.05893 | E30: -94.817656 | F30: -92.084277 | G30: -194.25931 | H30: -310.94187 | I30: =-'IS- Breakdown'!H172 -> -329.80701 | J30: =-'IS- Breakdown'!H172 -> -329.80701 | K30: =-'IS- Breakdown'!I172 -> -173.52313 | L30: =-'IS- Breakdown'!J172 -> -118.47001 | M30: =-'IS- Breakdown'!K172 -> -118.9
B31: Net foregin exchange gain | D31: -1.695406 | E31: -0.596919 | F31: 25.651093 | G31: 18.683006 | H31: 56.240536 | I31: 0 | J31: 0 | K31: 0 | L31: 0 | M31: 0
B32: Other income | D32: 1.019971 | E32: 0.041606 | F32: 5.90985 | G32: 7.476152 | H32: 27.305011 | I32: =I33*I4 -> 15.275551 | J32: =J33*J4 -> 16.868808 | K32: =K33*K4 -> 18.906993 | L32: =L33*L4 -> 20.492323 | M32: =M33*M4 -> 22.823975
B33: % of sales | D33: =D32/D$4 -> 0.0010622824 | E33: =E32/E$4 -> 3.338001e-05 | F33: =F32/F$4 -> 0.0039825091 | G33: =G32/G$4 -> 0.0038890676 | H33: =H32/H$4 -> 0.0098620743 | I33: =AVERAGE(D33:H33) -> 0.0037658627 | J33: =I33 -> 0.0037658627 | K33: =J33 -> 0.0037658627 | L33: =K33 -> 0.0037658627 | M33: =L33 -> 0.0037658627
B34: EBT | D34: =D26+SUM(D29:D32) -> 145.32528 | E34: =E26+SUM(E29:E32) -> 233.80886 | F34: =F26+SUM(F29:F32) -> 328.63859 | G34: =G26+SUM(G29:G32) -> 327.62466 | H34: =H26+SUM(H29:H32) -> 526.27269 | I34: =+I32+I31+I30+I29+I26 -> 724.17888 | J34: =+J32+J31+J30+J29+J26 -> 873.01388 | K34: =+K32+K31+K30+K29+K26 -> 1181.7845 | L34: =+L32+L31+L30+L29+L26 -> 1334.2054 | M34: =+M32+M31+M30+M29+M26 -> 1494.7882
B35: EBT Margin | D35: =D34/D4 -> 0.1513538 | E35: =E34/E4 -> 0.18758213 | F35: =F34/F4 -> 0.22146183 | G35: =G34/G4 -> 0.17042918 | H35: =H34/H4 -> 0.19008014 | I35: =I34/I4 -> 0.17853092 | J35: =J34/J4 -> 0.19489524 | K35: =K34/K4 -> 0.23538582 | ... M35: =M34/M4 -> 0.24663394
B37: Income Taxes | D37: -33.594619 | E37: -53.524475 | F37: -75.5664 | G37: -74.241526 | H37: -124.31159 | I37: =I34*-22.5% -> -162.94025 | J37: =J34*-22.5% -> -196.42812 | K37: =K34*-22.5% -> -265.90151 | L37: =L34*-22.5% -> -300.19621 | M37: =M34*-22.5% -> -336.32734
B38: Net Profit | D38: =D34+D37 -> 111.73066 | E38: =E34+E37 -> 180.28439 | F38: =F34+F37 -> 253.07219 | G38: =G34+G37 -> 253.38313 | H38: =H34+H37 -> 401.9611 | I38: =I34+I37 -> 561.23863 | J38: =J34+J37 -> 676.58576 | K38: =K34+K37 -> 915.88298 | ... M38: =M34+M37 -> 1158.4608
B39: Net Profit Margin | D39: =D38/D4 -> 0.11636557 | E39: =E38/E4 -> 0.14464007 | F39: =F38/F4 -> 0.17053941 | G39: =G38/G4 -> 0.131809 | H39: =H38/H4 -> 0.14518105 | I39: =I38/I4 -> 0.13836146 | J39: =J38/J4 -> 0.15104381 | K39: =K38/K4 -> 0.18242401 | ... M39: =M38/M4 -> 0.1911413
G40: 244.85945 | H40: 387.36687 | I40: =I38-I41 -> 546.79837 | J40: =J38-J41 -> 662.1455 | K40: =K38-K41 -> 901.44272 | L40: =L38-L41 -> 1019.5689 | M40: =M38-M41 -> 1144.0206
G41: 8.34646 | H41: 14.440262 | I41: =H41 -> 14.440262 | J41: =I41 -> 14.440262 | K41: =J41 -> 14.440262 | L41: =K41 -> 14.440262 | M41: =L41 -> 14.440262
G42: =G40+G41 -> 253.20591 | H42: =H40+H41 -> 401.80713 | I42: =I40+I41 -> 561.23863 | J42: =J40+J41 -> 676.58576 | K42: =K40+K41 -> 915.88298 | L42: =L40+L41 -> 1034.0092 | M42: =M40+M41 -> 1158.4608
B43: Checker | G43: =G42-G38 -> -0.17722488 | H43: =H42-H38 -> -0.15396319
B45: Balancesheet Statement
B46: For 2020-2024 | D46: 2020 | E46: 2021 | F46: 2022 | G46: 2023 | H46: 2024 | I46: =H46+1 -> 2025 | J46: =I46+1 -> 2026 | K46: =J46+1 -> 2027 | L46: =K46+1 -> 2028 | M46: =L46+1 -> 2029
B47: Assets
B48: Non-current assets | N48: Historic | O48: Fcsted
B49: Fixed assets and projects under construction | D49: ='BS-Breakdown'!C123 -> 521.90128 | E49: ='BS-Breakdown'!D123 -> 541.95483 | F49: ='BS-Breakdown'!E123 -> 540.76532 | G49: ='BS-Breakdown'!F123 -> 593.65777 | H49: ='BS-Breakdown'!G123 -> 613.15816 | I49: ='BS-Breakdown'!H123 -> 620.79879 | J49: ='BS-Breakdown'!I123 -> 646.72624 | K49: ='BS-Breakdown'!J123 -> 702.07017 | ... M49: ='BS-Breakdown'!L123 -> 990.22206 | N49: =H49/D49-1 -> 0.17485467 | O49: =M49/I49-1 -> 0.5950773
B50: Right of use assets | D50: ='BS-Breakdown'!C137 -> 16.258305 | E50: ='BS-Breakdown'!D137 -> 13.032359 | F50: ='BS-Breakdown'!E137 -> 16.21556 | G50: ='BS-Breakdown'!F137 -> 12.391296 | H50: ='BS-Breakdown'!G137 -> 8.357448 | I50: ='BS-Breakdown'!H137 -> 4.3236 | J50: ='BS-Breakdown'!I137 -> 0.289752 | K50: ='BS-Breakdown'!J137 -> 0.289752 | ... M50: ='BS-Breakdown'!L137 -> 0.289752 | N50: =H50/D50-1 -> -0.48595822 | O50: =M50/I50-1 -> -0.93298362
B51: Intangible assets | D51: ='BS-Breakdown'!C146 -> 214.57137 | E51: ='BS-Breakdown'!D146 -> 389.66329 | F51: ='BS-Breakdown'!E146 -> 457.56762 | G51: ='BS-Breakdown'!F146 -> 589.27153 | H51: ='BS-Breakdown'!G146 -> 552.78501 | I51: ='BS-Breakdown'!H146 -> 635.44308 | J51: ='BS-Breakdown'!I146 -> 729.94698 | K51: ='BS-Breakdown'!J146 -> 841.3815 | ... M51: ='BS-Breakdown'!L146 -> 903.80263 | N51: =H51/D51-1 -> 1.5762291 | O51: =M51/I51-1 -> 0.42231878
B52: Total N.C.A | D52: =SUM(D49:D51) -> 752.73096 | E52: =SUM(E49:E51) -> 944.65048 | F52: =SUM(F49:F51) -> 1014.5485 | G52: =SUM(G49:G51) -> 1195.3206 | H52: =SUM(H49:H51) -> 1174.3006 | I52: =SUM(I49:I51) -> 1260.5655 | J52: =SUM(J49:J51) -> 1376.963 | K52: =SUM(K49:K51) -> 1543.7414 | ... M52: =SUM(M49:M51) -> 1894.3144 | N52: =H52/D52-1 -> 0.56005356 | O52: =M52/I52-1 -> 0.50274975
B54: Current assets
B55: Inventories | D55: ='BS-Breakdown'!C166 -> 305.47956 | E55: ='BS-Breakdown'!D166 -> 259.39834 | F55: ='BS-Breakdown'!E166 -> 348.41061 | G55: ='BS-Breakdown'!F166 -> 303.2605 | H55: ='BS-Breakdown'!G166 -> 751.33779 | I55: ='BS-Breakdown'!H166 -> 846.05376 | J55: ='BS-Breakdown'!I166 -> 924.5079 | K55: ='BS-Breakdown'!J166 -> 1005.0412 | ... M55: ='BS-Breakdown'!L166 -> 1275.061
B56: Trade and notes recieveable | D56: ='BS-Breakdown'!C177 -> 633.52225 | E56: ='BS-Breakdown'!D177 -> 659.40359 | F56: ='BS-Breakdown'!E177 -> 900.68683 | G56: ='BS-Breakdown'!F177 -> 1271.7423 | H56: ='BS-Breakdown'!G177 -> 1478.9144 | I56: ='BS-Breakdown'!H177 -> 2009.3521 | J56: ='BS-Breakdown'!I177 -> 2218.9298 | K56: ='BS-Breakdown'!J177 -> 2487.0335 | ... M56: ='BS-Breakdown'!L177 -> 3002.2749
B57: Treasury bills | D57: ='BS-Breakdown'!C185 -> 469.34955 | E57: ='BS-Breakdown'!D185 -> 468.01095 | F57: ='BS-Breakdown'!E185 -> 361.8622 | G57: ='BS-Breakdown'!F185 -> 260.89542 | H57: ='BS-Breakdown'!G185 -> 189.7037 | I57: ='BS-Breakdown'!H185 -> 209.59553 | J57: ='BS-Breakdown'!I185 -> 70.606499 | K57: ='BS-Breakdown'!J185 -> 89.603848 | ... M57: ='BS-Breakdown'!L185 -> 198.41539
B58: Due from related parties | D58: ='BS-Breakdown'!C190 -> 0.0255 | E58: ='BS-Breakdown'!D190 -> 0.0255 | F58: ='BS-Breakdown'!E190 -> 0.0255 | G58: ='BS-Breakdown'!F190 -> 0.0255 | H58: ='BS-Breakdown'!G190 -> 0.0255 | I58: ='BS-Breakdown'!H190 -> 0.0255 | J58: ='BS-Breakdown'!I190 -> 0.0255 | K58: ='BS-Breakdown'!J190 -> 0.0255 | ... M58: ='BS-Breakdown'!L190 -> 0.0255
B59: Prepayments and other receivables | D59: ='BS-Breakdown'!C203 -> 74.974518 | E59: ='BS-Breakdown'!D203 -> 74.809972 | F59: ='BS-Breakdown'!E203 -> 80.541679 | G59: ='BS-Breakdown'!F203 -> 134.66945 | H59: ='BS-Breakdown'!G203 -> 558.50657 | I59: ='BS-Breakdown'!H203 -> 551.20749 | J59: ='BS-Breakdown'!I203 -> 608.69905 | K59: ='BS-Breakdown'!J203 -> 682.24553 | ... M59: ='BS-Breakdown'!L203 -> 823.58706
B60: Cash on hand and at banks | D60: =D152 -> 13.232834 | E60: =E152 -> 14.001699 | F60: =F152 -> 66.956028 | G60: =G152 -> 52.358275 | H60: =H152 -> 64.688059 | I60: =I152 -> 20 | J60: =J152 -> 40 | K60: =K152 -> 80 | ... M60: =M152 -> 320
B61: Other assets | H61: 93.839078 | I61: 0 | J61: 0 | K61: 0 | L61: 0 | M61: 0
B62: total C.A | D62: =SUM(D55:D61) -> 1496.5842 | E62: =SUM(E55:E61) -> 1475.6501 | F62: =SUM(F55:F61) -> 1758.4829 | G62: =SUM(G55:G61) -> 2022.9514 | H62: =SUM(H55:H61) -> 3137.0151 | I62: =SUM(I55:I61) -> 3636.2344 | J62: =SUM(J55:J61) -> 3862.7688 | K62: =SUM(K55:K61) -> 4343.9496 | ... M62: =SUM(M55:M61) -> 5619.3639 | N62: =H62/D62-1 -> 1.0961167 | O62: =M62/I62-1 -> 0.54537999
B63: Total Assets | D63: =D52+D62 -> 2249.3152 | E63: =E52+E62 -> 2420.3005 | F63: =F52+F62 -> 2773.0314 | G63: =G52+G62 -> 3218.272 | H63: =H52+H62 -> 4311.3158 | I63: =I52+I62 -> 4896.7999 | J63: =J52+J62 -> 5239.7317 | K63: =K52+K62 -> 5887.691 | ... M63: =M52+M62 -> 7513.6783 | N63: =H63/D63-1 -> 0.91672373 | O63: =M63/I63-1 -> 0.53440584
B65: Liabilities & Equity
B66: Equity
B67: Paid up capital | D67: ='BS-Breakdown'!C306 -> 192.15 | E67: ='BS-Breakdown'!D306 -> 250 | F67: ='BS-Breakdown'!E306 -> 250 | G67: ='BS-Breakdown'!F306 -> 375 | H67: ='BS-Breakdown'!G306 -> 378.23373 | I67: ='BS-Breakdown'!H306 -> 378.23373 | J67: ='BS-Breakdown'!I306 -> 378.23373 | K67: ='BS-Breakdown'!J306 -> 378.23373 | ... M67: ='BS-Breakdown'!L306 -> 378.23373
B68: Paid under capital increase | D68: 0 | E68: 0 | F68: 0.160606 | G68: 0 | H68: =G68 -> 0 | I68: =H68 -> 0 | J68: =I68 -> 0 | K68: =J68 -> 0 | L68: =K68 -> 0 | M68: =L68 -> 0
B69: Legal reserve | D69: ='BS-Breakdown'!C312 -> 20.798851 | E69: ='BS-Breakdown'!D312 -> 26.446118 | F69: ='BS-Breakdown'!E312 -> 125 | G69: ='BS-Breakdown'!F312 -> 125 | H69: ='BS-Breakdown'!G312 -> 189.11687 | I69: ='BS-Breakdown'!H312 -> 189.11687 | J69: ='BS-Breakdown'!I312 -> 189.11687 | K69: ='BS-Breakdown'!J312 -> 189.11687 | ... M69: ='BS-Breakdown'!L312 -> 189.11687
B70: General reserves - Insurance premium | D70: 486.965 | E70: 486.965 | F70: 397.52139 | G70: 377.69973 | H70: 327.50994 | I70: =H70 -> 327.50994 | J70: =I70 -> 327.50994 | K70: =J70 -> 327.50994 | L70: =K70 -> 327.50994 | M70: =L70 -> 327.50994
B71: Treasury shares | D71: 0 | E71: 0 | F71: -65.926198 | G71: -26.231267 | H71: -26.231267 | I71: =H71 -> -26.231267 | J71: =I71 -> -26.231267 | K71: =J71 -> -26.231267 | L71: =K71 -> -26.231267 | M71: =L71 -> -26.231267
B72: Share based payments reserve | D72: 0 | E72: 0 | F72: 14.873267 | G72: 13.927085 | H72: 13.029251 | I72: =H72 -> 13.029251 | J72: =I72 -> 13.029251 | K72: =J72 -> 13.029251 | L72: =K72 -> 13.029251 | M72: =L72 -> 13.029251
B73: Other reserves | D73: 0.278952 | E73: 0.278952 | F73: 0.278952 | G73: 0.278952 | H73: 0.278952 | I73: =H73 -> 0.278952 | J73: =I73 -> 0.278952 | K73: =J73 -> 0.278952 | L73: =K73 -> 0.278952 | M73: =L73 -> 0.278952
B74: Profits for the year and retained earning | D74: ='BS-Breakdown'!C320 -> 484.99595 | E74: ='BS-Breakdown'!D320 -> 584.4203 | F74: ='BS-Breakdown'!E320 -> 796.67861 | G74: ='BS-Breakdown'!F320 -> 896.88824 | H74: ='BS-Breakdown'!G320 -> 1162.3301 | I74: ='BS-Breakdown'!H320 -> 1538.8905 | J74: ='BS-Breakdown'!I320 -> 1995.8104 | K74: ='BS-Breakdown'!J320 -> 2619.4426 | ... M74: ='BS-Breakdown'!L320 -> 4118.0002
B75: Total equity of parent Company | D75: =SUM(D67:D74) -> 1185.1888 | E75: =SUM(E67:E74) -> 1348.1104 | F75: =SUM(F67:F74) -> 1518.5866 | G75: =SUM(G67:G74) -> 1762.5627 | H75: =SUM(H67:H74) -> 2044.2676 | I75: =SUM(I67:I74) -> 2420.828 | J75: =SUM(J67:J74) -> 2877.7479 | K75: =SUM(K67:K74) -> 3501.38 | ... M75: =SUM(M67:M74) -> 4999.9377 | N75: =H75/D75-1 -> 0.72484559 | O75: =M75/I75-1 -> 1.0653833
B76: Non-controlling interest | D76: -1.618706 | E76: -2.621626 | F76: 4.590062 | G76: 12.936522 | H76: 27.376784 | I76: =H76 -> 27.376784 | J76: =I76 -> 27.376784 | K76: =J76 -> 27.376784 | L76: =K76 -> 27.376784 | M76: =L76 -> 27.376784
B77: Total equity | D77: =D75+D76 -> 1183.57 | E77: =E75+E76 -> 1345.4887 | F77: =F75+F76 -> 1523.1767 | G77: =G75+G76 -> 1775.4993 | H77: =H75+H76 -> 2071.6444 | I77: =I75+I76 -> 2448.2048 | J77: =J75+J76 -> 2905.1247 | K77: =K75+K76 -> 3528.7568 | ... M77: =M75+M76 -> 5027.3145 | N77: =H77/D77-1 -> 0.75033525 | O77: =M77/I77-1 -> 1.0534697
B79: Liabilities
B80: Non-current liabilities
B81: Long term loans | D81: ='BS-Breakdown'!C242 -> 29.549676 | E81: ='BS-Breakdown'!D242 -> 0 | F81: ='BS-Breakdown'!E242 -> 0 | G81: ='BS-Breakdown'!F242 -> 0 | H81: ='BS-Breakdown'!G242 -> 0 | I81: ='BS-Breakdown'!H242 -> 0 | J81: ='BS-Breakdown'!I242 -> 0 | K81: ='BS-Breakdown'!J242 -> 0 | ... M81: ='BS-Breakdown'!L242 -> 0
B82: Long term lease liabilities | D82: ='BS-Breakdown'!C229 -> 14.807299 | E82: ='BS-Breakdown'!D229 -> 12.25616 | F82: ='BS-Breakdown'!E229 -> 16.343678 | G82: ='BS-Breakdown'!F229 -> 11.699588 | H82: ='BS-Breakdown'!G229 -> 7.189831 | I82: ='BS-Breakdown'!H229 -> 7.7828393 | J82: ='BS-Breakdown'!I229 -> 3.8914197 | K82: ='BS-Breakdown'!J229 -> 0 | ... M82: ='BS-Breakdown'!L229 -> 0
B83: Deferred tax liabilities | D83: ='BS-Breakdown'!C254 -> 31.061481 | E83: ='BS-Breakdown'!D254 -> 40.498236 | F83: ='BS-Breakdown'!E254 -> 51.555823 | G83: ='BS-Breakdown'!F254 -> 58.234398 | H83: ='BS-Breakdown'!G254 -> 77.282486 | I83: ='BS-Breakdown'!H254 -> 77.282486 | J83: ='BS-Breakdown'!I254 -> 77.282486 | K83: ='BS-Breakdown'!J254 -> 77.282486 | ... M83: ='BS-Breakdown'!L254 -> 77.282486
B84: Total N.C.L | D84: =SUM(D81:D83) -> 75.418456 | E84: =SUM(E81:E83) -> 52.754396 | F84: =SUM(F81:F83) -> 67.899501 | G84: =SUM(G81:G83) -> 69.933986 | H84: =SUM(H81:H83) -> 84.472317 | I84: =I81+I82+I83 -> 85.065325 | J84: =J81+J82+J83 -> 81.173906 | K84: =K81+K82+K83 -> 77.282486 | L84: =L81+L82+L83 -> 77.282486 | M84: =M81+M82+M83 -> 77.282486 | N84: =H84/D84-1 -> 0.12004835 | O84: =M84/I84-1 -> -0.091492501
B86: Current liabilities
B87: Provisions | D87: ='BS-Breakdown'!C261 -> 12.287619 | E87: ='BS-Breakdown'!D261 -> 14.261845 | F87: ='BS-Breakdown'!E261 -> 14.158105 | G87: ='BS-Breakdown'!F261 -> 15.034468 | H87: ='BS-Breakdown'!G261 -> 17.220844 | I87: ='BS-Breakdown'!H261 -> 31.040514 | J87: ='BS-Breakdown'!I261 -> 35.867319 | K87: ='BS-Breakdown'!J261 -> 42.042044 | ... M87: ='BS-Breakdown'!L261 -> 53.908621
B88: Credit facilities | D88: ='BS-Breakdown'!C280 -> 804.55855 | E88: ='BS-Breakdown'!D280 -> 820.65523 | F88: ='BS-Breakdown'!E280 -> 904.75287 | G88: ='BS-Breakdown'!F280 -> 1060.2213 | H88: ='BS-Breakdown'!G280 -> 1507.4604 | I88: ='BS-Breakdown'!H280 -> 1587.894 | J88: ='BS-Breakdown'!I280 -> 1418.0236 | K88: ='BS-Breakdown'!J280 -> 1354.9287 | ... M88: ='BS-Breakdown'!L280 -> 1290.6054
B89: Current portion of long term loans | D89: ='BS-Breakdown'!C238 -> 58.85 | E89: ='BS-Breakdown'!D238 -> 21.949676 | F89: ='BS-Breakdown'!E238 -> 0 | G89: ='BS-Breakdown'!F238 -> 0 | H89: ='BS-Breakdown'!G238 -> 0 | I89: ='BS-Breakdown'!H238 -> 0 | J89: ='BS-Breakdown'!I238 -> 0 | K89: ='BS-Breakdown'!J238 -> 0 | ... M89: ='BS-Breakdown'!L238 -> 0
B90: Current portion of lease liabilities | D90: ='BS-Breakdown'!C228 -> 2.601924 | E90: ='BS-Breakdown'!D228 -> 3.130595 | F90: ='BS-Breakdown'!E228 -> 3.66348 | G90: ='BS-Breakdown'!F228 -> 4.807464 | H90: ='BS-Breakdown'!G228 -> 4.484428 | I90: ='BS-Breakdown'!H228 -> 3.8914197 | J90: ='BS-Breakdown'!I228 -> 3.8914197 | K90: ='BS-Breakdown'!J228 -> 3.8914197 | ... M90: ='BS-Breakdown'!L228 -> 0
B91: Trade, notes and other payables | D91: ='BS-Breakdown'!C288 -> 93.719707 | E91: ='BS-Breakdown'!D288 -> 128.56869 | F91: ='BS-Breakdown'!E288 -> 205.66697 | G91: ='BS-Breakdown'!F288 -> 232.18469 | H91: ='BS-Breakdown'!G288 -> 527.24973 | I91: ='BS-Breakdown'!H288 -> 661.0166 | J91: ='BS-Breakdown'!I288 -> 715.96355 | K91: ='BS-Breakdown'!J288 -> 801.10232 | ... M91: ='BS-Breakdown'!L288 -> 984.88013
B92: Income taxes payables | D92: ='BS-Breakdown'!C297 -> 18.308864 | E92: ='BS-Breakdown'!D297 -> 33.491346 | F92: ='BS-Breakdown'!E297 -> 53.713738 | G92: ='BS-Breakdown'!F297 -> 60.590831 | H92: ='BS-Breakdown'!G297 -> 98.783684 | I92: ='BS-Breakdown'!H297 -> 79.687258 | J92: ='BS-Breakdown'!I297 -> 79.687258 | K92: ='BS-Breakdown'!J297 -> 79.687258 | ... M92: ='BS-Breakdown'!L297 -> 79.687258
B93: Total C.L | D93: =SUM(D87:D92) -> 990.32667 | E93: =SUM(E87:E92) -> 1022.0574 | F93: =SUM(F87:F92) -> 1181.9552 | G93: =SUM(G87:G92) -> 1372.8388 | H93: =SUM(H87:H92) -> 2155.1991 | I93: =SUM(I87:I92) -> 2363.5297 | J93: =SUM(J87:J92) -> 2253.4332 | K93: =SUM(K87:K92) -> 2281.6517 | ... M93: =SUM(M87:M92) -> 2409.0814 | N93: =H93/D93-1 -> 1.1762507 | O93: =M93/I93-1 -> 0.019272708
B94: Total Liabilities | D94: =D84+D93 -> 1065.7451 | E94: =E84+E93 -> 1074.8118 | F94: =F84+F93 -> 1249.8547 | G94: =G84+G93 -> 1442.7728 | H94: =H84+H93 -> 2239.6714 | I94: =I84+I93 -> 2448.5951 | J94: =J84+J93 -> 2334.6071 | K94: =K84+K93 -> 2358.9342 | ... M94: =M84+M93 -> 2486.3639 | N94: =H94/D94-1 -> 1.1015075 | O94: =M94/I94-1 -> 0.015424674
B95: Total Liabilities and equity | D95: =D94+D77 -> 2249.3152 | E95: =E94+E77 -> 2420.3005 | F95: =F94+F77 -> 2773.0314 | G95: =G94+G77 -> 3218.272 | H95: =H94+H77 -> 4311.3158 | I95: =I94+I77 -> 4896.7999 | J95: =J94+J77 -> 5239.7317 | K95: =K94+K77 -> 5887.691 | ... M95: =M94+M77 -> 7513.6783 | N95: =H95/D95-1 -> 0.91672373 | O95: =M95/I95-1 -> 0.53440584
B96: Checker | D96: =D95-D63 -> 0 | E96: =E95-E63 -> 0 | F96: =F95-F63 -> 0 | G96: =G95-G63 -> 0 | H96: =H95-H63 -> 0 | I96: =I95-I63 -> 0 | J96: =J95-J63 -> 0 | K96: =K95-K63 -> 0 | ... M96: =M95-M63 -> 0
B98: Working Capital | D98: =(D55+D56+D58+D59+D61)-(D87+D91+D92) -> 889.68564 | E98: =(E55+E56+E58+E59+E61)-(E87+E91+E92) -> 817.31552 | F98: =(F55+F56+F58+F59+F61)-(F87+F91+F92) -> 1056.1258 | G98: =(G55+G56+G58+G59+G61)-(G87+G91+G92) -> 1401.8877 | H98: =(H55+H56+H58+H59+H61)-(H87+H91+H92) -> 2239.3691 | I98: =(I55+I56+I58+I59)-(I87+I91+I92) -> 2634.8945 | J98: =(J55+J56+J58+J59)-(J87+J91+J92) -> 2920.6441 | K98: =(K55+K56+K58+K59)-(K87+K91+K92) -> 3251.5141 | L98: =(L55+L56+L58+L59)-(L87+L91+L92) -> 3608.5931 | M98: =(M55+M56+M58+M59)-(M87+M91+M92) -> 3982.4725
B99: Net working capital | E99: =E98-D98 -> -72.370124 | F99: =F98-E98 -> 238.8103 | G99: =G98-F98 -> 345.76192 | H99: =H98-G98 -> 837.48138 | I99: =I98-H98 -> 395.52539 | J99: =J98-I98 -> 285.74963 | K99: =K98-J98 -> 330.86997 | L99: =L98-K98 -> 357.07899 | M99: =M98-L98 -> 373.87939
B100: Credit facilities % of WC | D100: =D88/D98 -> 0.90431779 | E100: =E88/E98 -> 1.0040862 | F100: =F88/F98 -> 0.85667149 | G100: =G88/G98 -> 0.75628118 | H100: =H88/H98 -> 0.67316297 | I100: =I88/I98 -> 0.60264043 | J100: =J88/J98 -> 0.48551743 | K100: =K88/K98 -> 0.41670699 | ... M100: =M88/M98 -> 0.32407138
B103: Cash Flow
B104: For 2020-2024 | D104: 2020A | E104: 2021A | F104: 2022A | G104: 2023A | H104: 2024A | I104: 2025F | J104: 2026F | K104: 2027F | L104: 2028F | M104: 2029F
B105: Net Profit | D105: =D38 -> 111.73066 | E105: =E38 -> 180.28439 | F105: =F38 -> 253.07219 | G105: =G38 -> 253.38313 | H105: =H38 -> 401.9611 | I105: =I38 -> 561.23863 | J105: =J38 -> 676.58576 | K105: =K38 -> 915.88298 | ... M105: =M38 -> 1158.4608
B107: Depreciation and amortization | D107: =-D25 -> 56.201806 | E107: =-E25 -> 46.181573 | F107: =-F25 -> 65.484366 | G107: =-G25 -> 72.883988 | H107: =-H25 -> 83.432594 | I107: =-I25 -> 91.718364 | J107: =-J25 -> 100.12859 | K107: =-K25 -> 107.48684 | ... M107: =-M25 -> 123.97976
B108: Finance Expenses | D108: =-D30 -> 100.05893 | E108: =-E30 -> 94.817656 | F108: =-F30 -> 92.084277 | G108: =-G30 -> 194.25931 | H108: =-H30 -> 310.94187 | I108: =-I30 -> 329.80701 | J108: =-J30 -> 329.80701 | K108: =-K30 -> 173.52313 | ... M108: =-M30 -> 118.9
B109: Finance Income | D109: =-D29 -> -64.160293 | E109: =-E29 -> -59.973 | F109: =-F29 -> -56.732176 | G109: =-G29 -> -62.902521 | H109: =-H29 -> -65.852148 | I109: =-I29 -> -45.747704 | J109: =-J29 -> -15.428505 | K109: =-K29 -> -6.8757761 | ... M109: =-M29 -> -15.598651
B110: Net foregin exchange gain/loss | D110: =-D31 -> 1.695406 | E110: =-E31 -> 0.596919 | F110: =-F31 -> -25.651093 | G110: =-G31 -> -18.683006 | H110: =-H31 -> -56.240536 | I110: =-I31 -> 0 | J110: =-J31 -> 0 | K110: =-K31 -> 0 | ... M110: =-M31 -> 0
B111: Other Income | D111: =-D32 -> -1.019971 | E111: =-E32 -> -0.041606 | F111: =-F32 -> -5.90985 | G111: =-G32 -> -7.476152 | H111: =-H32 -> -27.305011 | I111: =-I32 -> -15.275551 | J111: =-J32 -> -16.868808 | K111: =-K32 -> -18.906993 | ... M111: =-M32 -> -22.823975
B112: Impairment of trade and notes receivable | D112: =-D13 -> 1.802092 | E112: =-E13 -> 0.1056 | F112: =-F13 -> 3.643441 | G112: =-G13 -> 3.808579 | H112: =-H13 -> 11.442943 | I112: =-I13 -> 9.3790789 | J112: =-J13 -> 3.7057049 | K112: =-K13 -> 4.7405492 | ... M112: =-M13 -> 5.4231146
B113: Provisions | D113: =-D14 -> 1.6 | E113: =-E14 -> 1.25 | F113: =-F14 -> 0 | G113: =-G14 -> 0.673282 | H113: =-H14 -> 0.5 | I113: =-I14 -> 4.4405911 | J113: =-J14 -> 1.1211002 | K113: =-K14 -> 1.4341753 | ... M113: =-M14 -> 1.6406743
B114: Contribution for health insurance | D114: =-D17 -> 2.56337 | E114: =-E17 -> 3.272995 | F114: =-F17 -> 3.975441 | G114: =-G17 -> 5.109505 | H114: =-H17 -> 7.471037 | I114: =-I17 -> 10.814882 | J114: =-J17 -> 11.942886 | K114: =-K17 -> 13.385894 | ... M114: =-M17 -> 16.159064
B115: Share based payments reserve | D115: =-D15 -> 0 | E115: =-E15 -> 0 | F115: =-F15 -> 17.84792 | G115: =-G15 -> 17.768011 | H115: =-H15 -> 16.286564 | I115: =-I15 -> 22.027905 | J115: =-J15 -> 24.325441 | K115: =-K15 -> 27.264579 | ... M115: =-M15 -> 32.91301
...

Sheet IS- Breakdown
B3: Revenue breakdown | C3: 2020 | D3: 2021 | E3: 2022 | F3: 2023 | G3: 2024 | H3: =G3+1 -> 2025 | I3: =H3+1 -> 2026 | J3: =I3+1 -> 2027 | K3: =J3+1 -> 2028 | L3: =K3+1 -> 2029
B4: Services Toll Manufacturing Domestic | C4: 50.839648 | D4: 77.490353 | E4: 132.43683 | F4: 134.00577 | G4: 181.86566 | H4: =G4-O7+P7 -> 284.43546 | I4: =IFERROR(I37*I51,"") -> 327.22695 | J4: =IFERROR(J37*J51,"") -> 371.09195 | K4: =IFERROR(K37*K51,"") -> 400.23072 | L4: =IFERROR(L37*L51,"") -> 436.49139
B5: Export | C5: 49.93875 | D5: 87.872886 | E5: 106.50658 | F5: 180.24423 | G5: 142.20235 | H5: =G5-O8+P8 -> 172.13497 | I5: =I36*I50 -> 207.91816 | J5: =J36*J50 -> 267.7243 | K5: =K36*K50 -> 307.63679 | L5: =L36*L50 -> 355.10627 | O5: TTM for Revenue Q3 2025F page no. 11 | P5: FS Report Q3
B6: Private Sales | C6: 659.7097 | D6: 829.08115 | E6: 1084.237 | F6: 1418.6302 | G6: 2208.1899 | H6: =G6-O9+P9 -> 2956.9811 | I6: =IFERROR(I35*I49,"") -> 3254.4621 | J6: =IFERROR(J35*J49,"") -> 3614.3993 | K6: =IFERROR(K35*K49,"") -> 3915.3239 | L6: =IFERROR(L35*L49,"") -> 4357.7937 | O6: 2024 | P6: 2025
B7: Tenders | C7: 199.68525 | D7: 251.99024 | E7: 160.77102 | F7: 189.47047 | G7: 236.4305 | H7: =G7-O10+P10 -> 534.47018 | I7: =I34*I48 -> 568.75719 | J7: =J34*J48 -> 632.14158 | K7: =K34*K48 -> 667.23157 | L7: =L34*L48 -> 742.40776 | N7: Toll | O7: 117.18985 | P7: 219.75965
B8: Total | C8: =SUM(C4:C7) -> 960.17335 | D8: =SUM(D4:D7) -> 1246.4346 | E8: =SUM(E4:E7) -> 1483.9514 | F8: =SUM(F4:F7) -> 1922.3507 | G8: =SUM(G4:G7) -> 2768.6884 | H8: =SUM(H4:H7) -> 3948.0217 | I8: =SUM(I4:I7) -> 4358.3644 | J8: =SUM(J4:J7) -> 4885.3571 | ... L8: =SUM(L4:L7) -> 5891.7992 | N8: X | O8: 139.12338 | P8: 169.056
N9: PS | O9: 1411.878 | P9: 2160.6692
A10: Note 21 | B10: Revenue | C10: 2020 | D10: 2021 | E10: 2022 | F10: 2023 | G10: 2024 | H10: =G10+1 -> 2025 | I10: =H10+1 -> 2026 | J10: =I10+1 -> 2027 | K10: =J10+1 -> 2028 | L10: =K10+1 -> 2029 | N10: T | O10: 116.17736 | P10: 414.21705
B11: Sale of goods (net) | C11: 909.3297 | D11: 1168.9443 | E11: 1351.5146 | F11: 1788.3449 | G11: =SUM(G5:G7) -> 2586.8228 | H11: =SUM(H5:H7) -> 3663.5863 | I11: =SUM(I5:I7) -> 4031.1375 | J11: =SUM(J5:J7) -> 4514.2652 | K11: =SUM(K5:K7) -> 4890.1923 | L11: =SUM(L5:L7) -> 5455.3078 | N11: Total | O11: =SUM(O7:O10) -> 1784.3686 | P11: =SUM(P7:P10) -> 2963.7019
B12: Cosmetics | G12: =3.5%*G14 -> 96.904095 | H12: =G12*(1+Assumptions!$Q36) -> 108.30012 | I12: =H12*(1+Assumptions!$Q36) -> 121.03632 | J12: =I12*(1+Assumptions!$Q36) -> 135.27032 | K12: =J12*(1+Assumptions!$Q36) -> 151.17825 | L12: =K12*(1+Assumptions!$Q36) -> 168.95697 | M12: =_xlfn.RRI(4,H12,L12) -> 0.11760104 | O12: TTM for Volume Q3 2025F
B13: Toll Maunfacturing services revenue | C13: 50.839648 | D13: 77.490353 | E13: 132.43683 | F13: 134.00577 | G13: =G4 -> 181.86566 | H13: =H4 -> 284.43546 | I13: =I4 -> 327.22695 | J13: =J4 -> 371.09195 | K13: =K4 -> 400.23072 | L13: =L4 -> 436.49139 | O13: 2024 | P13: 2025
B14: Total | C14: =SUM(C11:C13) -> 960.16935 | D14: =SUM(D11:D13) -> 1246.4346 | E14: =SUM(E11:E13) -> 1483.9514 | F14: =SUM(F11:F13) -> 1922.3507 | G14: =G11+G13 -> 2768.6884 | H14: =SUM(H11:H13) -> 4056.3218 | I14: =SUM(I11:I13) -> 4479.4008 | J14: =SUM(J11:J13) -> 5020.6274 | K14: =SUM(K11:K13) -> 5441.6012 | L14: =SUM(L11:L13) -> 6060.7561 | N14: Toll | O14: 43.4 | P14: 56.5
N15: X | O15: 3.9 | P15: 4.8
B16: Market Share | C16: =(C14*1000000)/(Assumptions!C25*1000000000) -> 0.014301429 | D16: =(D14*1000000)/(Assumptions!D25*1000000000) -> 0.011448624 | E16: =(E14*1000000)/(Assumptions!E25*1000000000) -> 0.011592827 | F16: =(F14*1000000)/(Assumptions!F25*1000000000) -> 0.010631177 | G16: =(G14*1000000)/(Assumptions!G25*1000000000) -> 0.011962258 | H16: =(H14*1000000)/(Assumptions!H25*1000000000) -> 0.013799595 | I16: =(I14*1000000)/(Assumptions!I25*1000000000) -> 0.013908461 | J16: =(J14*1000000)/(Assumptions!J25*1000000000) -> 0.014626524 | ... L16: =(L14*1000000)/(Assumptions!L25*1000000000) -> 0.015751675 | N16: PS | O16: 25.4 | P16: 34.1
B17: YoY % | D17: =D14/C14-1 -> 0.29814041 | E17: =E14/D14-1 -> 0.19055696 | F17: =F14/E14-1 -> 0.29542698 | G17: =G14/F14-1 -> 0.44026186 | H17: =H14/G14-1 -> 0.46506982 | I17: =I14/H14-1 -> 0.10430112 | J17: =J14/I14-1 -> 0.12082569 | K17: =K14/J14-1 -> 0.083848841 | L17: =L14/K14-1 -> 0.11378175 | N17: T | O17: 4.2 | P17: 14.6
B18: CAGR | C18: =_xlfn.RRI(COLUMNS(C14:G14)-1,C14,G14) -> 0.30311145 | H18: =_xlfn.RRI(COLUMNS(H14:L14)-1,H14,L14) -> 0.10560145 | N18: Total | O18: =SUM(O14:O17) -> 76.9 | P18: =SUM(P14:P17) -> 110
B20: % Revenue forecasted | C20: 2020 | D20: 2021 | E20: 2022 | F20: 2023 | G20: 2024 | H20: =G20+1 -> 2025 | I20: =H20+1 -> 2026 | J20: =I20+1 -> 2027 | K20: =J20+1 -> 2028 | L20: =K20+1 -> 2029
B21: Sale of goods (net) | G21: =(G11/G$14)-G22 -> 0.89931343 | H21: =H11/H$14 -> 0.90317938 | I21: =I11/I$14 -> 0.89992785 | J21: =J11/J$14 -> 0.89914363 | K21: =K11/K$14 -> 0.89866788 | L21: =L11/L$14 -> 0.90010349
B22: Cosmetics | G22: =G12/G$14 -> 0.035 | H22: =H12/H$14 -> 0.026699094 | I22: =I12/I$14 -> 0.027020651 | J22: =J12/J$14 -> 0.026942911 | K22: =K12/K$14 -> 0.027781942 | L22: =L12/L$14 -> 0.027877209
B23: Toll Maunfacturing services revenue | G23: =G13/G$14 -> 0.065686575 | H23: =H13/H$14 -> 0.070121521 | I23: =I13/I$14 -> 0.073051501 | J23: =J13/J$14 -> 0.073913461 | K23: =K13/K$14 -> 0.073550174 | L23: =L13/L$14 -> 0.072019296
B24: Total | G24: =SUM(G21:G23) -> 1 | H24: =SUM(H21:H23) -> 1 | I24: =SUM(I21:I23) -> 1 | J24: =SUM(J21:J23) -> 1 | K24: =SUM(K21:K23) -> 1 | L24: =SUM(L21:L23) -> 1
B26: Utilization & Capacity | C26: 2020 | D26: 2021 | E26: 2022 | F26: 2023 | G26: 2024 | H26: =G26+1 -> 2025 | I26: =H26+1 -> 2026 | J26: =I26+1 -> 2027 | K26: =J26+1 -> 2028 | L26: =K26+1 -> 2029
B27: Capacity | C27: 424.1 | D27: 424.1 | E27: 424.1 | F27: 424.1 | G27: 424.1 | H27: 424.1 | I27: 424.1 | J27: 424.1 | K27: 424.1 | L27: 424.1
B28: Utilization (Tender) | C28: =C34/C27 -> 0.071266211 | D28: =D34/D27 -> 0.062640887 | E28: =E34/E27 -> 0.038499882 | F28: =F34/F27 -> 0.030888941 | G28: =G34/G27 -> 0.019099269 | H28: =H34/H$27 -> 0.043621787 | I28: =I34/I$27 -> 0.041707265 | J28: =J34/J$27 -> 0.042802656 | K28: =K34/K$27 -> 0.042823335 | L28: =L34/L$27 -> 0.045249942
B29: Utilization (Private Sales) | C29: =C35/C27 -> 0.063923603 | D29: =D35/D27 -> 0.074529592 | E29: =E35/E27 -> 0.085135581 | F29: =F35/F27 -> 0.075030182 | G29: =G35/$G$27 -> 0.093138411 | H29: =H35/H$27 -> 0.11365244 | I29: =I35/I$27 -> 0.11238653 | J29: =J35/J$27 -> 0.11525047 | K29: =K35/K$27 -> 0.11833735 | L29: =L35/L$27 -> 0.12508131
B30: Utilization (Exports) | C30: =C36/C27 -> 0.0080853572 | D30: =D36/D27 -> 0.0065927847 | E30: =E36/E27 -> 0.014168828 | F30: =F36/F27 -> 0.016518746 | G30: =G36/$G$27 -> 0.0099033247 | H30: =H36/H$27 -> 0.012025466 | I30: =I36/I$27 -> 0.013180856 | J30: =J36/J$27 -> 0.01561383 | K30: =K36/K$27 -> 0.016658819 | L30: =L36/L$27 -> 0.017988153
B31: Utilization (Toll Manufacturing) | C31: =C37/C27 -> 0.061219052 | D31: =D37/D27 -> 0.081296864 | E31: =E37/E27 -> 0.20398963 | F31: =F37/F27 -> 0.14966753 | G31: =G37/$G$27 -> 0.15963216 | H31: =H37/H$27 -> 0.1905211 | I31: =I37/I$27 -> 0.19693062 | J31: =J37/J$27 -> 0.20621358 | K31: =K37/K$27 -> 0.2108112 | L31: =L37/L$27 -> 0.21833863
B32: Utilization rate total | C32: =C38/C27 -> 0.20449422 | D32: =D38/D27 -> 0.22506013 | E32: =E38/E27 -> 0.34179392 | F32: =F38/F27 -> 0.2721054 | G32: =G38/G27 -> 0.28177317 | H32: =H38/H27 -> 0.3598208 | I32: =I38/I27 -> 0.36420528 | J32: =J38/J27 -> 0.37988054 | ... L32: =L38/L27 -> 0.40665804 | N32: =HARMEAN(C32:G32) -> 0.25663253 | O32: =HARMEAN(H32:L32) -> 0.37909007
B33: Volume Sold | C33: 2020 | D33: 2021 | E33: 2022 | F33: 2023 | G33: 2024 | H33: =G33+1 -> 2025 | I33: =H33+1 -> 2026 | J33: =I33+1 -> 2027 | K33: =J33+1 -> 2028 | L33: =K33+1 -> 2029 | N33: Demand inc (toll &PS)
B34: Volume Sold (Tender) | C34: 30.224 | D34: 26.566 | E34: 16.3278 | F34: 13.1 | G34: 8.1 | H34: =G34-O17+P17 -> 18.5 | I34: =FORECAST(Assumptions!I26,'IS- Breakdown'!$F$34:$H$34,Assumptions!F26:H26) -> 17.688051 | J34: =FORECAST(Assumptions!J26,'IS- Breakdown'!$F$34:$H$34,Assumptions!G26:I26) -> 18.152606 | K34: =FORECAST(Assumptions!K26,'IS- Breakdown'!$F$34:$H$34,Assumptions!H26:J26) -> 18.161376 | L34: =FORECAST(Assumptions!L26,'IS- Breakdown'!$F$34:$H$34,Assumptions!I26:K26) -> 19.190501 | N34: Export will increase on a mid-term
B35: Volume Sold (Private Sales) | C35: 27.11 | D35: 31.608 | E35: 36.106 | F35: 31.8203 | G35: 39.5 | H35: =G35-O16+P16 -> 48.2 | I35: =FORECAST(Assumptions!I20,'IS- Breakdown'!C35:H35,Assumptions!C20:H20) -> 47.663129 | J35: =FORECAST(Assumptions!J20,'IS- Breakdown'!D35:I35,Assumptions!D20:I20) -> 48.877726 | K35: =FORECAST(Assumptions!K20,'IS- Breakdown'!E35:J35,Assumptions!E20:J20) -> 50.186869 | L35: =FORECAST(Assumptions!L20,'IS- Breakdown'!F35:K35,Assumptions!F20:K20) -> 53.046985 | N35: Sudan's demand also a contributing to increased volume
B36: Volume Sold (Exports) | C36: 3.429 | D36: 2.796 | E36: 6.009 | F36: 7.0056 | G36: 4.2 | H36: =G36-O15+P15 -> 5.1 | I36: =FORECAST(Assumptions!I14,'IS- Breakdown'!C36:H36,Assumptions!C14:H14) -> 5.590001 | J36: =FORECAST(Assumptions!J14,'IS- Breakdown'!D36:I36,Assumptions!D14:I14) -> 6.6218252 | K36: =FORECAST(Assumptions!K14,'IS- Breakdown'!E36:J36,Assumptions!E14:J14) -> 7.0650053 | L36: =FORECAST(Assumptions!L14,'IS- Breakdown'!F36:K36,Assumptions!F14:K14) -> 7.6287759
B37: Volume Sold (Toll Manufacturing) | C37: 25.963 | D37: 34.478 | E37: 86.512 | F37: 63.474 | G37: 67.7 | H37: =G37-O14+P14 -> 80.8 | I37: =FORECAST(Assumptions!I20,'IS- Breakdown'!F37:H37,Assumptions!F20:H20) -> 83.518277 | J37: =FORECAST(Assumptions!J20,'IS- Breakdown'!G37:I37,Assumptions!G20:I20) -> 87.45518 | K37: =FORECAST(Assumptions!K20,'IS- Breakdown'!H37:J37,Assumptions!H20:J20) -> 89.405031 | L37: =FORECAST(Assumptions!L20,'IS- Breakdown'!I37:K37,Assumptions!I20:K20) -> 92.597413
B38: Total | C38: =SUM(C34:C37) -> 86.726 | D38: =SUM(D34:D37) -> 95.448 | E38: =SUM(E34:E37) -> 144.9548 | F38: =SUM(F34:F37) -> 115.3999 | G38: =SUM(G34:G37) -> 119.5 | H38: =SUM(H34:H37) -> 152.6 | I38: =SUM(I34:I37) -> 154.45946 | J38: =SUM(J34:J37) -> 161.10734 | ... L38: =SUM(L34:L37) -> 172.46367
B39: Own Volume | C39: =C38-C37 -> 60.763 | D39: =D38-D37 -> 60.97 | E39: =E38-E37 -> 58.4428 | F39: =F38-F37 -> 51.9259 | G39: =G38-G37 -> 51.8 | H39: =H38-H37 -> 71.8 | I39: =I38-I37 -> 70.941181 | J39: =J38-J37 -> 73.652158 | ... L39: =L38-L37 -> 79.866261
B41: Volume Sold % | C41: 2020 | D41: 2021 | E41: 2022 | F41: 2023 | G41: 2024 | H41: =G41+1 -> 2025 | I41: =H41+1 -> 2026 | J41: =I41+1 -> 2027 | K41: =J41+1 -> 2028 | L41: =K41+1 -> 2029
B42: Volume Sold (Tender) | C42: =C34/C38 -> 0.34849987 | D42: =D34/D38 -> 0.27832956 | E42: =E34/E38 -> 0.11264063 | F42: =F34/F38 -> 0.1135183 | G42: =G34/G38 -> 0.067782427 | H42: =H34/H38 -> 0.12123198 | I42: =I34/I38 -> 0.11451582 | J42: =J34/J38 -> 0.11267399 | ... L42: =L34/L38 -> 0.11127271
B43: Volume Sold (Private Sales) | C43: =C35/C38 -> 0.31259369 | D43: =D35/D38 -> 0.33115414 | E43: =E35/E38 -> 0.24908454 | F43: =F35/F38 -> 0.27573941 | G43: =G35/G38 -> 0.33054393 | H43: =H35/H38 -> 0.31585845 | I43: =I35/I38 -> 0.30858019 | J43: =J35/J38 -> 0.3033861 | ... L43: =L35/L38 -> 0.30758353
B44: Volume Sold (Exports) | C44: =C36/C38 -> 0.039538316 | D44: =D36/D38 -> 0.029293437 | E44: =E36/E38 -> 0.041454302 | F44: =F36/F38 -> 0.060707158 | G44: =G36/G38 -> 0.035146444 | H44: =H36/H38 -> 0.033420708 | I44: =I36/I38 -> 0.036190733 | J44: =J36/J38 -> 0.041101947 | ... L44: =L36/L38 -> 0.044234103
B45: Volume Sold (Toll Manufacturing) | C45: =C37/C38 -> 0.29936812 | D45: =D37/D38 -> 0.36122286 | E45: =E37/E38 -> 0.59682053 | F45: =F37/F38 -> 0.55003514 | G45: =G37/G38 -> 0.5665272 | H45: =H37/H38 -> 0.52948886 | I45: =I37/I38 -> 0.54071326 | J45: =J37/J38 -> 0.54283797 | ... L45: =L37/L38 -> 0.53690966
B47: Average Selling Prices | C47: 2020 | D47: 2021 | E47: 2022 | F47: 2023 | G47: 2024 | H47: =G47+1 -> 2025 | I47: =H47+1 -> 2026 | J47: =I47+1 -> 2027 | K47: =J47+1 -> 2028 | L47: =K47+1 -> 2029
B48: ASP (Tender) | C48: =C7/C34 -> 6.6068439 | D48: =D7/D34 -> 9.4854414 | E48: =E7/E34 -> 9.8464592 | F48: =F7/F34 -> 14.463395 | G48: =G7/G34 -> 29.18895 | H48: =H7/H34 -> 28.89028 | I48: =H48*(1+Assumptions!I5) -> 32.154882 | J48: =I48*(1+Assumptions!J5) -> 34.823737 | K48: =J48*(1+Assumptions!K5) -> 36.739042 | L48: =K48*(1+Assumptions!L5) -> 38.686212
B49: ASP (Private Sales) | C49: =C6/C35 -> 24.334552 | D49: =D6/D35 -> 26.230105 | E49: =E6/E35 -> 30.029275 | F49: =F6/F35 -> 44.582554 | G49: =G6/G35 -> 55.903542 | H49: =H6/H35 -> 61.348156 | I49: =H49*(1+Assumptions!I5) -> 68.280498 | J49: =I49*(1+Assumptions!J5) -> 73.947779 | K49: =J49*(1+Assumptions!K5) -> 78.014907 | L49: =K49*(1+Assumptions!L5) -> 82.149697
B50: ASP (Exports) | C50: =C5/C36 -> 14.563648 | D50: =D5/D36 -> 31.428071 | E50: =E5/E36 -> 17.72451 | F50: =F5/F36 -> 25.728593 | G50: =G5/G36 -> 33.857702 | H50: =H5/H36 -> 33.751955 | I50: =H50*(1+Assumptions!I4) -> 37.194655 | J50: =I50*(1+Assumptions!J4) -> 40.43059 | K50: =J50*(1+Assumptions!K4) -> 43.543745 | L50: =K50*(1+Assumptions!L4) -> 46.548264
B51: ASP (Toll Manufacturing) | C51: =C4/C37 -> 1.9581577 | D51: =D4/D37 -> 2.2475304 | E51: =E4/E37 -> 1.5308493 | F51: =F4/F37 -> 2.1111915 | G51: =G4/G37 -> 2.6863465 | H51: =H4/H37 -> 3.5202408 | I51: =H51*(1+Assumptions!I5) -> 3.918028 | J51: =I51*(1+Assumptions!J5) -> 4.2432244 | K51: =J51*(1+Assumptions!K5) -> 4.4766017 | L51: =K51*(1+Assumptions!L5) -> 4.7138616
B52: Total | C52: =SUM(C48:C51) -> 47.463202 | D52: =SUM(D48:D51) -> 69.391147 | E52: =SUM(E48:E51) -> 59.131093 | F52: =SUM(F48:F51) -> 86.885734 | G52: =SUM(G48:G51) -> 121.63654 | H52: =SUM(H48:H51) -> 127.51063 | I52: =SUM(I48:I51) -> 141.54806 | J52: =SUM(J48:J51) -> 153.44533 | ... L52: =SUM(L48:L51) -> 172.09803
B53: ASP/USD | C53: =C52/Assumptions!C9 -> 3.0261793 | D53: =D52/Assumptions!D9 -> 4.4307965 | E53: =E52/Assumptions!E9 -> 2.3949992 | F53: =F52/Assumptions!F9 -> 2.8171787 | G53: =G52/Assumptions!G9 -> 2.3950519 | H53: =H52/Assumptions!H9 -> 2.707807 | I53: =I52/Assumptions!I9 -> 2.874656 | J53: =J52/Assumptions!J9 -> 3.0548543 | ... L53: =L52/Assumptions!L9 -> 3.293112
B55: Average Selling Prices % | C55: 2020 | D55: 2021 | E55: 2022 | F55: 2023 | G55: 2024 | H55: =G55+1 -> 2025 | I55: =H55+1 -> 2026 | J55: =I55+1 -> 2027 | K55: =J55+1 -> 2028 | L55: =K55+1 -> 2029
B56: ASP (Tender) | C56: =C48/C52 -> 0.13919929 | D56: =D48/D52 -> 0.13669527 | E56: =E48/E52 -> 0.16651915 | F56: =F48/F52 -> 0.16646455 | G56: =G48/G52 -> 0.2399686 | H56: =H48/H52 -> 0.22657154 | I56: =I48/I52 -> 0.22716582 | J56: =J48/J52 -> 0.22694556 | ... L56: =L48/L52 -> 0.22479171
B57: ASP (Private Sales) | C57: =C49/C52 -> 0.51270355 | D57: =D49/D52 -> 0.37800362 | E57: =E49/E52 -> 0.50784237 | F57: =F49/F52 -> 0.51311708 | G57: =G49/G52 -> 0.45959497 | H57: =H49/H52 -> 0.48112189 | I57: =I49/I52 -> 0.48238384 | J57: =J49/J52 -> 0.48191613 | ... L57: =L49/L52 -> 0.47734245
B58: ASP (Exports) | C58: =C50/C52 -> 0.30684083 | D58: =D50/D52 -> 0.45291182 | E58: =E50/E52 -> 0.29974941 | F58: =F50/F52 -> 0.29611988 | G58: =G50/G52 -> 0.2783514 | H58: =H50/H52 -> 0.26469915 | I58: =I50/I52 -> 0.2627705 | J58: =J50/J52 -> 0.26348531 | ... L58: =L50/L52 -> 0.27047528
B59: ASP (Toll Manufacturing) | C59: =C51/C52 -> 0.041256334 | D59: =D51/D52 -> 0.032389296 | E59: =E51/E52 -> 0.025889074 | F59: =F51/F52 -> 0.024298483 | G59: =G51/G52 -> 0.022085029 | H59: =H51/H52 -> 0.02760743 | I59: =I51/I52 -> 0.027679842 | J59: =J51/J52 -> 0.027653004 | ... L59: =L51/L52 -> 0.02739056
B60: Total | C60: =SUM(C56:C59) -> 1 | D60: =SUM(D56:D59) -> 1 | E60: =SUM(E56:E59) -> 1 | F60: =SUM(F56:F59) -> 1 | G60: =SUM(G56:G59) -> 1 | H60: =SUM(H56:H59) -> 1 | I60: =SUM(I56:I59) -> 1 | J60: =SUM(J56:J59) -> 1 | ... L60: =SUM(L56:L59) -> 1
B62: % of total Revenue | C62: 2020 | D62: 2021 | E62: 2022 | F62: 2023 | G62: 2024 | H62: =G62+1 -> 2025 | I62: =H62+1 -> 2026 | J62: =I62+1 -> 2027 | K62: =J62+1 -> 2028 | L62: =K62+1 -> 2029
B63: Services Toll Manufacturing Domestic | C63: =C4/C$8 -> 0.052948406 | D63: =D4/D$8 -> 0.062169609 | E63: =E4/E$8 -> 0.08924607 | F63: =F4/F$8 -> 0.069709325 | G63: =G4/G$8 -> 0.065686575 | H63: =H4/H$8 -> 0.072045059 | I63: =I4/I$8 -> 0.075080218 | J63: =J4/J$8 -> 0.075960046 | ... L63: =L4/L$8 -> 0.074084567
B64: Private Sales | C64: =C6/C$8 -> 0.68707354 | D64: =D6/D$8 -> 0.66516216 | E64: =E6/E$8 -> 0.73064184 | F64: =F6/F$8 -> 0.7379664 | G64: =G6/G$8 -> 0.79755811 | H64: =H6/H$8 -> 0.74897792 | I64: =I6/I$8 -> 0.74671639 | J64: =J6/J$8 -> 0.73984341 | ... L64: =L6/L$8 -> 0.73963718
B65: Tenders | C65: =C7/C$8 -> 0.20796792 | D65: =D7/D$8 -> 0.20216883 | E65: =E7/E$8 -> 0.10833981 | F65: =F7/F$8 -> 0.098561865 | G65: =G7/G$8 -> 0.085394404 | H65: =H7/H$8 -> 0.13537671 | I65: =I7/I$8 -> 0.13049785 | J65: =J7/J$8 -> 0.12939516 | ... L65: =L7/L$8 -> 0.12600697
B66: Export | C66: =C5/C$8 -> 0.05201014 | D66: =D5/D$8 -> 0.070499394 | E66: =E5/E$8 -> 0.071772283 | F66: =F5/F$8 -> 0.093762409 | G66: =G5/G$8 -> 0.051360906 | H66: =H5/H$8 -> 0.04360031 | I66: =I5/I$8 -> 0.047705547 | J66: =J5/J$8 -> 0.054801378 | ... L66: =L5/L$8 -> 0.060271279
B67: Total | C67: =SUM(C63:C65) -> 0.94798986 | D67: =SUM(D63:D65) -> 0.92950061 | E67: =SUM(E63:E65) -> 0.92822772 | F67: =SUM(F63:F65) -> 0.90623759 | G67: =SUM(G63:G65) -> 0.94863909 | H67: =SUM(H63:H65) -> 0.95639969 | I67: =SUM(I63:I65) -> 0.95229445 | J67: =SUM(J63:J65) -> 0.94519862 | ... L67: =SUM(L63:L65) -> 0.93972872
B68: % of salaries from total | C68: =C78/C76 -> 0 | D68: =D78/D76 -> 0.17832165 | E68: =E78/E76 -> 0.23506408 | F68: =F78/F76 -> 0.30050591 | G68: =G78/G76 -> 0.31746584 | H68: =AVERAGE(D68:G68) -> 0.25783937 | I68: =H68 -> 0.25783937 | J68: =I68 -> 0.25783937 | K68: =J68 -> 0.25783937 | L68: =K68 -> 0.25783937
B71: MR | D71: =(D14-C14)/(D38-C38) -> 32.821059 | E71: =(E14-D14)/(E38-D38) -> 4.7976601 | F71: =(F14-E14)/(F38-E38) -> -14.833388 | G71: =(G14-F14)/(G38-F38) -> 206.4188 | H71: =(H14-G14)/(H38-G38) -> 38.901312 | I71: =(I14-H14)/(I38-H38) -> 227.52815 | J71: =(J14-I14)/(J38-I38) -> 81.413428 | K71: =(K14-J14)/(K38-J38) -> 113.44114 | L71: =(L14-K14)/(L38-K38) -> 80.984051
B72: MC | D72: =(D95-C95)/(D38-C38) -> 17.808538 | E72: =(E95-D95)/(E38-D38) -> 1.9189082 | F72: =(F95-E95)/(F38-E38) -> -8.544338 | G72: =(G95-F95)/(G38-F38) -> 114.28717 | H72: =(H95-G95)/(H38-G38) -> 15.337968 | I72: =(I95-H95)/(I38-H38) -> 112.01005 | J72: =(J95-I95)/(J38-I38) -> 25.35657 | K72: =(K95-J95)/(K38-J38) -> 39.998762 | L72: =(L95-K95)/(L38-K38) -> 23.96328
B73: Profit-Max | D73: =IF(D71-D72>0,"Increase Q", IF(D71-D72<0,"Decrease Q")) -> Increase Q | E73: =IF(E71-E72>0,"Increase Q", IF(E71-E72<0,"Decrease Q")) -> Increase Q | F73: =IF(F71-F72>0,"Increase Q", IF(F71-F72<0,"Decrease Q")) -> Decrease Q | G73: =IF(G71-G72>0,"Increase Q", IF(G71-G72<0,"Decrease Q")) -> Increase Q | H73: =IF(H71-H72>0,"Increase Q", IF(H71-H72<0,"Decrease Q")) -> Increase Q | I73: =IF(I71-I72>0,"Increase Q", IF(I71-I72<0,"Decrease Q")) -> Increase Q | J73: =IF(J71-J72>0,"Increase Q", IF(J71-J72<0,"Decrease Q")) -> Increase Q | K73: =IF(K71-K72>0,"Increase Q", IF(K71-K72<0,"Decrease Q")) -> Increase Q | L73: =IF(L71-L72>0,"Increase Q", IF(L71-L72<0,"Decrease Q")) -> Increase Q
A75: Note 22 | B75: COGS | C75: 2020 | D75: 2021 | E75: 2022 | F75: 2023 | G75: 2024 | H75: =G75+1 -> 2025 | I75: =H75+1 -> 2026 | J75: =I75+1 -> 2027 | K75: =J75+1 -> 2028 | L75: =K75+1 -> 2029 | Q75: Cost Behaviour of COGS Total
A76: F | B76: Salaries and incentives | C76: 83.078733 | D76: 83.199259 | E76: 103.66834 | F76: 123.6722 | G76: 156.30517 | H76: =G76-N77+O77 -> 222.9646 | I76: =I77*I$14 -> 289.4602 | J76: =J77*J$14 -> 322.37748 | K76: =K77*K$14 -> 343.84755 | L76: =L77*L$14 -> 381.61256 | R76: 2020 | S76: 2021 | T76: 2022 | U76: 2023 | V76: 2024 | W76: =+V76+1 -> 2025 | X76: =+W76+1 -> 2026 | Y76: =+X76+1 -> 2027 | Z76: =+Y76+1 -> 2028 | AA76: =+Z76+1 -> 2029
B77: Salaries and incentives % | C77: =C76/C14 -> 0.086525083 | D77: =D76/D14 -> 0.066749797 | E77: =E76/E14 -> 0.069859661 | F77: =F76/F14 -> 0.06433384 | G77: =G76/G14 -> 0.056454589 | H77: =HARMEAN(C77:G77) -> 0.067466965 | I77: =HARMEAN(D77:H77) -> 0.064620296 | J77: =HARMEAN(E77:I77) -> 0.064210597 | K77: =HARMEAN(F77:J77) -> 0.063188671 | L77: =HARMEAN(G77:K77) -> 0.062964513 | M77: =G76 -> 156.30517 | N77: 112.68988 | O77: 179.34932
A78: F | B78: Social Insurance and other benefit | D78: 14.836229 | E78: 24.368704 | F78: 37.164228 | G78: 49.621551 | H78: =G78-N78+O78 -> 67.029483 | I78: =I76*I68 -> 74.634236 | J78: =J76*J68 -> 83.121608 | K78: =K76*K68 -> 88.657436 | L78: =L76*L68 -> 98.394741 | M78: =G78 -> 49.621551 | N78: 33.948866 | O78: 51.356798 | Q78: F | R78: =SUMIF($A$76:$A$93,"F",C$76:C$93) -> 203.54972 | S78: =SUMIF($A$76:$A$93,"F",D$76:D$93) -> 213.11879 | T78: =SUMIF($A$76:$A$93,"F",E$76:E$93) -> 276.33393 | U78: =SUMIF($A$76:$A$93,"F",F$76:F$93) -> 355.22198 | V78: =SUMIF($A$76:$A$93,"F",G$76:G$93) -> 422.78133 | W78: =SUMIF($A$76:$A$93,"F",H$76:H$93) -> 496.11713 | X78: =SUMIF($A$76:$A$93,"F",I$76:I$93) -> 571.2363 | Y78: =SUMIF($A$76:$A$93,"F",J$76:J$93) -> 636.60325 | ... AA78: =SUMIF($A$76:$A$93,"F",L$76:L$93) -> 758.52053
B79: Social Insurance and other benefit % | C79: =C76/C14 -> 0.086525083 | D79: =D78/D14 -> 0.011902934 | E79: =E78/E14 -> 0.016421497 | F79: =F78/F14 -> 0.019332699 | G79: =G78/G14 -> 0.017922403 | H79: =HARMEAN(C79:G79) -> 0.018940258 | I79: =HARMEAN(D79:H79) -> 0.016381186 | J79: =HARMEAN(E79:I79) -> 0.017714105 | K79: =HARMEAN(F79:J79) -> 0.017997437 | L79: =HARMEAN(G79:K79) -> 0.017752216 | M79: =G80 -> 953.62224 | N79: 599.21854 | O79: 992.99087
A80: V | B80: Raw material | C80: 250.72648 | D80: 398.91471 | E80: 424.31931 | F80: 578.56153 | G80: 953.62224 | H80: =G80-N79+O79 -> 1347.3946 | I80: =(I101*Assumptions!I9)+'IS- Breakdown'!I102 -> 1464.9034 | J80: =(J101*Assumptions!J9)+'IS- Breakdown'!J102 -> 1549.3949 | K80: =(K101*Assumptions!K9)+'IS- Breakdown'!K102 -> 1632.6219 | L80: =(L101*Assumptions!L9)+'IS- Breakdown'!L102 -> 1718.7838 | M80: =G82 -> 46.590595 | N80: 36.972258 | O80: 58.552199 | Q80: V | R80: =SUMIF($A$76:$A$93,"V",C$76:C$93) -> 310.03374 | S80: =SUMIF($A$76:$A$93,"V",D$76:D$93) -> 455.79074 | T80: =SUMIF($A$76:$A$93,"V",E$76:E$93) -> 487.5746 | U80: =SUMIF($A$76:$A$93,"V",F$76:F$93) -> 661.21361 | V80: =SUMIF($A$76:$A$93,"V",G$76:G$93) -> 1062.2431 | W80: =SUMIF($A$76:$A$93,"V",H$76:H$93) -> 1496.594 | X80: =SUMIF($A$76:$A$93,"V",I$76:I$93) -> 1629.7528 | Y80: =SUMIF($A$76:$A$93,"V",J$76:J$93) -> 1732.9532 | ... AA80: =SUMIF($A$76:$A$93,"V",L$76:L$93) -> 1942.6778
B81: Raw material % | C81: =C80/C14 -> 0.26112735 | D81: =D80/D14 -> 0.32004463 | E81: =E80/E14 -> 0.28593881 | F81: =F80/F14 -> 0.30096565 | G81: =G80/G14 -> 0.34443104 | H81: =H80/H14 -> 0.33217151 | I81: =HARMEAN(D81:H81) -> 0.31529259 | J81: =HARMEAN(E81:I81) -> 0.31435906 | K81: =HARMEAN(F81:J81) -> 0.3207348 | L81: =HARMEAN(G81:K81) -> 0.32500444 | M81: =G84 -> 22.899633 | N81: 15.214506 | O81: 18.768349
A82: V | B82: Spare parts and material | C82: 20.525288 | D82: 22.613961 | E82: 21.01795 | F82: 35.148212 | G82: 46.590595 | H82: =G82-N80+O80 -> 68.170536 | I82: =I83*I$14 -> 75.369013 | J82: =J83*J$14 -> 83.266451 | K82: =K83*K$14 -> 93.443223 | L82: =L83*L$14 -> 102.82467 | M82: =G86 -> 65.397347 | N82: 36.037977 | O82: 65.723798 | Q82: T | R82: =SUM(R78:R80) -> 513.58346 | S82: =SUM(S78:S80) -> 668.90952 | T82: =SUM(T78:T80) -> 763.90853 | U82: =SUM(U78:U80) -> 1016.4356 | V82: =SUM(V78:V80) -> 1485.0244 | W82: =SUM(W78:W80) -> 1992.7111 | X82: =SUM(X78:X80) -> 2200.9891 | Y82: =SUM(Y78:Y80) -> 2369.5565 | ... AA82: =SUM(AA78:AA80) -> 2701.1984
B83: Spare parts and material AVG % | C83: =C82/C14 -> 0.021376737 | D83: =D82/D14 -> 0.018142918 | E83: =E82/E14 -> 0.014163503 | F83: =F82/F14 -> 0.018283975 | G83: =G82/G14 -> 0.016827677 | H83: =HARMEAN(C83:G83) -> 0.017444678 | I83: =HARMEAN(D83:H83) -> 0.016825691 | J83: =HARMEAN(E83:I83) -> 0.016584869 | K83: =HARMEAN(F83:J83) -> 0.017172009 | L83: =HARMEAN(G83:K83) -> 0.01696565 | M83: =G88 -> 62.030249 | N83: 42.231266 | O83: 61.229931
A84: F | B84: Government fees and medical stamps | C84: 10.834657 | D84: 11.617092 | E84: 18.281611 | F84: 17.275521 | G84: 22.899633 | H84: =G84-N81+O81 -> 26.453476 | I84: =H84*(1+Assumptions!I5) -> 29.442719 | J84: =I84*(1+Assumptions!J5) -> 31.886464 | K84: =J84*(1+Assumptions!K5) -> 33.64022 | L84: =K84*(1+Assumptions!L5) -> 35.423152 | M84: =G90 -> 75.874291 | N84: 54.928131 | O84: 77.065698
B85: Government fees and medical stamps AVG % | C85: =C84/C14 -> 0.01128411 | D85: =D84/D14 -> 0.0093202577 | E85: =E84/E14 -> 0.012319548 | F85: =F84/F14 -> 0.0089866645 | G85: =G84/G14 -> 0.0082709317 | H85: =HARMEAN(C85:G85) -> 0.0098180418 | I85: =HARMEAN(D85:H85) -> 0.0095693847 | J85: =HARMEAN(E85:I85) -> 0.0096208168 | K85: =HARMEAN(F85:J85) -> 0.0092169999 | L85: =HARMEAN(G85:K85) -> 0.0092644912 | M85: =G91 -> 8.761148 | N85: 4.475882 | O85: 24.010418
A86: F | B86: other operating expense | C86: 44.520219 | D86: 48.126753 | E86: 46.148101 | F86: 70.15136 | G86: 65.397347 | H86: =G86-N82+O82 -> 95.083168 | I86: =I87*I$14 -> 105.00045 | J86: =J87*J$14 -> 117.6872 | K86: =K87*K$14 -> 127.55514 | L86: =L87*L$14 -> 142.06858 | M86: =G93 -> 43.922199 | N86: 33.134667 | O86: 45.503184
B87: other operating expense % | C87: =C86/C14 -> 0.046367049 | D87: =D86/D14 -> 0.038611534 | E87: =E86/E14 -> 0.031098121 | F87: =F86/F14 -> 0.036492488 | G87: =G86/G14 -> 0.023620335 | H87: =H86/H14 -> 0.023440736 | I87: =H87 -> 0.023440736 | J87: =I87 -> 0.023440736 | K87: =J87 -> 0.023440736 | L87: =K87 -> 0.023440736 | N87: =SUM(N77:N86) -> 968.85197 | O87: =SUM(O77:O86) -> 1574.5506 | Q87: COGS Per Unit
A88: V | B88: Energy expenses | C88: 38.78197 | D88: 34.262067 | E88: 42.237341 | F88: 47.503868 | G88: 62.030249 | H88: =G88-N83+O83 -> 81.028914 | I88: =I89*I$14 -> 89.48032 | J88: =J89*J$14 -> 100.29184 | K88: =K89*K$14 -> 108.7012 | L88: =L89*L$14 -> 121.06941 | R88: 2020 | S88: 2021 | T88: 2022 | U88: 2023 | V88: 2024 | W88: =+V88+1 -> 2025 | X88: =+W88+1 -> 2026 | Y88: =+X88+1 -> 2027 | Z88: =+Y88+1 -> 2028 | AA88: =+Z88+1 -> 2029
B89: Energy expenses % | C89: =C88/C14 -> 0.04039076 | D89: =D88/D14 -> 0.027488058 | E89: =E88/E14 -> 0.028462752 | F89: =F88/F14 -> 0.024711343 | G89: =G88/G14 -> 0.0224042 | H89: =H88/H14 -> 0.019975958 | I89: =H89 -> 0.019975958 | J89: =I89 -> 0.019975958 | K89: =J89 -> 0.019975958 | L89: =K89 -> 0.019975958
A90: F | B90: Depreciation and amortization | C90: 50.175532 | D90: 39.776868 | E90: 58.576291 | F90: 65.758528 | G90: 75.874291 | Q90: F | R90: =R78/SUM(C34:C37) -> 2.3470438 | S90: =S78/SUM(D34:D37) -> 2.2328261 | T90: =T78/SUM(E34:E37) -> 1.9063455 | U90: =U78/SUM(F34:F37) -> 3.0781827 | V90: =V78/SUM(G34:G37) -> 3.5379191 | W90: =W78/SUM(H34:H37) -> 3.2510952 | X90: =X78/SUM(I34:I37) -> 3.6982928 | Y90: =Y78/SUM(J34:J37) -> 3.9514231 | ... AA90: =AA78/SUM(L34:L37) -> 4.3981467
A91: F | B91: Rent | C91: 4.965466 | D91: 3.910976 | E91: 3.613147 | F91: 5.042077 | G91: 8.761148 | H91: =G91-N85+O85 -> 28.295684 | I91: =I92*I$14 -> 14.26519 | J91: =J92*J$14 -> 16.036722 | K91: =K92*K$14 -> 18.53766 | L91: =L92*L$14 -> 21.959315 | Q91: V | R91: =R80/SUM(C34:C37) -> 3.5748649 | S91: =S80/SUM(D34:D37) -> 4.775278 | T91: =T80/SUM(E34:E37) -> 3.363632 | U91: =U80/SUM(F34:F37) -> 5.7297589 | V91: =V80/SUM(G34:G37) -> 8.8890634 | W91: =W80/SUM(H34:H37) -> 9.8073002 | X91: =X80/SUM(I34:I37) -> 10.55133 | Y91: =Y80/SUM(J34:J37) -> 10.756513 | ... AA91: =AA80/SUM(L34:L37) -> 11.264273
B92: Rent % | C92: =C91/C14 -> 0.0051714481 | D92: =D91/D14 -> 0.0031377305 | E92: =E91/E14 -> 0.0024348149 | F92: =F91/F14 -> 0.0026228705 | G92: =G91/G14 -> 0.0031643676 | H92: =H91/H14 -> 0.0069756999 | I92: =HARMEAN(D92:H92) -> 0.0031846203 | J92: =HARMEAN(E92:I92) -> 0.0031941669 | K92: =HARMEAN(F92:J92) -> 0.0034066554 | L92: =HARMEAN(G92:K92) -> 0.0036231973
A93: F | B93: Maintenece | C93: 9.975115 | D93: 11.651609 | E93: 21.677732 | F93: 36.158059 | G93: 43.922199 | H93: =G93-N86+O86 -> 56.290716 | I93: =I94*I$14 -> 58.433504 | J93: =J94*J$14 -> 65.493773 | K93: =K94*K$14 -> 70.98535 | L93: =L94*L$14 -> 79.062187 | Q93: T | R93: =SUM(R90:R91) -> 5.9219087 | S93: =SUM(S90:S91) -> 7.0081041 | T93: =SUM(T90:T91) -> 5.2699775 | U93: =SUM(U90:U91) -> 8.8079416 | V93: =SUM(V90:V91) -> 12.426983 | W93: =SUM(W90:W91) -> 13.058395 | X93: =SUM(X90:X91) -> 14.249623 | Y93: =SUM(Y90:Y91) -> 14.707936 | ... AA93: =SUM(AA90:AA91) -> 15.662419
B94: Maintenece % | C94: =C93/C14 -> 0.010388912 | D94: =D93/D14 -> 0.0093479503 | E94: =E93/E14 -> 0.014608114 | F94: =F93/F14 -> 0.018809294 | G94: =G93/G14 -> 0.015863901 | H94: =H93/H14 -> 0.01387728 | I94: =HARMEAN(C94:H94) -> 0.013044938 | J94: =I94 -> 0.013044938 | K94: =J94 -> 0.013044938 | L94: =K94 -> 0.013044938
B95: Total | C95: =+C76+C78+C80+C82+C84+C86+C88+C90+C91+C93 -> 513.58346 | D95: =+D76+D78+D80+D82+D84+D86+D88+D90+D91+D93 -> 668.90952 | E95: =+E76+E78+E80+E82+E84+E86+E88+E90+E91+E93 -> 763.90853 | F95: =+F76+F78+F80+F82+F84+F86+F88+F90+F91+F93 -> 1016.4356 | G95: =+G76+G78+G80+G82+G84+G86+G88+G90+G91+G93 -> 1485.0244 | H95: =+H76+H78+H80+H82+H84+H86+H88+H90+H91+H93 -> 1992.7111 | I95: =+I76+I78+I80+I82+I84+I86+I88+I90+I91+I93 -> 2200.9891 | J95: =+J76+J78+J80+J82+J84+J86+J88+J90+J91+J93 -> 2369.5565 | ... L95: =+L76+L78+L80+L82+L84+L86+L88+L90+L91+L93 -> 2701.1984
B96: Total % | C96: =C77+C79+C81+C83+C85+C87+C89+C92+C94 -> 0.56915653 | D96: =D77+D79+D81+D83+D85+D87+D89+D92+D94 -> 0.50474581 | E96: =E77+E79+E81+E83+E85+E87+E89+E92+E94 -> 0.47530682 | F96: =F77+F79+F81+F83+F85+F87+F89+F92+F94 -> 0.49453882 | G96: =G77+G79+G81+G83+G85+G87+G89+G92+G94 -> 0.50895944 | H96: =H77+H79+H81+H83+H85+H87+H89+H92+H94 -> 0.51011113 | I96: =I77+I79+I81+I83+I85+I87+I89+I92+I94 -> 0.4823354 | J96: =J77+J79+J81+J83+J85+J87+J89+J92+J94 -> 0.48214525 | ... L96: =L77+L79+L81+L83+L85+L87+L89+L92+L94 -> 0.49203614
B97: Total from Revenue | C97: =C96*C14 -> 546.48666 | D97: =D96*D14 -> 629.13266 | E97: =E96*E14 -> 705.33224 | F97: =F96*F14 -> 950.67706 | G97: =G96*G14 -> 1409.1501 | H97: =H96*H14 -> 2069.1749 | I97: =I96*I14 -> 2160.5735 | J97: =J96*J14 -> 2420.6717 | ... L97: =L96*L14 -> 2982.111
B98: Inflation | G98: =G95-G90 -> 1409.1501 | H98: =G98*(1+Assumptions!H5) -> 1619.1135 | I98: =H98*(1+Assumptions!I5) -> 1802.0733 | J98: =I98*(1+Assumptions!J5) -> 1951.6454 | K98: =J98*(1+Assumptions!K5) -> 2058.9859 | L98: =K98*(1+Assumptions!L5) -> 2168.1122
B100: Raw Material Breakdown (assumed that 90% of raw material were imported) | C100: =C80*$B$101 -> 225.65383 | D100: =D80*$B$101 -> 359.02324 | E100: =E80*$B$101 -> 381.88738 | F100: =F80*$B$101 -> 520.70538 | G100: =G80*$B$101 -> 858.26001 | H100: =H80*$B$101 -> 1212.6551 | I100: =I80*$B$101 -> 1318.4131 | J100: =J80*$B$101 -> 1394.4554 | ... L100: =L80*$B$101 -> 1546.9054
B101: 0.9 | C101: =($B$101*C80)/Assumptions!C9 -> 14.387334 | D101: =($B$101*D80)/Assumptions!D9 -> 22.924522 | E101: =($B$101*E80)/Assumptions!E9 -> 15.467665 | F101: =($B$101*F80)/Assumptions!F9 -> 16.883325 | G101: =($B$101*G80)/Assumptions!G9 -> 16.89934 | H101: =($B$101*H80)/Assumptions!H9 -> 25.75186 | I101: =H101*(1+Assumptions!I3) -> 26.704679 | J101: =I101*(1+Assumptions!J3) -> 27.612638 | K101: =J101*(1+Assumptions!K3) -> 28.523855 | L101: =K101*(1+Assumptions!L3) -> 29.436619 | M101: $
B102: 0.1 | C102: =$B$102*C80 -> 25.072648 | D102: =$B$102*D80 -> 39.891471 | E102: =$B$102*E80 -> 42.431931 | F102: =$B$102*F80 -> 57.856153 | G102: =$B$102*G80 -> 95.362224 | H102: =$B$102*H80 -> 134.73946 | I102: =H102*(1+Assumptions!I5) -> 149.96502 | J102: =I102*(1+Assumptions!J5) -> 162.41211 | K102: =J102*(1+Assumptions!K5) -> 171.34478 | L102: =K102*(1+Assumptions!L5) -> 180.42605 | M102: EGP | Q102: Contribution Margin (Score)
B103: % of total COGS | C103: 2020 | D103: 2021 | E103: 2022 | F103: 2023 | G103: 2024 | H103: =G103+1 -> 2025 | I103: =H103+1 -> 2026 | J103: =I103+1 -> 2027 | K103: =J103+1 -> 2028 | L103: =K103+1 -> 2029 | R103: 2020 | S103: 2021 | T103: 2022 | U103: 2023 | V103: 2024 | W103: =+V103+1 -> 2025 | X103: =+W103+1 -> 2026 | Y103: =+X103+1 -> 2027 | Z103: =+Y103+1 -> 2028 | AA103: =+Z103+1 -> 2029
B105: Spain | C105: 0.1 | D105: 0.1 | E105: 0.1 | F105: 0.1 | G105: 0.1 | H105: 0.1 | I105: 0.1 | J105: 0.1 | K105: 0.1 | L105: 0.1
B106: China | C106: 0.3 | D106: 0.3 | E106: 0.3 | F106: 0.3 | G106: 0.3 | H106: 0.3 | I106: 0.3 | J106: 0.3 | K106: 0.3 | L106: 0.3
B107: India | C107: 0.6 | D107: 0.6 | E107: 0.6 | F107: 0.6 | G107: 0.6 | H107: 0.6 | I107: 0.6 | J107: 0.6 | K107: 0.6 | L107: 0.6
B108: Total | C108: =SUM(C105:C107) -> 1 | D108: =SUM(D105:D107) -> 1 | E108: =SUM(E105:E107) -> 1 | F108: =SUM(F105:F107) -> 1 | G108: =SUM(G105:G107) -> 1 | H108: =SUM(H105:H107) -> 1 | I108: =SUM(I105:I107) -> 1 | J108: =SUM(J105:J107) -> 1 | ... L108: =SUM(L105:L107) -> 1
A110: EUR | B110: Spain | C110: =C100*C105 -> 22.565383 | D110: =D100*D105 -> 35.902324 | E110: =E100*E105 -> 38.188738 | F110: =F100*F105 -> 52.070538 | G110: =G100*G105 -> 85.826001 | H110: =H100*H105 -> 121.26551 | I110: =I115*I116 -> 83.200696 | J110: =J115*J116 -> 94.431553 | K110: =K115*K116 -> 97.044646 | L110: =L115*L116 -> 97.510561
A111: $ | B111: China | C111: =C106*C100 -> 67.696149 | D111: =D106*D100 -> 107.70697 | E111: =E106*E100 -> 114.56621 | F111: =F106*F100 -> 156.21161 | G111: =G106*G100 -> 257.478 | H111: =H106*H100 -> 363.79653 | I111: =I117*Assumptions!I$9 -> 269.74631 | J111: =J117*Assumptions!J$9 -> 284.52549 | K111: =K117*Assumptions!K$9 -> 299.76622 | L111: =L117*Assumptions!L$9 -> 315.57852
A112: $ | B112: India | C112: =C107*C100 -> 135.3923 | D112: =D107*D100 -> 215.41394 | E112: =E107*E100 -> 229.13243 | F112: =F107*F100 -> 312.42323 | G112: =G107*G100 -> 514.95601 | H112: =H107*H100 -> 727.59307 | I112: =I118*Assumptions!I$9 -> 539.49262 | J112: =J118*Assumptions!J$9 -> 569.05099 | K112: =K118*Assumptions!K$9 -> 599.53243 | L112: =L118*Assumptions!L$9 -> 631.15704
B113: Total | C113: =SUM(C110:C112) -> 225.65383 | D113: =SUM(D110:D112) -> 359.02324 | E113: =SUM(E110:E112) -> 381.88738 | F113: =SUM(F110:F112) -> 520.70538 | G113: =SUM(G110:G112) -> 858.26001 | H113: =SUM(H110:H112) -> 1212.6551 | I113: =SUM(I110:I112) -> 892.43963 | J113: =SUM(J110:J112) -> 948.00803 | ... L113: =SUM(L110:L112) -> 1044.2461
A115: EUR | B115: Spain | C115: =C110/18.1 -> 1.2467062 | D115: =D110/18.55 -> 1.9354353 | E115: =E110/25.5 -> 1.4975976 | F115: =F110/33.3 -> 1.5636798 | G115: =G110/52.5 -> 1.634781 | H115: =G115*(1+Assumptions!H3) -> 1.7034418 | I115: =H115*(1+Assumptions!I3) -> 1.7664691 | J115: =I115*(1+Assumptions!J3) -> 1.8265291 | K115: =J115*(1+Assumptions!K3) -> 1.8868045 | L115: =K115*(1+Assumptions!L3) -> 1.9471823
...

Sheet BS-Breakdown
B1: Assest Breakdown
B2: Non-Current Assets Breakdown
B3: Fixed Assets Breakdown
B4: Beginning Balance | C4: 2020 | D4: 2021 | E4: 2022 | F4: 2023 | G4: 2024 | H4: 2025 | I4: 2026 | J4: 2027 | K4: 2028 | L4: 2029
B5: Freehold Land | C5: 18.637425 | D5: =C55 -> 18.637425 | E5: =D55 -> 18.637425 | F5: =E55 -> 18.637425 | G5: =F55 -> 18.637425 | H5: =G55 -> 18.637425 | I5: =H55 -> 18.637425 | J5: =I55 -> 18.637425 | K5: =J55 -> 18.637425 | L5: =K55 -> 18.637425
B6: Buildings | C6: 227.83557 | D6: =C56 -> 257.22539 | E6: =D56 -> 273.34111 | F6: =E56 -> 279.17253 | G6: =F56 -> 288.43279 | H6: =G56 -> 294.76843 | I6: =H56 -> 298.61083 | J6: =I56 -> 302.95727 | K6: =J56 -> 307.62968 | L6: =K56 -> 312.13581
B7: Machinery & equipment | C7: 313.60369 | D7: =C57 -> 397.71197 | E7: =D57 -> 414.7735 | F7: =E57 -> 444.85959 | G7: =F57 -> 482.79418 | H7: =G57 -> 530.79784 | I7: =H57 -> 543.39925 | J7: =I57 -> 555.9576 | K7: =J57 -> 569.59003 | L7: =K57 -> 583.62123
B8: Transportation & dragging equipment | C8: 12.411128 | D8: =C58 -> 13.025828 | E8: =D58 -> 13.369898 | F8: =E58 -> 16.305904 | G8: =F58 -> 16.060164 | H8: =G58 -> 18.226904 | I8: =H58 -> 19.532715 | J8: =I58 -> 20.932076 | K8: =J58 -> 22.43169 | L8: =K58 -> 24.03874
B9: Laboratory equipment | C9: 17.129924 | D9: =C59 -> 20.292443 | E9: =D59 -> 28.261762 | F9: =E59 -> 31.982677 | G9: =F59 -> 35.186599 | H9: =G59 -> 35.726446 | I9: =H59 -> 36.274576 | J9: =I59 -> 36.831115 | K9: =J59 -> 37.396193 | L9: =K59 -> 37.96994
B10: Tools | C10: 3.754591 | D10: =C60 -> 5.689305 | E10: =D60 -> 6.022977 | F10: =E60 -> 7.345392 | G10: =F60 -> 11.571461 | H10: =G60 -> 14.797847 | I10: =H60 -> 18.992541 | J10: =I60 -> 24.376291 | K10: =J60 -> 31.286154 | L10: =K60 -> 40.154732
B11: Office furniture & fixtures | C11: 21.797612 | D11: =C61 -> 25.385313 | E11: =D61 -> 29.123411 | F11: =E61 -> 33.1114 | G11: =F61 -> 39.423718 | H11: =G61 -> 46.76137 | I11: =H61 -> 54.226933 | J11: =I61 -> 62.88439 | K11: =J61 -> 72.924032 | L11: =K61 -> 84.566525
B12: Assets under construction | C12: 66.327646 | D12: =C62 -> 26.589818 | E12: =D62 -> 27.041385 | F12: =E62 -> 12.858215 | G12: =F62 -> 38.090575 | H12: =G62 -> 33.464541 | I12: =H62 -> 56.759477 | J12: =I62 -> 96.270204 | K12: =J62 -> 163.28467 | L12: =K62 -> 276.94843
B13: Total Beginning Balance | C13: =SUM(C5:C12) -> 681.49759 | D13: =SUM(D5:D12) -> 764.55749 | E13: =SUM(E5:E12) -> 810.57147 | F13: =SUM(F5:F12) -> 844.27314 | G13: =SUM(G5:G12) -> 930.19691 | H13: =SUM(H5:H12) -> 993.18081 | I13: =SUM(I5:I12) -> 1046.4337 | J13: =SUM(J5:J12) -> 1118.8464 | ... L13: =SUM(L5:L12) -> 1378.0728
B14: Additions
B15: =B5 -> Freehold Land | C15: 0 | D15: 0 | E15: 0 | F15: 0 | G15: 0 | H15: =H25*H5 -> 0 | I15: =I25*I5 -> 0 | J15: =J25*J5 -> 0 | K15: =K25*K5 -> 0 | L15: =L25*L5 -> 0
B16: =B6 -> Buildings | C16: 6.992398 | D16: 2.628798 | E16: 5.274519 | F16: 4.79919 | G16: 3.75981 | H16: =H26*H6 -> 3.842397 | I16: =I26*I6 -> 4.3464404 | J16: =J26*J6 -> 4.6724123 | K16: =K26*K6 -> 4.5061346 | L16: =L26*L6 -> 4.4133972
B17: =B7 -> Machinery & equipment | C17: 8.432595 | D17: 6.387704 | E17: 9.935733 | F17: 5.093589 | G17: 19.479544 | H17: =H27*H7 -> 12.601402 | I17: =I27*I7 -> 12.558349 | J17: =J27*J7 -> 13.632437 | K17: =K27*K7 -> 14.031195 | L17: =L27*L7 -> 15.915726
B18: =B8 -> Transportation & dragging equipment | C18: 0.6815 | D18: 0.34407 | E18: 1.898136 | F18: 0 | G18: 2.16674 | H18: =H28*H8 -> 1.3058106 | I18: =I28*I8 -> 1.3993614 | J18: =J28*J8 -> 1.4996143 | K18: =K28*K8 -> 1.6070496 | L18: =L28*L8 -> 1.7221817
B19: =B9 -> Laboratory equipment | C19: 2.974732 | D19: 3.454965 | E19: 2.181576 | F19: 3.203922 | G19: 0.539847 | H19: =H29*H9 -> 0.54812955 | I19: =I29*I9 -> 0.55653918 | J19: =J29*J9 -> 0.56507782 | K19: =K29*K9 -> 0.57374748 | L19: =L29*L9 -> 0.58255014
B20: =B10 -> Tools | C20: 1.293386 | D20: 0.357601 | E20: 1.333683 | F20: 4.226069 | G20: 3.280122 | H20: =H30*H10 -> 4.1946945 | I20: =I30*I10 -> 5.38375 | J20: =J30*J10 -> 6.909863 | K20: =K30*K10 -> 8.8685779 | L20: =L30*L10 -> 11.382523
B21: =B11 -> Office furniture & fixtures | C21: 4.572201 | D21: 1.310762 | E21: 4.145679 | F21: 5.345713 | G21: 9.18869 | H21: =H31*H11 -> 7.4655629 | I21: =I31*I11 -> 8.6574576 | J21: =J31*J11 -> 10.039641 | K21: =K31*K11 -> 11.642493 | L21: =L31*L11 -> 13.501245
B22: =B12 -> Assets under construction | C22: 60.038349 | D22: 38.187101 | E22: 9.606254 | F22: 68.376758 | G22: 26.515155 | H22: =H32*H12 -> 23.294936 | I22: =I32*I12 -> 39.510727 | J22: =J32*J12 -> 67.014462 | K22: =K32*K12 -> 113.66377 | L22: =L32*L12 -> 192.78603
B23: Total Additions | C23: =SUM(C15:C22) -> 84.985161 | D23: =SUM(D15:D22) -> 52.671001 | E23: =SUM(E15:E22) -> 34.37558 | F23: =SUM(F15:F22) -> 91.045241 | G23: =SUM(G15:G22) -> 64.929908 | H23: =SUM(H15:H22) -> 53.252932 | I23: =SUM(I15:I22) -> 72.412625 | J23: =SUM(J15:J22) -> 104.33351 | ... L23: =SUM(L15:L22) -> 240.30365
B25: =B15 -> Freehold Land | C25: =C15/C5 -> 0 | D25: =D15/D5 -> 0 | E25: =E15/E5 -> 0 | F25: =F15/F5 -> 0 | G25: =G15/G5 -> 0 | H25: =G25 -> 0 | I25: =H25 -> 0 | J25: =I25 -> 0 | K25: =J25 -> 0 | L25: =K25 -> 0
B26: =B16 -> Buildings | C26: =C16/C6 -> 0.030690545 | D26: =D16/D6 -> 0.010219823 | E26: =E16/E6 -> 0.019296472 | F26: =F16/F6 -> 0.017190767 | G26: =G16/G6 -> 0.013035307 | H26: =G26 -> 0.013035307 | I26: =AVERAGE(D26:H26) -> 0.014555535 | J26: =AVERAGE(E26:I26) -> 0.015422678 | K26: =AVERAGE(F26:J26) -> 0.014647919 | L26: =AVERAGE(G26:K26) -> 0.014139349
B27: =B17 -> Machinery & equipment | C27: =C17/C7 -> 0.026889336 | D27: =D17/D7 -> 0.016061131 | E27: =E17/E7 -> 0.023954599 | F27: =F17/F7 -> 0.01144988 | G27: =G17/G7 -> 0.040347512 | H27: =AVERAGE(C27:G27) -> 0.023740492 | I27: =AVERAGE(D27:H27) -> 0.023110723 | J27: =AVERAGE(E27:I27) -> 0.024520641 | K27: =AVERAGE(F27:J27) -> 0.02463385 | L27: =AVERAGE(G27:K27) -> 0.027270644
B28: =B18 -> Transportation & dragging equipment | C28: =C18/C8 -> 0.0549104 | D28: =D18/D8 -> 0.026414444 | E28: =E18/E8 -> 0.14197087 | F28: =F18/F8 -> 0 | G28: =G18/G8 -> 0.13491394 | H28: =AVERAGE(C28:G28) -> 0.07164193 | I28: =H28 -> 0.07164193 | J28: =I28 -> 0.07164193 | K28: =J28 -> 0.07164193 | L28: =K28 -> 0.07164193
B29: =B19 -> Laboratory equipment | C29: =C19/C9 -> 0.17365705 | D29: =D19/D9 -> 0.1702587 | E29: =E19/E9 -> 0.07719179 | F29: =F19/F9 -> 0.10017679 | G29: =G19/G9 -> 0.015342404 | H29: =G29 -> 0.015342404 | I29: =H29 -> 0.015342404 | J29: =I29 -> 0.015342404 | K29: =J29 -> 0.015342404 | L29: =K29 -> 0.015342404
B30: =B20 -> Tools | C30: =C20/C10 -> 0.3444812 | D30: =D20/D10 -> 0.062854953 | E30: =E20/E10 -> 0.22143252 | F30: =F20/F10 -> 0.57533607 | G30: =G20/G10 -> 0.28346654 | H30: =G30 -> 0.28346654 | I30: =H30 -> 0.28346654 | J30: =I30 -> 0.28346654 | K30: =J30 -> 0.28346654 | L30: =K30 -> 0.28346654
B31: =B21 -> Office furniture & fixtures | C31: =C21/C11 -> 0.20975697 | D31: =D21/D11 -> 0.05163466 | E31: =E21/E11 -> 0.14234868 | F31: =F21/F11 -> 0.1614463 | G31: =G21/G11 -> 0.23307518 | H31: =AVERAGE(C31:G31) -> 0.15965236 | I31: =H31 -> 0.15965236 | J31: =I31 -> 0.15965236 | K31: =J31 -> 0.15965236 | L31: =K31 -> 0.15965236
B32: =B22 -> Assets under construction | C32: =C22/C12 -> 0.90517835 | D32: =D22/D12 -> 1.436155 | E32: =E22/E12 -> 0.35524268 | F32: =F22/F12 -> 5.3177488 | G32: =G22/G12 -> 0.69610803 | H32: =G32 -> 0.69610803 | I32: =H32 -> 0.69610803 | J32: =I32 -> 0.69610803 | K32: =J32 -> 0.69610803 | L32: =K32 -> 0.69610803
B34: Transferred from Sales under Construction
B35: =B15 -> Freehold Land | C35: 0 | D35: 0 | E35: 0 | F35: 0 | G35: 0
B36: =B16 -> Buildings | C36: 22.397417 | D36: 13.48692 | E36: 0.556909 | F36: 4.461068 | G36: 2.575827
B37: =B17 -> Machinery & equipment | C37: 76.089143 | D37: 13.6396 | E37: 20.329505 | F37: 37.268407 | G37: 28.565362
B38: =B18 -> Transportation & dragging equipment | C38: 0 | D38: 0 | E38: 1.03787 | F38: 0 | G38: 0
B39: =B19 -> Laboratory equipment | C39: 0.526239 | D39: 7.93813 | E39: 1.811035 | F39: 0 | G39: 0
B40: =B20 -> Tools | C40: 0.645928 | D40: 0 | E40: 0 | F40: 0 | G40: 0
B41: =B21 -> Office furniture & fixtures | C41: 0.11745 | D41: 2.670884 | E41: 0.054105 | F41: 1.414923 | G41: 0
B42: =B22 -> Assets under construction | C42: -99.776177 | D42: -37.735534 | E42: -23.789424 | F42: -43.144398 | G42: -31.141189
B43: Total Construction | C43: =SUM(C35:C42) -> 0 | D43: =SUM(D35:D42) -> 0 | E43: =SUM(E35:E42) -> 0 | F43: =SUM(F35:F42) -> 0 | G43: =SUM(G35:G42) -> 0
B44: Disposals
B45: =B15 -> Freehold Land | C45: 0 | D45: 0 | E45: 0 | F45: 0 | G45: 0
B46: =B16 -> Buildings | C46: 0 | D46: 0 | E46: 0 | F46: 0 | G46: 0
B47: =B17 -> Machinery & equipment | C47: -0.413461 | D47: -2.965773 | E47: -0.17915 | F47: -4.427411 | G47: -0.041237
B48: =B18 -> Transportation & dragging equipment | C48: -0.0668 | D48: 0 | E48: 0 | F48: -0.24574 | G48: 0
B49: =B19 -> Laboratory equipment | C49: -0.338452 | D49: -3.423776 | E49: -0.271696 | F49: 0 | G49: 0
B50: =B20 -> Tools | C50: -0.0046 | D50: -0.023929 | E50: -0.011268 | F50: 0 | G50: -0.053736
B51: =B21 -> Office furniture & fixtures | C51: -1.10195 | D51: -0.243548 | E51: -0.211795 | F51: -0.448318 | G51: -1.851038
B52: =B22 -> Assets under construction | C52: 0 | D52: 0 | E52: 0 | F52: 0 | G52: 0
B53: Total Disposals | C53: =SUM(C45:C52) -> -1.925263 | D53: =SUM(D45:D52) -> -6.657026 | E53: =SUM(E45:E52) -> -0.673909 | F53: =SUM(F45:F52) -> -5.121469 | G53: =SUM(G45:G52) -> -1.946011
B54: Ending Balance
B55: =B45 -> Freehold Land | C55: =C5+C15+C45+C35 -> 18.637425 | D55: =D5+D15+D35+D45 -> 18.637425 | E55: =E5+E15+E35+E45 -> 18.637425 | F55: =F5+F15+F35+F45 -> 18.637425 | G55: =G5+G15+G45+G35 -> 18.637425 | H55: =H5+H15+H45+H35 -> 18.637425 | I55: =I5+I15+I45+I35 -> 18.637425 | J55: =J5+J15+J45+J35 -> 18.637425 | K55: =K5+K15+K45+K35 -> 18.637425 | L55: =L5+L15+L45+L35 -> 18.637425
B56: =B46 -> Buildings | C56: =C6+C16+C46+C36 -> 257.22539 | D56: =D6+D16+D36+D46 -> 273.34111 | E56: =E6+E16+E36+E46 -> 279.17253 | F56: =F6+F16+F36+F46 -> 288.43279 | G56: =G6+G16+G46+G36 -> 294.76843 | H56: =H6+H16+H46+H36 -> 298.61083 | I56: =I6+I16+I46+I36 -> 302.95727 | J56: =J6+J16+J46+J36 -> 307.62968 | K56: =K6+K16+K46+K36 -> 312.13581 | L56: =L6+L16+L46+L36 -> 316.54921
B57: =B47 -> Machinery & equipment | C57: =C7+C17+C47+C37 -> 397.71197 | D57: =D7+D17+D37+D47 -> 414.7735 | E57: =E7+E17+E37+E47 -> 444.85959 | F57: =F7+F17+F37+F47 -> 482.79418 | G57: =G7+G17+G47+G37 -> 530.79784 | H57: =H7+H17+H47+H37 -> 543.39925 | I57: =I7+I17+I47+I37 -> 555.9576 | J57: =J7+J17+J47+J37 -> 569.59003 | K57: =K7+K17+K47+K37 -> 583.62123 | L57: =L7+L17+L47+L37 -> 599.53695
B58: =B48 -> Transportation & dragging equipment | C58: =C8+C18+C48+C38 -> 13.025828 | D58: =D8+D18+D38+D48 -> 13.369898 | E58: =E8+E18+E38+E48 -> 16.305904 | F58: =F8+F18+F38+F48 -> 16.060164 | G58: =G8+G18+G48+G38 -> 18.226904 | H58: =H8+H18+H48+H38 -> 19.532715 | I58: =I8+I18+I48+I38 -> 20.932076 | J58: =J8+J18+J48+J38 -> 22.43169 | K58: =K8+K18+K48+K38 -> 24.03874 | L58: =L8+L18+L48+L38 -> 25.760922
B59: =B49 -> Laboratory equipment | C59: =C9+C19+C49+C39 -> 20.292443 | D59: =D9+D19+D39+D49 -> 28.261762 | E59: =E9+E19+E39+E49 -> 31.982677 | F59: =F9+F19+F39+F49 -> 35.186599 | G59: =G9+G19+G49+G39 -> 35.726446 | H59: =H9+H19+H49+H39 -> 36.274576 | I59: =I9+I19+I49+I39 -> 36.831115 | J59: =J9+J19+J49+J39 -> 37.396193 | K59: =K9+K19+K49+K39 -> 37.96994 | L59: =L9+L19+L49+L39 -> 38.55249
B60: =B50 -> Tools | C60: =C10+C20+C50+C40 -> 5.689305 | D60: =D10+D20+D40+D50 -> 6.022977 | E60: =E10+E20+E40+E50 -> 7.345392 | F60: =F10+F20+F40+F50 -> 11.571461 | G60: =G10+G20+G50+G40 -> 14.797847 | H60: =H10+H20+H50+H40 -> 18.992541 | I60: =I10+I20+I50+I40 -> 24.376291 | J60: =J10+J20+J50+J40 -> 31.286154 | K60: =K10+K20+K50+K40 -> 40.154732 | L60: =L10+L20+L50+L40 -> 51.537255
B61: =B51 -> Office furniture & fixtures | C61: =C11+C21+C51+C41 -> 25.385313 | D61: =D11+D21+D41+D51 -> 29.123411 | E61: =E11+E21+E41+E51 -> 33.1114 | F61: =F11+F21+F41+F51 -> 39.423718 | G61: =G11+G21+G51+G41 -> 46.76137 | H61: =H11+H21+H51+H41 -> 54.226933 | I61: =I11+I21+I51+I41 -> 62.88439 | J61: =J11+J21+J51+J41 -> 72.924032 | K61: =K11+K21+K51+K41 -> 84.566525 | L61: =L11+L21+L51+L41 -> 98.06777
B62: =B52 -> Assets under construction | C62: =C12+C22+C52+C42 -> 26.589818 | D62: =D12+D22+D42+D52 -> 27.041385 | E62: =E12+E22+E42+E52 -> 12.858215 | F62: =F12+F22+F42+F52 -> 38.090575 | G62: =G12+G22+G52+G42 -> 33.464541 | H62: =H12+H22+H52+H42 -> 56.759477 | I62: =I12+I22+I52+I42 -> 96.270204 | J62: =J12+J22+J52+J42 -> 163.28467 | K62: =K12+K22+K52+K42 -> 276.94843 | L62: =L12+L22+L52+L42 -> 469.73446
B63: Total Ending Balance | C63: =SUM(C55:C62) -> 764.55749 | D63: =SUM(D55:D62) -> 810.57147 | E63: =SUM(E55:E62) -> 844.27314 | F63: =SUM(F55:F62) -> 930.19691 | G63: =SUM(G55:G62) -> 993.18081 | H63: =SUM(H55:H62) -> 1046.4337 | I63: =SUM(I55:I62) -> 1118.8464 | J63: =SUM(J55:J62) -> 1223.1799 | ... L63: =SUM(L55:L62) -> 1618.3765
B64: Beginning Accumlated Depreciation
B65: =B55 -> Freehold Land | C65: 0 | D65: =C95 -> 0 | E65: =D95 -> 0 | F65: =E95 -> 0 | G65: =F95 -> 0 | H65: =G95 -> 0 | I65: =H95 -> 0 | J65: =I95 -> 0 | K65: =J95 -> 0 | L65: =K95 -> 0
B66: =B56 -> Buildings | C66: -50.634122 | D66: =C96 -> -57.853893 | E66: =D96 -> -66.075076 | F66: =E96 -> -74.889887 | G66: =F96 -> -84.033388 | H66: =G96 -> -93.620312 | I66: =H96 -> -103.3322 | J66: =I96 -> -113.05127 | K66: =J96 -> -122.95913 | L66: =K96 -> -133.05164
B67: =B57 -> Machinery & equipment | C67: -113.60146 | D67: =C97 -> -147.38161 | E67: =D97 -> -163.13541 | F67: =E97 -> -182.46048 | G67: =F97 -> -198.8037 | H67: =G97 -> -223.37229 | I67: =H97 -> -248.56614 | J67: =I97 -> -273.51417 | K67: =J97 -> -299.22986 | L67: =K97 -> -325.89384
B68: =B58 -> Transportation & dragging equipment | C68: -9.583519 | D68: =C98 -> -10.254249 | E68: =D98 -> -10.890741 | F68: =E98 -> -11.707422 | G68: =F98 -> -12.303486 | H68: =G98 -> -13.311924 | I68: =H98 -> -14.392608 | J68: =I98 -> -15.50805 | K68: =J98 -> -16.721369 | L68: =K98 -> -18.031672
B69: =B59 -> Laboratory equipment | C69: -8.559055 | D69: =C99 -> -9.971721 | E69: =D99 -> -8.406398 | F69: =E99 -> -11.027525 | G69: =F99 -> -14.143898 | H69: =G99 -> -17.434122 | I69: =H99 -> -20.774826 | J69: =I99 -> -24.092697 | K69: =J99 -> -27.484908 | L69: =K99 -> -30.949506
B70: =B60 -> Tools | C70: -1.309799 | D70: =C100 -> -1.728708 | E70: =D100 -> -2.234098 | F70: =E100 -> -2.818251 | G70: =F100 -> -3.642757 | H70: =G100 -> -4.740068 | I70: =H100 -> -6.2336098 | J70: =I100 -> -8.0987557 | K70: =J100 -> -10.464738 | L70: =K100 -> -13.545272
B71: =B61 -> Office furniture & fixtures | C71: -14.356886 | D71: =C101 -> -15.466027 | E71: =D101 -> -17.874916 | F71: =E101 -> -20.604244 | G71: =F101 -> -23.611916 | H71: =G101 -> -27.543933 | I71: =H101 -> -32.335557 | J71: =I101 -> -37.855178 | K71: =J101 -> -44.2497 | L71: =K101 -> -51.679946
B72: =B62 -> Assets under construction | C72: 0 | D72: =C102 -> 0 | E72: =D102 -> 0 | F72: =E102 -> 0 | G72: =F102 -> 0 | H72: =G102 -> 0 | I72: =H102 -> 0 | J72: =I102 -> 0 | K72: =J102 -> 0 | L72: =K102 -> 0
B73: Total Beg.Accumlated Depreciation | C73: =SUM(C65:C72) -> -198.04485 | D73: =SUM(D65:D72) -> -242.65621 | E73: =SUM(E65:E72) -> -268.61664 | F73: =SUM(F65:F72) -> -303.50781 | G73: =SUM(G65:G72) -> -336.53914 | H73: =SUM(H65:H72) -> -380.02265 | I73: =SUM(I65:I72) -> -425.63495 | J73: =SUM(J65:J72) -> -472.12012 | ... L73: =SUM(L65:L72) -> -573.15188
B74: Depreciation for the year
B75: =B65 -> Freehold Land | C75: 0 | D75: 0 | E75: 0 | F75: 0 | G75: 0 | H75: =IF(H65<H55,H55*H105,H55-H65) -> 0 | I75: =IF(I65<I55,I55*I105,I55-I65) -> 0 | J75: =IF(J65<J55,J55*J105,J55-J65) -> 0 | K75: =IF(K65<K55,K55*K105,K55-K65) -> 0 | L75: =IF(L65<L55,L55*L105,L55-L65) -> 0
B76: =B66 -> Buildings | C76: -7.219771 | D76: -8.221183 | E76: -8.814811 | F76: -9.143501 | G76: -9.586924 | H76: =IF(H66<H56,H56*H106,H56-H66) -> -9.7118925 | I76: =IF(I66<I56,I56*I106,I56-I66) -> -9.7190633 | J76: =IF(J66<J56,J56*J106,J56-J66) -> -9.9078618 | K76: =IF(K66<K56,K56*K106,K56-K66) -> -10.092514 | L76: =IF(L66<L56,L56*L106,L56-L66) -> -10.220191
B77: =B67 -> Machinery & equipment | C77: -34.09847 | D77: -18.065453 | E77: -19.475517 | F77: -20.755328 | G77: -24.609608 | H77: =IF(H67<H57,H57*H107,H57-H67) -> -25.193852 | I77: =IF(I67<I57,I57*I107,I57-I67) -> -24.948026 | J77: =IF(J67<J57,J57*J107,J57-J67) -> -25.715686 | K77: =IF(K67<K57,K57*K107,K57-K67) -> -26.663982 | L77: =IF(L67<L57,L57*L107,L57-L67) -> -27.28976
B78: =B68 -> Transportation & dragging equipment | C78: -0.73753 | D78: -0.636492 | E78: -0.816681 | F78: -0.841804 | G78: -1.008438 | H78: =IF(H68<H58,H58*H108,H58-H68) -> -1.0806844 | I78: =IF(I68<I58,I58*I108,I58-I68) -> -1.1154412 | J78: =IF(J68<J58,J58*J108,J58-J68) -> -1.2133192 | K78: =IF(K68<K58,K58*K108,K58-K68) -> -1.3103031 | L78: =IF(L68<L58,L58*L108,L58-L68) -> -1.3989017
B79: =B69 -> Laboratory equipment | C79: -1.662378 | D79: -1.787573 | E79: -2.800934 | F79: -3.116373 | G79: -3.290224 | H79: =IF(H69<H59,H59*H109,H59-H69) -> -3.3407039 | I79: =IF(I69<I59,I59*I109,I59-I69) -> -3.3178708 | J79: =IF(J69<J59,J59*J109,J59-J69) -> -3.3922109 | K79: =IF(K69<K59,K59*K109,K59-K69) -> -3.4645981 | L79: =IF(L69<L59,L59*L109,L59-L69) -> -3.5095696
B80: =B70 -> Tools | C80: -0.422819 | D80: -0.524798 | E80: -0.588204 | F80: -0.824506 | G80: -1.125958 | H80: =IF(H70<H60,H60*H110,H60-H70) -> -1.4935418 | I80: =IF(I70<I60,I60*I110,I60-I70) -> -1.8651459 | J80: =IF(J70<J60,J60*J110,J60-J70) -> -2.3659826 | K80: =IF(K70<K60,K60*K110,K60-K70) -> -3.080534 | L80: =IF(L70<L60,L60*L110,L60-L70) -> -3.9618444
B81: =B71 -> Office furniture & fixtures | C81: -2.189226 | D81: -2.641953 | E81: -2.917802 | F81: -3.429323 | G81: -4.097555 | H81: =IF(H71<H61,H61*H111,H61-H71) -> -4.7916242 | I81: =IF(I71<I61,I61*I111,I61-I71) -> -5.5196211 | J81: =IF(J71<J61,J61*J111,J61-J71) -> -6.3945217 | K81: =IF(K71<K61,K61*K111,K61-K71) -> -7.4302456 | L81: =IF(L71<L61,L61*L111,L61-L71) -> -8.622283
B82: =B72 -> Assets under construction | C82: 0 | D82: 0 | E82: 0 | F82: 0 | G82: 0 | H82: =IF(H72<H62,H62*H112,H62-H72) -> 0 | I82: =IF(I72<I62,I62*I112,I62-I72) -> 0 | J82: =IF(J72<J62,J62*J112,J62-J72) -> 0 | K82: =IF(K72<K62,K62*K112,K62-K72) -> 0 | L82: =IF(L72<L62,L62*L112,L62-L72) -> 0
B83: Total Depreciation | C83: =SUM(C75:C82) -> -46.330194 | D83: =SUM(D75:D82) -> -31.877452 | E83: =SUM(E75:E82) -> -35.413949 | F83: =SUM(F75:F82) -> -38.110835 | G83: =SUM(G75:G82) -> -43.718707 | H83: =SUM(H75:H82) -> -45.612299 | I83: =SUM(I75:I82) -> -46.485168 | J83: =SUM(J75:J82) -> -48.989582 | ... L83: =SUM(L75:L82) -> -55.00255
B84: Disposals for Depreciation | C84: TRUE | D84: TRUE | E84: TRUE | F84: TRUE | G84: TRUE
B85: =B75 -> Freehold Land | C85: 0 | D85: 0 | E85: 0 | F85: 0 | G85: 0
B86: =B76 -> Buildings | C86: 0 | D86: 0 | E86: 0 | F86: 0 | G86: 0
B87: =B77 -> Machinery & equipment | C87: 0.318322 | D87: 2.311656 | E87: 0.150442 | F87: 4.412116 | G87: 0.041012
B88: =B78 -> Transportation & dragging equipment | C88: 0.0668 | D88: 0 | E88: 0 | F88: 0.24574 | G88: 0
B89: =B79 -> Laboratory equipment | C89: 0.249712 | D89: 3.352896 | E89: 0.179807 | F89: 0 | G89: 0
B90: =B80 -> Tools | C90: 0.00391 | D90: 0.019408 | E90: 0.004051 | F90: 0 | G90: 0.028647
B91: =B81 -> Office furniture & fixtures | C91: 1.080085 | D91: 0.233064 | E91: 0.188474 | F91: 0.421651 | G91: 0.165538
B92: =B82 -> Assets under construction | C92: 0 | D92: 0 | E92: 0 | F92: 0 | G92: 0
B93: Total Disposals | C93: =SUM(C85:C92) -> 1.718829 | D93: =SUM(D85:D92) -> 5.917024 | E93: =SUM(E85:E92) -> 0.522774 | F93: =SUM(F85:F92) -> 5.079507 | G93: =SUM(G85:G92) -> 0.235197
B94: Ending Accumlated Deprciation
B95: =B85 -> Freehold Land | C95: =C65+C75+C85 -> 0 | D95: =D65+D75+D85 -> 0 | E95: =E65+E75+E85 -> 0 | F95: =F65+F75+F85 -> 0 | G95: =G65+G75+G85 -> 0 | H95: =H65+H75+H85 -> 0 | I95: =I65+I75+I85 -> 0 | J95: =J65+J75+J85 -> 0 | ... L95: =L65+L75+L85 -> 0
B96: =B86 -> Buildings | C96: =C66+C76+C86 -> -57.853893 | D96: =D66+D76+D86 -> -66.075076 | E96: =E66+E76+E86 -> -74.889887 | F96: =F66+F76+F86 -> -84.033388 | G96: =G66+G76+G86 -> -93.620312 | H96: =H66+H76+H86 -> -103.3322 | I96: =I66+I76+I86 -> -113.05127 | J96: =J66+J76+J86 -> -122.95913 | ... L96: =L66+L76+L86 -> -143.27183
B97: =B87 -> Machinery & equipment | C97: =C67+C77+C87 -> -147.38161 | D97: =D67+D77+D87 -> -163.13541 | E97: =E67+E77+E87 -> -182.46048 | F97: =F67+F77+F87 -> -198.8037 | G97: =G67+G77+G87 -> -223.37229 | H97: =H67+H77+H87 -> -248.56614 | I97: =I67+I77+I87 -> -273.51417 | J97: =J67+J77+J87 -> -299.22986 | ... L97: =L67+L77+L87 -> -353.1836
B98: =B88 -> Transportation & dragging equipment | C98: =C68+C78+C88 -> -10.254249 | D98: =D68+D78+D88 -> -10.890741 | E98: =E68+E78+E88 -> -11.707422 | F98: =F68+F78+F88 -> -12.303486 | G98: =G68+G78+G88 -> -13.311924 | H98: =H68+H78+H88 -> -14.392608 | I98: =I68+I78+I88 -> -15.50805 | J98: =J68+J78+J88 -> -16.721369 | ... L98: =L68+L78+L88 -> -19.430574
B99: =B89 -> Laboratory equipment | C99: =C69+C79+C89 -> -9.971721 | D99: =D69+D79+D89 -> -8.406398 | E99: =E69+E79+E89 -> -11.027525 | F99: =F69+F79+F89 -> -14.143898 | G99: =G69+G79+G89 -> -17.434122 | H99: =H69+H79+H89 -> -20.774826 | I99: =I69+I79+I89 -> -24.092697 | J99: =J69+J79+J89 -> -27.484908 | ... L99: =L69+L79+L89 -> -34.459075
B100: =B90 -> Tools | C100: =C70+C80+C90 -> -1.728708 | D100: =D70+D80+D90 -> -2.234098 | E100: =E70+E80+E90 -> -2.818251 | F100: =F70+F80+F90 -> -3.642757 | G100: =G70+G80+G90 -> -4.740068 | H100: =H70+H80+H90 -> -6.2336098 | I100: =I70+I80+I90 -> -8.0987557 | J100: =J70+J80+J90 -> -10.464738 | ... L100: =L70+L80+L90 -> -17.507117
B101: =B91 -> Office furniture & fixtures | C101: =C71+C81+C91 -> -15.466027 | D101: =D71+D81+D91 -> -17.874916 | E101: =E71+E81+E91 -> -20.604244 | F101: =F71+F81+F91 -> -23.611916 | G101: =G71+G81+G91 -> -27.543933 | H101: =H71+H81+H91 -> -32.335557 | I101: =I71+I81+I91 -> -37.855178 | J101: =J71+J81+J91 -> -44.2497 | ... L101: =L71+L81+L91 -> -60.302229
B102: =B92 -> Assets under construction | C102: =C72+C82+C92 -> 0 | D102: =D72+D82+D92 -> 0 | E102: =E72+E82+E92 -> 0 | F102: =F72+F82+F92 -> 0 | G102: =G72+G82+G92 -> 0 | H102: =H72+H82+H92 -> 0 | I102: =I72+I82+I92 -> 0 | J102: =J72+J82+J92 -> 0 | ... L102: =L72+L82+L92 -> 0
...

Sheet Assumptions
A2: Economy & Market Assumptions | B2: Scale | C2: 2020 | D2: =C2+1 -> 2021 | E2: =D2+1 -> 2022 | F2: =E2+1 -> 2023 | G2: =F2+1 -> 2024 | H2: =G2+1 -> 2025 | I2: =H2+1 -> 2026 | J2: =I2+1 -> 2027 | K2: =J2+1 -> 2028 | L2: =K2+1 -> 2029
A3: World Inflation | B3: % | C3: 0.033 | D3: 0.047 | E3: 0.087 | F3: 0.067 | G3: 0.058 | H3: 0.042 | I3: 0.037 | J3: 0.034 | K3: 0.033 | L3: 0.032
A4: MENA Inflation | B4: % | C4: 0.102 | D4: 0.117 | E4: 0.132 | F4: 0.117 | G4: 0.109 | H4: 0.104 | I4: 0.102 | J4: 0.087 | K4: 0.077 | L4: 0.069 | M4: Forecasting Exports (ASP)
A5: Egypt Inflation | B5: % | C5: 0.057 | D5: 0.049 | E5: 0.132 | F5: 0.357 | G5: 0.275 | H5: 0.149 | I5: 0.113 | J5: 0.083 | K5: 0.055 | L5: 0.053 | M5: anhy asah? correlation or R2
A6: Central Bank Policy Rate | B6: % | C6: 0.10262 | D6: 0.1004 | E6: 0.1633 | F6: 0.19365 | G6: 0.27335 | H6: 0.21 | I6: 0.1125 | J6: 0.0825 | K6: 0.0825 | L6: 0.0825
A7: Borrowing rate | B7: % | C7: =C6-1% -> 0.09262 | D7: =D6-1% -> 0.0904 | E7: =E6-1% -> 0.1533 | F7: =F6-1% -> 0.18365 | G7: =G6-1% -> 0.26335 | H7: =H6-1% -> 0.2 | I7: =I6-1% -> 0.1025 | J7: =J6-1% -> 0.0725 | ... L7: =L6-1% -> 0.0725
A8: Real Interest Rate | B8: % | C8: =C6-C5 -> 0.04562 | D8: =D6-D5 -> 0.0514 | E8: =E6-E5 -> 0.0313 | F8: =F6-F5 -> -0.16335 | G8: =G6-G5 -> -0.00165 | H8: =H6-H5 -> 0.061 | I8: =I6-I5 -> -0.0005 | J8: =J6-J5 -> -0.0005 | ... L8: =L6-L5 -> 0.0295
A9: Exchange Rate Per USD | B9: EGP | C9: 15.6842 | D9: 15.6611 | E9: 24.6894 | F9: 30.8414 | G9: 50.7866 | H9: 47.09 | I9: 49.24 | J9: 50.23 | K9: 51.23 | L9: 52.26 | M9: used in forecasting asp tender, ps,
A10: Nominal GDP USD | B10: USDbn | C10: 383.82 | D10: 424.67 | E10: 476.75 | F10: 395.93 | G10: 389.06 | H10: 324.5 | I10: 382.5 | J10: 422.3 | K10: 463.4 | L10: 508.5
A11: Nominal GDP | B11: EGPbn | C11: =C10*C9 -> 6019.9096 | D11: =D10*D9 -> 6650.7993 | E11: =E10*E9 -> 11770.671 | F11: =F10*F9 -> 12211.036 | G11: =G10*G9 -> 19759.035 | H11: 15822.62 | I11: 18834.3 | J11: 21212.129 | K11: 23739.982 | L11: 26574.21
A12: Real GDP | B12: EGPTn | C12: =C25/C19 -> 6159.4495 | D12: =D25/D19 -> 6679.2638 | E12: =E25/E19 -> 7853.1288 | F12: =F25/F19 -> 10158.539 | G12: =G25/G19 -> 13942.892 | H12: =H25/H19 -> 16421.508 | I12: =I25/I19 -> 19170.417 | J12: =J25/J19 -> 21453.438 | ... L12: =L25/L19 -> 26720.069
A13: Real GDP | B13: % | C13: 0.03573 | D13: 0.03253 | E13: 0.06653 | F13: 0.03759 | G13: 0.02672 | H13: 0.043 | I13: 0.045 | J13: 0.047 | K13: 0.049 | L13: 0.051
A14: MENA GDP Per Capita | B14: USD K | C14: 9.79 | D14: 12.01 | E14: 14.42 | F14: 13.83 | G14: 13.87 | H14: 13.79 | I14: 14.28 | J14: 14.85 | K14: 15.43 | L14: 15.97
H15: =150/12 -> 12.5 | L15: =L11/K11-1 -> 0.11938627
A17: Industry Assumptions | B17: Scale | C17: 2020 | D17: =C17+1 -> 2021 | E17: =D17+1 -> 2022 | F17: =E17+1 -> 2023 | G17: =F17+1 -> 2024 | H17: =G17+1 -> 2025 | I17: =H17+1 -> 2026 | J17: =I17+1 -> 2027 | K17: =J17+1 -> 2028 | L17: =K17+1 -> 2029
A18: Pharmaceutical Sales, % of health expenditure | B18: % | C18: 0.252 | D18: 0.354 | E18: 0.347 | F18: 0.385 | G18: 0.37 | H18: 0.391 | I18: 0.368 | J18: 0.35 | K18: 0.332 | L18: 0.316
A19: Pharmaceutical Sales, % of GDP | B19: % | C19: 0.0109 | D19: 0.0163 | E19: 0.0163 | F19: 0.0178 | G19: 0.0166 | H19: 0.0179 | I19: 0.0168 | J19: 0.016 | K19: 0.0152 | L19: 0.0144
A20: Pharmaceutical Sales, EGP per capita | B20: EGP | C20: 624.7 | D20: 996.4 | E20: 1153.3 | F20: 1604.2 | G20: 2021.7 | H20: 2528 | I20: 2728 | J20: 2864.3 | K20: 2990.3 | L20: 3118.5 | M20: used in forecasting vs toll,ps,X
A21: Patented Drug Sales | B21: EGPbn | C21: 17.928 | D21: 26.168 | E21: 28.108 | F21: 37.408 | G21: 39.347 | H21: 56.136 | I21: 61.068 | J21: 64.743 | K21: 68.226 | L21: 71.804
A22: Generic drug sales, EGPbn | B22: EGPbn | C22: 38.046 | D22: 66.262 | E22: 81.023 | F22: 117.534 | G22: 145.815 | H22: 187.838 | I22: 206.456 | J22: 220.734 | K22: 234.584 | L22: 248.983
A23: Prescription drug sales | B23: EGPbn | C23: =+C21+C22 -> 55.974 | D23: =+D21+D22 -> 92.43 | E23: =+E21+E22 -> 109.131 | F23: =+F21+F22 -> 154.942 | G23: =+G21+G22 -> 185.162 | H23: =+H21+H22 -> 243.974 | I23: =+I21+I22 -> 267.524 | J23: =+J21+J22 -> 285.477 | ... L23: =+L21+L22 -> 320.787
A24: OTC medicine sales, EGPbn (over-the-counter) | B24: EGPbn | C24: 11.164 | D24: 16.442 | E24: 18.875 | F24: 25.88 | G24: 46.29 | H24: 49.971 | I24: 54.539 | J24: 57.778 | K24: 60.841 | L24: 63.982 | M24: =_xlfn.RRI(4,H25,L25) -> 0.069629813
A25: Total Pharmaceutical Sales | B25: EGPbn | C25: =+C23+C24 -> 67.138 | D25: =+D23+D24 -> 108.872 | E25: =+E23+E24 -> 128.006 | F25: =+F23+F24 -> 180.822 | G25: =+G23+G24 -> 231.452 | H25: =+H23+H24 -> 293.945 | I25: =+I23+I24 -> 322.063 | J25: =+J23+J24 -> 343.255 | ... L25: =+L23+L24 -> 384.769 | M25: Used in CAGR | O25: Y.o.Y | P25: =H25/G25-1 -> 0.27000415 | Q25: leh el market ahsn mn rmda?
A26: Health Expenditure | B26: EGPbn | C26: =C25/C18 -> 266.42063 | D26: =D25/D18 -> 307.54802 | E26: =E25/E18 -> 368.89337 | F26: =F25/F18 -> 469.66753 | G26: =G25/G18 -> 625.54595 | H26: =H25/H18 -> 751.77749 | I26: =I25/I18 -> 875.1712 | J26: =J25/J18 -> 980.72857 | ... L26: =L25/L18 -> 1217.6234 | M26: used in forecasting vs tender
G27: =_xlfn.RRI(COLUMNS(C26:G26),C26,G26) -> 0.18614633
A29: Patented Drug Sales (%) | B29: % | C29: =C21/C23 -> 0.32029156 | D29: =D21/D23 -> 0.28311154 | E29: =E21/E23 -> 0.25756201 | F29: =F21/F23 -> 0.24143228 | G29: =G21/G23 -> 0.21250041 | H29: =H21/H23 -> 0.23009009 | I29: =I21/I23 -> 0.22827111 | J29: =J21/J23 -> 0.22678885 | ... L29: =L21/L23 -> 0.223837
A30: Generic drug sales, EGPbn (%) | B30: % | C30: =C22/C23 -> 0.67970844 | D30: =D22/D23 -> 0.71688846 | E30: =E22/E23 -> 0.74243799 | F30: =F22/F23 -> 0.75856772 | G30: =G22/G23 -> 0.78749959 | H30: =H22/H23 -> 0.76990991 | I30: =I22/I23 -> 0.77172889 | J30: =J22/J23 -> 0.77321115 | ... L30: =L22/L23 -> 0.776163
A31: Prescription drug sales | B31: % | C31: =SUM(C29:C30) -> 1 | D31: =SUM(D29:D30) -> 1 | E31: =SUM(E29:E30) -> 1 | F31: =SUM(F29:F30) -> 1 | G31: =SUM(G29:G30) -> 1 | H31: =SUM(H29:H30) -> 1 | I31: =SUM(I29:I30) -> 1 | J31: =SUM(J29:J30) -> 1 | ... L31: =SUM(L29:L30) -> 1
A33: Pharmaceutical Trade Assumptions | B33: Scale | C33: 2020 | D33: =C33+1 -> 2021 | E33: =D33+1 -> 2022 | F33: =E33+1 -> 2023 | G33: =F33+1 -> 2024 | H33: =G33+1 -> 2025 | I33: =H33+1 -> 2026 | J33: =I33+1 -> 2027 | K33: =J33+1 -> 2028 | L33: =K33+1 -> 2029
A34: Pharmaceutical Exports | B34: EGPMn | C34: 5235.9 | D34: 6082.4 | E34: 6977.92 | F34: 8812.17 | G34: 13984.52 | H34: 17327.71 | I34: 19367.68 | J34: 21553.67 | K34: 23838.22 | L34: 26257.23
A35: Pharmaceutical Imports | B35: EGPMn | C35: 22578.1 | D35: 23687.68 | E35: 24889.61 | F35: 108580.22 | G35: 138982.68 | H35: 163989.09 | I35: 172939.98 | J35: 180968.15 | K35: 189137.01 | L35: 197804.9 | N35: CAGR Phrmaceutical | Q35: =_xlfn.RRI(4,H25,L25) -> 0.069629813 | R35: For cosmetic forecasting
A36: Pharmaceutical Trade Balance | B36: EGPMn | C36: =C34-C35 -> -17342.2 | D36: =D34-D35 -> -17605.28 | E36: =E34-E35 -> -17911.69 | F36: =F34-F35 -> -99768.05 | G36: =G34-G35 -> -124998.16 | H36: =H34-H35 -> -146661.38 | I36: =I34-I35 -> -153572.3 | J36: =J34-J35 -> -159414.48 | ... L36: =L34-L35 -> -171547.67 | N36: CAGR Non-essentials | Q36: =_xlfn.RRI(4,H44,L44) -> 0.11760104
D37: =D34/D$36 -> -0.34548726 | N37: CAGR personal care | Q37: =_xlfn.RRI(4,H50,L50) -> 0.1143772
A38: Pharmaceutical Exports (%) | B38: % | C38: =C34/C$36 -> -0.30191671 | E38: =E34/E$36 -> -0.38957351 | F38: =F34/F$36 -> -0.088326573 | G38: =G34/G$36 -> -0.11187781 | H38: =H34/H$36 -> -0.11814774 | I38: =I34/I$36 -> -0.12611441 | J38: =J34/J$36 -> -0.13520522 | K38: =K34/K$36 -> -0.14421291 | L38: =L34/L$36 -> -0.15306084
A39: Pharmaceutical Imports (%) | B39: % | C39: =-C35/C$36 -> 1.3019167 | D39: =-D35/D$36 -> 1.3454873 | E39: =-E35/E$36 -> 1.3895735 | F39: =-F35/F$36 -> 1.0883266 | G39: =-G35/G$36 -> 1.1118778 | H39: =-H35/H$36 -> 1.1181477 | I39: =-I35/I$36 -> 1.1261144 | J39: =-J35/J$36 -> 1.1352052 | ... L39: =-L35/L$36 -> 1.1530608
A40: Pharmaceutical Trade Balance (%) | B40: % | C40: =SUM(C38:C39) -> 1 | D40: =SUM(D37:D39) -> 1 | E40: =SUM(E38:E39) -> 1 | F40: =SUM(F38:F39) -> 1 | G40: =SUM(G38:G39) -> 1 | H40: =SUM(H38:H39) -> 1 | I40: =SUM(I38:I39) -> 1 | J40: =SUM(J38:J39) -> 1 | K40: =SUM(K38:K39) -> 1 | L40: =SUM(L38:L39) -> 1
I41: =FORECAST(,'IS- Breakdown'!F37:H37,Assumptions!F20:H20) -> 31.674276
A42: Consumer Spending Assumptions | B42: Scale | C42: 2020 | D42: =C42+1 -> 2021 | E42: =D42+1 -> 2022 | F42: =E42+1 -> 2023 | G42: =F42+1 -> 2024 | H42: =G42+1 -> 2025 | I42: =H42+1 -> 2026 | J42: =I42+1 -> 2027 | K42: =J42+1 -> 2028 | L42: =K42+1 -> 2029
A43: Household Essential Spending | B43: EGPBn | C43: 1458 | D43: 1653.5 | E43: 4294.4 | F43: 5695.6 | G43: 8107.2 | H43: 9834.2 | I43: 11345.7 | J43: 12609.9 | K43: 14013.6 | L43: 15572.1
A44: Household Non-Essential Spending | B44: EGPBn | C44: 793 | D44: 907.4 | E44: 2176.9 | F44: 2824.1 | G44: 3936.2 | H44: 4733.6 | I44: 5431.8 | J44: 6016.3 | K44: 6665 | L44: 7384.8 | M44: Used in CAGR
A45: Total Household Spending | B45: EGPBn | C45: =C43+C44 -> 2251 | D45: =D43+D44 -> 2560.9 | E45: =E43+E44 -> 6471.3 | F45: =F43+F44 -> 8519.7 | G45: =G43+G44 -> 12043.4 | H45: =H43+H44 -> 14567.8 | I45: =I43+I44 -> 16777.5 | J45: =J43+J44 -> 18626.2 | ... L45: =L43+L44 -> 22956.9
A46: Household Goods Spending | B46: EGPBn | C46: 48.64 | D46: 55.42 | E46: 130.95 | F46: 180.71 | G46: 258.25 | H46: 313.79 | I46: 362.41 | J46: 403.08 | K46: 448.23 | L46: 498.36
A47: Household Goods Spending, EGP Per Household | B47: EGP | C47: 1856.75 | D47: 2059.38 | E47: 4571.74 | F47: 6188.57 | G47: 8673.4 | H47: 10335.99 | I47: 11710.99 | J47: 12781.49 | K47: 13950.78 | L47: 15227.7
A48: Household Goods Spending, EGP Per Capita | B48: EGP | C48: 472.46 | D48: 529.4 | E48: 1179.8 | F48: 1603.26 | G48: 2255.76 | H48: 2698.69 | I48: 3069.72 | J48: 3363.55 | K48: 3685.81 | L48: 4039.18
A50: Personal Care Products Spending | B50: EGPBn | C50: 21.02 | D50: 23.84 | E50: 149.69 | F50: 199.73 | G50: 274.02 | H50: 327.34 | I50: 374.07 | J50: 413.23 | K50: 456.65 | L50: 504.81 | M50: Used in CAGR
A51: Personal Effects Product Spending | B51: EGPBn | C51: 3.68 | D51: 3.79 | E51: 30.93 | F51: 38.32 | G51: 49.78 | H51: 58.01 | I51: 65.22 | J51: 71.26 | K51: 77.96 | L51: 85.4
A52: Total Personal Care & Effects Spending | B52: EGPBn | C52: =SUM(C50:C51) -> 24.7 | D52: =SUM(D50:D51) -> 27.63 | E52: =SUM(E50:E51) -> 180.62 | F52: =SUM(F50:F51) -> 238.05 | G52: =SUM(G50:G51) -> 323.8 | H52: =SUM(H50:H51) -> 385.35 | I52: =SUM(I50:I51) -> 439.29 | J52: =SUM(J50:J51) -> 484.49 | ... L52: =SUM(L50:L51) -> 590.21
A53: Personal Care & Effect Spending, EGP per household | B53: EGP | C53: 942.83 | D53: 1026.52 | E53: 6306.13 | F53: 8152.13 | G53: 10874.88 | H53: 12693.24 | I53: 14195.45 | J53: 15362.89 | K53: 16639.2 | L53: 18034.1
A54: Personal Care & Effect Spending, EGP per Capita | B54: EGP | C54: 239.91 | D54: 263.89 | E54: 1627.39 | F54: 2111.95 | G54: 2828.32 | H54: 3314.16 | I54: 3720.96 | J54: 4042.87 | K54: 4396.09 | L54: 4783.58
A56: Population | B56: Mn | C56: 107.47 | D56: 109.17208 | E56: 110.90618 | F56: 112.66782 | G56: 114.45745 | H56: 116.2755 | I56: 118.06 | J56: 119.84 | K56: 121.61 | L56: 123.38
A57: Population, 40-64 years | C57: 23419.3 | D57: 24127.749 | E57: 24857.735 | F57: 25609.806 | G57: 26384.632 | H57: 27182.9 | I57: 28144 | J57: 29139 | K57: 30169 | L57: 31234.9
A58: GDP Per Capita | C58: =C12/C56 -> 57.313199 | D58: =D12/D56 -> 61.18106 | E58: =E12/E56 -> 70.808757 | F58: =F12/F56 -> 90.163624 | G58: =G12/G56 -> 121.81725 | H58: =H12/H56 -> 141.22931 | I58: =I12/I56 -> 162.37859 | J58: =J12/J56 -> 179.01734 | ... L58: =L12/L56 -> 216.56727 | M58: For volume forecasting
A60: Inflations for fixed cost forecasting | B60: Scale | C60: 2020 | D60: =C60+1 -> 2021 | E60: =D60+1 -> 2022 | F60: =E60+1 -> 2023 | G60: =F60+1 -> 2024 | H60: =G60+1 -> 2025 | I60: =H60+1 -> 2026 | J60: =I60+1 -> 2027 | K60: =J60+1 -> 2028 | L60: =K60+1 -> 2029
A61: General Inflation (CPI) | B61: % | H61: 0.16 | I61: 0.11 | J61: 0.09 | K61: 0.07 | L61: 0.06 | N61: ik gemini bs where is the defend?
A62: Wage Inflation | B62: % | H62: 0.22 | I62: 0.15 | J62: 0.12 | K62: 0.1 | L62: 0.08
A63: Electricity Price Hike | B63: % | H63: 0.1 | I63: 0.25 | J63: 0.1 | K63: 0.05 | L63: 0.05
A64: Tech/Import Inflation | B64: % | H64: 0.15 | I64: 0.1 | J64: 0.06 | K64: 0.04 | L64: 0.03
A65: Rent Escalation | B65: % | H65: 0.05 | I65: 0.05 | J65: 0.05 | K65: 0.05 | L65: 0.05

Sheet Revenue Bridge
B1: Revenue Bridge
B3: Average Selling Prices | C3: 2020 | D3: 2021 | E3: 2022 | F3: 2023 | G3: 2024 | H3: =G3+1 -> 2025 | I3: =H3+1 -> 2026 | J3: =I3+1 -> 2027 | K3: =J3+1 -> 2028 | L3: =K3+1 -> 2029
B4: ASP (Tender) | C4: ='IS- Breakdown'!C$48 -> 6.6068439 | D4: ='IS- Breakdown'!D$48 -> 9.4854414 | E4: ='IS- Breakdown'!E$48 -> 9.8464592 | F4: ='IS- Breakdown'!F$48 -> 14.463395 | G4: ='IS- Breakdown'!G$48 -> 29.18895 | H4: ='IS- Breakdown'!H$48 -> 28.89028 | I4: ='IS- Breakdown'!I$48 -> 32.154882 | J4: ='IS- Breakdown'!J$48 -> 34.823737 | ... L4: ='IS- Breakdown'!L$48 -> 38.686212
B5: ASP (Private Sales) | C5: ='IS- Breakdown'!C49 -> 24.334552 | D5: ='IS- Breakdown'!D49 -> 26.230105 | E5: ='IS- Breakdown'!E49 -> 30.029275 | F5: ='IS- Breakdown'!F49 -> 44.582554 | G5: ='IS- Breakdown'!G49 -> 55.903542 | H5: ='IS- Breakdown'!H$49 -> 61.348156 | I5: ='IS- Breakdown'!I$49 -> 68.280498 | J5: ='IS- Breakdown'!J$49 -> 73.947779 | K5: ='IS- Breakdown'!K$49 -> 78.014907 | L5: ='IS- Breakdown'!L$49 -> 82.149697
B6: ASP (Exports) | C6: ='IS- Breakdown'!C50 -> 14.563648 | D6: ='IS- Breakdown'!D50 -> 31.428071 | E6: ='IS- Breakdown'!E50 -> 17.72451 | F6: ='IS- Breakdown'!F50 -> 25.728593 | G6: ='IS- Breakdown'!G50 -> 33.857702 | H6: ='IS- Breakdown'!H$50 -> 33.751955 | I6: ='IS- Breakdown'!I$50 -> 37.194655 | J6: ='IS- Breakdown'!J$50 -> 40.43059 | K6: ='IS- Breakdown'!K$50 -> 43.543745 | L6: ='IS- Breakdown'!L$50 -> 46.548264
B7: ASP (Toll Manufacturing) | C7: ='IS- Breakdown'!C51 -> 1.9581577 | D7: ='IS- Breakdown'!D51 -> 2.2475304 | E7: ='IS- Breakdown'!E51 -> 1.5308493 | F7: ='IS- Breakdown'!F51 -> 2.1111915 | G7: ='IS- Breakdown'!G51 -> 2.6863465 | H7: ='IS- Breakdown'!H$51 -> 3.5202408 | I7: ='IS- Breakdown'!I$51 -> 3.918028 | J7: ='IS- Breakdown'!J$51 -> 4.2432244 | K7: ='IS- Breakdown'!K$51 -> 4.4766017 | L7: ='IS- Breakdown'!L$51 -> 4.7138616
B9: Volume Sold | C9: 2020 | D9: 2021 | E9: 2022 | F9: 2023 | G9: 2024 | H9: =G9+1 -> 2025 | I9: =H9+1 -> 2026 | J9: =I9+1 -> 2027 | K9: =J9+1 -> 2028 | L9: =K9+1 -> 2029
B10: Volume Sold (Tender) | C10: ='IS- Breakdown'!C34 -> 30.224 | D10: ='IS- Breakdown'!D34 -> 26.566 | E10: ='IS- Breakdown'!E34 -> 16.3278 | F10: ='IS- Breakdown'!F34 -> 13.1 | G10: ='IS- Breakdown'!G34 -> 8.1 | H10: ='IS- Breakdown'!H$34 -> 18.5 | I10: ='IS- Breakdown'!I$34 -> 17.688051 | J10: ='IS- Breakdown'!J$34 -> 18.152606 | K10: ='IS- Breakdown'!K$34 -> 18.161376 | L10: ='IS- Breakdown'!L$34 -> 19.190501
B11: Volume Sold (Private Sales) | C11: ='IS- Breakdown'!C35 -> 27.11 | D11: ='IS- Breakdown'!D35 -> 31.608 | E11: ='IS- Breakdown'!E35 -> 36.106 | F11: ='IS- Breakdown'!F35 -> 31.8203 | G11: ='IS- Breakdown'!G35 -> 39.5 | H11: ='IS- Breakdown'!H$35 -> 48.2 | I11: ='IS- Breakdown'!I$35 -> 47.663129 | J11: ='IS- Breakdown'!J$35 -> 48.877726 | K11: ='IS- Breakdown'!K$35 -> 50.186869 | L11: ='IS- Breakdown'!L$35 -> 53.046985
B12: Volume Sold (Exports) | C12: ='IS- Breakdown'!C36 -> 3.429 | D12: ='IS- Breakdown'!D36 -> 2.796 | E12: ='IS- Breakdown'!E36 -> 6.009 | F12: ='IS- Breakdown'!F36 -> 7.0056 | G12: ='IS- Breakdown'!G36 -> 4.2 | H12: ='IS- Breakdown'!H$36 -> 5.1 | I12: ='IS- Breakdown'!I$36 -> 5.590001 | J12: ='IS- Breakdown'!J$36 -> 6.6218252 | K12: ='IS- Breakdown'!K$36 -> 7.0650053 | L12: ='IS- Breakdown'!L$36 -> 7.6287759
B13: Volume Sold (Toll Manufacturing) | C13: ='IS- Breakdown'!C37 -> 25.963 | D13: ='IS- Breakdown'!D37 -> 34.478 | E13: ='IS- Breakdown'!E37 -> 86.512 | F13: ='IS- Breakdown'!F37 -> 63.474 | G13: ='IS- Breakdown'!G37 -> 67.7 | H13: ='IS- Breakdown'!H$37 -> 80.8 | I13: ='IS- Breakdown'!I$37 -> 83.518277 | J13: ='IS- Breakdown'!J$37 -> 87.45518 | K13: ='IS- Breakdown'!K$37 -> 89.405031 | L13: ='IS- Breakdown'!L$37 -> 92.597413
B14: Total | C14: =SUM(C10:C13) -> 86.726 | D14: =SUM(D10:D13) -> 95.448 | E14: =SUM(E10:E13) -> 144.9548 | F14: =SUM(F10:F13) -> 115.3999 | G14: =SUM(G10:G13) -> 119.5 | H14: =SUM(H10:H13) -> 152.6 | I14: =SUM(I10:I13) -> 154.45946 | J14: =SUM(J10:J13) -> 161.10734 | ... L14: =SUM(L10:L13) -> 172.46367
B16: Sales | C16: 2020 | D16: 2021 | E16: 2022 | F16: 2023 | G16: 2024 | H16: =G16+1 -> 2025 | I16: =H16+1 -> 2026 | J16: =I16+1 -> 2027 | K16: =J16+1 -> 2028 | L16: =K16+1 -> 2029
B17: Sales (Tender) | C17: =C$4*C$10 -> 199.68525 | D17: =D$4*D$10 -> 251.99024 | E17: =E$4*E$10 -> 160.77102 | F17: =F$4*F$10 -> 189.47047 | G17: =G$4*G$10 -> 236.4305 | H17: =H4*H10 -> 534.47018 | I17: =I4*I10 -> 568.75719 | J17: =J4*J10 -> 632.14158 | K17: =K4*K10 -> 667.23157 | L17: =L4*L10 -> 742.40776
B18: Sales (Private Sales) | C18: =C$5*C$11 -> 659.7097 | D18: =D$5*D$11 -> 829.08115 | E18: =E$5*E$11 -> 1084.237 | F18: =F$5*F$11 -> 1418.6302 | G18: =G$5*G$11 -> 2208.1899 | H18: =H5*H11 -> 2956.9811 | I18: =I5*I11 -> 3254.4621 | J18: =J5*J11 -> 3614.3993 | K18: =K5*K11 -> 3915.3239 | L18: =L5*L11 -> 4357.7937
B19: Sales (Exports) | C19: =C$6*C12 -> 49.93875 | D19: =D$6*D12 -> 87.872886 | E19: =E$6*E12 -> 106.50658 | F19: =F$6*F12 -> 180.24423 | G19: =G$6*G12 -> 142.20235 | H19: =H6*H12 -> 172.13497 | I19: =I6*I12 -> 207.91816 | J19: =J6*J12 -> 267.7243 | K19: =K6*K12 -> 307.63679 | L19: =L6*L12 -> 355.10627
B20: Sales (Toll Manufacturing) | C20: =C$7*C13 -> 50.839648 | D20: =D$7*D13 -> 77.490353 | E20: =E$7*E13 -> 132.43683 | F20: =F$7*F13 -> 134.00577 | G20: =G$7*G13 -> 181.86566 | H20: =H7*H13 -> 284.43546 | I20: =I7*I13 -> 327.22695 | J20: =J7*J13 -> 371.09195 | K20: =K7*K13 -> 400.23072 | L20: =L7*L13 -> 436.49139
B21: Total | C21: =SUM(C$17:C$20) -> 960.17335 | D21: =SUM(D$17:D$20) -> 1246.4346 | E21: =SUM(E$17:E$20) -> 1483.9514 | F21: =SUM(F$17:F$20) -> 1922.3507 | G21: =SUM(G$17:G$20) -> 2768.6884 | H21: =SUM(H$17:H$20) -> 3948.0217 | I21: =SUM(I$17:I$20) -> 4358.3644 | J21: =SUM(J$17:J$20) -> 4885.3571 | ... L21: =SUM(L$17:L$20) -> 5891.7992
B23: Total ASP | C23: =C21/C14 -> 11.071344 | D23: =D21/D14 -> 13.058782 | E23: =E21/E14 -> 10.237339 | F23: =F21/F14 -> 16.658166 | G23: =G21/G14 -> 23.168941 | H23: =H21/H14 -> 25.871702 | I23: =I21/I14 -> 28.216883 | J23: =J21/J14 -> 30.323617 | ... L23: =L21/L14 -> 34.162551
B25: Price Effect | C25: 2020 | D25: 2021 | E25: 2022 | F25: 2023 | G25: 2024 | H25: =G25+1 -> 2025 | I25: =H25+1 -> 2026 | J25: =I25+1 -> 2027 | K25: =J25+1 -> 2028 | L25: =K25+1 -> 2029
B26: PE (Tender) | D26: =(D4-C4)*C10 -> 87.00273 | E26: =(E4-D4)*D10 -> 9.5907999 | F26: =(F4-E4)*E10 -> 75.384401 | G26: =(G4-F4)*F10 -> 192.90478 | H26: =(H4-G4)*G10 -> -2.419231 | I26: =(I4-H4)*H10 -> 60.39513 | J26: =(J4-I4)*I10 -> 47.206847 | K26: =(K4-J4)*J10 -> 34.767787 | L26: =(L4-K4)*K10 -> 35.363273
B27: PE (Private Sales) | D27: =(D5-C5)*C11 -> 51.388442 | E27: =(E5-D5)*D11 -> 120.08416 | F27: =(F5-E5)*E11 -> 525.4607 | G27: =(G5-F5)*F11 -> 360.23725 | H27: =(H5-G5)*G11 -> 215.06224 | I27: =(I5-H5)*H11 -> 334.13887 | J27: =(J5-I5)*I11 -> 270.12036 | K27: =(K5-J5)*J11 -> 198.79196 | L27: =(L5-K5)*K11 -> 207.51217
B28: PE (Exports) | D28: =(D6-C6)*C12 -> 57.828105 | E28: =(E6-D6)*D12 -> -38.315155 | F28: =(F6-E6)*E12 -> 48.096536 | G28: =(G6-F6)*F12 -> 56.949281 | H28: =(H6-G6)*G12 -> -0.44413394 | I28: =(I6-H6)*H12 -> 17.557767 | J28: =(J6-I6)*I12 -> 18.08888 | K28: =(K6-J6)*J12 -> 20.614771 | L28: =(L6-K6)*K12 -> 21.226939
B29: PE (Toll Manufacturing) | D29: =(D7-C7)*C13 -> 7.5129837 | E29: =(E7-D7)*D13 -> -24.709731 | F29: =(F7-E7)*E13 -> 50.20657 | G29: =(G7-F7)*F13 -> 36.507387 | H29: =(H7-G7)*G13 -> 56.454645 | I29: =(I7-H7)*H13 -> 32.141207 | J29: =(J7-I7)*I13 -> 27.159837 | K29: =(K7-J7)*J13 -> 20.410057 | L29: =(L7-K7)*K13 -> 21.212228
B30: Total | C30: =SUM(C26:C29) -> 0 | D30: =SUM(D26:D29) -> 203.73226 | E30: =SUM(E26:E29) -> 66.650076 | F30: =SUM(F26:F29) -> 699.14821 | G30: =SUM(G26:G29) -> 646.59869 | H30: =SUM(H26:H29) -> 268.65352 | I30: =SUM(I26:I29) -> 444.23297 | J30: =SUM(J26:J29) -> 362.57592 | ... L30: =SUM(L26:L29) -> 285.31461
B32: Volume Effect | C32: 2020 | D32: 2021 | E32: 2022 | F32: 2023 | G32: 2024 | H32: =G32+1 -> 2025 | I32: =H32+1 -> 2026 | J32: =I32+1 -> 2027 | K32: =J32+1 -> 2028 | L32: =K32+1 -> 2029
B33: VE (Tender) | D33: =(D10-C10)*C4 -> -24.167835 | E33: =(E10-D10)*D4 -> -97.113846 | F33: =(F10-E10)*E4 -> -31.782401 | G33: =(G10-F10)*F4 -> -72.316974 | H33: =(H10-G10)*G4 -> 303.56509 | I33: =(I10-H10)*H4 -> -23.457433 | J33: =(J10-I10)*I4 -> 14.937718 | K33: =(K10-J10)*J4 -> 0.30540298 | L33: =(L10-K10)*K4 -> 37.809041
B34: VE (Private Sales) | D34: =(D11-C11)*C5 -> 109.45681 | E34: =(E11-D11)*D5 -> 117.98301 | F34: =(F11-E11)*E5 -> -128.69646 | G34: =(G11-F11)*F5 -> 342.38064 | H34: =(H11-G11)*G5 -> 486.36082 | I34: =(I11-H11)*H5 -> -32.936074 | J34: =(J11-I11)*I5 -> 82.933325 | K34: =(K11-J11)*J5 -> 96.808203 | L34: =(L11-K11)*K5 -> 223.13169
B35: VE (Exports) | D35: =(D12-C12)*C6 -> -9.2187894 | E35: =(E12-D12)*D6 -> 100.97839 | F35: =(F12-E12)*E6 -> 17.664247 | G35: =(G12-F12)*F6 -> -72.184142 | H35: =(H12-G12)*G6 -> 30.471931 | I35: =(I12-H12)*H6 -> 16.538493 | J35: =(J12-I12)*I6 -> 38.378345 | K35: =(K12-J12)*J6 -> 17.918032 | L35: =(L12-K12)*K6 -> 24.548683
B36: VE (Toll Manufacturing) | D36: =(D13-C13)*C7 -> 16.673713 | E36: =(E13-D13)*D7 -> 116.948 | F36: =(F13-E13)*E7 -> -35.267706 | G36: =(G13-F13)*F7 -> 8.9218955 | H36: =(H13-G13)*G7 -> 35.191139 | I36: =(I13-H13)*H7 -> 9.5689891 | J36: =(J13-I13)*I7 -> 15.424895 | K36: =(K13-J13)*J7 -> 8.273658 | L36: =(L13-K13)*K7 -> 14.291023
B37: Total | D37: =SUM(D33:D36) -> 92.743902 | E37: =SUM(E33:E36) -> 238.79555 | F37: =SUM(F33:F36) -> -178.08232 | G37: =SUM(G33:G36) -> 206.80142 | H37: =SUM(H33:H36) -> 855.58897 | I37: =SUM(I33:I36) -> -30.286025 | J37: =SUM(J33:J36) -> 151.67428 | K37: =SUM(K33:K36) -> 123.3053 | L37: =SUM(L33:L36) -> 299.78044
B39: Cross Effect | C39: 2020 | D39: 2021 | E39: 2022 | F39: 2023 | G39: 2024 | H39: =G39+1 -> 2025 | I39: =H39+1 -> 2026 | J39: =I39+1 -> 2027 | K39: =J39+1 -> 2028 | L39: =K39+1 -> 2029
B40: CE (Tender) | D40: =(D4-C4)*(D10-C10) -> -10.52991 | E40: =(E4-D4)*(E10-D10) -> -3.6961728 | F40: =(F4-E4)*(F10-E10) -> -14.902545 | G40: =(G4-F4)*(G10-F10) -> -73.627778 | H40: =(H4-G4)*(H10-G10) -> -3.1061731 | I40: =(I4-H4)*(I10-H10) -> -2.6506899 | J40: =(J4-I4)*(J10-I10) -> 1.2398306 | K40: =(K4-J4)*(K10-J10) -> 0.016797164 | L40: =(L4-K4)*(L10-K10) -> 2.0038792
B41: CE (Private Sales) | D41: =(D5-C5)*(D11-C11) -> 8.5261973 | E41: =(E5-D5)*(E11-D11) -> 17.088666 | F41: =(F5-E5)*(F11-E11) -> -62.370989 | G41: =(G5-F5)*(G11-F11) -> 86.941794 | H41: =(H5-G5)*(H11-G11) -> 47.368138 | I41: =(I5-H5)*(I11-H11) -> -3.7217764 | J41: =(J5-I5)*(J11-I11) -> 6.883466 | K41: =(K5-J5)*(K11-J11) -> 5.3244512 | L41: =(L5-K5)*(L11-K11) -> 11.82598
B42: CE (Exports) | D42: =(D6-C6)*(D12-C12) -> -10.675179 | E42: =(E6-D6)*(E12-D12) -> -44.02954 | F42: =(F6-E6)*(F12-E12) -> 7.9768693 | G42: =(G6-F6)*(G12-F12) -> -22.807026 | H42: =(H6-G6)*(H12-G12) -> -0.095171559 | I42: =(I6-H6)*(I12-H12) -> 1.6869263 | J42: =(J6-I6)*(J12-I12) -> 3.3389161 | K42: =(K6-J6)*(K12-J12) -> 1.3796884 | L42: =(L6-K6)*(L12-K12) -> 1.6938591
B43: CE (Toll Manufacturing) | D43: =(D7-C7)*(D13-C13) -> 2.4640086 | E43: =(E7-D7)*(E13-D13) -> -37.291785 | F43: =(F7-E7)*(F13-E13) -> -13.369925 | G43: =(G7-F7)*(G13-F13) -> 2.4306049 | H43: =(H7-G7)*(H13-G13) -> 10.924016 | I43: =(I7-H7)*(I13-H13) -> 1.0812958 | J43: =(J7-I7)*(J13-I13) -> 1.2802663 | K43: =(K7-J7)*(K13-J13) -> 0.45505119 | L43: =(L7-K7)*(L13-K13) -> 0.75742423
B44: Total | D44: =SUM(D40:D43) -> -10.214883 | E44: =SUM(E40:E43) -> -67.928832 | F44: =SUM(F40:F43) -> -82.666589 | G44: =SUM(G40:G43) -> -7.0624054 | H44: =SUM(H40:H43) -> 55.090809 | I44: =SUM(I40:I43) -> -3.6042443 | J44: =SUM(J40:J43) -> 12.742479 | K44: =SUM(K40:K43) -> 7.175988 | L44: =SUM(L40:L43) -> 16.281142
B46: Effects Sum | D46: =D30+D37+D44 -> 286.26128 | E46: =E30+E37+E44 -> 237.5168 | F46: =F30+F37+F44 -> 438.39929 | G46: =G30+G37+G44 -> 846.33771 | H46: =H30+H37+H44 -> 1179.3333 | I46: =I30+I37+I44 -> 410.3427 | J46: =J30+J37+J44 -> 526.99268 | K46: =K30+K37+K44 -> 405.06586 | L46: =L30+L37+L44 -> 601.37619
B47: Total Change | D47: =D21-C21 -> 286.26128 | E47: =E21-D21 -> 237.5168 | F47: =F21-E21 -> 438.39929 | G47: =G21-F21 -> 846.33771 | H47: =H21-G21 -> 1179.3333 | I47: =I21-H21 -> 410.3427 | J47: =J21-I21 -> 526.99268 | K47: =K21-J21 -> 405.06586 | L47: =L21-K21 -> 601.37619
B48: Checker | D48: =D46=D47 -> TRUE | E48: =E46=E47 -> TRUE | F48: =F46=F47 -> TRUE | G48: =G46=G47 -> TRUE | H48: =H46-H47 -> 0 | I48: =I46-I47 -> 0 | J48: =J46=J47 -> TRUE | K48: =K46-K47 -> 5.1159077e-13 | L48: =L46-L47 -> 0 | M48: Why checker states false?
B50: Waterfall Bridge Data | C50: Amount
B51: Prior Sales | D51: =C55 -> 960.17335 | E51: =D55 -> 1246.4346 | F51: =E55 -> 1483.9514 | G51: =F55 -> 1922.3507 | H51: =G55 -> 2768.6884 | I51: =H55 -> 3948.0217 | J51: =I55 -> 4358.3644 | K51: =J55 -> 4885.3571 | L51: =K55 -> 5290.423 | M51: =D51 -> 960.17335 | N51: =H51 -> 2768.6884
B52: Price Effect | C52: =C23 -> 11.071344 | D52: =D30 -> 203.73226 | E52: =E30 -> 66.650076 | F52: =F30 -> 699.14821 | G52: =G30 -> 646.59869 | H52: =H30 -> 268.65352 | I52: =I30 -> 444.23297 | J52: =J30 -> 362.57592 | K52: =K30 -> 274.58458 | L52: =L30 -> 285.31461 | M52: =SUM(D52:G52) -> 1616.1292 | N52: =SUM(H52:L52) -> 1635.3616
B53: Volume Effect | C53: =C37 -> 0 | D53: =D37 -> 92.743902 | E53: =E37 -> 238.79555 | F53: =F37 -> -178.08232 | G53: =G37 -> 206.80142 | H53: =H37 -> 855.58897 | I53: =I37 -> -30.286025 | J53: =J37 -> 151.67428 | ... L53: =L37 -> 299.78044 | M53: =SUM(D53:G53) -> 360.25855 | N53: =SUM(H53:L53) -> 1400.063
B54: Cross Effect | C54: =C44 -> 0 | D54: =D44 -> -10.214883 | E54: =E44 -> -67.928832 | F54: =F44 -> -82.666589 | G54: =G44 -> -7.0624054 | H54: =H44 -> 55.090809 | I54: =I44 -> -3.6042443 | J54: =J44 -> 12.742479 | ... L54: =L44 -> 16.281142 | M54: =SUM(D54:G54) -> -167.87271 | N54: =SUM(H54:L54) -> 87.686174
B55: Current Sale | C55: =C21 -> 960.17335 | D55: =SUM(D51:D54) -> 1246.4346 | E55: =SUM(E51:E54) -> 1483.9514 | F55: =SUM(F51:F54) -> 1922.3507 | G55: =SUM(G51:G54) -> 2768.6884 | H55: =SUM(H51:H54) -> 3948.0217 | I55: =SUM(I51:I54) -> 4358.3644 | J55: =SUM(J51:J54) -> 4885.3571 | K55: =SUM(K51:K54) -> 5290.423 | ... N55: =SUM(N51:N54) -> 5891.7992
B56: Total | D56: =D21 -> 1246.4346 | E56: =E21 -> 1483.9514 | F56: =F21 -> 1922.3507 | G56: =G21 -> 2768.6884 | H56: =H21 -> 3948.0217 | I56: =I21 -> 4358.3644 | J56: =J21 -> 4885.3571 | K56: =K21 -> 5290.423 | L56: =L21 -> 5891.7992
B57: Checker | D57: =D55=D56 -> TRUE | E57: =E55=E56 -> TRUE | F57: =F55=F56 -> TRUE | G57: =G55=G56 -> TRUE | H57: =H55=H56 -> TRUE | I57: =I55=I56 -> TRUE | J57: =J55=J56 -> TRUE | K57: =K55=K56 -> TRUE | L57: =L55=L56 -> TRUE
B59: Summary
B60: Prior Sales | C60: =C21 -> 960.17335 | D60: =C61 -> 960.17335 | E60: =D61 -> 1246.4346 | F60: =E61 -> 1483.9514 | G60: =F61 -> 1922.3507 | H60: =G61 -> 2768.6884 | I60: =H61 -> 3948.0217 | J60: =I61 -> 4358.3644 | K60: =J61 -> 4885.3571 | L60: =K61 -> 5290.423
B61: New Sales | C61: =C21 -> 960.17335 | D61: =D21 -> 1246.4346 | E61: =E21 -> 1483.9514 | F61: =F21 -> 1922.3507 | G61: =G21 -> 2768.6884 | H61: =H21 -> 3948.0217 | I61: =I21 -> 4358.3644 | J61: =J21 -> 4885.3571 | ... L61: =L21 -> 5891.7992
B62: Δ Sales | C62: =C61-C60 -> 0 | D62: =D61-D60 -> 286.26128 | E62: =E61-E60 -> 237.5168 | F62: =F61-F60 -> 438.39929 | G62: =G61-G60 -> 846.33771 | H62: =H61-H60 -> 1179.3333 | I62: =I61-I60 -> 410.3427 | J62: =J61-J60 -> 526.99268 | ... L62: =L61-L60 -> 601.37619
B63: % Change | C63: =IF(C60=0,NA(),C62/C60) -> 0 | D63: =IF(D60=0,NA(),D62/D60) -> 0.298135 | E63: =IF(E60=0,NA(),E62/E60) -> 0.19055696 | F63: =IF(F60=0,NA(),F62/F60) -> 0.29542698 | G63: =IF(G60=0,NA(),G62/G60) -> 0.44026186 | H63: =IF(H60=0,NA(),H62/H60) -> 0.42595378 | I63: =IF(I60=0,NA(),I62/I60) -> 0.10393628 | J63: =IF(J60=0,NA(),J62/J60) -> 0.12091524 | ... L63: =IF(L60=0,NA(),L62/L60) -> 0.11367261
C66: 🔺Quantity | D66: 🔺 ASP | E66: Elasticity
C67: =L14/C14-1 -> 0.98860405 | D67: =L23/C23-1 -> 2.0856735 | E67: =C67/D67 -> 0.47399752
D68: Results: | E68: Inelastic
C69: customers are not sensitive to price
C70: Prices grow by 114%, and instead of demand dropping, volume grew 45%. This shows your customers kept buying regardless of price.

Sheet Valuation
B1: WACC Breakdown | C1: 2025 | D1: =C1+1 -> 2026 | E1: =D1+1 -> 2027 | F1: =E1+1 -> 2028 | G1: =F1+1 -> 2029 | I1: Assumptions | J1: 2025 | K1: =J1+1 -> 2026 | L1: =K1+1 -> 2027 | M1: =L1+1 -> 2028 | N1: =M1+1 -> 2029 | P1: unlevered beta | Q1: =T2/(1+(1-C3))*(J5/J4) -> 0.063282243 | S1: Beta Calculation
B2: Interest Rate | C2: =-'Financial Statements'!I30/('Financial Statements'!I81+'Financial Statements'!I82+'Financial Statements'!I88+'Financial Statements'!I89+'Financial Statements'!I90) -> 0.20618502 | D2: =-'Financial Statements'!J30/('Financial Statements'!J81+'Financial Statements'!J82+'Financial Statements'!J88+'Financial Statements'!J89+'Financial Statements'!J90) -> 0.23131261 | E2: =-'Financial Statements'!K30/('Financial Statements'!K81+'Financial Statements'!K82+'Financial Statements'!K88+'Financial Statements'!K89+'Financial Statements'!K90) -> 0.12770133 | F2: =-'Financial Statements'!L30/('Financial Statements'!L81+'Financial Statements'!L82+'Financial Statements'!L88+'Financial Statements'!L89+'Financial Statements'!L90) -> 0.082440147 | G2: =-'Financial Statements'!M30/('Financial Statements'!M81+'Financial Statements'!M82+'Financial Statements'!M88+'Financial Statements'!M89+'Financial Statements'!M90) -> 0.092127312 | I2: Share Price | J2: 4.24 | K2: 4.24 | L2: 4.24 | M2: 4.24 | N2: 4.24 | P2: levered beta | Q2: =Q1*(1+(1-C3))*(J5/J4) -> 0.021187862 | S2: Raw Beta | T2: =SLOPE(U6:U1218,T6:T1218) -> 0.5954884 | X2: Table 1:WACC & Terminal Growth Rate SA | AR2: Raw Beta | AS2: =SLOPE(AT7:AT270,AS7:AS270) -> 0.54234799
B3: Corporate Tax | C3: 0.225 | D3: 0.225 | E3: 0.225 | F3: 0.225 | G3: 0.225 | I3: Shares Outstanding | J3: =Ratios!I55 -> 2000 | K3: =Ratios!J55 -> 2000 | L3: =Ratios!K55 -> 2000 | M3: =Ratios!L55 -> 2000 | N3: =Ratios!M55 -> 2000 | P3: unlevered adjusted | Q3: =T3/(1+(1-C3))*(J5/J4) -> 0.077611322 | S3: Adjusted Beta | T3: =((2/3)*T2)+(1/3)*1 -> 0.7303256 | X3: WACC | AS3: =RSQ(AT7:AT270,AS7:AS270) -> 0.098879106 | AY3: relative volatility
B4: Cost of Debt | C4: =C2*(1-C3) -> 0.15979339 | D4: =D2*(1-D3) -> 0.17926727 | E4: =E2*(1-E3) -> 0.09896853 | F4: =F2*(1-F3) -> 0.063891114 | G4: =G2*(1-G3) -> 0.071398667 | I4: Market Cap | J4: =J2*J3 -> 8480 | K4: =K2*K3 -> 8480 | L4: =L2*L3 -> 8480 | M4: =M2*M3 -> 8480 | N4: =N2*N3 -> 8480 | P4: levered adjusted | Q4: =Q3*(1+(1-C3))*(J5/J4) -> 0.025985457 | X4: =C36 -> 3.6781221 | Y4: =Z4-1% -> 0.11959356 | Z4: =AA4-1% -> 0.12959356 | AA4: =G11 -> 0.13959356 | AB4: =AA4+1% -> 0.14959356 | AC4: =AB4+1% -> 0.15959356 | AW4: =_xlfn.STDEV.S(AW7:AW18) -> 0.03168768 | AX4: =_xlfn.STDEV.S(AX7:AX18) -> 0.019095454 | AY4: =AX5/AW5 -> 0.60261445 | AZ4: 0.0446
B5: RFR | C5: =(1+$J$12)*(1+J13)/(1+J14)-1 -> 0.1700276 | D5: =(1+$J$12)*(1+K13)/(1+K14)-1 -> 0.13558671 | E5: =(1+$J$12)*(1+L13)/(1+L14)-1 -> 0.10497791 | F5: =(1+$J$12)*(1+M13)/(1+M14)-1 -> 0.076409687 | G5: =(1+$J$12)*(1+N13)/(1+N14)-1 -> 0.0743691 | I5: Interest bearing Debt | J5: =('Financial Statements'!I81+'Financial Statements'!I82+'Financial Statements'!I88+'Financial Statements'!I89+'Financial Statements'!I90) -> 1599.5682 | K5: =('Financial Statements'!J81+'Financial Statements'!J82+'Financial Statements'!J88+'Financial Statements'!J89+'Financial Statements'!J90) -> 1425.8065 | L5: =('Financial Statements'!K81+'Financial Statements'!K82+'Financial Statements'!K88+'Financial Statements'!K89+'Financial Statements'!K90) -> 1358.8201 | M5: =('Financial Statements'!L81+'Financial Statements'!L82+'Financial Statements'!L88+'Financial Statements'!L89+'Financial Statements'!L90) -> 1437.0427 | N5: =('Financial Statements'!M81+'Financial Statements'!M82+'Financial Statements'!M88+'Financial Statements'!M89+'Financial Statements'!M90) -> 1290.6054 | P5: unlevered investing | Q5: =C13/(1+(1-C3))*(J5/J4) -> 0.014877727 | S5: Date | T5: EGX30 | U5: RMDA | X5: =X6-1% -> 0.049629813 | Y5: =$X$4*($X5/$J$7)*(Y$4/$G$11) -> 2.2460321 | Z5: =$X$4*($X5/$J$7)*(Z$4/$G$11) -> 2.4338375 | AA5: =$X$4*($X5/$J$7)*(AA$4/$G$11) -> 2.621643 | AB5: =$X$4*($X5/$J$7)*(AB$4/$G$11) -> 2.8094484 | AC5: =$X$4*($X5/$J$7)*(AC$4/$G$11) -> 2.9972539 | AE5: =IF(Y5>$G$35,"Buy",IF(Y5>=$G$36,"Hold","Sell")) -> Sell | AF5: =IF(Z5>$G$35,"Buy",IF(Z5>=$G$36,"Hold","Sell")) -> Sell | AG5: =IF(AA5>$G$35,"Buy",IF(AA5>=$G$36,"Hold","Sell")) -> Sell | AH5: =IF(AB5>$G$35,"Buy",IF(AB5>=$G$36,"Hold","Sell")) -> Sell | AI5: =IF(AC5>$G$35,"Buy",IF(AC5>=$G$36,"Hold","Sell")) -> Sell | AW5: =AW4*SQRT(12) -> 0.10976934 | AX5: =AX4*SQRT(12) -> 0.066148593 | AZ5: =AY4*AZ4 -> 0.026876604
B6: Adjusted Beta | C6: =AS2 -> 0.54234799 | D6: =C6 -> 0.54234799 | E6: =D6 -> 0.54234799 | F6: =E6 -> 0.54234799 | G6: =F6 -> 0.54234799 | I6: Total Capitalization | J6: =SUM(J4:J5) -> 10079.568 | K6: =SUM(K4:K5) -> 9905.8065 | L6: =SUM(L4:L5) -> 9838.8201 | M6: =SUM(M4:M5) -> 9917.0427 | N6: =SUM(N4:N5) -> 9770.6054 | P6: levered inveting | Q6: =Q5*(1+(1-C3))*(J5/J4) -> 0.0049812905 | S6: 46062 | T6: 0.0052 | U6: 0.0199 | W6: TGR | X6: =X7-1% -> 0.059629813 | Y6: =$X$4*($X6/$J$7)*(Y$4/$G$11) -> 2.6985891 | Z6: =$X$4*($X6/$J$7)*(Z$4/$G$11) -> 2.9242358 | AA6: =$X$4*($X6/$J$7)*(AA$4/$G$11) -> 3.1498825 | AB6: =$X$4*($X6/$J$7)*(AB$4/$G$11) -> 3.3755292 | AC6: =$X$4*($X6/$J$7)*(AC$4/$G$11) -> 3.6011759 | AE6: =IF(Y6>$G$35,"Buy",IF(Y6>=$G$36,"Hold","Sell")) -> Sell | AF6: =IF(Z6>$G$35,"Buy",IF(Z6>=$G$36,"Hold","Sell")) -> Sell | AG6: =IF(AA6>$G$35,"Buy",IF(AA6>=$G$36,"Hold","Sell")) -> Sell | AH6: =IF(AB6>$G$35,"Buy",IF(AB6>=$G$36,"Hold","Sell")) -> Sell | AI6: =IF(AC6>$G$35,"Buy",IF(AC6>=$G$36,"Hold","Sell")) -> Sell | AL6: Sell | AM6: =COUNTIF(AE5:AI9,"Sell") -> 19 | AN6: =AM6/$AM$9 -> 0.76 | AS6: EGX30 | AT6: RMDA | AW6: S&P | AX6: EGX30 | AY6: =AY4*AZ4 -> 0.026876604
B7: Equity Risk Premium | C7: 0.1394 | D7: 0.1394 | E7: 0.1394 | F7: 0.1394 | G7: 0.1394 | I7: Terminal Growth Rate | J7: =Assumptions!Q35 -> 0.069629813 | P7: Peers Beta | S7: 46061 | T7: 0.006 | U7: 0.0115 | X7: =J7 -> 0.069629813 | Y7: =$X$4*($X7/$J$7)*(Y$4/$G$11) -> 3.1511461 | Z7: =$X$4*($X7/$J$7)*(Z$4/$G$11) -> 3.4146341 | AA7: =$X$4*($X7/$J$7)*(AA$4/$G$11) -> 3.6781221 | AB7: =$X$4*($X7/$J$7)*(AB$4/$G$11) -> 3.94161 | AC7: =$X$4*($X7/$J$7)*(AC$4/$G$11) -> 4.205098 | AE7: =IF(Y7>$G$35,"Buy",IF(Y7>=$G$36,"Hold","Sell")) -> Sell | AF7: =IF(Z7>$G$35,"Buy",IF(Z7>=$G$36,"Hold","Sell")) -> Sell | AG7: =IF(AA7>$G$35,"Buy",IF(AA7>=$G$36,"Hold","Sell")) -> Sell | AH7: =IF(AB7>$G$35,"Buy",IF(AB7>=$G$36,"Hold","Sell")) -> Sell | AI7: =IF(AC7>$G$35,"Buy",IF(AC7>=$G$36,"Hold","Sell")) -> Sell | AL7: Hold | AM7: =COUNTIF(AE5:AI9,"Hold") -> 4 | AN7: =AM7/$AM$9 -> 0.16 | AR7: 46061 | AS7: 0.0151 | AT7: 0.0891 | AW7: -0.0005 | AX7: 0.0264
B8: Cost of Equity | C8: =C5+C6*(C7) -> 0.24563091 | D8: =D5+D6*(D7) -> 0.21119002 | E8: =E5+E6*(E7) -> 0.18058122 | F8: =F5+F6*(F7) -> 0.152013 | G8: =G5+G6*(G7) -> 0.14997241 | I8: R - G | J8: =G11-J7 -> 0.069963742 | P8: EIPICO | Q8: 0.63 | S8: 46058 | T8: 0.0022 | U8: 0.0482 | X8: =X7+1% -> 0.079629813 | Y8: =$X$4*($X8/$J$7)*(Y$4/$G$11) -> 3.6037032 | Z8: =$X$4*($X8/$J$7)*(Z$4/$G$11) -> 3.9050324 | AA8: =$X$4*($X8/$J$7)*(AA$4/$G$11) -> 4.2063616 | AB8: =$X$4*($X8/$J$7)*(AB$4/$G$11) -> 4.5076908 | AC8: =$X$4*($X8/$J$7)*(AC$4/$G$11) -> 4.80902 | AE8: =IF(Y8>$G$35,"Buy",IF(Y8>=$G$36,"Hold","Sell")) -> Sell | AF8: =IF(Z8>$G$35,"Buy",IF(Z8>=$G$36,"Hold","Sell")) -> Sell | AG8: =IF(AA8>$G$35,"Buy",IF(AA8>=$G$36,"Hold","Sell")) -> Sell | AH8: =IF(AB8>$G$35,"Buy",IF(AB8>=$G$36,"Hold","Sell")) -> Hold | AI8: =IF(AC8>$G$35,"Buy",IF(AC8>=$G$36,"Hold","Sell")) -> Hold | AL8: Buy | AM8: =COUNTIF(AE5:AI9,"Buy") -> 2 | AN8: =AM8/$AM$9 -> 0.08 | AR8: 46054 | AS8: 0.0409 | AT8: 0.1262 | AW8: 0.0013 | AX8: 0.065
B9: Weight of Debt | C9: =1-C10 -> 0.15869412 | D9: =1-D10 -> 0.14393643 | E9: =1-E10 -> 0.13810803 | F9: =1-F10 -> 0.14490637 | G9: =1-G10 -> 0.13209062 | P9: MinaPharm | Q9: -0.05 | S9: 46057 | T9: 0.0133 | U9: 0.0091 | V9: =RSQ(U6:U1218,T6:T1218) -> 0.097687869 | X9: =X8+1% -> 0.089629813 | Y9: =$X$4*($X9/$J$7)*(Y$4/$G$11) -> 4.0562602 | Z9: =$X$4*($X9/$J$7)*(Z$4/$G$11) -> 4.3954307 | AA9: =$X$4*($X9/$J$7)*(AA$4/$G$11) -> 4.7346011 | AB9: =$X$4*($X9/$J$7)*(AB$4/$G$11) -> 5.0737716 | AC9: =$X$4*($X9/$J$7)*(AC$4/$G$11) -> 5.4129421 | AE9: =IF(Y9>$G$35,"Buy",IF(Y9>=$G$36,"Hold","Sell")) -> Sell | AF9: =IF(Z9>$G$35,"Buy",IF(Z9>=$G$36,"Hold","Sell")) -> Hold | AG9: =IF(AA9>$G$35,"Buy",IF(AA9>=$G$36,"Hold","Sell")) -> Hold | AH9: =IF(AB9>$G$35,"Buy",IF(AB9>=$G$36,"Hold","Sell")) -> Buy | AI9: =IF(AC9>$G$35,"Buy",IF(AC9>=$G$36,"Hold","Sell")) -> Buy | AL9: Total | AM9: =SUM(AM6:AM8) -> 25 | AN9: =SUM(AN6:AN8) -> 1 | AR9: 46047 | AS9: 0.0285 | AT9: -0.0344 | AW9: 0.0227 | AX9: 0.0436
B10: Weight of Equity | C10: =J4/J6 -> 0.84130588 | D10: =K4/K6 -> 0.85606357 | E10: =L4/L6 -> 0.86189197 | F10: =M4/M6 -> 0.85509363 | G10: =N4/N6 -> 0.86790938 | P10: Ibnsina | Q10: 0.59 | S10: 46056 | T10: 0.0288 | U10: 0.0281 | AR10: 46040 | AS10: 0.0719 | AT10: 0.0323 | AW10: 0.0353 | AX10: 0.0433
B11: WACC | C11: =(C10*C8)+(C9*C4) -> 0.232009 | D11: =(D10*D8)+(D9*D4) -> 0.20659518 | E11: =(E10*E8)+(E9*E4) -> 0.16930985 | F11: =(F10*F8)+(F9*F4) -> 0.13924357 | G11: =(G10*G8)+(G9*G4) -> 0.13959356 | J11: 2025 | K11: =J11+1 -> 2026 | L11: =K11+1 -> 2027 | M11: =L11+1 -> 2028 | N11: =M11+1 -> 2029 | P11: Mimphis | Q11: -0.02 | S11: 46055 | T11: -0.0012 | U11: 0.0063 | AR11: 46033 | AS11: 0.0356 | AT11: -0.0343 | AW11: 0.0191 | AX11: 0.0278
C12: =C11-Assumptions!H6 -> 0.022008999 | D12: =D11-Assumptions!I6 -> 0.094095176 | E12: =E11-Assumptions!J6 -> 0.086809849 | F12: =F11-Assumptions!K6 -> 0.056743575 | G12: =G11-Assumptions!L6 -> 0.057093555 | I12: 10 years US t-bonds "investing" | J12: 0.04274 | P12: Alex | Q12: -0.07 | S12: 46054 | T12: -0.0026 | U12: 0.0291 | W12: Table 2: P/E Sensitivity Analysis | AR12: 46026 | AS12: 0.0007 | AT12: -0.036 | AW12: 0.0217 | AX12: 0.0408
B13: Beta "Investing" | C13: 0.14 | I13: EGP inf | J13: =Assumptions!H5 -> 0.149 | K13: =Assumptions!I5 -> 0.113 | L13: =Assumptions!J5 -> 0.083 | M13: =Assumptions!K5 -> 0.055 | N13: =Assumptions!L5 -> 0.053 | P13: Unleverd | S13: 46050 | T13: -0.001 | U13: -0.0252 | X13: EPS | AR13: 46019 | AS13: 0.014 | AT13: 0.003 | AW13: 0.0496 | AX13: 0.0049
I14: US inf | J14: 0.024 | K14: 0.022 | L14: 0.022 | M14: 0.022 | N14: 0.022 | P14: =P8 -> EIPICO | Q14: =Q8/(1+(1-C3)*'Peers Spreading'!C17) -> 0.29972953 | S14: 46049 | T14: 0.0069 | U14: -0.0063 | X14: =C51 -> 4.1319135 | Y14: =Z14-0.09 -> 0.020980549 | Z14: =AA14-0.09 -> 0.11098055 | AA14: =C50 -> 0.20098055 | AB14: =AA14+0.09 -> 0.29098055 | AC14: =AB14+0.09 -> 0.38098055 | AR14: 46012 | AS14: 0.008 | AT14: 0.0506 | AW14: 0.0615 | AX14: 0.0178
P15: =P9 -> MinaPharm | Q15: =Q9/(1+(1-C3)*'Peers Spreading'!D17) -> -0.029295917 | S15: 46048 | T15: 0.0139 | U15: -0.0031 | X15: =X16-1 -> 18.558773 | Y15: =$X$14*($X15/$C$47)*(Y$14/$C$50) -> 0.38937324 | Z15: =$X$14*($X15/$C$47)*(Z$14/$C$50) -> 2.0596628 | AA15: =$X$14*($X15/$C$47)*(AA$14/$C$50) -> 3.7299524 | AB15: =$X$14*($X15/$C$47)*(AB$14/$C$50) -> 5.4002419 | AC15: =$X$14*($X15/$C$47)*(AC$14/$C$50) -> 7.0705315 | AE15: =IF(Y15>$G$35,"Buy",IF(Y15>=$G$36,"Hold","Sell")) -> Sell | AF15: =IF(Z15>$G$35,"Buy",IF(Z15>=$G$36,"Hold","Sell")) -> Sell | AG15: =IF(AA15>$G$35,"Buy",IF(AA15>=$G$36,"Hold","Sell")) -> Sell | AH15: =IF(AB15>$G$35,"Buy",IF(AB15>=$G$36,"Hold","Sell")) -> Buy | AI15: =IF(AC15>$G$35,"Buy",IF(AC15>=$G$36,"Hold","Sell")) -> Buy | AR15: 46005 | AS15: -0.0263 | AT15: -0.0094 | AW15: -0.0076 | AX15: 0.0031
B16: Income Valuation - DCF | C16: 2025F | D16: 2026F | E16: 2027F | F16: 2028F | G16: 2029F | P16: =P10 -> Ibnsina | Q16: =Q10/(1+(1-C3)*'Peers Spreading'!E17) -> 0.067482963 | S16: 46047 | T16: 0.0085 | U16: 0 | X16: =X17-1 -> 19.558773 | Y16: =$X$14*($X16/$C$47)*(Y$14/$C$50) -> 0.41035379 | Z16: =$X$14*($X16/$C$47)*(Z$14/$C$50) -> 2.1706434 | AA16: =$X$14*($X16/$C$47)*(AA$14/$C$50) -> 3.9309329 | AB16: =$X$14*($X16/$C$47)*(AB$14/$C$50) -> 5.6912225 | AC16: =$X$14*($X16/$C$47)*(AC$14/$C$50) -> 7.4515121 | AE16: =IF(Y16>$G$35,"Buy",IF(Y16>=$G$36,"Hold","Sell")) -> Sell | AF16: =IF(Z16>$G$35,"Buy",IF(Z16>=$G$36,"Hold","Sell")) -> Sell | AG16: =IF(AA16>$G$35,"Buy",IF(AA16>=$G$36,"Hold","Sell")) -> Sell | AH16: =IF(AB16>$G$35,"Buy",IF(AB16>=$G$36,"Hold","Sell")) -> Buy | AI16: =IF(AC16>$G$35,"Buy",IF(AC16>=$G$36,"Hold","Sell")) -> Buy | AL16: Sell | AM16: =COUNTIF(AE15:AI19,"Sell") -> 13 | AN16: =AM16/$AM$19 -> 0.52 | AR16: 45998 | AS16: 0.0129 | AT16: 0.0324 | AW16: -0.0575 | AX16: 0.0462
B17: EBIT | C17: ='Financial Statements'!I26 -> 992.96263 | D17: ='Financial Statements'!J26 -> 1170.5236 | E17: ='Financial Statements'!K26 -> 1329.5248 | F17: ='Financial Statements'!L26 -> 1420.5288 | G17: ='Financial Statements'!M26 -> 1575.2655 | P17: =P11 -> Mimphis | Q17: =Q11/(1+(1-C3)*'Peers Spreading'!E17) -> -0.0022875581 | S17: 46044 | T17: 0.009 | U17: 0.0289 | W17: P/E AVG | X17: =C47 -> 20.558773 | Y17: =$X$14*($X17/$C$47)*(Y$14/$C$50) -> 0.43133434 | Z17: =$X$14*($X17/$C$47)*(Z$14/$C$50) -> 2.2816239 | AA17: =$X$14*($X17/$C$47)*(AA$14/$C$50) -> 4.1319135 | AB17: =$X$14*($X17/$C$47)*(AB$14/$C$50) -> 5.982203 | AC17: =$X$14*($X17/$C$47)*(AC$14/$C$50) -> 7.8324926 | AE17: =IF(Y17>$G$35,"Buy",IF(Y17>=$G$36,"Hold","Sell")) -> Sell | AF17: =IF(Z17>$G$35,"Buy",IF(Z17>=$G$36,"Hold","Sell")) -> Sell | AG17: =IF(AA17>$G$35,"Buy",IF(AA17>=$G$36,"Hold","Sell")) -> Sell | AH17: =IF(AB17>$G$35,"Buy",IF(AB17>=$G$36,"Hold","Sell")) -> Buy | AI17: =IF(AC17>$G$35,"Buy",IF(AC17>=$G$36,"Hold","Sell")) -> Buy | AL17: Hold | AM17: =COUNTIF(AE15:AI19,"Hold") -> 2 | AN17: =AM17/$AM$19 -> 0.08 | AR17: 45991 | AS17: 0.0365 | AT17: -0.0097 | AW17: -0.0142 | AX17: 0.02
B18: Tax Rate | C18: 0.225 | D18: 0.225 | E18: 0.225 | F18: 0.225 | G18: 0.225 | P18: =P12 -> Alex | Q18: =Q12/(1+(1-C3)*'Peers Spreading'!G17) -> -0.06977828 | S18: 46043 | T18: 0.0031 | U18: 0.0032 | X18: =X17+1 -> 21.558773 | Y18: =$X$14*($X18/$C$47)*(Y$14/$C$50) -> 0.45231488 | Z18: =$X$14*($X18/$C$47)*(Z$14/$C$50) -> 2.3926045 | AA18: =$X$14*($X18/$C$47)*(AA$14/$C$50) -> 4.332894 | AB18: =$X$14*($X18/$C$47)*(AB$14/$C$50) -> 6.2731836 | AC18: =$X$14*($X18/$C$47)*(AC$14/$C$50) -> 8.2134732 | AE18: =IF(Y18>$G$35,"Buy",IF(Y18>=$G$36,"Hold","Sell")) -> Sell | AF18: =IF(Z18>$G$35,"Buy",IF(Z18>=$G$36,"Hold","Sell")) -> Sell | AG18: =IF(AA18>$G$35,"Buy",IF(AA18>=$G$36,"Hold","Sell")) -> Hold | AH18: =IF(AB18>$G$35,"Buy",IF(AB18>=$G$36,"Hold","Sell")) -> Buy | AI18: =IF(AC18>$G$35,"Buy",IF(AC18>=$G$36,"Hold","Sell")) -> Buy | AL18: Buy | AM18: =COUNTIF(AE15:AI19,"Buy") -> 10 | AN18: =AM18/$AM$19 -> 0.4 | AR18: 45984 | AS18: -0.0065 | AT18: -0.012 | AW18: 0.027 | AX18: 0.0091
B19: NOPAT | C19: =C17*(1-C18) -> 769.54604 | D19: =D17*(1-D18) -> 907.15577 | E19: =E17*(1-E18) -> 1030.3818 | F19: =F17*(1-F18) -> 1100.9099 | G19: =G17*(1-G18) -> 1220.8308 | P19: AVG | Q19: =AVERAGE(Q14:Q15) -> 0.13521681 | S19: 46042 | T19: 0.019 | U19: -0.0096 | X19: =X18+1 -> 22.558773 | Y19: =$X$14*($X19/$C$47)*(Y$14/$C$50) -> 0.47329543 | Z19: =$X$14*($X19/$C$47)*(Z$14/$C$50) -> 2.503585 | AA19: =$X$14*($X19/$C$47)*(AA$14/$C$50) -> 4.5338746 | AB19: =$X$14*($X19/$C$47)*(AB$14/$C$50) -> 6.5641641 | AC19: =$X$14*($X19/$C$47)*(AC$14/$C$50) -> 8.5944537 | AE19: =IF(Y19>$G$35,"Buy",IF(Y19>=$G$36,"Hold","Sell")) -> Sell | AF19: =IF(Z19>$G$35,"Buy",IF(Z19>=$G$36,"Hold","Sell")) -> Sell | AG19: =IF(AA19>$G$35,"Buy",IF(AA19>=$G$36,"Hold","Sell")) -> Hold | AH19: =IF(AB19>$G$35,"Buy",IF(AB19>=$G$36,"Hold","Sell")) -> Buy | AI19: =IF(AC19>$G$35,"Buy",IF(AC19>=$G$36,"Hold","Sell")) -> Buy | AL19: Total | AM19: =SUM(AM16:AM18) -> 25 | AN19: =SUM(AN16:AN18) -> 1 | AR19: 45977 | AS19: 0.0028 | AT19: 0
B20: Non-Cash Items | C20: =-'Financial Statements'!I25 -> 91.718364 | D20: =-'Financial Statements'!J25 -> 100.12859 | E20: =-'Financial Statements'!K25 -> 107.48684 | F20: =-'Financial Statements'!L25 -> 121.01938 | G20: =-'Financial Statements'!M25 -> 123.97976 | P20: levered with average | Q20: =Q19*(1+(1-C3)*(J5/J4)) -> 0.15498374 | S20: 46041 | T20: 0.0249 | U20: 0.0097 | AR20: 45970 | AS20: 0.006 | AT20: -0.0234
B21: Less: Change in Net Working Capital | C21: =SUM('Financial Statements'!I117:I123) -> -376.42897 | D21: =SUM('Financial Statements'!J117:J123) -> -285.74963 | E21: =SUM('Financial Statements'!K117:K123) -> -330.86997 | F21: =SUM('Financial Statements'!L117:L123) -> -357.07899 | G21: =SUM('Financial Statements'!M117:M123) -> -373.87939 | S21: 46040 | T21: 0.014 | U21: 0 | W21: Table 3: EV/EBITDA SA | AR21: 45963 | AS21: 0.0439 | AT21: -0.0138
B22: Less: CAPEX | C22: =-Ratios!I44 -> -175.47074 | D22: =-Ratios!J44 -> -216.52609 | E22: =-Ratios!K44 -> -274.2653 | F22: =-Ratios!L44 -> -355.2685 | G22: =-Ratios!M44 -> -240.30365 | P22: AVG | Q22: =AVERAGE(Q8:Q12) -> 0.216 | S22: 46037 | T22: 0.0067 | U22: -0.0064 | X22: EBITDA | AR22: 45956 | AS22: 0.0154 | AT22: -0.0225
B23: Free Cash Flow (FCF) | C23: =SUM(C19:C22) -> 309.3647 | D23: =SUM(D19:D22) -> 505.00864 | E23: =SUM(E19:E22) -> 532.73334 | F23: =SUM(F19:F22) -> 509.58174 | G23: =SUM(G19:G22) -> 730.62751 | I23: =_xlfn.RRI(COLUMNS(C23:G23),C23,G23) -> 0.18753127 | S23: 46036 | T23: -0.0143 | U23: -0.0095 | X23: =C71 -> 2.9692196 | Y23: =Z23-100 -> 571.24945 | Z23: =AA23-100 -> 671.24945 | AA23: =C66 -> 771.24945 | AB23: =AA23+100 -> 871.24945 | AC23: =AB23+100 -> 971.24945 | AR23: 45949 | AS23: 0.0003 | AT23: 0.0137
B24: Terminal Value GGM | G24: =(G23*(1+J7)/J8) -> 11170.085 | H24: =(G17+G20)*C65 -> 15870.261 | S24: 46035 | T24: 0.0065 | U24: -0.0217 | X24: =X25-1 -> 7.3395937 | Y24: =$X$23*($X24/$C$65)*(Y$23/$C$66) -> 1.7282926 | Z24: =$X$23*($X24/$C$65)*(Z$23/$C$66) -> 2.0308387 | AA24: =$X$23*($X24/$C$65)*(AA$23/$C$66) -> 2.3333847 | AB24: =$X$23*($X24/$C$65)*(AB$23/$C$66) -> 2.6359308 | AC24: =$X$23*($X24/$C$65)*(AC$23/$C$66) -> 2.9384768 | AE24: =IF(Y24>$G$35,"Buy",IF(Y24>=$G$36,"Hold","Sell")) -> Sell | AF24: =IF(Z24>$G$35,"Buy",IF(Z24>=$G$36,"Hold","Sell")) -> Sell | AG24: =IF(AA24>$G$35,"Buy",IF(AA24>=$G$36,"Hold","Sell")) -> Sell | AH24: =IF(AB24>$G$35,"Buy",IF(AB24>=$G$36,"Hold","Sell")) -> Sell | AI24: =IF(AC24>$G$35,"Buy",IF(AC24>=$G$36,"Hold","Sell")) -> Sell | AL24: Sell | AM24: =COUNTIF(AE24:AI28,"Sell") -> 24 | AN24: =AM24/$AM$28 -> 0.96 | AR24: 45942 | AS24: 0.008 | AT24: 0.0162
C25: 1 | D25: 2 | E25: 3 | F25: 4 | G25: 5 | S25: 46034 | T25: 0.0119 | U25: -0.0123 | X25: =X26-1 -> 8.3395937 | Y25: =$X$23*($X25/$C$65)*(Y$23/$C$66) -> 1.9637679 | Z25: =$X$23*($X25/$C$65)*(Z$23/$C$66) -> 2.307535 | AA25: =$X$23*($X25/$C$65)*(AA$23/$C$66) -> 2.6513022 | AB25: =$X$23*($X25/$C$65)*(AB$23/$C$66) -> 2.9950693 | AC25: =$X$23*($X25/$C$65)*(AC$23/$C$66) -> 3.3388364 | AE25: =IF(Y25>$G$35,"Buy",IF(Y25>=$G$36,"Hold","Sell")) -> Sell | AF25: =IF(Z25>$G$35,"Buy",IF(Z25>=$G$36,"Hold","Sell")) -> Sell | AG25: =IF(AA25>$G$35,"Buy",IF(AA25>=$G$36,"Hold","Sell")) -> Sell | AH25: =IF(AB25>$G$35,"Buy",IF(AB25>=$G$36,"Hold","Sell")) -> Sell | AI25: =IF(AC25>$G$35,"Buy",IF(AC25>=$G$36,"Hold","Sell")) -> Sell | AL25: Sell | AM25: =COUNTIF(AE24:AI28,"Sell") -> 24 | AN25: =AM25/$AM$28 -> 0.96 | AR25: 45935 | AS25: 0.0129 | AT25: -0.0023
B26: PV | C26: =C23/(1+C11)^C25 -> 251.10587 | D26: =D23/(1+D11)^D25 -> 346.87711 | E26: =E23/(1+E11)^E25 -> 333.21232 | F26: =F23/(1+F11)^F25 -> 302.51541 | G26: =G23/(1+G11)^G25 -> 380.14221 | S26: 46033 | T26: 0.0248 | U26: 0.0156 | W26: EBITDA AVG | X26: =C65 -> 9.3395937 | Y26: =$X$23*($X26/$C$65)*(Y$23/$C$66) -> 2.1992431 | Z26: =$X$23*($X26/$C$65)*(Z$23/$C$66) -> 2.5842314 | AA26: =$X$23*($X26/$C$65)*(AA$23/$C$66) -> 2.9692196 | AB26: =$X$23*($X26/$C$65)*(AB$23/$C$66) -> 3.3542078 | AC26: =$X$23*($X26/$C$65)*(AC$23/$C$66) -> 3.739196 | AE26: =IF(Y26>$G$35,"Buy",IF(Y26>=$G$36,"Hold","Sell")) -> Sell | AF26: =IF(Z26>$G$35,"Buy",IF(Z26>=$G$36,"Hold","Sell")) -> Sell | AG26: =IF(AA26>$G$35,"Buy",IF(AA26>=$G$36,"Hold","Sell")) -> Sell | AH26: =IF(AB26>$G$35,"Buy",IF(AB26>=$G$36,"Hold","Sell")) -> Sell | AI26: =IF(AC26>$G$35,"Buy",IF(AC26>=$G$36,"Hold","Sell")) -> Sell | AL26: Hold | AM26: =COUNTIF(AE24:AI28,"Hold") -> 1 | AN26: =AM26/$AM$28 -> 0.04 | AR26: 45928 | AS26: 0.0345 | AT26: 0.064
B27: TV GGM | G27: =G24/(1+G11)^G25 -> 5811.7453 | H27: =H24/(1+G11)^G25 -> 8257.2254 | S27: 46030 | T27: 0.0075 | U27: -0.0273 | X27: =X26+1 -> 10.339594 | Y27: =$X$23*($X27/$C$65)*(Y$23/$C$66) -> 2.4347184 | Z27: =$X$23*($X27/$C$65)*(Z$23/$C$66) -> 2.8609277 | AA27: =$X$23*($X27/$C$65)*(AA$23/$C$66) -> 3.287137 | AB27: =$X$23*($X27/$C$65)*(AB$23/$C$66) -> 3.7133463 | AC27: =$X$23*($X27/$C$65)*(AC$23/$C$66) -> 4.1395556 | AE27: =IF(Y27>$G$35,"Buy",IF(Y27>=$G$36,"Hold","Sell")) -> Sell | AF27: =IF(Z27>$G$35,"Buy",IF(Z27>=$G$36,"Hold","Sell")) -> Sell | AG27: =IF(AA27>$G$35,"Buy",IF(AA27>=$G$36,"Hold","Sell")) -> Sell | AH27: =IF(AB27>$G$35,"Buy",IF(AB27>=$G$36,"Hold","Sell")) -> Sell | AI27: =IF(AC27>$G$35,"Buy",IF(AC27>=$G$36,"Hold","Sell")) -> Sell | AL27: Buy | AM27: =COUNTIF(AE24:AI28,"Buy") -> 0 | AN27: =AM27/$AM$28 -> 0 | AR27: 45921 | AS27: 0.0076 | AT27: -0.0073
B28: Enterprice Value | C28: =SUM(C26:G26,G28) -> 8648.3383 | G28: =AVERAGE(G27:H27) -> 7034.4853 | S28: 46028 | T28: 0.0213 | U28: 0.0185 | X28: =X27+1 -> 11.339594 | Y28: =$X$23*($X28/$C$65)*(Y$23/$C$66) -> 2.6701936 | Z28: =$X$23*($X28/$C$65)*(Z$23/$C$66) -> 3.137624 | AA28: =$X$23*($X28/$C$65)*(AA$23/$C$66) -> 3.6050544 | AB28: =$X$23*($X28/$C$65)*(AB$23/$C$66) -> 4.0724848 | AC28: =$X$23*($X28/$C$65)*(AC$23/$C$66) -> 4.5399152 | AE28: =IF(Y28>$G$35,"Buy",IF(Y28>=$G$36,"Hold","Sell")) -> Sell | AF28: =IF(Z28>$G$35,"Buy",IF(Z28>=$G$36,"Hold","Sell")) -> Sell | AG28: =IF(AA28>$G$35,"Buy",IF(AA28>=$G$36,"Hold","Sell")) -> Sell | AH28: =IF(AB28>$G$35,"Buy",IF(AB28>=$G$36,"Hold","Sell")) -> Sell | AI28: =IF(AC28>$G$35,"Buy",IF(AC28>=$G$36,"Hold","Sell")) -> Hold | AL28: Total | AM28: =SUM(AM25:AM27) -> 25 | AN28: =SUM(AN25:AN27) -> 1 | AR28: 45914 | AS28: 0.0133 | AT28: -0.0192
B29: Add: | S29: 46027 | T29: -0.0054 | U29: -0.0182 | AR29: 45907 | AS29: 0.005 | AT29: 0.0271
B30: ='Financial Statements'!B58 -> Due from related parties | C30: ='Financial Statements'!H58 -> 0.0255 | S30: 46026 | T30: -0.0223 | U30: -0.009 | AR30: 45900 | AS30: -0.027 | AT30: -0.0514
B31: Cash | C31: ='Financial Statements'!H57+'Financial Statements'!H60 -> 254.39175 | S31: 46022 | T31: 0.0033 | U31: 0.006 | AR31: 45893 | AS31: 0.0029 | AT31: 0.0142
B32: Less: | S32: 46021 | T32: -0.001 | U32: 0.003 | AR32: 45886 | AS32: 0.0013 | AT32: -0.0254
B33: Interest bearing liability | C33: ='Financial Statements'!H82+'Financial Statements'!H88+'Financial Statements'!H89+'Financial Statements'!H90 -> 1519.1346 | S33: 46020 | T33: 0.0031 | U33: -0.012 | AR33: 45879 | AS33: -0.0065 | AT33: -0.0442
B34: ='Financial Statements'!B76 -> Non-controlling interest | C34: ='Financial Statements'!H76 -> 27.376784 | S34: 46019 | T34: 0.0085 | U34: 0.006 | AR34: 45872 | AS34: 0.0471 | AT34: 0.0044
B35: Fair Value of shareholder equity | C35: =C28+C30+C31-C33-C34 -> 7356.2441 | D35: =IF(C36>G35,"Buy",IF(C36>=G36,"Hold","Sell")) -> Sell | F35: buy after | G35: =J2*(1+G11) -> 4.8318767 | S35: 46016 | T35: -0.0062 | U35: 0.0122 | AR35: 45865 | AS35: 0.0021 | AT35: 0.0158
B36: DCF Fair Value Per Share | C36: =C35/J3 -> 3.6781221 | F36: Hold until | G36: =J2 -> 4.24 | S36: 46015 | T36: 0.0021 | U36: 0.0218 | AR36: 45858 | AS36: 0.009 | AT36: -0.0067
B37: =IF(C36>=J2,"Upside","Downside") -> Downside | C37: =C36/J2-1 -> -0.13251838 | S37: 46014 | T37: 0.0077 | U37: 0.0158 | AR37: 45851 | AS37: 0.0149 | AT37: -0.0132
S38: 46013 | T38: -0.0059 | U38: 0.0032 | AR38: 45844 | AS38: 0.0154 | AT38: 0.0272
B39: Multiples Method | S39: 46012 | T39: 0.0103 | U39: -0.0032 | AR39: 45837 | AS39: -0.0055 | AT39: -0.0413
B40: P/E Ratio | C40: EIPICO | D40: MinaPharm | E40: IbnSina | F40: Memphis | G40: Alex Pharma | S40: 46009 | T40: -0.0139 | U40: 0.0032 | AR40: 45830 | AS40: 0.0911 | AT40: 0.0952
B41: Net Profit | C41: 1022.1901 | D41: 162.79141 | E41: 620.52574 | F41: 127.2 | G41: 94.25 | S41: 46008 | T41: -0.0119 | U41: -0.0063 | AR41: 45823 | AS41: -0.0696 | AT41: -0.0749
B42: Number of Shares | C42: 148.75575 | D42: 11.064096 | E42: 1008 | F42: 22.75 | G42: 5 | S42: 46007 | T42: -0.0072 | U42: -0.0094 | AR42: 45816 | AS42: -0.0051 | AT42: 0.0134
B43: Earnings Per Share | C43: =C41/C42 -> 6.8716003 | D43: =D41/D42 -> 14.713485 | E43: =E41/E42 -> 0.61560093 | F43: =F41/F42 -> 5.5912088 | G43: =G41/G42 -> 18.85 | S43: 46006 | T43: 0.0057 | U43: 0.0095 | AR43: 45809 | AS43: -0.0006 | AT43: -0.0067
B44: Market Price Per Share | C44: 45.91 | D44: 320 | E44: 3.23 | F44: 153.13 | G44: 786.6 | S44: 46005 | T44: 0.0007 | U44: -0.0063 | AR44: 45802 | AS44: 0.0226 | AT44: 0
B45: P/E | C45: =C44/C43 -> 6.681122 | D45: =D44/D43 -> 21.748757 | E45: =E44/E43 -> 5.2469057 | F45: =F44/F43 -> 27.387638 | G45: =G44/G43 -> 41.729443 | S45: 46002 | T45: -0.0005 | U45: 0.0063 | AR45: 45795 | AS45: 0.0011 | AT45: -0.0465
S46: 46001 | T46: 0.0027 | U46: 0.0128 | AR46: 45788 | AS46: 0.0053 | AT46: 0.0396
B47: AVG P/E | C47: =AVERAGE(C45:G45) -> 20.558773 | S47: 46000 | T47: -0.0005 | U47: 0.0032 | AR47: 45781 | AS47: -0.011 | AT47: -0.0381
B48: RMDA No. of Shares | C48: =J3 -> 2000 | S48: 45999 | T48: 0.0048 | U48: 0.0032 | AR48: 45774 | AS48: 0.0154 | AT48: 0.0849
B49: RMDA Net Profit LTM | C49: ='Financial Statements'!H38 -> 401.9611 | S49: 45998 | T49: 0.0063 | U49: 0.0065 | AR49: 45767 | AS49: 0.0186 | AT49: 0.014
B50: RMDA EPS | C50: =C49/C48 -> 0.20098055 | S50: 45995 | T50: 0.0038 | U50: -0.0252 | AR50: 45760 | AS50: 0.0082 | AT50: -0.038
B51: P/E Fair Value Per Share | C51: =C50*C47 -> 4.1319135 | D51: =IF(C51>G35,"Buy",IF(C51>=G36,"Hold","Sell")) -> Sell | S51: 45994 | T51: 0.0176 | U51: 0.0062 | AR51: 45753 | AS51: -0.028 | AT51: -0.0022
S52: 45993 | T52: -0.0017 | U52: 0.0121 | AR52: 45746 | AS52: -0.0102 | AT52: 0.0182
B53: EV/EBITDA | C53: =F40 -> Memphis | D53: =D40 -> MinaPharm | E53: =E40 -> IbnSina | F53: =C40 -> EIPICO | G53: =G40 -> Alex Pharma | S53: 45992 | T53: -0.0015 | U53: -0.0048 | AR53: 45739 | AS53: 0.011 | AT53: 0.028
B54: Market Price Per Share | C54: =F44 -> 153.13 | D54: =D44 -> 320 | E54: =E44 -> 3.23 | F54: =C44 -> 45.91 | G54: =G44 -> 786.6 | S54: 45991 | T54: 0.0178 | U54: 0.0024 | AR54: 45732 | AS54: 0.0124 | AT54: -0.0756
B55: Number of Shares | C55: =F42 -> 22.75 | D55: =D42 -> 11.064096 | E55: =E42 -> 1008 | F55: =C42 -> 148.75575 | G55: =G42 -> 5 | S55: 45988 | T55: 0.0127 | U55: 0 | AR55: 45725 | AS55: 0.0111 | AT55: 0.0998
B56: Market Cap | C56: =C54*C55 -> 3483.7075 | D56: =D54*D55 -> 3540.5107 | E56: =E54*E55 -> 3255.84 | F56: =F54*F55 -> 6829.3765 | G56: =G54*G55 -> 3933 | S56: 45987 | T56: -0.0092 | U56: 0 | AR56: 45718 | AS56: 0.011 | AT56: 0.0194
B57: Long Term Debt | C57: 110.16815 | D57: 689.85023 | E57: 1023.6401 | F57: 4782.1286 | G57: 1.24 | S57: 45986 | T57: 0.0045 | U57: -0.0072 | AR57: 45711 | AS57: -0.0098 | AT57: 0.0955
B58: Short Term Debt | C58: 850.63345 | D58: 3083.3428 | E58: 10227.333 | F58: 4376.401 | G58: 13.52 | S58: 45985 | T58: -0.0178 | U58: -0.0024 | AR58: 45704 | AS58: 0.0306 | AT58: 0.1254
B59: Interest Bearing Debt | C59: =SUM(C57:C58) -> 960.8016 | D59: =SUM(D57:D58) -> 3773.193 | E59: =SUM(E57:E58) -> 11250.974 | F59: =SUM(F57:F58) -> 9158.5296 | G59: =SUM(G58:G58) -> 13.52 | S59: 45984 | T59: 0.0036 | U59: -0.0024 | AR59: 45697 | AS59: -0.0005 | AT59: -0.0669
B60: Cash | C60: 553.61363 | D60: 1507.7751 | E60: 1023.6401 | F60: 1257.9212 | G60: 34.46 | S60: 45981 | T60: -0.0051 | U60: -0.0024 | AR60: 45690 | AS60: 0 | AT60: -0.0028
B61: Enterprice Value | C61: =(C56+C59)-C60 -> 3890.8955 | D61: =(D56+D59)-D60 -> 5805.9286 | E61: =(E56+E59)-E60 -> 13483.173 | F61: =(F56+F59)-F60 -> 14729.985 | G61: =(G56+G59)-G60 -> 3912.06 | S61: 45980 | T61: 0.0002 | U61: -0.0048 | AR61: 45683 | AS61: 0.0004 | AT61: 0.0619
B62: EBITDA | C62: 362.82131 | D62: 778.94121 | E62: 2473.5061 | F62: 1523.5532 | G62: 291.92 | S62: 45979 | T62: -0.0137 | U62: -0.0186 | AR62: 45676 | AS62: 0.0133 | AT62: 0.0399
B63: EV/EBITDA | C63: =C61/C62 -> 10.723999 | D63: =D61/D62 -> 7.4536159 | E63: =E61/E62 -> 5.451037 | F63: =F61/F62 -> 9.6681791 | G63: =G61/G62 -> 13.401137 | S63: 45978 | T63: -0.0035 | U63: 0.0313 | AR63: 45669 | AS63: 0.0054 | AT63: -0.0765
S64: 45977 | T64: 0.0254 | U64: -0.0048 | AR64: 45662 | AS64: -0.0205 | AT64: 0.0352
B65: AVG EBITDA | C65: =AVERAGE(C63:G63) -> 9.3395937 | S65: 45974 | T65: -0.0009 | U65: 0.0024 | AR65: 45655 | AS65: 0.0034 | AT65: 0.021
B66: RMDA LTM EBITDA | C66: ='Financial Statements'!H20 -> 771.24945 | S66: 45973 | T66: -0.0008 | U66: -0.0071 | AR66: 45648 | AS66: -0.0186 | AT66: -0.0147
B67: RMDA Enterprice Value | C67: =C65*C66 -> 7203.1565 | S67: 45972 | T67: -0.0041 | U67: 0.0048 | AR67: 45641 | AS67: -0.0087 | AT67: -0.0029
B68: RMDA Net Debt | C68: =C33-C30-C31 -> 1264.7174 | S68: 45971 | T68: -0.0097 | U68: -0.0095 | AR68: 45634 | AS68: -0.0014 | AT68: -0.0202
B69: Shareholder Equity Fair Value | C69: =C67-C68 -> 5938.4392 | S69: 45970 | T69: 0.0218 | U69: -0.014 | AR69: 45627 | AS69: 0.0198 | AT69: 0.0029
B70: =B48 -> RMDA No. of Shares | C70: =C48 -> 2000 | S70: 45967 | T70: 0.0209 | U70: 0.0288 | AR70: 45620 | AS70: -0.0127 | AT70: 0.0267
B71: EV/EBITDA Fair Value Per Share | C71: =C69/C70 -> 2.9692196 | D71: =IF(C71>G35,"Buy",IF(C71>=G36,"Hold","Sell")) -> Sell | S71: 45966 | T71: 0.0017 | U71: -0.0165 | AR71: 45613 | AS71: -0.0264 | AT71: -0.0534
S72: 45965 | T72: 0.0115 | U72: -0.007 | AR72: 45606 | AS72: 0.0062 | AT72: -0.0193
C73: Fair Value | D73: Weights | E73: Weighted Average FV | S73: 45964 | T73: 0.0142 | U73: -0.0093 | AR73: 45599 | AS73: 0.0199 | AT73: 0.0111
B74: DCF | C74: =C36 -> 3.6781221 | D74: =1-SUM(D75:D76) -> 0.7 | E74: =C74*D74 -> 2.5746854 | S74: 45963 | T74: -0.0048 | U74: -0.0092 | AR74: 45592 | AS74: 0.0034 | AT74: -0.0747
B75: EV/EBITDA | C75: =C71 -> 2.9692196 | D75: 0.15 | E75: =C75*D75 -> 0.44538294 | S75: 45960 | T75: 0.001 | U75: -0.0136 | AR75: 45585 | AS75: 0.0136 | AT75: 0.0992
B76: P/E | C76: =C51 -> 4.1319135 | D76: 0.15 | E76: =C76*D76 -> 0.61978702 | S76: 45959 | T76: -0.002 | U76: 0.0023 | AR76: 45578 | AS76: -0.0201 | AT76: 0.165
B77: Total | E77: =SUM(E74:E76) -> 3.6398554 | F77: =IF(E77>G35,"Buy",IF(E77>=G36,"Hold","Sell")) -> Sell | S77: 45958 | T77: 0.0037 | U77: -0.0135 | AR77: 45571 | AS77: -0.0302 | AT77: -0.035
B78: =IF(E77>=G36,"Upside","Downside") -> Downside | E78: =E77/J2-1 -> -0.14154354 | S78: 45957 | T78: 0.0016 | U78: -0.0111 | AR78: 45564 | AS78: 0.0142 | AT78: 0.1418
S79: 45956 | T79: 0.011 | U79: 0.0135 | AR79: 45557 | AS79: 0.011 | AT79: 0.0377
S80: 45953 | T80: 0.0029 | U80: -0.0022 | AR80: 45550 | AS80: 0.0144 | AT80: 0.0311
S81: 45952 | T81: -0.0032 | U81: -0.0067 | AR81: 45543 | AS81: -0.0171 | AT81: -0.0039
S82: 45951 | T82: -0.0073 | U82: 0 | AR82: 45536 | AS82: 0.0083 | AT82: 0.1026
S83: 45950 | T83: 0.0017 | U83: 0.0228 | AR83: 45529 | AS83: 0.021 | AT83: -0.025
S84: 45949 | T84: 0.0062 | U84: 0 | AR84: 45522 | AS84: 0.0173 | AT84: 0.0169
S85: 45946 | T85: 0.0006 | U85: 0 | AR85: 45515 | AS85: 0.0305 | AT85: -0.0445
S86: 45945 | T86: 0.0052 | U86: 0.0023 | AR86: 45508 | AS86: -0.0207 | AT86: 0.0601
S87: 45944 | T87: 0.0013 | U87: 0.0186 | AR87: 45501 | AS87: 0.0093 | AT87: 0.0219
S88: 45943 | T88: 0.0008 | U88: 0 | AR88: 45494 | AS88: 0.0152 | AT88: -0.0215
S89: 45942 | T89: 0 | U89: -0.0046 | AR89: 45487 | AS89: 0.0129 | AT89: 0.0043
S90: 45938 | T90: 0.0075 | U90: 0.0023 | AR90: 45480 | AS90: -0.0027 | AT90: -0.0085
... S270: 45662 | T270: 0.0041 | U270: 0.0557 | AR270: 44199 | AS270: 0.0099 | AT270: -0.0341
S271: 45659 | T271: 0.0108 | U271: 0.021
S272: 45657 | T272: 0.0142 | U272: 0.0152
S273: 45656 | T273: -0.0091 | U273: -0.012
S274: 45655 | T274: -0.0121 | U274: -0.003
S275: 45652 | T275: -0.0016 | U275: 0.003
S276: 45651 | T276: 0.0011 | U276: -0.0235
S277: 45650 | T277: -0.0048 | U277: 0.0333
S278: 45649 | T278: -0.0084 | U278: -0.0323
S279: 45648 | T279: -0.005 | U279: 0.0059
...

Sheet Peers Spreading
B1: Category | C1: EBICO | D1: IbnSina | E1: MinaPharm
B2: Gross Profit Margin | C2: 0.4525 | D2: 0.08 | E2: 0.331
B3: EBITDA Margin | C3: 0.2008 | D3: 0.045 | E3: 0.23
B4: EBIT Margin | C4: 0.19 | D4: 0.0405 | E4: 0.21
B5: EBT Margin | C5: 0.192 | D5: 0.0128 | E5: 0.05
B6: Net Profit Margin | C6: 0.14 | D6: 0.0111 | E6: 0.0484
B7: Current Ratio | C7: 1.34 | D7: 1 | E7: 0.9
B8: Quick Ratio | C8: 0.76 | D8: 0.74 | E8: 0.64
B9: Cash Ratio | C9: 0.21 | D9: 0.03 | E9: 0.28
B10: Total Liabilities to Equity | C10: 2.43 | D10: 12.74 | E10: 2.46
B11: Total Assets to Equity | C11: 3.43 | D11: 13.74 | E11: 1.46
B12: Volume Sold
B13: ASP
C14: EIPICO | D14: MinaPharm | E14: ibnsina | F14: memphis | G14: alex
B15: Net Debt | C15: 7646 | D15: 2152 | E15: 4220 | F15: 1115 | G15: 474
B16: Market Cap | C16: 1392 | D16: 5530 | E16: 11880 | F16: 3300 | G16: 3890
B17: Total D/E "Investing" | C17: 1.4218 | D17: 0.9119 | E17: 9.9909 | F17: 0.1505 | G17: 0.0041

Sheet ESG MSCI Score
B1: MSCI Framework ESG Score
B3: Pillars | C3: Main Theme | D3: Key Issues | E3: Risk-based Key Issue | F3: Opportunity-based Key Issue | G3: Weights | H3: Weighted Score | N3: Materiality Key themes and it's sub contents
B4: Environmental | G4: 0.3 | N4: Environment | S4: Governance (Deduction Method)
C5: Climate Change | D5: GHG Emissions | E5: =7-(MAX(Q6,2)-P6) -> 7.5 | F5: =Q6*P6/10 -> 3.9 | G5: =$G$4/COUNTA($D$5:$D$9) -> 0.06 | H5: =AVERAGE(E5:F5)*G5 -> 0.342 | I5: =(E5+F5)/2 -> 5.7 | N5: Theme | O5: Key issues | P5: Management Score | Q5: Exposure Score | S5: Theme | T5: Key Issue | U5: Key Metrics | V5: Points | W5: Max Value | X5: Score
D6: Climate Strategy | E6: =7-(MAX(Q7,2)-P7) -> 8 | F6: =Q7*P7/10 -> 3 | G6: =$G$4/COUNTA($D$5:$D$9) -> 0.06 | H6: =AVERAGE(E6:F6)*G6 -> 0.33 | I6: =(E6+F6)/2 -> 5.5 | N6: Climate Change | O6: GHG Emissions | P6: 6.5 | Q6: 6 | S6: Corporate Governance | T6: Board (58) | U6: % Indpendent Directors | V6: =U43 -> 4 | W6: =$W$10/COUNTA($U$6:$U$9) -> 14.5 | X6: =10*(1-V6/W6) -> 7.2413793
C7: Natural Capital & Waste | D7: Water Stress | E7: =7-(MAX(Q8,2)-P8) -> 4.5 | F7: =Q8*P8/10 -> 7.5 | G7: =$G$4/COUNTA($D$5:$D$9) -> 0.06 | H7: =AVERAGE(E7:F7)*G7 -> 0.36 | I7: =(E7+F7)/2 -> 6 | O7: Climate Strategy | P7: 6 | Q7: 5 | U7: Board Diversity | V7: =U46 -> 3 | W7: =$W$10/COUNTA($U$6:$U$9) -> 14.5 | X7: =10*(1-V7/W7) -> 7.9310345
D8: Waste Management | E8: =7-(MAX(Q9,2)-P9) -> 7 | F8: =Q9*P9/10 -> 4.9 | G8: =$G$4/COUNTA($D$5:$D$9) -> 0.06 | H8: =AVERAGE(E8:F8)*G8 -> 0.357 | I8: =(E8+F8)/2 -> 5.95 | N8: Natural Capital & Waste | O8: Water Stress | P8: 7.5 | Q8: 10 | U8: CEO = Chair duality | V8: =U44 -> 4 | W8: =$W$10/COUNTA($U$6:$U$9) -> 14.5 | X8: =10*(1-V8/W8) -> 7.2413793
C9: Environmental Management | D9: Environmental Policy & Management | E9: =7-(MAX(Q10,2)-P10) -> 9 | F9: =Q10*P10/10 -> 5.525 | G9: =$G$4/COUNTA($D$5:$D$9) -> 0.06 | H9: =AVERAGE(E9:F9)*G9 -> 0.43575 | I9: =(E9+F9)/2 -> 7.2625 | O9: Waste Management | P9: 7 | Q9: 7 | U9: Avg. Director Tenure | V9: =U45 -> 2 | W9: =$W$10/COUNTA($U$6:$U$9) -> 14.5 | X9: =10*(1-V9/W9) -> 8.6206897
I10: =SUM(I5:I9)/5 -> 6.0825 | N10: Environmental Management | O10: Environmental Policy & Management | P10: 8.5 | Q10: 6.5 | S10: Total | V10: =SUM(V6:V9) -> 13 | W10: 58 | X10: =10*(1-V10/W10) -> 7.7586207
B11: Social | G11: 0.3 | T11: Ownership (29) | U11: Staggered Board | V11: =U50 -> 4 | W11: =$W$13/COUNTA($U$11:$U$12) -> 14.5 | X11: =10*(1-V11/W11) -> 7.2413793
C12: Product Liability | D12: Product Quality & Safety | E12: =7-(MAX(Q14,2)-P14) -> 7 | F12: =Q14*P14/10 -> 8.1 | G12: =$G$11/COUNTA($D$12:$D$18) -> 0.042857143 | H12: =AVERAGE(E12:F12)*G12 -> 0.32357143 | I12: =(E12+F12)/2 -> 7.55 | N12: Social | U12: Controlling Shareholder | V12: =U49 -> 3 | W12: =$W$13/COUNTA($U$11:$U$12) -> 14.5 | X12: =10*(1-V12/W12) -> 7.9310345
D13: Product Recalls | E13: =7-(MAX(Q15,2)-P15) -> 8.5 | F13: =Q15*P15/10 -> 7.6 | G13: =$G$11/COUNTA($D$12:$D$18) -> 0.042857143 | H13: =AVERAGE(E13:F13)*G13 -> 0.345 | I13: =(E13+F13)/2 -> 8.05 | N13: Theme | O13: Key issues | S13: Total | V13: =SUM(V11:V12) -> 7 | W13: 29 | X13: =10*(1-V13/W13) -> 7.5862069
D14: Product Design & Lifecycle Management | E14: =7-(MAX(Q16,2)-P16) -> 7 | F14: =Q16*P16/10 -> 7.225 | G14: =$G$11/COUNTA($D$12:$D$18) -> 0.042857143 | H14: =AVERAGE(E14:F14)*G14 -> 0.30482143 | I14: =(E14+F14)/2 -> 7.1125 | N14: Product Liability | O14: Product Quality & Safety | P14: 9 | Q14: 9 | T14: Pay (22) | U14: ESG-Linked Metrics | V14: 5 | W14: =$W$16/COUNTA($U$14:$U$15) -> 11 | X14: =10*(1-V14/W14) -> 5.4545455
C15: Social Opportunity | D15: Healthcare Accessablilty | E15: =7-(MAX(Q17,2)-P17) -> 7 | F15: =Q17*P17/10 -> 9.025 | G15: =$G$11/COUNTA($D$12:$D$18) -> 0.042857143 | H15: =AVERAGE(E15:F15)*G15 -> 0.34339286 | I15: =(E15+F15)/2 -> 8.0125 | O15: Product Recalls | P15: 9.5 | Q15: 8 | U15: Pay Transparency | V15: 5 | W15: =$W$16/COUNTA($U$14:$U$15) -> 11 | X15: =10*(1-V15/W15) -> 5.4545455
D16: Customer Wellfare & Relations | E16: =7-(MAX(Q18,2)-P18) -> 8 | F16: =Q18*P18/10 -> 5.6 | G16: =$G$11/COUNTA($D$12:$D$18) -> 0.042857143 | H16: =AVERAGE(E16:F16)*G16 -> 0.29142857 | I16: =(E16+F16)/2 -> 6.8 | O16: Product Design & Lifecycle Management | P16: 8.5 | Q16: 8.5 | S16: Total | V16: =SUM(V14:V15) -> 10 | W16: 22 | X16: =10*(1-V16/W16) -> 5.4545455
C17: Human Capital | D17: Human Capital Development | E17: =7-(MAX(Q19,2)-P19) -> 9.5 | F17: =Q19*P19/10 -> 5.1 | G17: =$G$11/COUNTA($D$12:$D$18) -> 0.042857143 | H17: =AVERAGE(E17:F17)*G17 -> 0.31285714 | I17: =(E17+F17)/2 -> 7.3 | N17: Social Opportunity | O17: Healthcare Accessablilty | P17: 9.5 | Q17: 9.5 | T17: Accounting (17) | U17: Auditor Tenure | V17: =U35 -> 3 | W17: =$W$19/COUNTA($U$17:$U$18) -> 8.5 | X17: =10*(1-V17/W17) -> 6.4705882
D18: Labor & Health and Safety | E18: =7-(MAX(Q20,2)-P20) -> 9 | F18: =Q20*P20/10 -> 6.3 | G18: =$G$11/COUNTA($D$12:$D$18) -> 0.042857143 | H18: =AVERAGE(E18:F18)*G18 -> 0.32785714 | I18: =(E18+F18)/2 -> 7.65 | O18: Customer Wellfare & Relations | P18: 8 | Q18: 7 | U18: Material Weakness | V18: =U34 -> 0 | W18: =$W$19/COUNTA($U$17:$U$18) -> 8.5 | X18: =10*(1-V18/W18) -> 10
I19: =SUM(I12:I18)/COUNT(I12:I18) -> 7.4964286 | N19: Human Capital | O19: Human Capital Development | P19: 8.5 | Q19: 6 | S19: Total | V19: =SUM(V17:V18) -> 3 | W19: 17 | X19: =10*(1-V19/W19) -> 8.2352941
B20: Governance | G20: 0.4 | O20: Labor & Health and Safety | P20: 9 | Q20: 7 | S20: Total Corporate Governance | V20: =SUM(V10,V13,V16,V19) -> 33 | W20: 100 | X20: =10*(1-V20/W20) -> 6.7
C21: Corporate Governance | D21: Board | E21: =X10 -> 7.7586207 | G21: =$G$20/COUNTA($D$21:$D$26) -> 0.066666667 | H21: =E21*G21 -> 0.51724138 | I21: =E21 -> 7.7586207
D22: Ownership | E22: =X13 -> 7.5862069 | G22: =$G$20/COUNTA($D$21:$D$26) -> 0.066666667 | H22: =E22*G22 -> 0.50574713 | I22: =E22 -> 7.5862069 | S22: Corporate Behaviour | T22: Business Ethics (49) | U22: Whistleblowing | V22: =U39 -> 1 | W22: =$W$24/COUNTA($U$22:$U$23) -> 24.5 | X22: =10*(1-V22/W22) -> 9.5918367
D23: Pay | E23: =X16 -> 5.4545455 | G23: =$G$20/COUNTA($D$21:$D$26) -> 0.066666667 | H23: =E23*G23 -> 0.36363636 | I23: =E23 -> 5.4545455 | U23: Anti-Bribery Training | V23: =U38 -> 0 | W23: =$W$24/COUNTA($U$22:$U$23) -> 24.5 | X23: =10*(1-V23/W23) -> 10
D24: Accounting | E24: =X19 -> 8.2352941 | G24: =$G$20/COUNTA($D$21:$D$26) -> 0.066666667 | H24: =E24*G24 -> 0.54901961 | I24: =E24 -> 8.2352941 | S24: Total | V24: =SUM(V22:V23) -> 1 | W24: 49 | X24: =10*(1-V24/W24) -> 9.7959184
C25: Corporate Behaviour | D25: Business Ethics | E25: =X24 -> 9.7959184 | G25: =$G$20/COUNTA($D$21:$D$26) -> 0.066666667 | H25: =E25*G25 -> 0.65306122 | I25: =E25 -> 9.7959184 | T25: Tax Transparency (10) | U25: Country-by-country | V25: 5 | W25: 10 | X25: =10*(1-V25/W25) -> 5
D26: Tax Transparency | E26: =X26 -> 5 | G26: =$G$20/COUNTA($D$21:$D$26) -> 0.066666667 | H26: =E26*G26 -> 0.33333333 | I26: =E26 -> 5 | S26: Total | V26: =V25 -> 5 | W26: =W25 -> 10 | X26: =10*(1-V26/W26) -> 5
I27: =SUM(I21:J26)/COUNT(I21:J26) -> 7.3050976 | S27: Total Corporate Behaviour | V27: =SUM(V24+V26) -> 6 | W27: 50 | X27: =10*(1-V27/W27) -> 8.8
S28: Total Raw Deduction | X28: =+V27+V20 -> 39
B29: Total | E29: =COUNT(E5:E9,E12:E18,E21:E27) -> 18 | F29: =COUNT(F5:F9,F12:F18,F21:F27) -> 12 | G29: =SUM(G5:G9,G12:G18,G21:G27) -> 1 | S29: Final Governance score | X29: =10*(1-X28/128) -> 6.953125
F30: Weighted Average Key Issue Score "WAKIS" | H30: =SUM(H5:H9,H12:H18,H21:H26) -> 6.9957176
F31: Total Available score | H31: 10
F32: Final Score Percentage | H32: =H30/H31 -> 0.69957176 | S32: Key Issue | T32: Key Metric | U32: Points
F33: industry_min | H33: ='ESG IAS'!AE7 -> 4.4724286 | S33: Audit & Controls | T33: Financial restatement | U33: 6 | AA33: is that for Governance?
F34: industry_max | H34: ='ESG IAS'!AF7 -> 7.7988571 | S34: Audit & Controls | T34: Material weakness | U34: 0 | AA34: MSCI Framework Scoring Guidelines
F35: Industry-Adjusted Score "IAS" | H35: =ROUND(MAX(0,MIN(10, 10*(H30-H33)/(H34-H33))),1) -> 7.6 | S35: Audit & Controls | T35: Auditor tenure | U35: 3 | AA35: Risk-Based Key Issue Scores (0–10)
F36: MSCI Score | H36: {=_xlfn.IFS(H35>=8.571,"AAA",H35>=7.143,"AA",H35>=5.714,"A",H35>=4.286,"BBB",H35>=2.857,"BB",H35>=1.429,"B",TRUE,"CCC")} -> AA | S36: Total | U36: =SUM(U33:U35) -> 9 | AA36: Score | AB36: Detailed Description
AA37: 10 | AB37: Very low ESG risk. Industry-leading governance and controls. Risks are minimal and well anticipated. Strong policies, KPIs, audits, and board oversight fully aligned with exposure.
S38: Business Ethics | T38: Bribery/major ethics controversy | U38: 0 | AA38: 9 | AB38: Excellent risk management. Minor residual risks exist but are actively monitored and mitigated. Controls are proactive and regularly improved.
S39: Business Ethics | T39: Whistleblower policy strength | U39: 1 | AA39: 8 | AB39: Strong ESG risk controls. Clear policies, good implementation, and limited exposure. Some gaps, but unlikely to cause material issues.
S40: Business Ethics | T40: Political spending disclosure | U40: 5 | AA40: 7 | AB40: Generally effective risk management. Exposure exists, but controls are mostly adequate. Occasional weaknesses or inconsistent enforcement.
S41: Total | U41: =SUM(U38:U40) -> 6 | AA41: 6 | AB41: Acceptable ESG risk management. Policies exist, but implementation may lag in certain areas. Risks are manageable but not fully optimized.
AA42: 5 | AB42: Moderate ESG risk. Basic controls in place, but they are reactive rather than proactive. Exposure could lead to issues if conditions worsen.
S43: Board Independence | T43: % Independent directors | U43: 4 | AA43: 4 | AB43: Below-average risk management. Controls are weak or uneven. ESG risks are known but insufficiently addressed.
S44: Board Independence | T44: CEO = Chair | U44: 4 | AA44: 3 | AB44: High ESG risk. Limited policies, weak enforcement, and material exposure. Past incidents or controversies may exist.
S45: Board Independence | T45: Avg director tenure | U45: 2 | AA45: 2 | AB45: Very high ESG risk. Poor governance and minimal controls. ESG risks are largely unmanaged and likely to cause financial or reputational damage.
S46: Board Independence | T46: Board diversity | U46: 3 | AA46: 1 | AB46: Severe ESG risk. Systemic management failure, repeated violations, and very high exposure.
S47: Total | U47: =SUM(U43:U46) -> 13 | AA47: 0 | AB47: Extreme ESG risk. No meaningful risk management. Very poor governance and typically very high exposure. ESG risks are almost certain to materialize.
S49: Shareholder Rights | T49: class shares | U49: 3
S50: Shareholder Rights | T50: Staggered board | U50: 4
S51: Shareholder Rights | T51: Special meeting "EGM" | U51: 6
S52: Total | U52: =SUM(U49:U51) -> 13

Sheet ESG IAS
B3: Main Theme | C3: Key issues | D3: Weights | E3: RMDA | F3: RMDA WS | G3: PHAR | H3: PHAR WS | I3: GSK | J3: GSK WS | K3: MIPH | L3: MIPH WS | M3: AXPH | N3: AXPH WS | O3: OCPH | P3: OCPH WS | Q3: CPCI | R3: CPCI WS | S3: ADCI | T3: ADCI WS | U3: NIPH | V3: NIPH WS | W3: MPCI | X3: MPCI WS
B4: Environmental | D4: 0.3
B5: Climate Change | C5: GHG Emissions | D5: =$D$4/COUNTA($C$5:$C$9) -> 0.06 | E5: =AVERAGE('ESG MSCI Score'!E5:F5) -> 5.7 | F5: =E5*$D$5 -> 0.342 | G5: 6 | H5: =G5*$D$5 -> 0.36 | I5: 8.5 | J5: =I5*$D$5 -> 0.51 | K5: 7 | L5: =K5*$D$5 -> 0.42 | M5: 4 | N5: =M5*$D$5 -> 0.24 | O5: 4.5 | P5: =O5*$D$5 -> 0.27 | Q5: 3.5 | R5: =Q5*$D$5 -> 0.21 | S5: 4.2 | T5: =S5*$D$5 -> 0.252 | U5: 3.5 | V5: =U5*$D$5 -> 0.21 | W5: 4 | X5: =W5*$D$5 -> 0.24 | AA5: Peer Comparison Summary
C6: Climate Strategy | D6: =$D$4/COUNTA($C$5:$C$9) -> 0.06 | E6: =AVERAGE('ESG MSCI Score'!E6:F6) -> 5.5 | F6: =E6*$D$5 -> 0.33 | G6: 5 | H6: =G6*$D$5 -> 0.3 | I6: 9 | J6: =I6*$D$5 -> 0.54 | K6: 6.5 | L6: =K6*$D$5 -> 0.39 | M6: 3 | N6: =M6*$D$5 -> 0.18 | O6: 3.5 | P6: =O6*$D$5 -> 0.21 | Q6: 2.5 | R6: =Q6*$D$5 -> 0.15 | S6: 3 | T6: =S6*$D$5 -> 0.18 | U6: 2.5 | V6: =U6*$D$5 -> 0.15 | W6: 3 | X6: =W6*$D$5 -> 0.18 | AB6: WAKIS | AC6: TAS | AD6: FSP | AE6: IMIN | AF6: IMAX | AG6: IAS | AH6: MSCI Score
B7: Natural Capital & Waste | C7: Water Stress | D7: =$D$4/COUNTA($C$5:$C$9) -> 0.06 | E7: =AVERAGE('ESG MSCI Score'!E7:F7) -> 6 | F7: =E7*$D$5 -> 0.36 | G7: 6.5 | H7: =G7*$D$5 -> 0.39 | I7: 7.5 | J7: =I7*$D$5 -> 0.45 | K7: 5.5 | L7: =K7*$D$5 -> 0.33 | M7: 4.5 | N7: =M7*$D$5 -> 0.27 | O7: 4 | P7: =O7*$D$5 -> 0.24 | Q7: 3.5 | R7: =Q7*$D$5 -> 0.21 | S7: 4 | T7: =S7*$D$5 -> 0.24 | U7: 3.5 | V7: =U7*$D$5 -> 0.21 | W7: 4 | X7: =W7*$D$5 -> 0.24 | AA7: RMDA | AB7: =SUM(F5:F9,F12:F18,F21:F26) -> 6.9957176 | AC7: 10 | AD7: =AB7/$AC$7 -> 0.69957176 | AE7: =_xlfn.PERCENTILE.INC($AB$7:$AB$16,0.05) -> 4.4724286 | AF7: =_xlfn.PERCENTILE.INC($AB$7:$AB$16,0.95) -> 7.7988571 | AG7: =ROUND(MAX(0,MIN(10,10*(AB7-AE7)/(AF7-AE7))),1) -> 7.6 | AH7: {=_xlfn.IFS(AG7>=8.571,"AAA",AG7>=7.143,"AA",AG7>=5.714,"A",AG7>=4.286,"BBB",AG7>=2.857,"BB",AG7>=1.429,"B",TRUE,"CCC")} -> AA
C8: Waste Management | D8: =$D$4/COUNTA($C$5:$C$9) -> 0.06 | E8: =AVERAGE('ESG MSCI Score'!E8:F8) -> 5.95 | F8: =E8*$D$5 -> 0.357 | G8: 5.5 | H8: =G8*$D$5 -> 0.33 | I8: 8 | J8: =I8*$D$5 -> 0.48 | K8: 6 | L8: =K8*$D$5 -> 0.36 | M8: 3.5 | N8: =M8*$D$5 -> 0.21 | O8: 4 | P8: =O8*$D$5 -> 0.24 | Q8: 3 | R8: =Q8*$D$5 -> 0.18 | S8: 3.5 | T8: =S8*$D$5 -> 0.21 | U8: 3 | V8: =U8*$D$5 -> 0.18 | W8: 4 | X8: =W8*$D$5 -> 0.24 | AA8: PHAR | AB8: =SUM(H5:H9,H12:H18,H21:H26) -> 6.8319048 | AC8: 10 | AD8: =AB8/$AC$7 -> 0.68319048 | AE8: =_xlfn.PERCENTILE.INC($AB$7:$AB$16,0.05) -> 4.4724286 | AF8: =_xlfn.PERCENTILE.INC($AB$7:$AB$16,0.95) -> 7.7988571 | AG8: =ROUND(MAX(0,MIN(10,10*(AB8-AE8)/(AF8-AE8))),1) -> 7.1 | AH8: {=_xlfn.IFS(AG8>=8.571,"AAA",AG8>=7.143,"AA",AG8>=5.714,"A",AG8>=4.286,"BBB",AG8>=2.857,"BB",AG8>=1.429,"B",TRUE,"CCC")} -> A
B9: Environmental Management | C9: Environmental Policy & Management | D9: =$D$4/COUNTA($C$5:$C$9) -> 0.06 | E9: =AVERAGE('ESG MSCI Score'!E9:F9) -> 7.2625 | F9: =E9*$D$5 -> 0.43575 | G9: 7 | H9: =G9*$D$5 -> 0.42 | I9: 9.5 | J9: =I9*$D$5 -> 0.57 | K9: 8 | L9: =K9*$D$5 -> 0.48 | M9: 5 | N9: =M9*$D$5 -> 0.3 | O9: 5.5 | P9: =O9*$D$5 -> 0.33 | Q9: 4.5 | R9: =Q9*$D$5 -> 0.27 | S9: 5 | T9: =S9*$D$5 -> 0.3 | U9: 4.5 | V9: =U9*$D$5 -> 0.27 | W9: 5 | X9: =W9*$D$5 -> 0.3 | AA9: GSK | AB9: =SUM(J5:J9,J12:J18,J21:J26) -> 8.2985714 | AC9: 10 | AD9: =AB9/$AC$7 -> 0.82985714 | AE9: =_xlfn.PERCENTILE.INC($AB$7:$AB$16,0.05) -> 4.4724286 | AF9: =_xlfn.PERCENTILE.INC($AB$7:$AB$16,0.95) -> 7.7988571 | AG9: =ROUND(MAX(0,MIN(10,10*(AB9-AE9)/(AF9-AE9))),1) -> 10 | AH9: {=_xlfn.IFS(AG9>=8.571,"AAA",AG9>=7.143,"AA",AG9>=5.714,"A",AG9>=4.286,"BBB",AG9>=2.857,"BB",AG9>=1.429,"B",TRUE,"CCC")} -> AAA
AA10: MIPH | AB10: =SUM(L5:L9,L12:L18,L21:L26) -> 7.1880952 | AC10: 10 | AD10: =AB10/$AC$7 -> 0.71880952 | AE10: =_xlfn.PERCENTILE.INC($AB$7:$AB$16,0.05) -> 4.4724286 | AF10: =_xlfn.PERCENTILE.INC($AB$7:$AB$16,0.95) -> 7.7988571 | AG10: =ROUND(MAX(0,MIN(10,10*(AB10-AE10)/(AF10-AE10))),1) -> 8.2 | AH10: {=_xlfn.IFS(AG10>=8.571,"AAA",AG10>=7.143,"AA",AG10>=5.714,"A",AG10>=4.286,"BBB",AG10>=2.857,"BB",AG10>=1.429,"B",TRUE,"CCC")} -> AA
B11: Social | D11: 0.3 | AA11: AXPH | AB11: =SUM(N5:N9,N12:N18,N21:N26) -> 5.2033333 | AC11: 10 | AD11: =AB11/$AC$7 -> 0.52033333 | AE11: =_xlfn.PERCENTILE.INC($AB$7:$AB$16,0.05) -> 4.4724286 | AF11: =_xlfn.PERCENTILE.INC($AB$7:$AB$16,0.95) -> 7.7988571 | AG11: =ROUND(MAX(0,MIN(10,10*(AB11-AE11)/(AF11-AE11))),1) -> 2.2 | AH11: {=_xlfn.IFS(AG11>=8.571,"AAA",AG11>=7.143,"AA",AG11>=5.714,"A",AG11>=4.286,"BBB",AG11>=2.857,"BB",AG11>=1.429,"B",TRUE,"CCC")} -> B
B12: Product Liability | C12: Product Quality & Safety | D12: =$D$11/COUNTA($C$12:$C$18) -> 0.042857143 | E12: =AVERAGE('ESG MSCI Score'!E12:F12) -> 7.55 | F12: =E12*$D$12 -> 0.32357143 | G12: 8.5 | H12: =G12*$D$12 -> 0.36428571 | I12: 9 | J12: =I12*$D$12 -> 0.38571429 | K12: 8.5 | L12: =K12*$D$12 -> 0.36428571 | M12: 7 | N12: =M12*$D$12 -> 0.3 | O12: 7.5 | P12: =O12*$D$12 -> 0.32142857 | Q12: 6.5 | R12: =Q12*$D$12 -> 0.27857143 | S12: 7 | T12: =S12*$D$12 -> 0.3 | U12: 6.5 | V12: =U12*$D$12 -> 0.27857143 | W12: 7.5 | X12: =W12*$D$12 -> 0.32142857 | AA12: OCPH | AB12: =SUM(P5:P9,P12:P18,P21:P26) -> 5.6452381 | AC12: 10 | AD12: =AB12/$AC$7 -> 0.56452381 | AE12: =_xlfn.PERCENTILE.INC($AB$7:$AB$16,0.05) -> 4.4724286 | AF12: =_xlfn.PERCENTILE.INC($AB$7:$AB$16,0.95) -> 7.7988571 | AG12: =ROUND(MAX(0,MIN(10,10*(AB12-AE12)/(AF12-AE12))),1) -> 3.5 | AH12: {=_xlfn.IFS(AG12>=8.571,"AAA",AG12>=7.143,"AA",AG12>=5.714,"A",AG12>=4.286,"BBB",AG12>=2.857,"BB",AG12>=1.429,"B",TRUE,"CCC")} -> BB
C13: Product Recalls | D13: =$D$11/COUNTA($C$12:$C$18) -> 0.042857143 | E13: =AVERAGE('ESG MSCI Score'!E13:F13) -> 8.05 | F13: =E13*$D$12 -> 0.345 | G13: 7.5 | H13: =G13*$D$12 -> 0.32142857 | I13: 8.5 | J13: =I13*$D$12 -> 0.36428571 | K13: 7.5 | L13: =K13*$D$12 -> 0.32142857 | M13: 6 | N13: =M13*$D$12 -> 0.25714286 | O13: 6.5 | P13: =O13*$D$12 -> 0.27857143 | Q13: 6 | R13: =Q13*$D$12 -> 0.25714286 | S13: 6.5 | T13: =S13*$D$12 -> 0.27857143 | U13: 6 | V13: =U13*$D$12 -> 0.25714286 | W13: 6.5 | X13: =W13*$D$12 -> 0.27857143 | AA13: CPCI | AB13: =SUM(R5:R9,R12:R18,R21:R26) -> 4.5295238 | AC13: 10 | AD13: =AB13/$AC$7 -> 0.45295238 | AE13: =_xlfn.PERCENTILE.INC($AB$7:$AB$16,0.05) -> 4.4724286 | AF13: =_xlfn.PERCENTILE.INC($AB$7:$AB$16,0.95) -> 7.7988571 | AG13: =ROUND(MAX(0,MIN(10,10*(AB13-AE13)/(AF13-AE13))),1) -> 0.2 | AH13: {=_xlfn.IFS(AG13>=8.571,"AAA",AG13>=7.143,"AA",AG13>=5.714,"A",AG13>=4.286,"BBB",AG13>=2.857,"BB",AG13>=1.429,"B",TRUE,"CCC")} -> CCC
C14: Product Design & Lifecycle Management | D14: =$D$11/COUNTA($C$12:$C$18) -> 0.042857143 | E14: =AVERAGE('ESG MSCI Score'!E14:F14) -> 7.1125 | F14: =E14*$D$12 -> 0.30482143 | G14: 7 | H14: =G14*$D$12 -> 0.3 | I14: 7.5 | J14: =I14*$D$12 -> 0.32142857 | K14: 9 | L14: =K14*$D$12 -> 0.38571429 | M14: 6.5 | N14: =M14*$D$12 -> 0.27857143 | O14: 6 | P14: =O14*$D$12 -> 0.25714286 | Q14: 5.5 | R14: =Q14*$D$12 -> 0.23571429 | S14: 5.5 | T14: =S14*$D$12 -> 0.23571429 | U14: 6 | V14: =U14*$D$12 -> 0.25714286 | W14: 5.5 | X14: =W14*$D$12 -> 0.23571429 | AA14: ADCI | AB14: =SUM(T5:T9,T12:T18,T21:T26) -> 4.9439048 | AC14: 10 | AD14: =AB14/$AC$7 -> 0.49439048 | AE14: =_xlfn.PERCENTILE.INC($AB$7:$AB$16,0.05) -> 4.4724286 | AF14: =_xlfn.PERCENTILE.INC($AB$7:$AB$16,0.95) -> 7.7988571 | AG14: =ROUND(MAX(0,MIN(10,10*(AB14-AE14)/(AF14-AE14))),1) -> 1.4 | AH14: {=_xlfn.IFS(AG14>=8.571,"AAA",AG14>=7.143,"AA",AG14>=5.714,"A",AG14>=4.286,"BBB",AG14>=2.857,"BB",AG14>=1.429,"B",TRUE,"CCC")} -> CCC
B15: Social Opportunity | C15: Healthcare Accessablilty | D15: =$D$11/COUNTA($C$12:$C$18) -> 0.042857143 | E15: =AVERAGE('ESG MSCI Score'!E15:F15) -> 8.0125 | F15: =E15*$D$12 -> 0.34339286 | G15: 9 | H15: =G15*$D$12 -> 0.38571429 | I15: 8.5 | J15: =I15*$D$12 -> 0.36428571 | K15: 8 | L15: =K15*$D$12 -> 0.34285714 | M15: 7.5 | N15: =M15*$D$12 -> 0.32142857 | O15: 6 | P15: =O15*$D$12 -> 0.25714286 | Q15: 7.5 | R15: =Q15*$D$12 -> 0.32142857 | S15: 7.5 | T15: =S15*$D$12 -> 0.32142857 | U15: 6.5 | V15: =U15*$D$12 -> 0.27857143 | W15: 6.5 | X15: =W15*$D$12 -> 0.27857143 | AA15: NIPH | AB15: =SUM(V5:V9,V12:V18,V21:V26) -> 4.4257143 | AC15: 10 | AD15: =AB15/$AC$7 -> 0.44257143 | AE15: =_xlfn.PERCENTILE.INC($AB$7:$AB$16,0.05) -> 4.4724286 | AF15: =_xlfn.PERCENTILE.INC($AB$7:$AB$16,0.95) -> 7.7988571 | AG15: =ROUND(MAX(0,MIN(10,10*(AB15-AE15)/(AF15-AE15))),1) -> 0 | AH15: {=_xlfn.IFS(AG15>=8.571,"AAA",AG15>=7.143,"AA",AG15>=5.714,"A",AG15>=4.286,"BBB",AG15>=2.857,"BB",AG15>=1.429,"B",TRUE,"CCC")} -> CCC
C16: Customer Wellfare & Relations | D16: =$D$11/COUNTA($C$12:$C$18) -> 0.042857143 | E16: =AVERAGE('ESG MSCI Score'!E16:F16) -> 6.8 | F16: =E16*$D$12 -> 0.29142857 | G16: 8 | H16: =G16*$D$12 -> 0.34285714 | I16: 8 | J16: =I16*$D$12 -> 0.34285714 | K16: 7.5 | L16: =K16*$D$12 -> 0.32142857 | M16: 6 | N16: =M16*$D$12 -> 0.25714286 | O16: 6 | P16: =O16*$D$12 -> 0.25714286 | Q16: 5.5 | R16: =Q16*$D$12 -> 0.23571429 | S16: 6 | T16: =S16*$D$12 -> 0.25714286 | U16: 5.5 | V16: =U16*$D$12 -> 0.23571429 | W16: 6 | X16: =W16*$D$12 -> 0.25714286 | AA16: MPCI | AB16: =SUM(X5:X9,X12:X18,X21:X26) -> 5.1166667 | AC16: 10 | AD16: =AB16/$AC$7 -> 0.51166667 | AE16: =_xlfn.PERCENTILE.INC($AB$7:$AB$16,0.05) -> 4.4724286 | AF16: =_xlfn.PERCENTILE.INC($AB$7:$AB$16,0.95) -> 7.7988571 | AG16: =ROUND(MAX(0,MIN(10,10*(AB16-AE16)/(AF16-AE16))),1) -> 1.9 | AH16: {=_xlfn.IFS(AG16>=8.571,"AAA",AG16>=7.143,"AA",AG16>=5.714,"A",AG16>=4.286,"BBB",AG16>=2.857,"BB",AG16>=1.429,"B",TRUE,"CCC")} -> B
B17: Human Capital | C17: Human Capital Development | D17: =$D$11/COUNTA($C$12:$C$18) -> 0.042857143 | E17: =AVERAGE('ESG MSCI Score'!E17:F17) -> 7.3 | F17: =E17*$D$12 -> 0.31285714 | G17: 7 | H17: =G17*$D$12 -> 0.3 | I17: 8.5 | J17: =I17*$D$12 -> 0.36428571 | K17: 8.5 | L17: =K17*$D$12 -> 0.36428571 | M17: 6 | N17: =M17*$D$12 -> 0.25714286 | O17: 6.5 | P17: =O17*$D$12 -> 0.27857143 | Q17: 5.5 | R17: =Q17*$D$12 -> 0.23571429 | S17: 6 | T17: =S17*$D$12 -> 0.25714286 | U17: 7 | V17: =U17*$D$12 -> 0.3 | W17: 6.5 | X17: =W17*$D$12 -> 0.27857143
C18: Labor & Health and Safety | D18: =$D$11/COUNTA($C$12:$C$18) -> 0.042857143 | E18: =AVERAGE('ESG MSCI Score'!E18:F18) -> 7.65 | F18: =E18*$D$12 -> 0.32785714 | G18: 8.5 | H18: =G18*$D$12 -> 0.36428571 | I18: 9 | J18: =I18*$D$12 -> 0.38571429 | K18: 7.5 | L18: =K18*$D$12 -> 0.32142857 | M18: 6.5 | N18: =M18*$D$12 -> 0.27857143 | O18: 6.5 | P18: =O18*$D$12 -> 0.27857143 | Q18: 6.5 | R18: =Q18*$D$12 -> 0.27857143 | S18: 6.5 | T18: =S18*$D$12 -> 0.27857143 | U18: 6.5 | V18: =U18*$D$12 -> 0.27857143 | W18: 7 | X18: =W18*$D$12 -> 0.3
B20: Governance | D20: 0.4
B21: Corporate Governance | C21: Board | D21: =$D$20/COUNTA($C$21:$C$26) -> 0.066666667 | E21: ='ESG MSCI Score'!E21 -> 7.7586207 | F21: =E21*$D$21 -> 0.51724138 | G21: 5.8 | H21: =G21*$D$21 -> 0.38666667 | I21: 7.8 | J21: =I21*$D$21 -> 0.52 | K21: 6.5 | L21: =K21*$D$21 -> 0.43333333 | M21: 4.8 | N21: =M21*$D$21 -> 0.32 | O21: 6.1 | P21: =O21*$D$21 -> 0.40666667 | Q21: 3 | R21: =Q21*$D$21 -> 0.2 | S21: 3.5 | T21: =S21*$D$21 -> 0.23333333 | U21: 2.8 | V21: =U21*$D$21 -> 0.18666667 | W21: 4.2 | X21: =W21*$D$21 -> 0.28
C22: Ownership | D22: =$D$20/COUNTA($C$21:$C$26) -> 0.066666667 | E22: ='ESG MSCI Score'!E22 -> 7.5862069 | F22: =E22*$D$21 -> 0.50574713 | G22: 6.5 | H22: =G22*$D$21 -> 0.43333333 | I22: 8.5 | J22: =I22*$D$21 -> 0.56666667 | K22: 5.5 | L22: =K22*$D$21 -> 0.36666667 | M22: 5 | N22: =M22*$D$21 -> 0.33333333 | O22: 7 | P22: =O22*$D$21 -> 0.46666667 | Q22: 4 | R22: =Q22*$D$21 -> 0.26666667 | S22: 4 | T22: =S22*$D$21 -> 0.26666667 | U22: 3.5 | V22: =U22*$D$21 -> 0.23333333 | W22: 5 | X22: =W22*$D$21 -> 0.33333333
C23: Pay | D23: =$D$20/COUNTA($C$21:$C$26) -> 0.066666667 | E23: ='ESG MSCI Score'!E23 -> 5.4545455 | F23: =E23*$D$21 -> 0.36363636 | G23: 6 | H23: =G23*$D$21 -> 0.4 | I23: 7.2 | J23: =I23*$D$21 -> 0.48 | K23: 6.8 | L23: =K23*$D$21 -> 0.45333333 | M23: 5.5 | N23: =M23*$D$21 -> 0.36666667 | O23: 6 | P23: =O23*$D$21 -> 0.4 | Q23: 4.5 | R23: =Q23*$D$21 -> 0.3 | S23: 5 | T23: =S23*$D$21 -> 0.33333333 | U23: 4.5 | V23: =U23*$D$21 -> 0.3 | W23: 5 | X23: =W23*$D$21 -> 0.33333333
C24: Accounting | D24: =$D$20/COUNTA($C$21:$C$26) -> 0.066666667 | E24: ='ESG MSCI Score'!E24 -> 8.2352941 | F24: =E24*$D$21 -> 0.54901961 | G24: 7.5 | H24: =G24*$D$21 -> 0.5 | I24: 8.8 | J24: =I24*$D$21 -> 0.58666667 | K24: 8 | L24: =K24*$D$21 -> 0.53333333 | M24: 6 | N24: =M24*$D$21 -> 0.4 | O24: 6.5 | P24: =O24*$D$21 -> 0.43333333 | Q24: 5 | R24: =Q24*$D$21 -> 0.33333333 | S24: 5.5 | T24: =S24*$D$21 -> 0.36666667 | U24: 4.5 | V24: =U24*$D$21 -> 0.3 | W24: 5.5 | X24: =W24*$D$21 -> 0.36666667
B25: Corpoorate Behaviour | C25: Business Ethics | D25: =$D$20/COUNTA($C$21:$C$26) -> 0.066666667 | E25: ='ESG MSCI Score'!E25 -> 9.7959184 | F25: =E25*$D$21 -> 0.65306122 | G25: 7 | H25: =G25*$D$21 -> 0.46666667 | I25: 9 | J25: =I25*$D$21 -> 0.6 | K25: 8.2 | L25: =K25*$D$21 -> 0.54666667 | M25: 5 | N25: =M25*$D$21 -> 0.33333333 | O25: 5.8 | P25: =O25*$D$21 -> 0.38666667 | Q25: 4.5 | R25: =Q25*$D$21 -> 0.3 | S25: 5 | T25: =S25*$D$21 -> 0.33333333 | U25: 4 | V25: =U25*$D$21 -> 0.26666667 | W25: 5 | X25: =W25*$D$21 -> 0.33333333
C26: Tax Transparency | D26: =$D$20/COUNTA($C$21:$C$26) -> 0.066666667 | E26: ='ESG MSCI Score'!E26 -> 5 | F26: =E26*$D$21 -> 0.33333333 | G26: 7 | H26: =G26*$D$21 -> 0.46666667 | I26: 7 | J26: =I26*$D$21 -> 0.46666667 | K26: 6.8 | L26: =K26*$D$21 -> 0.45333333 | M26: 4.5 | N26: =M26*$D$21 -> 0.3 | O26: 5 | P26: =O26*$D$21 -> 0.33333333 | Q26: 4 | R26: =Q26*$D$21 -> 0.26666667 | S26: 4.5 | T26: =S26*$D$21 -> 0.3 | U26: 3.5 | V26: =U26*$D$21 -> 0.23333333 | W26: 4.8 | X26: =W26*$D$21 -> 0.32

Sheet ESG Defend
B2: The Defend and Rationale Behind the Scoring
B3: Environmental | C3: Main Theme | D3: Key Issues | E3: Defend | O3: Source | AB3: MSCI Framework Scoring Guidelines
C4: Climate Change | D4: GHG Emissions | E4: Rameda faces moderate exposure as a manufacturer, but is actively mitigating Scope 1 and 2 risks by transitioning from diesel to natural gas. It systematically monitors emissions data but lacks detailed Scope 3 disclosures. | O4: https://ramedapharma.com/environmental-leadership/ | AB4: Risk-Based Key Issue Scores (0–10)
D5: Climate Strategy | E5: The company has matured its strategy through TCFD reporting and a partnership with the IFC to "green" its operations. However, it lacks science-based "Net Zero" target dates common among global leaders. | O5: https://ramedapharma-ir.com/ar/tcfd-report-23/ | AB5: Score | AC5: Detailed Description
C6: Natural Capital & Waste | D6: Water Stress | E6: Operating 100% in Egypt creates extreme exposure. Management is strong due to a new 2024 water treatment station expected to reduce annual freshwater consumption by 50%. | O6: https://ramedapharma-ir.com/wp-content/uploads/2024/02/Rameda-NR-Water-Treatment-Station-E.pdf | AB6: 10 | AC6: Very low ESG risk. Industry-leading governance and controls. Risks are minimal and well anticipated. Strong policies, KPIs, audits, and board oversight fully aligned with exposure.
D7: Waste Management | E7: High exposure from hazardous pharma waste. Management utilizes a circular model, reselling untreatable solid waste to cement producers for co-processing. | O7: https://ramedapharma.com/environmental-leadership/ | AB7: 9 | AC7: Excellent risk management. Minor residual risks exist but are actively monitored and mitigated. Controls are proactive and regularly improved.
C8: Environmental Management | D8: Environmental Policy & Management | E8: Strong management through ISO 14001:2015 certification across all factories. The company demonstrates full compliance with Egyptian environmental laws (EEAA). | O8: https://ramedapharma.com/environmental-leadership/ | AB8: 8 | AC8: Strong ESG risk controls. Clear policies, good implementation, and limited exposure. Some gaps, but unlikely to cause material issues.
AB9: 7 | AC9: Generally effective risk management. Exposure exists, but controls are mostly adequate. Occasional weaknesses or inconsistent enforcement.
B10: Social | AB10: 6 | AC10: Acceptable ESG risk management. Policies exist, but implementation may lag in certain areas. Risks are manageable but not fully optimized.
C11: Product Liability | D11: Product Quality & Safety | E11: High inherent risk in pharma. Management is "Best-in-Class" with ISO 9001:2015 and WHO GMP compliance across all production lines. | O11: https://ramedapharma.com/overview-2/ | AB11: 5 | AC11: Moderate ESG risk. Basic controls in place, but they are reactive rather than proactive. Exposure could lead to issues if conditions worsen.
D12: Product Recalls | E12: The company maintains a Zero Class I and Class II recall record for 2024-2025. Risk is managed via a robust SAP Batch Traceability system. | O12: https://ramedapharma-ir.com/wp-content/uploads/2024/10/Rameda-ESG-Presentation-1Q24.pdf | AB12: 4 | AC12: Below-average risk management. Controls are weak or uneven. ESG risks are known but insufficiently addressed.
D13: Product Design & Lifecycle Management | E13: Rameda captures social opportunity by "designing" its portfolio for Chronic Disease needs in Egypt (Diabetes, Cardio) through strategic, accretive acquisitions. | O13: https://ramedapharma-ir.com/wp-content/uploads/2025/07/Rameda-Initiates-First-Acquisition-of-2025-.pdf | AB13: 3 | AC13: High ESG risk. Limited policies, weak enforcement, and material exposure. Past incidents or controversies may exist.
C14: Social Opportunity | D14: Healthcare Accessablilty | E14: Strongest performance area. Rameda repriced 90% of its revenue base in 2024 with the Egyptian Drug Authority (EDA) to ensure essential medicines remained available during inflation. | O14: https://ramedapharma-ir.com/wp-content/uploads/2025/04/Rameda-FY24-Investor-Presentation-.pdf | AB14: 2 | AC14: Very high ESG risk. Poor governance and minimal controls. ESG risks are largely unmanaged and likely to cause financial or reputational damage.
D15: Customer Wellfare & Relations | E15: Managed through a strict Code of Conduct and ethical marketing to physicians. The company emphasizes patient well-being in its core business philosophy. | O15: https://ramedapharma.com/wp-content/uploads/2021/03/Code-of-Conduct-English-1.pdf | AB15: 1 | AC15: Severe ESG risk. Systemic management failure, repeated violations, and very high exposure.
C16: Human Capital | D16: Human Capital Development | E16: Strong institutional management via the Rameda Learning and Development Academy (RLDA). Women represent 29% of the workforce, supported by wellness and sports programs. | O16: https://ramedapharma.com/health-safety/ | AB16: 0 | AC16: Extreme ESG risk. No meaningful risk management. Very poor governance and typically very high exposure. ESG risks are almost certain to materialize.
D17: Labor & Health and Safety | E17: Certified under OHSAS 18001:2007. The company reported a Total Injury Frequency Rate of 0.0 per million hours worked. | O17: https://ramedapharma.com/health-safety/
AB18: Opportunity-Based Key Issue Scores (0–10)
B19: Governance | AB19: Score | AC19: Detailed Description
C20: Corporate Governance | D20: Board | E20: Strong separation of CEO/Chair roles; Non-executive majority. | O20: https://ramedapharma-ir.com/wp-content/uploads/2024/04/BOD-Shareholding-Structure-2024-Q1.pdf | AB20: 10 | AC20: Best-in-class ESG opportunity positioning. Core business model directly benefits from ESG trends (e.g. renewables, inclusive finance). Clear strategy, strong revenue contribution.
D21: Ownership | E21: EGX listing ensures minority protection despite block shareholders | O21: https://ramedapharma.com/governance/ | AB21: 9 | AC21: Very strong ESG opportunity capture. ESG products/services are a major growth driver with clear competitive advantage.
D22: Pay | E22: Oversight is provided by the Board's Strategy Committee. The company demonstrated resilience during the 2024 FX crisis and "market confusion" setbacks. | O22: https://ramedapharma-ir.com/wp-content/uploads/2025/09/1H25-SF-Earnings-Investor-Presentation.pdf | AB22: 8 | AC22: Strong positioning. ESG opportunities are embedded in strategy and product development, though not yet dominant revenue sources.
D23: Accounting | E23: Clean audit history; active Audit Committee oversight. | O23: https://ramedapharma-ir.com/wp-content/uploads/2025/09/1H25-SF-Earnings-Investor-Presentation.pdf | AB23: 7 | AC23: Good opportunity alignment. ESG initiatives contribute meaningfully to growth but remain secondary to core operations.
C24: Corporate Behaviour | D24: Business Ethics | E24: Formal Code of Conduct and whistleblower protections in place. | O24: https://ramedapharma.com/wp-content/uploads/2021/03/Code-of-Conduct-English-1.pdf | AB24: 6 | AC24: Moderate–good ESG opportunity exposure. Clear initiatives exist, but scale or monetization is still developing.
D25: Tax transparency | E25: Full compliance with local Egyptian tax laws and disclosure. | O25: https://www.egx.com.eg/downloads/Bulletins/330001_2.pdf | AB25: 5 | AC25: Moderate position. Some ESG-aligned products or services, but limited strategic focus or financial impact so far.
AB26: 4 | AC26: Weak–moderate opportunity capture. ESG initiatives exist mainly for compliance or branding rather than growth.
AB27: 3 | AC27: Weak ESG opportunity positioning. Minimal innovation related to ESG trends. Little revenue impact.
AB28: 2 | AC28: Very weak positioning. ESG opportunities are largely ignored or underdeveloped.
AB29: 1 | AC29: Almost no ESG opportunity focus. Business model is misaligned with ESG trends.
AB30: 0 | AC30: No ESG opportunity exposure. No initiatives, products, or services benefiting from ESG-related demand.
D39: Governance
E40: Key issue | F40: Points | G40: Maximum Value | H40: 0-10
D41: 1 | E41: Board Independence | F41: =G70 -> 13 | G41: =G43/COUNTA($E$41:$E$42) -> 29 | H41: =10*(1-F41/G41) -> 5.5172414
D42: 2 | E42: Shareholder Rights | F42: =G75 -> 13 | G42: =G43/COUNTA($E$41:$E$42) -> 29 | H42: =10*(1-F42/G42) -> 5.5172414 | J42: it is demo numbers of score bardo to score the points
D43: Corporate Governance | E43: Board & Oversight | F43: =+F41+F42 -> 26 | G43: 58 | H43: =10*(1-F43/G43) -> 5.5172414 | J43: Look at the picture u will find i put the total which is 100 and 128 and 50
E45: Ownership | F45: 10 | G45: 29 | H45: =10*(1-F45/G45) -> 6.5517241
E46: Accounting | F46: 10 | G46: 17 | H46: =10*(1-F46/G46) -> 4.1176471
E48: Corporate governance | F48: =F43+F45+F46 -> 46 | G48: 100 | H48: =10*(1-F48/G48) -> 5.4
D49: 3 | E49: Audit & Controls | F49: =G59 -> 9 | G49: =G51/COUNTA($E$49:$E$50) -> 24.5 | H49: =10*(1-F49/G49) -> 6.3265306 | J49: but in board alone is 58 and ethics alone is 49 so add ur max value and adjust accordingly
D50: 4 | E50: Business Ethics | F50: =G64 -> 6 | G50: =G51/COUNTA($E$49:$E$50) -> 24.5 | H50: =10*(1-F50/G50) -> 7.5510204
D51: Corporate behavior | E51: Ethics & Transparency | F51: =+F49+F50 -> 15 | G51: 49 | H51: =10*(1-F51/G51) -> 6.9387755
E52: Corporate behavior | F52: =F51 -> 15 | G52: 50 | H52: =10*(1-F52/G52) -> 7
E53: Governance Pillar | F53: =F52+F48 -> 61 | G53: 128 | H53: =10*(1-F53/G53) -> 5.234375
E55: Key Issue | F55: Key Metric | G55: Points
E56: Audit & Controls | F56: Financial restatement | G56: 6
E57: Audit & Controls | F57: Material weakness | G57: 0
E58: Audit & Controls | F58: Auditor tenure | G58: 3
E59: Total | G59: =SUM(G56:G58) -> 9
E61: Business Ethics | F61: Bribery/major ethics controversy | G61: 0
E62: Business Ethics | F62: Whistleblower policy strength | G62: 1
E63: Business Ethics | F63: Political spending disclosure | G63: 5
E64: Total | G64: =SUM(G61:G63) -> 6
E66: Board Independence | F66: % Independent directors | G66: 4
E67: Board Independence | F67: CEO = Chair | G67: 4
E68: Board Independence | F68: Avg director tenure | G68: 2
E69: Board Independence | F69: Board diversity | G69: 3
E70: Total | G70: =SUM(G66:G69) -> 13
E72: Shareholder Rights | F72: class shares | G72: 3
E73: Shareholder Rights | F73: Staggered board | G73: 4
E74: Shareholder Rights | F74: Special meeting "EGM" | G74: 6
E75: Total | G75: =SUM(G72:G74) -> 13

Sheet Ratios
B1: Profitability Ratios
B2: Ratio | C2: Formula | D2: 2020A | E2: 2021A | F2: 2022A | G2: 2023A | H2: 2024A | I2: 2025F | J2: 2026F | K2: 2027F | L2: 2028F | M2: 2029F
B3: Gross Profit Margin | C3: Gross Profit/Revenue | D3: ='Financial Statements'!D6/'Financial Statements'!D4 -> 0.51736855 | E3: ='Financial Statements'!E6/'Financial Statements'!E4 -> 0.49525419 | F3: ='Financial Statements'!F6/'Financial Statements'!F4 -> 0.52469318 | G3: ='Financial Statements'!G6/'Financial Statements'!G4 -> 0.50546118 | H3: ='Financial Statements'!H6/'Financial Statements'!H4 -> 0.49104056 | I3: ='Financial Statements'!I6/'Financial Statements'!I4 -> 0.50873939 | J3: ='Financial Statements'!J6/'Financial Statements'!J4 -> 0.5176646 | K3: ='Financial Statements'!K6/'Financial Statements'!K4 -> 0.51785475 | ... M3: ='Financial Statements'!M6/'Financial Statements'!M4 -> 0.50796386
B4: EBITDA Margin | C4: EBITDA/Revenue | D4: ='Financial Statements'!D20/'Financial Statements'!D4 -> 0.2479783 | E4: ='Financial Statements'!E20/'Financial Statements'!E4 -> 0.25303405 | F4: ='Financial Statements'!F20/'Financial Statements'!F4 -> 0.26814497 | G4: ='Financial Statements'!G20/'Financial Statements'!G4 -> 0.2630666 | H4: ='Financial Statements'!H20/'Financial Statements'!H4 -> 0.2785613 | I4: ='Financial Statements'!I20/'Financial Statements'!I4 -> 0.26740506 | J4: ='Financial Statements'!J20/'Financial Statements'!J4 -> 0.28366566 | K4: ='Financial Statements'!K20/'Financial Statements'!K4 -> 0.28622154 | ... M4: ='Financial Statements'!M20/'Financial Statements'!M4 -> 0.28036853
B5: Operating Margin | C5: EBIT/Revenue | D5: ='Financial Statements'!D26/'Financial Statements'!D4 -> 0.18944507 | E5: ='Financial Statements'!E26/'Financial Statements'!E4 -> 0.21598311 | F5: ='Financial Statements'!F26/'Financial Statements'!F4 -> 0.2240166 | G5: ='Financial Statements'!G26/'Financial Statements'!G4 -> 0.22515261 | H5: ='Financial Statements'!H26/'Financial Statements'!H4 -> 0.24842696 | I5: ='Financial Statements'!I26/'Financial Statements'!I4 -> 0.24479385 | J5: ='Financial Statements'!J26/'Financial Statements'!J4 -> 0.26131254 | K5: ='Financial Statements'!K26/'Financial Statements'!K4 -> 0.26481249 | ... M5: ='Financial Statements'!M26/'Financial Statements'!M4 -> 0.25991238
B6: Net Profit Margin | C6: Net Profit/Revenue | D6: ='Financial Statements'!D38/'Financial Statements'!D4 -> 0.11636557 | E6: ='Financial Statements'!E38/'Financial Statements'!E4 -> 0.14464007 | F6: ='Financial Statements'!F38/'Financial Statements'!F4 -> 0.17053941 | G6: ='Financial Statements'!G38/'Financial Statements'!G4 -> 0.131809 | H6: ='Financial Statements'!H38/'Financial Statements'!H4 -> 0.14518105 | I6: ='Financial Statements'!I38/'Financial Statements'!I4 -> 0.13836146 | J6: ='Financial Statements'!J38/'Financial Statements'!J4 -> 0.15104381 | K6: ='Financial Statements'!K38/'Financial Statements'!K4 -> 0.18242401 | ... M6: ='Financial Statements'!M38/'Financial Statements'!M4 -> 0.1911413
